Workbook

Sheet Resumen Ejecutivo
A1: Solución Energética — GRUPO POSADAS / FIDEICOMISO F/1596 (FIBRAHOTEL)
A2: Resumen ejecutivo · pre-IVA · valores del motor CFE Brain (verificado sin errores) · finanzas 100% en vivo desde Supuestos
A4: RECOMENDACIÓN POR PROYECTO
A5: Sitio | B5: Tarifa Actual $/año | C5: Ahorro bruto $/año | D5: Ahorro % | E5: Inversión $ | F5: TIR compra | G5: PPA $/kWh | H5: Benef. cliente PPA a1 $ | I5: Ahorro cliente % (PPA a1)
A6: Médano / Cabo San Lucas (Posadas F/1596) | B6: ='Médano - Cabo San Lucas (Pos'!$E$38*'Médano - Cabo San Lucas (Pos'!$B$39 | C6: ='Médano - Cabo San Lucas (Pos'!$J$38*'Médano - Cabo San Lucas (Pos'!$B$39 | D6: =C6/B6 | E6: ='Médano - Cabo San Lucas (Pos'!$B$22 | F6: ='Médano - Cabo San Lucas (Pos'!$B$64 | G6: =Supuestos!$I$26 | H6: ='Médano - Cabo San Lucas (Pos'!$J$43 | I6: ='Médano - Cabo San Lucas (Pos'!$J$43/'Médano - Cabo San Lucas (Pos'!$B$43
A7: Fairfield Inn Vallejo (F/1596) | B7: ='Fairfield Inn Vallejo (F-159'!$E$38*'Fairfield Inn Vallejo (F-159'!$B$39 | C7: ='Fairfield Inn Vallejo (F-159'!$J$38*'Fairfield Inn Vallejo (F-159'!$B$39 | D7: =C7/B7 | E7: ='Fairfield Inn Vallejo (F-159'!$B$22 | F7: ='Fairfield Inn Vallejo (F-159'!$B$64 | G7: =Supuestos!$I$27 | H7: ='Fairfield Inn Vallejo (F-159'!$J$43 | I7: ='Fairfield Inn Vallejo (F-159'!$J$43/'Fairfield Inn Vallejo (F-159'!$B$43
A8: Fiesta Americana Condesa Cancún | B8: ='Fiesta Americana Condesa Can'!$E$38*'Fiesta Americana Condesa Can'!$B$39 | C8: ='Fiesta Americana Condesa Can'!$J$38*'Fiesta Americana Condesa Can'!$B$39 | D8: =C8/B8 | E8: ='Fiesta Americana Condesa Can'!$B$22 | F8: ='Fiesta Americana Condesa Can'!$B$64 | G8: =Supuestos!$I$28 | H8: ='Fiesta Americana Condesa Can'!$J$43 | I8: ='Fiesta Americana Condesa Can'!$J$43/'Fiesta Americana Condesa Can'!$B$43
A9: Fiesta Inn Periférico Sur (CDMX) | B9: ='Fiesta Inn Periférico Sur (C'!$E$38*'Fiesta Inn Periférico Sur (C'!$B$39 | C9: ='Fiesta Inn Periférico Sur (C'!$J$38*'Fiesta Inn Periférico Sur (C'!$B$39 | D9: =C9/B9 | E9: ='Fiesta Inn Periférico Sur (C'!$B$22 | F9: ='Fiesta Inn Periférico Sur (C'!$B$64 | G9: =Supuestos!$I$29 | H9: ='Fiesta Inn Periférico Sur (C'!$J$43 | I9: ='Fiesta Inn Periférico Sur (C'!$J$43/'Fiesta Inn Periférico Sur (C'!$B$43
A10: Fiesta Americana Viaducto Aeropuerto (CDMX) | B10: ='Fiesta Americana Viaducto Ae'!$E$38*'Fiesta Americana Viaducto Ae'!$B$39 | C10: ='Fiesta Americana Viaducto Ae'!$J$38*'Fiesta Americana Viaducto Ae'!$B$39 | D10: =C10/B10 | E10: ='Fiesta Americana Viaducto Ae'!$B$22 | F10: ='Fiesta Americana Viaducto Ae'!$B$64 | G10: =Supuestos!$I$30 | H10: ='Fiesta Americana Viaducto Ae'!$J$43 | I10: ='Fiesta Americana Viaducto Ae'!$J$43/'Fiesta Americana Viaducto Ae'!$B$43
A11: PORTAFOLIO | B11: =SUM(B6:B10) | C11: =SUM(C6:C10) | D11: =C11/B11 | E11: =SUM(E6:E10) | H11: =SUM(H6:H10) | I11: =H11/('Médano - Cabo San Lucas (Pos'!$B$43+'Fairfield Inn Vallejo (F-159'!$B$43+'Fiesta Americana Condesa Can'!$B$43+'Fiesta Inn Periférico Sur (C'!$B$43+'Fiesta Americana Viaducto Ae'!$B$43)
A13: INDICADORES CLAVE
A14: Gasto eléctrico actual $/año | C14: Ahorro proyecto $/año | E14: Ahorro % del gasto | G14: Ahorro cliente % (PPA a1) | I14: Inversión total (compra) $
A15: =B11 | C15: =C11 | E15: =C11/B11 | G15: =I11 | I15: =E11

Sheet Supuestos
A1: SUPUESTOS — Panel de control en vivo
A2: LIBRO 100% EN VIVO: financieras (AZUL) y dimensionamiento (ÁMBAR) recalculan todo — el motor mensual de cada hoja es fórmula sobre sus datos de recibo (§6).
A3: A. SUPUESTOS GLOBALES
A4: EPC PV (USD/Wp) | B4: 0.75
A5: Tipo de cambio (MXN/USD) | B5: 17.55
A6: EPC BESS (USD/kWh) | B6: 280
A7: WACC / descuento | B7: 0.12
A8: Escalación CFE / año | B8: 0.05
A9: Escalación PPA / año | B9: 0.05
A10: Disponibilidad (factor SaaS) | B10: 0.75
A11: Degradación PV año 1 | B11: 0.01
A12: Degradación PV año 2+ | B12: 0.004
A13: Degradación BESS / año | B13: 0.0125
A14: Comisión BESS financiador | B14: 0.5
A15: Horizonte (años) | B15: 20
... A22: Plazo BESS / comisión (años) | B22: 15
A24: B. VARIABLES POR PROYECTO (AZUL = financiero · ÁMBAR = dimensionamiento)
A25: Proyecto | B25: PV kWp | C25: BESS kW | D25: BESS kWh | E25: FP corr | F25: PV USD/Wp | G25: BESS USD/kWh | H25: Capacitor $ | I25: PPA $/kWh | J25: PPA plazo | K25: Comisión % | L25: TIR compra | M25: TIR financiador | N25: Ahorro bruto/año $ | O25: Ahorro bruto % | P25: Ahorro cliente % (PPA a1)
A26: Médano / Cabo San Lucas (Posadas F/1596) | B26: 290.6 | C26: 0 | D26: 0 | E26: Sí | F26: 0.75 | G26: 280 | H26: 0 | I26: 1.5543 | J26: 15 | K26: 0.5 | L26: ='Médano - Cabo San Lucas (Pos'!$B$64 | M26: ='Médano - Cabo San Lucas (Pos'!$B$65 | N26: ='Médano - Cabo San Lucas (Pos'!$J$38 | O26: ='Médano - Cabo San Lucas (Pos'!$J$38/'Médano - Cabo San Lucas (Pos'!$E$38 | P26: ='Médano - Cabo San Lucas (Pos'!$J$43/'Médano - Cabo San Lucas (Pos'!$B$43
A27: Fairfield Inn Vallejo (F/1596) | B27: 96.9 | C27: 186 | D27: 743 | E27: Sí | F27: 0.75 | G27: 280 | H27: 0 | I27: 4.4867 | J27: 15 | K27: 0.5 | L27: ='Fairfield Inn Vallejo (F-159'!$B$64 | M27: ='Fairfield Inn Vallejo (F-159'!$B$65 | N27: ='Fairfield Inn Vallejo (F-159'!$J$38 | O27: ='Fairfield Inn Vallejo (F-159'!$J$38/'Fairfield Inn Vallejo (F-159'!$E$38 | P27: ='Fairfield Inn Vallejo (F-159'!$J$43/'Fairfield Inn Vallejo (F-159'!$B$43
A28: Fiesta Americana Condesa Cancún | B28: 194.48 | C28: 1503 | D28: 2940 | E28: Sí | F28: 0.75 | G28: 280 | H28: 0 | I28: 4.352 | J28: 15 | K28: 0.5 | L28: ='Fiesta Americana Condesa Can'!$B$64 | M28: ='Fiesta Americana Condesa Can'!$B$65 | N28: ='Fiesta Americana Condesa Can'!$J$38 | O28: ='Fiesta Americana Condesa Can'!$J$38/'Fiesta Americana Condesa Can'!$E$38 | P28: ='Fiesta Americana Condesa Can'!$J$43/'Fiesta Americana Condesa Can'!$B$43
A29: Fiesta Inn Periférico Sur (CDMX) | B29: 348.8 | C29: 207 | D29: 827 | E29: Sí | F29: 0.75 | G29: 280 | H29: 0 | I29: 2.8194 | J29: 15 | K29: 0.5 | L29: ='Fiesta Inn Periférico Sur (C'!$B$64 | M29: ='Fiesta Inn Periférico Sur (C'!$B$65 | N29: ='Fiesta Inn Periférico Sur (C'!$J$38 | O29: ='Fiesta Inn Periférico Sur (C'!$J$38/'Fiesta Inn Periférico Sur (C'!$E$38 | P29: ='Fiesta Inn Periférico Sur (C'!$J$43/'Fiesta Inn Periférico Sur (C'!$B$43
A30: Fiesta Americana Viaducto Aeropuerto (CDMX) | B30: 233.9 | C30: 254 | D30: 1017 | E30: Sí | F30: 0.75 | G30: 280 | H30: 0 | I30: 3.3408 | J30: 15 | K30: 0.5 | L30: ='Fiesta Americana Viaducto Ae'!$B$64 | M30: ='Fiesta Americana Viaducto Ae'!$B$65 | N30: ='Fiesta Americana Viaducto Ae'!$J$38 | O30: ='Fiesta Americana Viaducto Ae'!$J$38/'Fiesta Americana Viaducto Ae'!$E$38 | P30: ='Fiesta Americana Viaducto Ae'!$J$43/'Fiesta Americana Viaducto Ae'!$B$43
A31: PORTAFOLIO | B31: =SUM(B26:B30) | C31: =SUM(C26:C30) | D31: =SUM(D26:D30) | H31: =SUM(H26:H30) | N31: =SUM(N26:N30) | O31: =N31/('Médano - Cabo San Lucas (Pos'!$E$38+'Fairfield Inn Vallejo (F-159'!$E$38+'Fiesta Americana Condesa Can'!$E$38+'Fiesta Inn Periférico Sur (C'!$E$38+'Fiesta Americana Viaducto Ae'!$E$38) | P31: =('Médano - Cabo San Lucas (Pos'!$J$43+'Fairfield Inn Vallejo (F-159'!$J$43+'Fiesta Americana Condesa Can'!$J$43+'Fiesta Inn Periférico Sur (C'!$J$43+'Fiesta Americana Viaducto Ae'!$J$43)/('Médano - Cabo San Lucas (Pos'!$B$43+'Fairfield Inn Vallejo (F-159'!$B$43+'Fiesta Americana Condesa Can'!$B$43+'Fiesta Inn Periférico Sur (C'!$B$43+'Fiesta Americana Viaducto Ae'!$B$43)

Sheet Médano - Cabo San Lucas (Pos
A1: Médano / Cabo San Lucas (Posadas F/1596) — Memoria de cálculo y propuesta energética
A2: RPU 008111000167 · GDMTH BCS · Demanda contratada 326 kW · 12 meses de recibo
A3: Régimen: GENERADOR EXENTO — Medición Neta (sin permiso; Art. 30 LSE; RES/142/2017)
A5: PARÁMETROS (desde Supuestos — edítalos ahí)
A6: PV kWp | B6: =Supuestos!$B$26 | C6: BESS kW | D6: =Supuestos!$C$26 | E6: BESS kWh | F6: =Supuestos!$D$26 | G6: FP corrección | H6: =Supuestos!$E$26 | I6: Entrega útil kWh | J6: =Supuestos!$D$26*Supuestos!$B$17*SQRT(Supuestos!$B$18) | K6: FC umbral | L6: 0.57
A8: 1. ESTRUCTURA DE COSTO Y AHORRO (pre-IVA, año base · fórmulas vivas ← §3)
A9: Concepto | B9: $ / año | C9: Nota
A10: Tarifa Actual (CFE pleno, sin proyecto) | B10: =$E$38*$B$39 | C10: Σ recibos × anualización
A11: (−) Ahorro PV (energía + demanda) | B11: =$F$38*$B$39 | C11: intermedio + umbral
A12: (−) Ahorro BESS (punta + arbitraje) | B12: =$G$38*$B$39 | C12: recorte punta + arbitraje (incl. claw)
A13: (−) Ahorro FP (corrección) | B13: =$H$38*$B$39 | C13: multa factor de potencia
A14: (=) Costo neto con proyecto | B14: =B10-B11-B12-B13
A15: Ahorro proyecto / año | B15: =B11+B12+B13
A16: Ahorro % | B16: =B15/B10
A18: 2. CAPEX (fórmulas vivas desde Supuestos)
A19: CAPEX PV | B19: =Supuestos!$B$26*1000*Supuestos!$F$26*Supuestos!$B$5
A20: CAPEX BESS | B20: =Supuestos!$D$26*Supuestos!$G$26*Supuestos!$B$5
A21: CAPEX capacitor (FP) | B21: =Supuestos!$H$26
A22: CAPEX TOTAL | B22: =B19+B20+B21
A24: 3. RESUMEN MENSUAL — Tarifa Actual vs Con Proyecto (fórmulas vivas ← §6 y Supuestos)
A25: Mes | B25: kWh Consumo | C25: Gen PV kWh | D25: BESS desc kWh | E25: Tarifa Actual $ | F25: Ah PV $ | G25: Ah BESS $ | H25: Ah FP $ | I25: Costo c/proy $ | J25: Ahorro $ | K25: Ahorro %
A26: =A80 | B26: =V80 | C26: =Supuestos!$B$26*S80 | D26: =MIN($J$6*U80,E80) | E26: =SUM(J80:Q80) | F26: =(MIN(C26,D80)*Y80+(MIN(H80,AA80)-MIN(H80,(V80-MIN(C26,D80))/($B$80*24*$L$6)))*AB80)*IF(Q80<0,1+Q80/SUM(J80:P80),1) | G26: =((MIN(H80,(V80-MIN(C26,D80))/($B$80*24*$L$6))-MIN(MAX(H80-MIN(Supuestos!$C$26,IF(T80>0,$J$6/T80,0)),0),(V80-MIN(C26,D80))/($B$80*24*$L$6)))*AB80+D26*Z80-D26/Supuestos!$B$18*X80)*IF(Q80<0,1+Q80/SUM(J80:P80),1) | H26: =IF(Supuestos!$E$26="Sí",R80,0) | I26: =E26-J26 | J26: =F26+G26+H26 | K26: =J26/E26
A27: =A81 | B27: =V81 | C27: =Supuestos!$B$26*S81 | D27: =MIN($J$6*U81,E81) | E27: =SUM(J81:Q81) | F27: =(MIN(C27,D81)*Y81+(MIN(H81,AA81)-MIN(H81,(V81-MIN(C27,D81))/($B$81*24*$L$6)))*AB81)*IF(Q81<0,1+Q81/SUM(J81:P81),1) | G27: =((MIN(H81,(V81-MIN(C27,D81))/($B$81*24*$L$6))-MIN(MAX(H81-MIN(Supuestos!$C$26,IF(T81>0,$J$6/T81,0)),0),(V81-MIN(C27,D81))/($B$81*24*$L$6)))*AB81+D27*Z81-D27/Supuestos!$B$18*X81)*IF(Q81<0,1+Q81/SUM(J81:P81),1) | H27: =IF(Supuestos!$E$26="Sí",R81,0) | I27: =E27-J27 | J27: =F27+G27+H27 | K27: =J27/E27
A28: =A82 | B28: =V82 | C28: =Supuestos!$B$26*S82 | D28: =MIN($J$6*U82,E82) | E28: =SUM(J82:Q82) | F28: =(MIN(C28,D82)*Y82+(MIN(H82,AA82)-MIN(H82,(V82-MIN(C28,D82))/($B$82*24*$L$6)))*AB82)*IF(Q82<0,1+Q82/SUM(J82:P82),1) | G28: =((MIN(H82,(V82-MIN(C28,D82))/($B$82*24*$L$6))-MIN(MAX(H82-MIN(Supuestos!$C$26,IF(T82>0,$J$6/T82,0)),0),(V82-MIN(C28,D82))/($B$82*24*$L$6)))*AB82+D28*Z82-D28/Supuestos!$B$18*X82)*IF(Q82<0,1+Q82/SUM(J82:P82),1) | H28: =IF(Supuestos!$E$26="Sí",R82,0) | I28: =E28-J28 | J28: =F28+G28+H28 | K28: =J28/E28
A29: =A83 | B29: =V83 | C29: =Supuestos!$B$26*S83 | D29: =MIN($J$6*U83,E83) | E29: =SUM(J83:Q83) | F29: =(MIN(C29,D83)*Y83+(MIN(H83,AA83)-MIN(H83,(V83-MIN(C29,D83))/($B$83*24*$L$6)))*AB83)*IF(Q83<0,1+Q83/SUM(J83:P83),1) | G29: =((MIN(H83,(V83-MIN(C29,D83))/($B$83*24*$L$6))-MIN(MAX(H83-MIN(Supuestos!$C$26,IF(T83>0,$J$6/T83,0)),0),(V83-MIN(C29,D83))/($B$83*24*$L$6)))*AB83+D29*Z83-D29/Supuestos!$B$18*X83)*IF(Q83<0,1+Q83/SUM(J83:P83),1) | H29: =IF(Supuestos!$E$26="Sí",R83,0) | I29: =E29-J29 | J29: =F29+G29+H29 | K29: =J29/E29
A30: =A84 | B30: =V84 | C30: =Supuestos!$B$26*S84 | D30: =MIN($J$6*U84,E84) | E30: =SUM(J84:Q84) | F30: =(MIN(C30,D84)*Y84+(MIN(H84,AA84)-MIN(H84,(V84-MIN(C30,D84))/($B$84*24*$L$6)))*AB84)*IF(Q84<0,1+Q84/SUM(J84:P84),1) | G30: =((MIN(H84,(V84-MIN(C30,D84))/($B$84*24*$L$6))-MIN(MAX(H84-MIN(Supuestos!$C$26,IF(T84>0,$J$6/T84,0)),0),(V84-MIN(C30,D84))/($B$84*24*$L$6)))*AB84+D30*Z84-D30/Supuestos!$B$18*X84)*IF(Q84<0,1+Q84/SUM(J84:P84),1) | H30: =IF(Supuestos!$E$26="Sí",R84,0) | I30: =E30-J30 | J30: =F30+G30+H30 | K30: =J30/E30
A31: =A85 | B31: =V85 | C31: =Supuestos!$B$26*S85 | D31: =MIN($J$6*U85,E85) | E31: =SUM(J85:Q85) | F31: =(MIN(C31,D85)*Y85+(MIN(H85,AA85)-MIN(H85,(V85-MIN(C31,D85))/($B$85*24*$L$6)))*AB85)*IF(Q85<0,1+Q85/SUM(J85:P85),1) | G31: =((MIN(H85,(V85-MIN(C31,D85))/($B$85*24*$L$6))-MIN(MAX(H85-MIN(Supuestos!$C$26,IF(T85>0,$J$6/T85,0)),0),(V85-MIN(C31,D85))/($B$85*24*$L$6)))*AB85+D31*Z85-D31/Supuestos!$B$18*X85)*IF(Q85<0,1+Q85/SUM(J85:P85),1) | H31: =IF(Supuestos!$E$26="Sí",R85,0) | I31: =E31-J31 | J31: =F31+G31+H31 | K31: =J31/E31
A32: =A86 | B32: =V86 | C32: =Supuestos!$B$26*S86 | D32: =MIN($J$6*U86,E86) | E32: =SUM(J86:Q86) | F32: =(MIN(C32,D86)*Y86+(MIN(H86,AA86)-MIN(H86,(V86-MIN(C32,D86))/($B$86*24*$L$6)))*AB86)*IF(Q86<0,1+Q86/SUM(J86:P86),1) | G32: =((MIN(H86,(V86-MIN(C32,D86))/($B$86*24*$L$6))-MIN(MAX(H86-MIN(Supuestos!$C$26,IF(T86>0,$J$6/T86,0)),0),(V86-MIN(C32,D86))/($B$86*24*$L$6)))*AB86+D32*Z86-D32/Supuestos!$B$18*X86)*IF(Q86<0,1+Q86/SUM(J86:P86),1) | H32: =IF(Supuestos!$E$26="Sí",R86,0) | I32: =E32-J32 | J32: =F32+G32+H32 | K32: =J32/E32
A33: =A87 | B33: =V87 | C33: =Supuestos!$B$26*S87 | D33: =MIN($J$6*U87,E87) | E33: =SUM(J87:Q87) | F33: =(MIN(C33,D87)*Y87+(MIN(H87,AA87)-MIN(H87,(V87-MIN(C33,D87))/($B$87*24*$L$6)))*AB87)*IF(Q87<0,1+Q87/SUM(J87:P87),1) | G33: =((MIN(H87,(V87-MIN(C33,D87))/($B$87*24*$L$6))-MIN(MAX(H87-MIN(Supuestos!$C$26,IF(T87>0,$J$6/T87,0)),0),(V87-MIN(C33,D87))/($B$87*24*$L$6)))*AB87+D33*Z87-D33/Supuestos!$B$18*X87)*IF(Q87<0,1+Q87/SUM(J87:P87),1) | H33: =IF(Supuestos!$E$26="Sí",R87,0) | I33: =E33-J33 | J33: =F33+G33+H33 | K33: =J33/E33
A34: =A88 | B34: =V88 | C34: =Supuestos!$B$26*S88 | D34: =MIN($J$6*U88,E88) | E34: =SUM(J88:Q88) | F34: =(MIN(C34,D88)*Y88+(MIN(H88,AA88)-MIN(H88,(V88-MIN(C34,D88))/($B$88*24*$L$6)))*AB88)*IF(Q88<0,1+Q88/SUM(J88:P88),1) | G34: =((MIN(H88,(V88-MIN(C34,D88))/($B$88*24*$L$6))-MIN(MAX(H88-MIN(Supuestos!$C$26,IF(T88>0,$J$6/T88,0)),0),(V88-MIN(C34,D88))/($B$88*24*$L$6)))*AB88+D34*Z88-D34/Supuestos!$B$18*X88)*IF(Q88<0,1+Q88/SUM(J88:P88),1) | H34: =IF(Supuestos!$E$26="Sí",R88,0) | I34: =E34-J34 | J34: =F34+G34+H34 | K34: =J34/E34
A35: =A89 | B35: =V89 | C35: =Supuestos!$B$26*S89 | D35: =MIN($J$6*U89,E89) | E35: =SUM(J89:Q89) | F35: =(MIN(C35,D89)*Y89+(MIN(H89,AA89)-MIN(H89,(V89-MIN(C35,D89))/($B$89*24*$L$6)))*AB89)*IF(Q89<0,1+Q89/SUM(J89:P89),1) | G35: =((MIN(H89,(V89-MIN(C35,D89))/($B$89*24*$L$6))-MIN(MAX(H89-MIN(Supuestos!$C$26,IF(T89>0,$J$6/T89,0)),0),(V89-MIN(C35,D89))/($B$89*24*$L$6)))*AB89+D35*Z89-D35/Supuestos!$B$18*X89)*IF(Q89<0,1+Q89/SUM(J89:P89),1) | H35: =IF(Supuestos!$E$26="Sí",R89,0) | I35: =E35-J35 | J35: =F35+G35+H35 | K35: =J35/E35
A36: =A90 | B36: =V90 | C36: =Supuestos!$B$26*S90 | D36: =MIN($J$6*U90,E90) | E36: =SUM(J90:Q90) | F36: =(MIN(C36,D90)*Y90+(MIN(H90,AA90)-MIN(H90,(V90-MIN(C36,D90))/($B$90*24*$L$6)))*AB90)*IF(Q90<0,1+Q90/SUM(J90:P90),1) | G36: =((MIN(H90,(V90-MIN(C36,D90))/($B$90*24*$L$6))-MIN(MAX(H90-MIN(Supuestos!$C$26,IF(T90>0,$J$6/T90,0)),0),(V90-MIN(C36,D90))/($B$90*24*$L$6)))*AB90+D36*Z90-D36/Supuestos!$B$18*X90)*IF(Q90<0,1+Q90/SUM(J90:P90),1) | H36: =IF(Supuestos!$E$26="Sí",R90,0) | I36: =E36-J36 | J36: =F36+G36+H36 | K36: =J36/E36
A37: =A91 | B37: =V91 | C37: =Supuestos!$B$26*S91 | D37: =MIN($J$6*U91,E91) | E37: =SUM(J91:Q91) | F37: =(MIN(C37,D91)*Y91+(MIN(H91,AA91)-MIN(H91,(V91-MIN(C37,D91))/($B$91*24*$L$6)))*AB91)*IF(Q91<0,1+Q91/SUM(J91:P91),1) | G37: =((MIN(H91,(V91-MIN(C37,D91))/($B$91*24*$L$6))-MIN(MAX(H91-MIN(Supuestos!$C$26,IF(T91>0,$J$6/T91,0)),0),(V91-MIN(C37,D91))/($B$91*24*$L$6)))*AB91+D37*Z91-D37/Supuestos!$B$18*X91)*IF(Q91<0,1+Q91/SUM(J91:P91),1) | H37: =IF(Supuestos!$E$26="Sí",R91,0) | I37: =E37-J37 | J37: =F37+G37+H37 | K37: =J37/E37
A38: TOTAL | B38: =SUM(B26:B37) | C38: =SUM(C26:C37) | D38: =SUM(D26:D37) | E38: =SUM(E26:E37) | F38: =SUM(F26:F37) | G38: =SUM(G26:G37) | H38: =SUM(H26:H37) | I38: =SUM(I26:I37) | J38: =SUM(J26:J37) | K38: =J38/E38
A39: Factor anualización (12/meses): | B39: 1
A40: 4. PROYECCIÓN 20 AÑOS — Comprar vs PPA/Ahorro compartido
A41: Año | B41: Tarifa Actual $ | C41: Ah PV $ | D41: Ah BESS $ | E41: Ah FP $ | F41: Costo c/proy $ | G41: Flujo Compra $ | H41: Pago PPA $ | I41: Comisión $ | J41: Flujo Cliente PPA $ | K41: Flujo Financiador $ | L41: Acum Compra $ | M41: Acum Cliente PPA $
A42: 0 | G42: =-B22 | K42: =-B22 | L42: =G42 | M42: 0
A43: 1 | B43: =$E$38*$B$39*(1+Supuestos!$B$8)^1 | C43: =$F$38*$B$39*(1+Supuestos!$B$8)^1*((1-Supuestos!$B$11)*(1-Supuestos!$B$12)^0) | D43: =$G$38*$B$39*(1+Supuestos!$B$8)^1*(1-Supuestos!$B$13)^1*Supuestos!$B$10 | E43: =$H$38*$B$39*(1+Supuestos!$B$8)^1 | F43: =B43-C43-D43-E43 | G43: =C43+D43+E43-(IF(1<=Supuestos!$J$26,Supuestos!$B$19*Supuestos!$B$26*(1+Supuestos!$B$8)^0,0)+IF(1<=Supuestos!$B$22,Supuestos!$B$20*Supuestos!$D$26*(1+Supuestos!$B$8)^0,0)) | H43: =IF(1<=Supuestos!$J$26,$C$38*$B$39*((1-Supuestos!$B$11)*(1-Supuestos!$B$12)^0)*Supuestos!$I$26*(1+Supuestos!$B$9)^0,0) | I43: =IF(1<=Supuestos!$B$22,D43*Supuestos!$K$26,0) | J43: =C43+D43+E43-H43-I43 | K43: =H43+I43-(IF(1<=Supuestos!$J$26,Supuestos!$B$19*Supuestos!$B$26*(1+Supuestos!$B$8)^0,0)+IF(1<=Supuestos!$B$22,Supuestos!$B$20*Supuestos!$D$26*(1+Supuestos!$B$8)^0,0))-H43*Supuestos!$B$21 | L43: =L42+G43 | M43: =M42+J43
A44: 2 | B44: =$E$38*$B$39*(1+Supuestos!$B$8)^2 | C44: =$F$38*$B$39*(1+Supuestos!$B$8)^2*((1-Supuestos!$B$11)*(1-Supuestos!$B$12)^1) | D44: =$G$38*$B$39*(1+Supuestos!$B$8)^2*(1-Supuestos!$B$13)^2*Supuestos!$B$10 | E44: =$H$38*$B$39*(1+Supuestos!$B$8)^2 | F44: =B44-C44-D44-E44 | G44: =C44+D44+E44-(IF(2<=Supuestos!$J$26,Supuestos!$B$19*Supuestos!$B$26*(1+Supuestos!$B$8)^1,0)+IF(2<=Supuestos!$B$22,Supuestos!$B$20*Supuestos!$D$26*(1+Supuestos!$B$8)^1,0)) | H44: =IF(2<=Supuestos!$J$26,$C$38*$B$39*((1-Supuestos!$B$11)*(1-Supuestos!$B$12)^1)*Supuestos!$I$26*(1+Supuestos!$B$9)^1,0) | I44: =IF(2<=Supuestos!$B$22,D44*Supuestos!$K$26,0) | J44: =C44+D44+E44-H44-I44 | K44: =H44+I44-(IF(2<=Supuestos!$J$26,Supuestos!$B$19*Supuestos!$B$26*(1+Supuestos!$B$8)^1,0)+IF(2<=Supuestos!$B$22,Supuestos!$B$20*Supuestos!$D$26*(1+Supuestos!$B$8)^1,0))-H44*Supuestos!$B$21 | L44: =L43+G44 | M44: =M43+J44
A45: 3 | B45: =$E$38*$B$39*(1+Supuestos!$B$8)^3 | C45: =$F$38*$B$39*(1+Supuestos!$B$8)^3*((1-Supuestos!$B$11)*(1-Supuestos!$B$12)^2) | D45: =$G$38*$B$39*(1+Supuestos!$B$8)^3*(1-Supuestos!$B$13)^3*Supuestos!$B$10 | E45: =$H$38*$B$39*(1+Supuestos!$B$8)^3 | F45: =B45-C45-D45-E45 | G45: =C45+D45+E45-(IF(3<=Supuestos!$J$26,Supuestos!$B$19*Supuestos!$B$26*(1+Supuestos!$B$8)^2,0)+IF(3<=Supuestos!$B$22,Supuestos!$B$20*Supuestos!$D$26*(1+Supuestos!$B$8)^2,0)) | H45: =IF(3<=Supuestos!$J$26,$C$38*$B$39*((1-Supuestos!$B$11)*(1-Supuestos!$B$12)^2)*Supuestos!$I$26*(1+Supuestos!$B$9)^2,0) | I45: =IF(3<=Supuestos!$B$22,D45*Supuestos!$K$26,0) | J45: =C45+D45+E45-H45-I45 | K45: =H45+I45-(IF(3<=Supuestos!$J$26,Supuestos!$B$19*Supuestos!$B$26*(1+Supuestos!$B$8)^2,0)+IF(3<=Supuestos!$B$22,Supuestos!$B$20*Supuestos!$D$26*(1+Supuestos!$B$8)^2,0))-H45*Supuestos!$B$21 | L45: =L44+G45 | M45: =M44+J45
A46: 4 | B46: =$E$38*$B$39*(1+Supuestos!$B$8)^4 | C46: =$F$38*$B$39*(1+Supuestos!$B$8)^4*((1-Supuestos!$B$11)*(1-Supuestos!$B$12)^3) | D46: =$G$38*$B$39*(1+Supuestos!$B$8)^4*(1-Supuestos!$B$13)^4*Supuestos!$B$10 | E46: =$H$38*$B$39*(1+Supuestos!$B$8)^4 | F46: =B46-C46-D46-E46 | G46: =C46+D46+E46-(IF(4<=Supuestos!$J$26,Supuestos!$B$19*Supuestos!$B$26*(1+Supuestos!$B$8)^3,0)+IF(4<=Supuestos!$B$22,Supuestos!$B$20*Supuestos!$D$26*(1+Supuestos!$B$8)^3,0)) | H46: =IF(4<=Supuestos!$J$26,$C$38*$B$39*((1-Supuestos!$B$11)*(1-Supuestos!$B$12)^3)*Supuestos!$I$26*(1+Supuestos!$B$9)^3,0) | I46: =IF(4<=Supuestos!$B$22,D46*Supuestos!$K$26,0) | J46: =C46+D46+E46-H46-I46 | K46: =H46+I46-(IF(4<=Supuestos!$J$26,Supuestos!$B$19*Supuestos!$B$26*(1+Supuestos!$B$8)^3,0)+IF(4<=Supuestos!$B$22,Supuestos!$B$20*Supuestos!$D$26*(1+Supuestos!$B$8)^3,0))-H46*Supuestos!$B$21 | L46: =L45+G46 | M46: =M45+J46
A47: 5 | B47: =$E$38*$B$39*(1+Supuestos!$B$8)^5 | C47: =$F$38*$B$39*(1+Supuestos!$B$8)^5*((1-Supuestos!$B$11)*(1-Supuestos!$B$12)^4) | D47: =$G$38*$B$39*(1+Supuestos!$B$8)^5*(1-Supuestos!$B$13)^5*Supuestos!$B$10 | E47: =$H$38*$B$39*(1+Supuestos!$B$8)^5 | F47: =B47-C47-D47-E47 | G47: =C47+D47+E47-(IF(5<=Supuestos!$J$26,Supuestos!$B$19*Supuestos!$B$26*(1+Supuestos!$B$8)^4,0)+IF(5<=Supuestos!$B$22,Supuestos!$B$20*Supuestos!$D$26*(1+Supuestos!$B$8)^4,0)) | H47: =IF(5<=Supuestos!$J$26,$C$38*$B$39*((1-Supuestos!$B$11)*(1-Supuestos!$B$12)^4)*Supuestos!$I$26*(1+Supuestos!$B$9)^4,0) | I47: =IF(5<=Supuestos!$B$22,D47*Supuestos!$K$26,0) | J47: =C47+D47+E47-H47-I47 | K47: =H47+I47-(IF(5<=Supuestos!$J$26,Supuestos!$B$19*Supuestos!$B$26*(1+Supuestos!$B$8)^4,0)+IF(5<=Supuestos!$B$22,Supuestos!$B$20*Supuestos!$D$26*(1+Supuestos!$B$8)^4,0))-H47*Supuestos!$B$21 | L47: =L46+G47 | M47: =M46+J47
A48: 6 | B48: =$E$38*$B$39*(1+Supuestos!$B$8)^6 | C48: =$F$38*$B$39*(1+Supuestos!$B$8)^6*((1-Supuestos!$B$11)*(1-Supuestos!$B$12)^5) | D48: =$G$38*$B$39*(1+Supuestos!$B$8)^6*(1-Supuestos!$B$13)^6*Supuestos!$B$10 | E48: =$H$38*$B$39*(1+Supuestos!$B$8)^6 | F48: =B48-C48-D48-E48 | G48: =C48+D48+E48-(IF(6<=Supuestos!$J$26,Supuestos!$B$19*Supuestos!$B$26*(1+Supuestos!$B$8)^5,0)+IF(6<=Supuestos!$B$22,Supuestos!$B$20*Supuestos!$D$26*(1+Supuestos!$B$8)^5,0)) | H48: =IF(6<=Supuestos!$J$26,$C$38*$B$39*((1-Supuestos!$B$11)*(1-Supuestos!$B$12)^5)*Supuestos!$I$26*(1+Supuestos!$B$9)^5,0) | I48: =IF(6<=Supuestos!$B$22,D48*Supuestos!$K$26,0) | J48: =C48+D48+E48-H48-I48 | K48: =H48+I48-(IF(6<=Supuestos!$J$26,Supuestos!$B$19*Supuestos!$B$26*(1+Supuestos!$B$8)^5,0)+IF(6<=Supuestos!$B$22,Supuestos!$B$20*Supuestos!$D$26*(1+Supuestos!$B$8)^5,0))-H48*Supuestos!$B$21 | L48: =L47+G48 | M48: =M47+J48
A49: 7 | B49: =$E$38*$B$39*(1+Supuestos!$B$8)^7 | C49: =$F$38*$B$39*(1+Supuestos!$B$8)^7*((1-Supuestos!$B$11)*(1-Supuestos!$B$12)^6) | D49: =$G$38*$B$39*(1+Supuestos!$B$8)^7*(1-Supuestos!$B$13)^7*Supuestos!$B$10 | E49: =$H$38*$B$39*(1+Supuestos!$B$8)^7 | F49: =B49-C49-D49-E49 | G49: =C49+D49+E49-(IF(7<=Supuestos!$J$26,Supuestos!$B$19*Supuestos!$B$26*(1+Supuestos!$B$8)^6,0)+IF(7<=Supuestos!$B$22,Supuestos!$B$20*Supuestos!$D$26*(1+Supuestos!$B$8)^6,0)) | H49: =IF(7<=Supuestos!$J$26,$C$38*$B$39*((1-Supuestos!$B$11)*(1-Supuestos!$B$12)^6)*Supuestos!$I$26*(1+Supuestos!$B$9)^6,0) | I49: =IF(7<=Supuestos!$B$22,D49*Supuestos!$K$26,0) | J49: =C49+D49+E49-H49-I49 | K49: =H49+I49-(IF(7<=Supuestos!$J$26,Supuestos!$B$19*Supuestos!$B$26*(1+Supuestos!$B$8)^6,0)+IF(7<=Supuestos!$B$22,Supuestos!$B$20*Supuestos!$D$26*(1+Supuestos!$B$8)^6,0))-H49*Supuestos!$B$21 | L49: =L48+G49 | M49: =M48+J49
A50: 8 | B50: =$E$38*$B$39*(1+Supuestos!$B$8)^8 | C50: =$F$38*$B$39*(1+Supuestos!$B$8)^8*((1-Supuestos!$B$11)*(1-Supuestos!$B$12)^7) | D50: =$G$38*$B$39*(1+Supuestos!$B$8)^8*(1-Supuestos!$B$13)^8*Supuestos!$B$10 | E50: =$H$38*$B$39*(1+Supuestos!$B$8)^8 | F50: =B50-C50-D50-E50 | G50: =C50+D50+E50-(IF(8<=Supuestos!$J$26,Supuestos!$B$19*Supuestos!$B$26*(1+Supuestos!$B$8)^7,0)+IF(8<=Supuestos!$B$22,Supuestos!$B$20*Supuestos!$D$26*(1+Supuestos!$B$8)^7,0)) | H50: =IF(8<=Supuestos!$J$26,$C$38*$B$39*((1-Supuestos!$B$11)*(1-Supuestos!$B$12)^7)*Supuestos!$I$26*(1+Supuestos!$B$9)^7,0) | I50: =IF(8<=Supuestos!$B$22,D50*Supuestos!$K$26,0) | J50: =C50+D50+E50-H50-I50 | K50: =H50+I50-(IF(8<=Supuestos!$J$26,Supuestos!$B$19*Supuestos!$B$26*(1+Supuestos!$B$8)^7,0)+IF(8<=Supuestos!$B$22,Supuestos!$B$20*Supuestos!$D$26*(1+Supuestos!$B$8)^7,0))-H50*Supuestos!$B$21 | L50: =L49+G50 | M50: =M49+J50
A51: 9 | B51: =$E$38*$B$39*(1+Supuestos!$B$8)^9 | C51: =$F$38*$B$39*(1+Supuestos!$B$8)^9*((1-Supuestos!$B$11)*(1-Supuestos!$B$12)^8) | D51: =$G$38*$B$39*(1+Supuestos!$B$8)^9*(1-Supuestos!$B$13)^9*Supuestos!$B$10 | E51: =$H$38*$B$39*(1+Supuestos!$B$8)^9 | F51: =B51-C51-D51-E51 | G51: =C51+D51+E51-(IF(9<=Supuestos!$J$26,Supuestos!$B$19*Supuestos!$B$26*(1+Supuestos!$B$8)^8,0)+IF(9<=Supuestos!$B$22,Supuestos!$B$20*Supuestos!$D$26*(1+Supuestos!$B$8)^8,0)) | H51: =IF(9<=Supuestos!$J$26,$C$38*$B$39*((1-Supuestos!$B$11)*(1-Supuestos!$B$12)^8)*Supuestos!$I$26*(1+Supuestos!$B$9)^8,0) | I51: =IF(9<=Supuestos!$B$22,D51*Supuestos!$K$26,0) | J51: =C51+D51+E51-H51-I51 | K51: =H51+I51-(IF(9<=Supuestos!$J$26,Supuestos!$B$19*Supuestos!$B$26*(1+Supuestos!$B$8)^8,0)+IF(9<=Supuestos!$B$22,Supuestos!$B$20*Supuestos!$D$26*(1+Supuestos!$B$8)^8,0))-H51*Supuestos!$B$21 | L51: =L50+G51 | M51: =M50+J51
A52: 10 | B52: =$E$38*$B$39*(1+Supuestos!$B$8)^10 | C52: =$F$38*$B$39*(1+Supuestos!$B$8)^10*((1-Supuestos!$B$11)*(1-Supuestos!$B$12)^9) | D52: =$G$38*$B$39*(1+Supuestos!$B$8)^10*(1-Supuestos!$B$13)^10*Supuestos!$B$10 | E52: =$H$38*$B$39*(1+Supuestos!$B$8)^10 | F52: =B52-C52-D52-E52 | G52: =C52+D52+E52-(IF(10<=Supuestos!$J$26,Supuestos!$B$19*Supuestos!$B$26*(1+Supuestos!$B$8)^9,0)+IF(10<=Supuestos!$B$22,Supuestos!$B$20*Supuestos!$D$26*(1+Supuestos!$B$8)^9,0)) | H52: =IF(10<=Supuestos!$J$26,$C$38*$B$39*((1-Supuestos!$B$11)*(1-Supuestos!$B$12)^9)*Supuestos!$I$26*(1+Supuestos!$B$9)^9,0) | I52: =IF(10<=Supuestos!$B$22,D52*Supuestos!$K$26,0) | J52: =C52+D52+E52-H52-I52 | K52: =H52+I52-(IF(10<=Supuestos!$J$26,Supuestos!$B$19*Supuestos!$B$26*(1+Supuestos!$B$8)^9,0)+IF(10<=Supuestos!$B$22,Supuestos!$B$20*Supuestos!$D$26*(1+Supuestos!$B$8)^9,0))-H52*Supuestos!$B$21 | L52: =L51+G52 | M52: =M51+J52
A53: 11 | B53: =$E$38*$B$39*(1+Supuestos!$B$8)^11 | C53: =$F$38*$B$39*(1+Supuestos!$B$8)^11*((1-Supuestos!$B$11)*(1-Supuestos!$B$12)^10) | D53: =$G$38*$B$39*(1+Supuestos!$B$8)^11*(1-Supuestos!$B$13)^11*Supuestos!$B$10 | E53: =$H$38*$B$39*(1+Supuestos!$B$8)^11 | F53: =B53-C53-D53-E53 | G53: =C53+D53+E53-(IF(11<=Supuestos!$J$26,Supuestos!$B$19*Supuestos!$B$26*(1+Supuestos!$B$8)^10,0)+IF(11<=Supuestos!$B$22,Supuestos!$B$20*Supuestos!$D$26*(1+Supuestos!$B$8)^10,0)) | H53: =IF(11<=Supuestos!$J$26,$C$38*$B$39*((1-Supuestos!$B$11)*(1-Supuestos!$B$12)^10)*Supuestos!$I$26*(1+Supuestos!$B$9)^10,0) | I53: =IF(11<=Supuestos!$B$22,D53*Supuestos!$K$26,0) | J53: =C53+D53+E53-H53-I53 | K53: =H53+I53-(IF(11<=Supuestos!$J$26,Supuestos!$B$19*Supuestos!$B$26*(1+Supuestos!$B$8)^10,0)+IF(11<=Supuestos!$B$22,Supuestos!$B$20*Supuestos!$D$26*(1+Supuestos!$B$8)^10,0))-H53*Supuestos!$B$21 | L53: =L52+G53 | M53: =M52+J53
A54: 12 | B54: =$E$38*$B$39*(1+Supuestos!$B$8)^12 | C54: =$F$38*$B$39*(1+Supuestos!$B$8)^12*((1-Supuestos!$B$11)*(1-Supuestos!$B$12)^11) | D54: =$G$38*$B$39*(1+Supuestos!$B$8)^12*(1-Supuestos!$B$13)^12*Supuestos!$B$10 | E54: =$H$38*$B$39*(1+Supuestos!$B$8)^12 | F54: =B54-C54-D54-E54 | G54: =C54+D54+E54-(IF(12<=Supuestos!$J$26,Supuestos!$B$19*Supuestos!$B$26*(1+Supuestos!$B$8)^11,0)+IF(12<=Supuestos!$B$22,Supuestos!$B$20*Supuestos!$D$26*(1+Supuestos!$B$8)^11,0)) | H54: =IF(12<=Supuestos!$J$26,$C$38*$B$39*((1-Supuestos!$B$11)*(1-Supuestos!$B$12)^11)*Supuestos!$I$26*(1+Supuestos!$B$9)^11,0) | I54: =IF(12<=Supuestos!$B$22,D54*Supuestos!$K$26,0) | J54: =C54+D54+E54-H54-I54 | K54: =H54+I54-(IF(12<=Supuestos!$J$26,Supuestos!$B$19*Supuestos!$B$26*(1+Supuestos!$B$8)^11,0)+IF(12<=Supuestos!$B$22,Supuestos!$B$20*Supuestos!$D$26*(1+Supuestos!$B$8)^11,0))-H54*Supuestos!$B$21 | L54: =L53+G54 | M54: =M53+J54
A55: 13 | B55: =$E$38*$B$39*(1+Supuestos!$B$8)^13 | C55: =$F$38*$B$39*(1+Supuestos!$B$8)^13*((1-Supuestos!$B$11)*(1-Supuestos!$B$12)^12) | D55: =$G$38*$B$39*(1+Supuestos!$B$8)^13*(1-Supuestos!$B$13)^13*Supuestos!$B$10 | E55: =$H$38*$B$39*(1+Supuestos!$B$8)^13 | F55: =B55-C55-D55-E55 | G55: =C55+D55+E55-(IF(13<=Supuestos!$J$26,Supuestos!$B$19*Supuestos!$B$26*(1+Supuestos!$B$8)^12,0)+IF(13<=Supuestos!$B$22,Supuestos!$B$20*Supuestos!$D$26*(1+Supuestos!$B$8)^12,0)) | H55: =IF(13<=Supuestos!$J$26,$C$38*$B$39*((1-Supuestos!$B$11)*(1-Supuestos!$B$12)^12)*Supuestos!$I$26*(1+Supuestos!$B$9)^12,0) | I55: =IF(13<=Supuestos!$B$22,D55*Supuestos!$K$26,0) | J55: =C55+D55+E55-H55-I55 | K55: =H55+I55-(IF(13<=Supuestos!$J$26,Supuestos!$B$19*Supuestos!$B$26*(1+Supuestos!$B$8)^12,0)+IF(13<=Supuestos!$B$22,Supuestos!$B$20*Supuestos!$D$26*(1+Supuestos!$B$8)^12,0))-H55*Supuestos!$B$21 | L55: =L54+G55 | M55: =M54+J55
A56: 14 | B56: =$E$38*$B$39*(1+Supuestos!$B$8)^14 | C56: =$F$38*$B$39*(1+Supuestos!$B$8)^14*((1-Supuestos!$B$11)*(1-Supuestos!$B$12)^13) | D56: =$G$38*$B$39*(1+Supuestos!$B$8)^14*(1-Supuestos!$B$13)^14*Supuestos!$B$10 | E56: =$H$38*$B$39*(1+Supuestos!$B$8)^14 | F56: =B56-C56-D56-E56 | G56: =C56+D56+E56-(IF(14<=Supuestos!$J$26,Supuestos!$B$19*Supuestos!$B$26*(1+Supuestos!$B$8)^13,0)+IF(14<=Supuestos!$B$22,Supuestos!$B$20*Supuestos!$D$26*(1+Supuestos!$B$8)^13,0)) | H56: =IF(14<=Supuestos!$J$26,$C$38*$B$39*((1-Supuestos!$B$11)*(1-Supuestos!$B$12)^13)*Supuestos!$I$26*(1+Supuestos!$B$9)^13,0) | I56: =IF(14<=Supuestos!$B$22,D56*Supuestos!$K$26,0) | J56: =C56+D56+E56-H56-I56 | K56: =H56+I56-(IF(14<=Supuestos!$J$26,Supuestos!$B$19*Supuestos!$B$26*(1+Supuestos!$B$8)^13,0)+IF(14<=Supuestos!$B$22,Supuestos!$B$20*Supuestos!$D$26*(1+Supuestos!$B$8)^13,0))-H56*Supuestos!$B$21 | L56: =L55+G56 | M56: =M55+J56
A57: 15 | B57: =$E$38*$B$39*(1+Supuestos!$B$8)^15 | C57: =$F$38*$B$39*(1+Supuestos!$B$8)^15*((1-Supuestos!$B$11)*(1-Supuestos!$B$12)^14) | D57: =$G$38*$B$39*(1+Supuestos!$B$8)^15*(1-Supuestos!$B$13)^15*Supuestos!$B$10 | E57: =$H$38*$B$39*(1+Supuestos!$B$8)^15 | F57: =B57-C57-D57-E57 | G57: =C57+D57+E57-(IF(15<=Supuestos!$J$26,Supuestos!$B$19*Supuestos!$B$26*(1+Supuestos!$B$8)^14,0)+IF(15<=Supuestos!$B$22,Supuestos!$B$20*Supuestos!$D$26*(1+Supuestos!$B$8)^14,0)) | H57: =IF(15<=Supuestos!$J$26,$C$38*$B$39*((1-Supuestos!$B$11)*(1-Supuestos!$B$12)^14)*Supuestos!$I$26*(1+Supuestos!$B$9)^14,0) | I57: =IF(15<=Supuestos!$B$22,D57*Supuestos!$K$26,0) | J57: =C57+D57+E57-H57-I57 | K57: =H57+I57-(IF(15<=Supuestos!$J$26,Supuestos!$B$19*Supuestos!$B$26*(1+Supuestos!$B$8)^14,0)+IF(15<=Supuestos!$B$22,Supuestos!$B$20*Supuestos!$D$26*(1+Supuestos!$B$8)^14,0))-H57*Supuestos!$B$21 | L57: =L56+G57 | M57: =M56+J57
A58: 16 | B58: =$E$38*$B$39*(1+Supuestos!$B$8)^16 | C58: =$F$38*$B$39*(1+Supuestos!$B$8)^16*((1-Supuestos!$B$11)*(1-Supuestos!$B$12)^15) | D58: =$G$38*$B$39*(1+Supuestos!$B$8)^16*(1-Supuestos!$B$13)^16*Supuestos!$B$10 | E58: =$H$38*$B$39*(1+Supuestos!$B$8)^16 | F58: =B58-C58-D58-E58 | G58: =C58+D58+E58-(IF(16<=Supuestos!$J$26,Supuestos!$B$19*Supuestos!$B$26*(1+Supuestos!$B$8)^15,0)+IF(16<=Supuestos!$B$22,Supuestos!$B$20*Supuestos!$D$26*(1+Supuestos!$B$8)^15,0)) | H58: =IF(16<=Supuestos!$J$26,$C$38*$B$39*((1-Supuestos!$B$11)*(1-Supuestos!$B$12)^15)*Supuestos!$I$26*(1+Supuestos!$B$9)^15,0) | I58: =IF(16<=Supuestos!$B$22,D58*Supuestos!$K$26,0) | J58: =C58+D58+E58-H58-I58 | K58: =H58+I58-(IF(16<=Supuestos!$J$26,Supuestos!$B$19*Supuestos!$B$26*(1+Supuestos!$B$8)^15,0)+IF(16<=Supuestos!$B$22,Supuestos!$B$20*Supuestos!$D$26*(1+Supuestos!$B$8)^15,0))-H58*Supuestos!$B$21 | L58: =L57+G58 | M58: =M57+J58
A59: 17 | B59: =$E$38*$B$39*(1+Supuestos!$B$8)^17 | C59: =$F$38*$B$39*(1+Supuestos!$B$8)^17*((1-Supuestos!$B$11)*(1-Supuestos!$B$12)^16) | D59: =$G$38*$B$39*(1+Supuestos!$B$8)^17*(1-Supuestos!$B$13)^17*Supuestos!$B$10 | E59: =$H$38*$B$39*(1+Supuestos!$B$8)^17 | F59: =B59-C59-D59-E59 | G59: =C59+D59+E59-(IF(17<=Supuestos!$J$26,Supuestos!$B$19*Supuestos!$B$26*(1+Supuestos!$B$8)^16,0)+IF(17<=Supuestos!$B$22,Supuestos!$B$20*Supuestos!$D$26*(1+Supuestos!$B$8)^16,0)) | H59: =IF(17<=Supuestos!$J$26,$C$38*$B$39*((1-Supuestos!$B$11)*(1-Supuestos!$B$12)^16)*Supuestos!$I$26*(1+Supuestos!$B$9)^16,0) | I59: =IF(17<=Supuestos!$B$22,D59*Supuestos!$K$26,0) | J59: =C59+D59+E59-H59-I59 | K59: =H59+I59-(IF(17<=Supuestos!$J$26,Supuestos!$B$19*Supuestos!$B$26*(1+Supuestos!$B$8)^16,0)+IF(17<=Supuestos!$B$22,Supuestos!$B$20*Supuestos!$D$26*(1+Supuestos!$B$8)^16,0))-H59*Supuestos!$B$21 | L59: =L58+G59 | M59: =M58+J59
A60: 18 | B60: =$E$38*$B$39*(1+Supuestos!$B$8)^18 | C60: =$F$38*$B$39*(1+Supuestos!$B$8)^18*((1-Supuestos!$B$11)*(1-Supuestos!$B$12)^17) | D60: =$G$38*$B$39*(1+Supuestos!$B$8)^18*(1-Supuestos!$B$13)^18*Supuestos!$B$10 | E60: =$H$38*$B$39*(1+Supuestos!$B$8)^18 | F60: =B60-C60-D60-E60 | G60: =C60+D60+E60-(IF(18<=Supuestos!$J$26,Supuestos!$B$19*Supuestos!$B$26*(1+Supuestos!$B$8)^17,0)+IF(18<=Supuestos!$B$22,Supuestos!$B$20*Supuestos!$D$26*(1+Supuestos!$B$8)^17,0)) | H60: =IF(18<=Supuestos!$J$26,$C$38*$B$39*((1-Supuestos!$B$11)*(1-Supuestos!$B$12)^17)*Supuestos!$I$26*(1+Supuestos!$B$9)^17,0) | I60: =IF(18<=Supuestos!$B$22,D60*Supuestos!$K$26,0) | J60: =C60+D60+E60-H60-I60 | K60: =H60+I60-(IF(18<=Supuestos!$J$26,Supuestos!$B$19*Supuestos!$B$26*(1+Supuestos!$B$8)^17,0)+IF(18<=Supuestos!$B$22,Supuestos!$B$20*Supuestos!$D$26*(1+Supuestos!$B$8)^17,0))-H60*Supuestos!$B$21 | L60: =L59+G60 | M60: =M59+J60
A61: 19 | B61: =$E$38*$B$39*(1+Supuestos!$B$8)^19 | C61: =$F$38*$B$39*(1+Supuestos!$B$8)^19*((1-Supuestos!$B$11)*(1-Supuestos!$B$12)^18) | D61: =$G$38*$B$39*(1+Supuestos!$B$8)^19*(1-Supuestos!$B$13)^19*Supuestos!$B$10 | E61: =$H$38*$B$39*(1+Supuestos!$B$8)^19 | F61: =B61-C61-D61-E61 | G61: =C61+D61+E61-(IF(19<=Supuestos!$J$26,Supuestos!$B$19*Supuestos!$B$26*(1+Supuestos!$B$8)^18,0)+IF(19<=Supuestos!$B$22,Supuestos!$B$20*Supuestos!$D$26*(1+Supuestos!$B$8)^18,0)) | H61: =IF(19<=Supuestos!$J$26,$C$38*$B$39*((1-Supuestos!$B$11)*(1-Supuestos!$B$12)^18)*Supuestos!$I$26*(1+Supuestos!$B$9)^18,0) | I61: =IF(19<=Supuestos!$B$22,D61*Supuestos!$K$26,0) | J61: =C61+D61+E61-H61-I61 | K61: =H61+I61-(IF(19<=Supuestos!$J$26,Supuestos!$B$19*Supuestos!$B$26*(1+Supuestos!$B$8)^18,0)+IF(19<=Supuestos!$B$22,Supuestos!$B$20*Supuestos!$D$26*(1+Supuestos!$B$8)^18,0))-H61*Supuestos!$B$21 | L61: =L60+G61 | M61: =M60+J61
A62: 20 | B62: =$E$38*$B$39*(1+Supuestos!$B$8)^20 | C62: =$F$38*$B$39*(1+Supuestos!$B$8)^20*((1-Supuestos!$B$11)*(1-Supuestos!$B$12)^19) | D62: =$G$38*$B$39*(1+Supuestos!$B$8)^20*(1-Supuestos!$B$13)^20*Supuestos!$B$10 | E62: =$H$38*$B$39*(1+Supuestos!$B$8)^20 | F62: =B62-C62-D62-E62 | G62: =C62+D62+E62-(IF(20<=Supuestos!$J$26,Supuestos!$B$19*Supuestos!$B$26*(1+Supuestos!$B$8)^19,0)+IF(20<=Supuestos!$B$22,Supuestos!$B$20*Supuestos!$D$26*(1+Supuestos!$B$8)^19,0)) | H62: =IF(20<=Supuestos!$J$26,$C$38*$B$39*((1-Supuestos!$B$11)*(1-Supuestos!$B$12)^19)*Supuestos!$I$26*(1+Supuestos!$B$9)^19,0) | I62: =IF(20<=Supuestos!$B$22,D62*Supuestos!$K$26,0) | J62: =C62+D62+E62-H62-I62 | K62: =H62+I62-(IF(20<=Supuestos!$J$26,Supuestos!$B$19*Supuestos!$B$26*(1+Supuestos!$B$8)^19,0)+IF(20<=Supuestos!$B$22,Supuestos!$B$20*Supuestos!$D$26*(1+Supuestos!$B$8)^19,0))-H62*Supuestos!$B$21 | L62: =L61+G62 | M62: =M61+J62
A64: TIR compra (proyecto): | B64: =IRR(G42:G62) | C64: VPN compra @WACC: | D64: =G42+NPV(Supuestos!$B$7,G43:G62)
A65: TIR financiador: | B65: =IRR(K42:K62) | C65: VPN cliente PPA @WACC: | D65: =NPV(Supuestos!$B$7,J43:J62)
A66: Acumulado cliente PPA 20a: | B66: =SUM(J43:J62) | C66: Acumulado compra 20a: | D66: =SUM(G42:G62)
A68: 5. POR QUÉ ESTE DIMENSIONAMIENTO ES ÓPTIMO
A69: • PV 291 kWp — generador exento <0.7 MW (medición neta, sin permiso CNE). En BCS la generación solar cae en intermedio → recorta energía intermedia; no genera en punta, por lo que el BESS es la palanca de demanda.
A70: • BESS 0 kW / 0 kWh — recorta el pico de punta (arbitraje carga en base, descarga en punta, topado al kWh punta del recibo).
A71: • Dimensionado al consumo (rend. inputs.json); excedentes bajo medición neta expiran en 12 meses, por eso no se sobredimensiona el PV.
A72: • PV/BESS dimensionados por **barrido de máximo NPV del cliente** (NO se topó a 0.7 MW): el óptimo cae en 291 kWp / 0 kW de BESS (sweep NPV (exento)). Más allá del punto de autoconsumo solar el excedente se valúa ~$0 y el NPV cae; el barrido compara explícitamente quedarse exento <0.7 MW vs cruzar a autoconsumo.
A73: • Corrección de factor de potencia incluida — palanca separada, capacitores a cargo del financiador en el esquema PPA (el cliente conserva 100% del ahorro FP).
A74: • LIBRO 100% EN VIVO: motor mensual §3 = fórmulas sobre los datos del recibo (§6) y Supuestos (réplica exacta del motor determinista, verificada al peso) — edita kWp/BESS/FC/tarifas o cualquier mes y TODO recalcula hasta la TIR.
A78: 6. DATOS DEL RECIBO (editables — el motor mensual §3 se alimenta de aquí)
A79: Mes | B79: Días | C79: kWh B | D79: kWh I | E79: kWh P | F79: kW B | G79: kW I | H79: kW P | I79: FP % | J79: Gen B $ | K79: Gen I $ | L79: Gen P $ | M79: Distribución $ | N79: Capacidad $ | O79: Otros vol $ | P79: Suministro $ | Q79: 2%BT+FP neto $ | R79: Cargo FP $ | S79: Yield kWh/kWp | T79: Hrs punta | U79: Días punta | V79: kWh tot | W79: Vol $/kWh | X79: Tarifa B $/kWh | Y79: Tarifa I $/kWh | Z79: Tarifa P $/kWh | AA79: Umbral kW | AB79: $/kW cap
A80: Abr-25 | B80: 30 | C80: 7498 | D80: 31967 | E80: 14345 | F80: 0 | G80: 96 | H80: 93 | I80: 99.42 | J80: 15358.15 | K80: 84945.91 | L80: 54883.97 | M80: 8854.1 | N80: 27402.07 | O80: 10417.62 | P80: 782.9 | Q80: -907.86 | R80: 0 | S80: 173.28 | T80: 10 | U80: 22 | V80: =C80+D80+E80 | W80: =O80/V80 | X80: =IF(C80=0,Y80,J80/C80+W80) | Y80: =IF(D80=0,0,K80/D80+W80) | Z80: =IF(E80=0,0,L80/E80+W80) | AA80: =V80/(B80*24*$L$6) | AB80: =IFERROR(N80/MIN(H80,AA80),0)
A81: May-25 | B81: 31 | C81: 0 | D81: 38936 | E81: 17178 | F81: 0 | G81: 94 | H81: 93 | I81: 99.23 | J81: 0 | K81: 103464.63 | L81: 65723.03 | M81: 8822.84 | N81: 25697.76 | O81: 10863.66 | P81: 782.9 | Q81: -745.12 | R81: 0 | S81: 178.064 | T81: 10 | U81: 21 | V81: =C81+D81+E81 | W81: =O81/V81 | X81: =IF(C81=0,Y81,J81/C81+W81) | Y81: =IF(D81=0,0,K81/D81+W81) | Z81: =IF(E81=0,0,L81/E81+W81) | AA81: =V81/(B81*24*$L$6) | AB81: =IFERROR(N81/MIN(H81,AA81),0)
A82: Jun-25 | B82: 30 | C82: 0 | D82: 40421 | E82: 18650 | F82: 0 | G82: 117 | H82: 103 | I82: 98.63 | J82: 0 | K82: 109961.29 | L82: 73050.19 | M82: 10981.62 | N82: 29136.64 | O82: 11436.16 | P82: 782.9 | Q82: -574.25 | R82: 0 | S82: 183.12 | T82: 10 | U82: 21 | V82: =C82+D82+E82 | W82: =O82/V82 | X82: =IF(C82=0,Y82,J82/C82+W82) | Y82: =IF(D82=0,0,K82/D82+W82) | Z82: =IF(E82=0,0,L82/E82+W82) | AA82: =V82/(B82*24*$L$6) | AB82: =IFERROR(N82/MIN(H82,AA82),0)
A83: Jul-25 | B83: 31 | C83: 0 | D83: 47232 | E83: 22853 | F83: 0 | G83: 125 | H83: 140 | I83: 97.23 | J83: 0 | K83: 130417 | L83: 90854.39 | M83: 13140.4 | N83: 40196.8 | O83: 13568.46 | P83: 782.9 | Q83: 179.16 | R83: 0 | S83: 164.672 | T83: 10 | U83: 23 | V83: =C83+D83+E83 | W83: =O83/V83 | X83: =IF(C83=0,Y83,J83/C83+W83) | Y83: =IF(D83=0,0,K83/D83+W83) | Z83: =IF(E83=0,0,L83/E83+W83) | AA83: =V83/(B83*24*$L$6) | AB83: =IFERROR(N83/MIN(H83,AA83),0)
A84: Ago-25 | B84: 31 | C84: 0 | D84: 50015 | E84: 22650 | F84: 0 | G84: 150 | H84: 137 | I84: 96.81 | J84: 0 | K84: 138291.48 | L84: 90171.92 | M84: 14079 | N84: 39390.24 | O84: 14067.95 | P84: 782.9 | Q84: 486.73 | R84: 0 | S84: 161.448 | T84: 10 | U84: 21 | V84: =C84+D84+E84 | W84: =O84/V84 | X84: =IF(C84=0,Y84,J84/C84+W84) | Y84: =IF(D84=0,0,K84/D84+W84) | Z84: =IF(E84=0,0,L84/E84+W84) | AA84: =V84/(B84*24*$L$6) | AB84: =IFERROR(N84/MIN(H84,AA84),0)
A85: Sep-25 | B85: 30 | C85: 0 | D85: 45307 | E85: 21062 | F85: 0 | G85: 152 | H85: 152 | I85: 97.86 | J85: 0 | K85: 124132.12 | L85: 83083.27 | M85: 14266.72 | N85: 43303.28 | O85: 13121.15 | P85: 782.9 | Q85: -111.47 | R85: 0 | S85: 153.12 | T85: 10 | U85: 21 | V85: =C85+D85+E85 | W85: =O85/V85 | X85: =IF(C85=0,Y85,J85/C85+W85) | Y85: =IF(D85=0,0,K85/D85+W85) | Z85: =IF(E85=0,0,L85/E85+W85) | AA85: =V85/(B85*24*$L$6) | AB85: =IFERROR(N85/MIN(H85,AA85),0)
A86: Oct-25 | B86: 31 | C86: 10092 | D86: 39156 | E86: 18098 | F86: 105 | G86: 92 | H86: 0 | I86: 88.73 | J86: 21313.29 | K86: 107279.61 | L86: 71392.99 | M86: 12504.73 | N86: 40216.77 | O86: 13314.3 | P86: 782.9 | Q86: 2437.83 | R86: 0 | S86: 162.936 | T86: 10 | U86: 23 | V86: =C86+D86+E86 | W86: =O86/V86 | X86: =IF(C86=0,Y86,J86/C86+W86) | Y86: =IF(D86=0,0,K86/D86+W86) | Z86: =IF(E86=0,0,L86/E86+W86) | AA86: =V86/(B86*24*$L$6) | AB86: =IFERROR(N86/MIN(H86,AA86),0)
A87: Nov-25 | B87: 30 | C87: 51142 | D87: 8866 | E87: 0 | F87: 143 | G87: 121 | H87: 0 | I87: 88.51 | J87: 104764.39 | K87: 23561.4 | L87: 0 | M87: 13421.98 | N87: 40621.98 | O87: 11863.59 | P87: 782.9 | Q87: 5889.49 | R87: 1989.17 | S87: 145.44 | T87: 0 | U87: 19 | V87: =C87+D87+E87 | W87: =O87/V87 | X87: =IF(C87=0,Y87,J87/C87+W87) | Y87: =IF(D87=0,0,K87/D87+W87) | Z87: =IF(E87=0,0,L87/E87+W87) | AA87: =V87/(B87*24*$L$6) | AB87: =IFERROR(N87/MIN(H87,AA87),0)
A88: Dic-25 | B88: 31 | C88: 47858 | D88: 8458 | E88: 0 | F88: 110 | G88: 101 | H88: 0 | I88: 89.21 | J88: 93136.45 | K88: 21353.91 | L88: 0 | M88: 10324.6 | N88: 34916.49 | O88: 11133.66 | P88: 782.9 | Q88: 4308.36 | R88: 875.4 | S88: 129.704 | T88: 0 | U88: 22 | V88: =C88+D88+E88 | W88: =O88/V88 | X88: =IF(C88=0,Y88,J88/C88+W88) | Y88: =IF(D88=0,0,K88/D88+W88) | Z88: =IF(E88=0,0,L88/E88+W88) | AA88: =V88/(B88*24*$L$6) | AB88: =IFERROR(N88/MIN(H88,AA88),0)
A89: Ene-26 | B89: 31 | C89: 46347 | D89: 8113 | E89: 0 | F89: 98 | G89: 101 | H89: 0 | I89: 89.37 | J89: 88165.9 | K89: 20021.26 | L89: 0 | M89: 9091.01 | N89: 33103.98 | O89: 10597.91 | P89: 414.9 | Q89: 3886.39 | R89: 658.49 | S89: 139.872 | T89: 0 | U89: 21 | V89: =C89+D89+E89 | W89: =O89/V89 | X89: =IF(C89=0,Y89,J89/C89+W89) | Y89: =IF(D89=0,0,K89/D89+W89) | Z89: =IF(E89=0,0,L89/E89+W89) | AA89: =V89/(B89*24*$L$6) | AB89: =IFERROR(N89/MIN(H89,AA89),0)
A90: Feb-26 | B90: 28 | C90: 43043 | D90: 7657 | E90: 0 | F90: 121 | G90: 101 | H90: 0 | I90: 88.94 | J90: 81928.05 | K90: 18907.43 | L90: 0 | M90: 10891.21 | N90: 34150.41 | O90: 9866.22 | P90: 414.9 | Q90: 4238.13 | R90: 1114.97 | S90: 140.672 | T90: 0 | U90: 19 | V90: =C90+D90+E90 | W90: =O90/V90 | X90: =IF(C90=0,Y90,J90/C90+W90) | Y90: =IF(D90=0,0,K90/D90+W90) | Z90: =IF(E90=0,0,L90/E90+W90) | AA90: =V90/(B90*24*$L$6) | AB90: =IFERROR(N90/MIN(H90,AA90),0)
A91: Mar-26 | B91: 31 | C91: 47776 | D91: 8409 | E91: 0 | F91: 98 | G91: 95 | H91: 0 | I91: 88.28 | J91: 90989.39 | K91: 20776.96 | L91: 0 | M91: 8820.98 | N91: 34170.36 | O91: 10933.6 | P91: 414.9 | Q91: 5355.26 | R91: 2033.14 | S91: 179.304 | T91: 0 | U91: 21 | V91: =C91+D91+E91 | W91: =O91/V91 | X91: =IF(C91=0,Y91,J91/C91+W91) | Y91: =IF(D91=0,0,K91/D91+W91) | Z91: =IF(E91=0,0,L91/E91+W91) | AA91: =V91/(B91*24*$L$6) | AB91: =IFERROR(N91/MIN(H91,AA91),0)
A92: Filas = recibo ancla (parseado) + meses reconstruidos del CONSUMO HISTÓRICO (subtotal al peso; split TOU por shares del ancla). Capacidad a MIN(kW punta, umbral); tarifas por banda = concepto/kWh + vol/kWh; col Q<0 (bonificación FP) aplica claw-back al ahorro. Válido <700 kWp (medición neta). Excedentes PV a $0.
O94: Techo — referencia satelital (ruta HelioScope; cruz roja = punto verificado) · confianza ?

Sheet Fairfield Inn Vallejo (F-159
A1: Fairfield Inn Vallejo (F/1596) — Memoria de cálculo y propuesta energética
A2: RPU 573170411137 · GDMTH SIN · Demanda contratada 608 kW · 12 meses de recibo
A3: Régimen: GENERADOR EXENTO — Medición Neta (sin permiso; Art. 30 LSE; RES/142/2017)
A5: PARÁMETROS (desde Supuestos — edítalos ahí)
A6: PV kWp | B6: =Supuestos!$B$27 | C6: BESS kW | D6: =Supuestos!$C$27 | E6: BESS kWh | F6: =Supuestos!$D$27 | G6: FP corrección | H6: =Supuestos!$E$27 | I6: Entrega útil kWh | J6: =Supuestos!$D$27*Supuestos!$B$17*SQRT(Supuestos!$B$18) | K6: FC umbral | L6: 0.57
A8: 1. ESTRUCTURA DE COSTO Y AHORRO (pre-IVA, año base · fórmulas vivas ← §3)
A9: Concepto | B9: $ / año | C9: Nota
A10: Tarifa Actual (CFE pleno, sin proyecto) | B10: =$E$38*$B$39 | C10: Σ recibos × anualización
A11: (−) Ahorro PV (energía + demanda) | B11: =$F$38*$B$39 | C11: intermedio + umbral
A12: (−) Ahorro BESS (punta + arbitraje) | B12: =$G$38*$B$39 | C12: recorte punta + arbitraje (incl. claw)
A13: (−) Ahorro FP (corrección) | B13: =$H$38*$B$39 | C13: multa factor de potencia
A14: (=) Costo neto con proyecto | B14: =B10-B11-B12-B13
A15: Ahorro proyecto / año | B15: =B11+B12+B13
A16: Ahorro % | B16: =B15/B10
A18: 2. CAPEX (fórmulas vivas desde Supuestos)
A19: CAPEX PV | B19: =Supuestos!$B$27*1000*Supuestos!$F$27*Supuestos!$B$5
A20: CAPEX BESS | B20: =Supuestos!$D$27*Supuestos!$G$27*Supuestos!$B$5
A21: CAPEX capacitor (FP) | B21: =Supuestos!$H$27
A22: CAPEX TOTAL | B22: =B19+B20+B21
A24: 3. RESUMEN MENSUAL — Tarifa Actual vs Con Proyecto (fórmulas vivas ← §6 y Supuestos)
A25: Mes | B25: kWh Consumo | C25: Gen PV kWh | D25: BESS desc kWh | E25: Tarifa Actual $ | F25: Ah PV $ | G25: Ah BESS $ | H25: Ah FP $ | I25: Costo c/proy $ | J25: Ahorro $ | K25: Ahorro %
A26: =A80 | B26: =V80 | C26: =Supuestos!$B$27*S80 | D26: =MIN($J$6*U80,E80) | E26: =SUM(J80:Q80) | F26: =(MIN(C26,D80)*Y80+(MIN(H80,AA80)-MIN(H80,(V80-MIN(C26,D80))/($B$80*24*$L$6)))*AB80)*IF(Q80<0,1+Q80/SUM(J80:P80),1) | G26: =((MIN(H80,(V80-MIN(C26,D80))/($B$80*24*$L$6))-MIN(MAX(H80-MIN(Supuestos!$C$27,IF(T80>0,$J$6/T80,0)),0),(V80-MIN(C26,D80))/($B$80*24*$L$6)))*AB80+D26*Z80-D26/Supuestos!$B$18*X80)*IF(Q80<0,1+Q80/SUM(J80:P80),1) | H26: =IF(Supuestos!$E$27="Sí",R80,0) | I26: =E26-J26 | J26: =F26+G26+H26 | K26: =J26/E26
A27: =A81 | B27: =V81 | C27: =Supuestos!$B$27*S81 | D27: =MIN($J$6*U81,E81) | E27: =SUM(J81:Q81) | F27: =(MIN(C27,D81)*Y81+(MIN(H81,AA81)-MIN(H81,(V81-MIN(C27,D81))/($B$81*24*$L$6)))*AB81)*IF(Q81<0,1+Q81/SUM(J81:P81),1) | G27: =((MIN(H81,(V81-MIN(C27,D81))/($B$81*24*$L$6))-MIN(MAX(H81-MIN(Supuestos!$C$27,IF(T81>0,$J$6/T81,0)),0),(V81-MIN(C27,D81))/($B$81*24*$L$6)))*AB81+D27*Z81-D27/Supuestos!$B$18*X81)*IF(Q81<0,1+Q81/SUM(J81:P81),1) | H27: =IF(Supuestos!$E$27="Sí",R81,0) | I27: =E27-J27 | J27: =F27+G27+H27 | K27: =J27/E27
A28: =A82 | B28: =V82 | C28: =Supuestos!$B$27*S82 | D28: =MIN($J$6*U82,E82) | E28: =SUM(J82:Q82) | F28: =(MIN(C28,D82)*Y82+(MIN(H82,AA82)-MIN(H82,(V82-MIN(C28,D82))/($B$82*24*$L$6)))*AB82)*IF(Q82<0,1+Q82/SUM(J82:P82),1) | G28: =((MIN(H82,(V82-MIN(C28,D82))/($B$82*24*$L$6))-MIN(MAX(H82-MIN(Supuestos!$C$27,IF(T82>0,$J$6/T82,0)),0),(V82-MIN(C28,D82))/($B$82*24*$L$6)))*AB82+D28*Z82-D28/Supuestos!$B$18*X82)*IF(Q82<0,1+Q82/SUM(J82:P82),1) | H28: =IF(Supuestos!$E$27="Sí",R82,0) | I28: =E28-J28 | J28: =F28+G28+H28 | K28: =J28/E28
A29: =A83 | B29: =V83 | C29: =Supuestos!$B$27*S83 | D29: =MIN($J$6*U83,E83) | E29: =SUM(J83:Q83) | F29: =(MIN(C29,D83)*Y83+(MIN(H83,AA83)-MIN(H83,(V83-MIN(C29,D83))/($B$83*24*$L$6)))*AB83)*IF(Q83<0,1+Q83/SUM(J83:P83),1) | G29: =((MIN(H83,(V83-MIN(C29,D83))/($B$83*24*$L$6))-MIN(MAX(H83-MIN(Supuestos!$C$27,IF(T83>0,$J$6/T83,0)),0),(V83-MIN(C29,D83))/($B$83*24*$L$6)))*AB83+D29*Z83-D29/Supuestos!$B$18*X83)*IF(Q83<0,1+Q83/SUM(J83:P83),1) | H29: =IF(Supuestos!$E$27="Sí",R83,0) | I29: =E29-J29 | J29: =F29+G29+H29 | K29: =J29/E29
A30: =A84 | B30: =V84 | C30: =Supuestos!$B$27*S84 | D30: =MIN($J$6*U84,E84) | E30: =SUM(J84:Q84) | F30: =(MIN(C30,D84)*Y84+(MIN(H84,AA84)-MIN(H84,(V84-MIN(C30,D84))/($B$84*24*$L$6)))*AB84)*IF(Q84<0,1+Q84/SUM(J84:P84),1) | G30: =((MIN(H84,(V84-MIN(C30,D84))/($B$84*24*$L$6))-MIN(MAX(H84-MIN(Supuestos!$C$27,IF(T84>0,$J$6/T84,0)),0),(V84-MIN(C30,D84))/($B$84*24*$L$6)))*AB84+D30*Z84-D30/Supuestos!$B$18*X84)*IF(Q84<0,1+Q84/SUM(J84:P84),1) | H30: =IF(Supuestos!$E$27="Sí",R84,0) | I30: =E30-J30 | J30: =F30+G30+H30 | K30: =J30/E30
A31: =A85 | B31: =V85 | C31: =Supuestos!$B$27*S85 | D31: =MIN($J$6*U85,E85) | E31: =SUM(J85:Q85) | F31: =(MIN(C31,D85)*Y85+(MIN(H85,AA85)-MIN(H85,(V85-MIN(C31,D85))/($B$85*24*$L$6)))*AB85)*IF(Q85<0,1+Q85/SUM(J85:P85),1) | G31: =((MIN(H85,(V85-MIN(C31,D85))/($B$85*24*$L$6))-MIN(MAX(H85-MIN(Supuestos!$C$27,IF(T85>0,$J$6/T85,0)),0),(V85-MIN(C31,D85))/($B$85*24*$L$6)))*AB85+D31*Z85-D31/Supuestos!$B$18*X85)*IF(Q85<0,1+Q85/SUM(J85:P85),1) | H31: =IF(Supuestos!$E$27="Sí",R85,0) | I31: =E31-J31 | J31: =F31+G31+H31 | K31: =J31/E31
A32: =A86 | B32: =V86 | C32: =Supuestos!$B$27*S86 | D32: =MIN($J$6*U86,E86) | E32: =SUM(J86:Q86) | F32: =(MIN(C32,D86)*Y86+(MIN(H86,AA86)-MIN(H86,(V86-MIN(C32,D86))/($B$86*24*$L$6)))*AB86)*IF(Q86<0,1+Q86/SUM(J86:P86),1) | G32: =((MIN(H86,(V86-MIN(C32,D86))/($B$86*24*$L$6))-MIN(MAX(H86-MIN(Supuestos!$C$27,IF(T86>0,$J$6/T86,0)),0),(V86-MIN(C32,D86))/($B$86*24*$L$6)))*AB86+D32*Z86-D32/Supuestos!$B$18*X86)*IF(Q86<0,1+Q86/SUM(J86:P86),1) | H32: =IF(Supuestos!$E$27="Sí",R86,0) | I32: =E32-J32 | J32: =F32+G32+H32 | K32: =J32/E32
A33: =A87 | B33: =V87 | C33: =Supuestos!$B$27*S87 | D33: =MIN($J$6*U87,E87) | E33: =SUM(J87:Q87) | F33: =(MIN(C33,D87)*Y87+(MIN(H87,AA87)-MIN(H87,(V87-MIN(C33,D87))/($B$87*24*$L$6)))*AB87)*IF(Q87<0,1+Q87/SUM(J87:P87),1) | G33: =((MIN(H87,(V87-MIN(C33,D87))/($B$87*24*$L$6))-MIN(MAX(H87-MIN(Supuestos!$C$27,IF(T87>0,$J$6/T87,0)),0),(V87-MIN(C33,D87))/($B$87*24*$L$6)))*AB87+D33*Z87-D33/Supuestos!$B$18*X87)*IF(Q87<0,1+Q87/SUM(J87:P87),1) | H33: =IF(Supuestos!$E$27="Sí",R87,0) | I33: =E33-J33 | J33: =F33+G33+H33 | K33: =J33/E33
A34: =A88 | B34: =V88 | C34: =Supuestos!$B$27*S88 | D34: =MIN($J$6*U88,E88) | E34: =SUM(J88:Q88) | F34: =(MIN(C34,D88)*Y88+(MIN(H88,AA88)-MIN(H88,(V88-MIN(C34,D88))/($B$88*24*$L$6)))*AB88)*IF(Q88<0,1+Q88/SUM(J88:P88),1) | G34: =((MIN(H88,(V88-MIN(C34,D88))/($B$88*24*$L$6))-MIN(MAX(H88-MIN(Supuestos!$C$27,IF(T88>0,$J$6/T88,0)),0),(V88-MIN(C34,D88))/($B$88*24*$L$6)))*AB88+D34*Z88-D34/Supuestos!$B$18*X88)*IF(Q88<0,1+Q88/SUM(J88:P88),1) | H34: =IF(Supuestos!$E$27="Sí",R88,0) | I34: =E34-J34 | J34: =F34+G34+H34 | K34: =J34/E34
A35: =A89 | B35: =V89 | C35: =Supuestos!$B$27*S89 | D35: =MIN($J$6*U89,E89) | E35: =SUM(J89:Q89) | F35: =(MIN(C35,D89)*Y89+(MIN(H89,AA89)-MIN(H89,(V89-MIN(C35,D89))/($B$89*24*$L$6)))*AB89)*IF(Q89<0,1+Q89/SUM(J89:P89),1) | G35: =((MIN(H89,(V89-MIN(C35,D89))/($B$89*24*$L$6))-MIN(MAX(H89-MIN(Supuestos!$C$27,IF(T89>0,$J$6/T89,0)),0),(V89-MIN(C35,D89))/($B$89*24*$L$6)))*AB89+D35*Z89-D35/Supuestos!$B$18*X89)*IF(Q89<0,1+Q89/SUM(J89:P89),1) | H35: =IF(Supuestos!$E$27="Sí",R89,0) | I35: =E35-J35 | J35: =F35+G35+H35 | K35: =J35/E35
A36: =A90 | B36: =V90 | C36: =Supuestos!$B$27*S90 | D36: =MIN($J$6*U90,E90) | E36: =SUM(J90:Q90) | F36: =(MIN(C36,D90)*Y90+(MIN(H90,AA90)-MIN(H90,(V90-MIN(C36,D90))/($B$90*24*$L$6)))*AB90)*IF(Q90<0,1+Q90/SUM(J90:P90),1) | G36: =((MIN(H90,(V90-MIN(C36,D90))/($B$90*24*$L$6))-MIN(MAX(H90-MIN(Supuestos!$C$27,IF(T90>0,$J$6/T90,0)),0),(V90-MIN(C36,D90))/($B$90*24*$L$6)))*AB90+D36*Z90-D36/Supuestos!$B$18*X90)*IF(Q90<0,1+Q90/SUM(J90:P90),1) | H36: =IF(Supuestos!$E$27="Sí",R90,0) | I36: =E36-J36 | J36: =F36+G36+H36 | K36: =J36/E36
A37: =A91 | B37: =V91 | C37: =Supuestos!$B$27*S91 | D37: =MIN($J$6*U91,E91) | E37: =SUM(J91:Q91) | F37: =(MIN(C37,D91)*Y91+(MIN(H91,AA91)-MIN(H91,(V91-MIN(C37,D91))/($B$91*24*$L$6)))*AB91)*IF(Q91<0,1+Q91/SUM(J91:P91),1) | G37: =((MIN(H91,(V91-MIN(C37,D91))/($B$91*24*$L$6))-MIN(MAX(H91-MIN(Supuestos!$C$27,IF(T91>0,$J$6/T91,0)),0),(V91-MIN(C37,D91))/($B$91*24*$L$6)))*AB91+D37*Z91-D37/Supuestos!$B$18*X91)*IF(Q91<0,1+Q91/SUM(J91:P91),1) | H37: =IF(Supuestos!$E$27="Sí",R91,0) | I37: =E37-J37 | J37: =F37+G37+H37 | K37: =J37/E37
A38: TOTAL | B38: =SUM(B26:B37) | C38: =SUM(C26:C37) | D38: =SUM(D26:D37) | E38: =SUM(E26:E37) | F38: =SUM(F26:F37) | G38: =SUM(G26:G37) | H38: =SUM(H26:H37) | I38: =SUM(I26:I37) | J38: =SUM(J26:J37) | K38: =J38/E38
A39: Factor anualización (12/meses): | B39: 1
A40: 4. PROYECCIÓN 20 AÑOS — Comprar vs PPA/Ahorro compartido
A41: Año | B41: Tarifa Actual $ | C41: Ah PV $ | D41: Ah BESS $ | E41: Ah FP $ | F41: Costo c/proy $ | G41: Flujo Compra $ | H41: Pago PPA $ | I41: Comisión $ | J41: Flujo Cliente PPA $ | K41: Flujo Financiador $ | L41: Acum Compra $ | M41: Acum Cliente PPA $
A42: 0 | G42: =-B22 | K42: =-B22 | L42: =G42 | M42: 0
A43: 1 | B43: =$E$38*$B$39*(1+Supuestos!$B$8)^1 | C43: =$F$38*$B$39*(1+Supuestos!$B$8)^1*((1-Supuestos!$B$11)*(1-Supuestos!$B$12)^0) | D43: =$G$38*$B$39*(1+Supuestos!$B$8)^1*(1-Supuestos!$B$13)^1*Supuestos!$B$10 | E43: =$H$38*$B$39*(1+Supuestos!$B$8)^1 | F43: =B43-C43-D43-E43 | G43: =C43+D43+E43-(IF(1<=Supuestos!$J$27,Supuestos!$B$19*Supuestos!$B$27*(1+Supuestos!$B$8)^0,0)+IF(1<=Supuestos!$B$22,Supuestos!$B$20*Supuestos!$D$27*(1+Supuestos!$B$8)^0,0)) | H43: =IF(1<=Supuestos!$J$27,$C$38*$B$39*((1-Supuestos!$B$11)*(1-Supuestos!$B$12)^0)*Supuestos!$I$27*(1+Supuestos!$B$9)^0,0) | I43: =IF(1<=Supuestos!$B$22,D43*Supuestos!$K$27,0) | J43: =C43+D43+E43-H43-I43 | K43: =H43+I43-(IF(1<=Supuestos!$J$27,Supuestos!$B$19*Supuestos!$B$27*(1+Supuestos!$B$8)^0,0)+IF(1<=Supuestos!$B$22,Supuestos!$B$20*Supuestos!$D$27*(1+Supuestos!$B$8)^0,0))-H43*Supuestos!$B$21 | L43: =L42+G43 | M43: =M42+J43
A44: 2 | B44: =$E$38*$B$39*(1+Supuestos!$B$8)^2 | C44: =$F$38*$B$39*(1+Supuestos!$B$8)^2*((1-Supuestos!$B$11)*(1-Supuestos!$B$12)^1) | D44: =$G$38*$B$39*(1+Supuestos!$B$8)^2*(1-Supuestos!$B$13)^2*Supuestos!$B$10 | E44: =$H$38*$B$39*(1+Supuestos!$B$8)^2 | F44: =B44-C44-D44-E44 | G44: =C44+D44+E44-(IF(2<=Supuestos!$J$27,Supuestos!$B$19*Supuestos!$B$27*(1+Supuestos!$B$8)^1,0)+IF(2<=Supuestos!$B$22,Supuestos!$B$20*Supuestos!$D$27*(1+Supuestos!$B$8)^1,0)) | H44: =IF(2<=Supuestos!$J$27,$C$38*$B$39*((1-Supuestos!$B$11)*(1-Supuestos!$B$12)^1)*Supuestos!$I$27*(1+Supuestos!$B$9)^1,0) | I44: =IF(2<=Supuestos!$B$22,D44*Supuestos!$K$27,0) | J44: =C44+D44+E44-H44-I44 | K44: =H44+I44-(IF(2<=Supuestos!$J$27,Supuestos!$B$19*Supuestos!$B$27*(1+Supuestos!$B$8)^1,0)+IF(2<=Supuestos!$B$22,Supuestos!$B$20*Supuestos!$D$27*(1+Supuestos!$B$8)^1,0))-H44*Supuestos!$B$21 | L44: =L43+G44 | M44: =M43+J44
A45: 3 | B45: =$E$38*$B$39*(1+Supuestos!$B$8)^3 | C45: =$F$38*$B$39*(1+Supuestos!$B$8)^3*((1-Supuestos!$B$11)*(1-Supuestos!$B$12)^2) | D45: =$G$38*$B$39*(1+Supuestos!$B$8)^3*(1-Supuestos!$B$13)^3*Supuestos!$B$10 | E45: =$H$38*$B$39*(1+Supuestos!$B$8)^3 | F45: =B45-C45-D45-E45 | G45: =C45+D45+E45-(IF(3<=Supuestos!$J$27,Supuestos!$B$19*Supuestos!$B$27*(1+Supuestos!$B$8)^2,0)+IF(3<=Supuestos!$B$22,Supuestos!$B$20*Supuestos!$D$27*(1+Supuestos!$B$8)^2,0)) | H45: =IF(3<=Supuestos!$J$27,$C$38*$B$39*((1-Supuestos!$B$11)*(1-Supuestos!$B$12)^2)*Supuestos!$I$27*(1+Supuestos!$B$9)^2,0) | I45: =IF(3<=Supuestos!$B$22,D45*Supuestos!$K$27,0) | J45: =C45+D45+E45-H45-I45 | K45: =H45+I45-(IF(3<=Supuestos!$J$27,Supuestos!$B$19*Supuestos!$B$27*(1+Supuestos!$B$8)^2,0)+IF(3<=Supuestos!$B$22,Supuestos!$B$20*Supuestos!$D$27*(1+Supuestos!$B$8)^2,0))-H45*Supuestos!$B$21 | L45: =L44+G45 | M45: =M44+J45
A46: 4 | B46: =$E$38*$B$39*(1+Supuestos!$B$8)^4 | C46: =$F$38*$B$39*(1+Supuestos!$B$8)^4*((1-Supuestos!$B$11)*(1-Supuestos!$B$12)^3) | D46: =$G$38*$B$39*(1+Supuestos!$B$8)^4*(1-Supuestos!$B$13)^4*Supuestos!$B$10 | E46: =$H$38*$B$39*(1+Supuestos!$B$8)^4 | F46: =B46-C46-D46-E46 | G46: =C46+D46+E46-(IF(4<=Supuestos!$J$27,Supuestos!$B$19*Supuestos!$B$27*(1+Supuestos!$B$8)^3,0)+IF(4<=Supuestos!$B$22,Supuestos!$B$20*Supuestos!$D$27*(1+Supuestos!$B$8)^3,0)) | H46: =IF(4<=Supuestos!$J$27,$C$38*$B$39*((1-Supuestos!$B$11)*(1-Supuestos!$B$12)^3)*Supuestos!$I$27*(1+Supuestos!$B$9)^3,0) | I46: =IF(4<=Supuestos!$B$22,D46*Supuestos!$K$27,0) | J46: =C46+D46+E46-H46-I46 | K46: =H46+I46-(IF(4<=Supuestos!$J$27,Supuestos!$B$19*Supuestos!$B$27*(1+Supuestos!$B$8)^3,0)+IF(4<=Supuestos!$B$22,Supuestos!$B$20*Supuestos!$D$27*(1+Supuestos!$B$8)^3,0))-H46*Supuestos!$B$21 | L46: =L45+G46 | M46: =M45+J46
A47: 5 | B47: =$E$38*$B$39*(1+Supuestos!$B$8)^5 | C47: =$F$38*$B$39*(1+Supuestos!$B$8)^5*((1-Supuestos!$B$11)*(1-Supuestos!$B$12)^4) | D47: =$G$38*$B$39*(1+Supuestos!$B$8)^5*(1-Supuestos!$B$13)^5*Supuestos!$B$10 | E47: =$H$38*$B$39*(1+Supuestos!$B$8)^5 | F47: =B47-C47-D47-E47 | G47: =C47+D47+E47-(IF(5<=Supuestos!$J$27,Supuestos!$B$19*Supuestos!$B$27*(1+Supuestos!$B$8)^4,0)+IF(5<=Supuestos!$B$22,Supuestos!$B$20*Supuestos!$D$27*(1+Supuestos!$B$8)^4,0)) | H47: =IF(5<=Supuestos!$J$27,$C$38*$B$39*((1-Supuestos!$B$11)*(1-Supuestos!$B$12)^4)*Supuestos!$I$27*(1+Supuestos!$B$9)^4,0) | I47: =IF(5<=Supuestos!$B$22,D47*Supuestos!$K$27,0) | J47: =C47+D47+E47-H47-I47 | K47: =H47+I47-(IF(5<=Supuestos!$J$27,Supuestos!$B$19*Supuestos!$B$27*(1+Supuestos!$B$8)^4,0)+IF(5<=Supuestos!$B$22,Supuestos!$B$20*Supuestos!$D$27*(1+Supuestos!$B$8)^4,0))-H47*Supuestos!$B$21 | L47: =L46+G47 | M47: =M46+J47
A48: 6 | B48: =$E$38*$B$39*(1+Supuestos!$B$8)^6 | C48: =$F$38*$B$39*(1+Supuestos!$B$8)^6*((1-Supuestos!$B$11)*(1-Supuestos!$B$12)^5) | D48: =$G$38*$B$39*(1+Supuestos!$B$8)^6*(1-Supuestos!$B$13)^6*Supuestos!$B$10 | E48: =$H$38*$B$39*(1+Supuestos!$B$8)^6 | F48: =B48-C48-D48-E48 | G48: =C48+D48+E48-(IF(6<=Supuestos!$J$27,Supuestos!$B$19*Supuestos!$B$27*(1+Supuestos!$B$8)^5,0)+IF(6<=Supuestos!$B$22,Supuestos!$B$20*Supuestos!$D$27*(1+Supuestos!$B$8)^5,0)) | H48: =IF(6<=Supuestos!$J$27,$C$38*$B$39*((1-Supuestos!$B$11)*(1-Supuestos!$B$12)^5)*Supuestos!$I$27*(1+Supuestos!$B$9)^5,0) | I48: =IF(6<=Supuestos!$B$22,D48*Supuestos!$K$27,0) | J48: =C48+D48+E48-H48-I48 | K48: =H48+I48-(IF(6<=Supuestos!$J$27,Supuestos!$B$19*Supuestos!$B$27*(1+Supuestos!$B$8)^5,0)+IF(6<=Supuestos!$B$22,Supuestos!$B$20*Supuestos!$D$27*(1+Supuestos!$B$8)^5,0))-H48*Supuestos!$B$21 | L48: =L47+G48 | M48: =M47+J48
A49: 7 | B49: =$E$38*$B$39*(1+Supuestos!$B$8)^7 | C49: =$F$38*$B$39*(1+Supuestos!$B$8)^7*((1-Supuestos!$B$11)*(1-Supuestos!$B$12)^6) | D49: =$G$38*$B$39*(1+Supuestos!$B$8)^7*(1-Supuestos!$B$13)^7*Supuestos!$B$10 | E49: =$H$38*$B$39*(1+Supuestos!$B$8)^7 | F49: =B49-C49-D49-E49 | G49: =C49+D49+E49-(IF(7<=Supuestos!$J$27,Supuestos!$B$19*Supuestos!$B$27*(1+Supuestos!$B$8)^6,0)+IF(7<=Supuestos!$B$22,Supuestos!$B$20*Supuestos!$D$27*(1+Supuestos!$B$8)^6,0)) | H49: =IF(7<=Supuestos!$J$27,$C$38*$B$39*((1-Supuestos!$B$11)*(1-Supuestos!$B$12)^6)*Supuestos!$I$27*(1+Supuestos!$B$9)^6,0) | I49: =IF(7<=Supuestos!$B$22,D49*Supuestos!$K$27,0) | J49: =C49+D49+E49-H49-I49 | K49: =H49+I49-(IF(7<=Supuestos!$J$27,Supuestos!$B$19*Supuestos!$B$27*(1+Supuestos!$B$8)^6,0)+IF(7<=Supuestos!$B$22,Supuestos!$B$20*Supuestos!$D$27*(1+Supuestos!$B$8)^6,0))-H49*Supuestos!$B$21 | L49: =L48+G49 | M49: =M48+J49
A50: 8 | B50: =$E$38*$B$39*(1+Supuestos!$B$8)^8 | C50: =$F$38*$B$39*(1+Supuestos!$B$8)^8*((1-Supuestos!$B$11)*(1-Supuestos!$B$12)^7) | D50: =$G$38*$B$39*(1+Supuestos!$B$8)^8*(1-Supuestos!$B$13)^8*Supuestos!$B$10 | E50: =$H$38*$B$39*(1+Supuestos!$B$8)^8 | F50: =B50-C50-D50-E50 | G50: =C50+D50+E50-(IF(8<=Supuestos!$J$27,Supuestos!$B$19*Supuestos!$B$27*(1+Supuestos!$B$8)^7,0)+IF(8<=Supuestos!$B$22,Supuestos!$B$20*Supuestos!$D$27*(1+Supuestos!$B$8)^7,0)) | H50: =IF(8<=Supuestos!$J$27,$C$38*$B$39*((1-Supuestos!$B$11)*(1-Supuestos!$B$12)^7)*Supuestos!$I$27*(1+Supuestos!$B$9)^7,0) | I50: =IF(8<=Supuestos!$B$22,D50*Supuestos!$K$27,0) | J50: =C50+D50+E50-H50-I50 | K50: =H50+I50-(IF(8<=Supuestos!$J$27,Supuestos!$B$19*Supuestos!$B$27*(1+Supuestos!$B$8)^7,0)+IF(8<=Supuestos!$B$22,Supuestos!$B$20*Supuestos!$D$27*(1+Supuestos!$B$8)^7,0))-H50*Supuestos!$B$21 | L50: =L49+G50 | M50: =M49+J50
A51: 9 | B51: =$E$38*$B$39*(1+Supuestos!$B$8)^9 | C51: =$F$38*$B$39*(1+Supuestos!$B$8)^9*((1-Supuestos!$B$11)*(1-Supuestos!$B$12)^8) | D51: =$G$38*$B$39*(1+Supuestos!$B$8)^9*(1-Supuestos!$B$13)^9*Supuestos!$B$10 | E51: =$H$38*$B$39*(1+Supuestos!$B$8)^9 | F51: =B51-C51-D51-E51 | G51: =C51+D51+E51-(IF(9<=Supuestos!$J$27,Supuestos!$B$19*Supuestos!$B$27*(1+Supuestos!$B$8)^8,0)+IF(9<=Supuestos!$B$22,Supuestos!$B$20*Supuestos!$D$27*(1+Supuestos!$B$8)^8,0)) | H51: =IF(9<=Supuestos!$J$27,$C$38*$B$39*((1-Supuestos!$B$11)*(1-Supuestos!$B$12)^8)*Supuestos!$I$27*(1+Supuestos!$B$9)^8,0) | I51: =IF(9<=Supuestos!$B$22,D51*Supuestos!$K$27,0) | J51: =C51+D51+E51-H51-I51 | K51: =H51+I51-(IF(9<=Supuestos!$J$27,Supuestos!$B$19*Supuestos!$B$27*(1+Supuestos!$B$8)^8,0)+IF(9<=Supuestos!$B$22,Supuestos!$B$20*Supuestos!$D$27*(1+Supuestos!$B$8)^8,0))-H51*Supuestos!$B$21 | L51: =L50+G51 | M51: =M50+J51
A52: 10 | B52: =$E$38*$B$39*(1+Supuestos!$B$8)^10 | C52: =$F$38*$B$39*(1+Supuestos!$B$8)^10*((1-Supuestos!$B$11)*(1-Supuestos!$B$12)^9) | D52: =$G$38*$B$39*(1+Supuestos!$B$8)^10*(1-Supuestos!$B$13)^10*Supuestos!$B$10 | E52: =$H$38*$B$39*(1+Supuestos!$B$8)^10 | F52: =B52-C52-D52-E52 | G52: =C52+D52+E52-(IF(10<=Supuestos!$J$27,Supuestos!$B$19*Supuestos!$B$27*(1+Supuestos!$B$8)^9,0)+IF(10<=Supuestos!$B$22,Supuestos!$B$20*Supuestos!$D$27*(1+Supuestos!$B$8)^9,0)) | H52: =IF(10<=Supuestos!$J$27,$C$38*$B$39*((1-Supuestos!$B$11)*(1-Supuestos!$B$12)^9)*Supuestos!$I$27*(1+Supuestos!$B$9)^9,0) | I52: =IF(10<=Supuestos!$B$22,D52*Supuestos!$K$27,0) | J52: =C52+D52+E52-H52-I52 | K52: =H52+I52-(IF(10<=Supuestos!$J$27,Supuestos!$B$19*Supuestos!$B$27*(1+Supuestos!$B$8)^9,0)+IF(10<=Supuestos!$B$22,Supuestos!$B$20*Supuestos!$D$27*(1+Supuestos!$B$8)^9,0))-H52*Supuestos!$B$21 | L52: =L51+G52 | M52: =M51+J52
A53: 11 | B53: =$E$38*$B$39*(1+Supuestos!$B$8)^11 | C53: =$F$38*$B$39*(1+Supuestos!$B$8)^11*((1-Supuestos!$B$11)*(1-Supuestos!$B$12)^10) | D53: =$G$38*$B$39*(1+Supuestos!$B$8)^11*(1-Supuestos!$B$13)^11*Supuestos!$B$10 | E53: =$H$38*$B$39*(1+Supuestos!$B$8)^11 | F53: =B53-C53-D53-E53 | G53: =C53+D53+E53-(IF(11<=Supuestos!$J$27,Supuestos!$B$19*Supuestos!$B$27*(1+Supuestos!$B$8)^10,0)+IF(11<=Supuestos!$B$22,Supuestos!$B$20*Supuestos!$D$27*(1+Supuestos!$B$8)^10,0)) | H53: =IF(11<=Supuestos!$J$27,$C$38*$B$39*((1-Supuestos!$B$11)*(1-Supuestos!$B$12)^10)*Supuestos!$I$27*(1+Supuestos!$B$9)^10,0) | I53: =IF(11<=Supuestos!$B$22,D53*Supuestos!$K$27,0) | J53: =C53+D53+E53-H53-I53 | K53: =H53+I53-(IF(11<=Supuestos!$J$27,Supuestos!$B$19*Supuestos!$B$27*(1+Supuestos!$B$8)^10,0)+IF(11<=Supuestos!$B$22,Supuestos!$B$20*Supuestos!$D$27*(1+Supuestos!$B$8)^10,0))-H53*Supuestos!$B$21 | L53: =L52+G53 | M53: =M52+J53
A54: 12 | B54: =$E$38*$B$39*(1+Supuestos!$B$8)^12 | C54: =$F$38*$B$39*(1+Supuestos!$B$8)^12*((1-Supuestos!$B$11)*(1-Supuestos!$B$12)^11) | D54: =$G$38*$B$39*(1+Supuestos!$B$8)^12*(1-Supuestos!$B$13)^12*Supuestos!$B$10 | E54: =$H$38*$B$39*(1+Supuestos!$B$8)^12 | F54: =B54-C54-D54-E54 | G54: =C54+D54+E54-(IF(12<=Supuestos!$J$27,Supuestos!$B$19*Supuestos!$B$27*(1+Supuestos!$B$8)^11,0)+IF(12<=Supuestos!$B$22,Supuestos!$B$20*Supuestos!$D$27*(1+Supuestos!$B$8)^11,0)) | H54: =IF(12<=Supuestos!$J$27,$C$38*$B$39*((1-Supuestos!$B$11)*(1-Supuestos!$B$12)^11)*Supuestos!$I$27*(1+Supuestos!$B$9)^11,0) | I54: =IF(12<=Supuestos!$B$22,D54*Supuestos!$K$27,0) | J54: =C54+D54+E54-H54-I54 | K54: =H54+I54-(IF(12<=Supuestos!$J$27,Supuestos!$B$19*Supuestos!$B$27*(1+Supuestos!$B$8)^11,0)+IF(12<=Supuestos!$B$22,Supuestos!$B$20*Supuestos!$D$27*(1+Supuestos!$B$8)^11,0))-H54*Supuestos!$B$21 | L54: =L53+G54 | M54: =M53+J54
A55: 13 | B55: =$E$38*$B$39*(1+Supuestos!$B$8)^13 | C55: =$F$38*$B$39*(1+Supuestos!$B$8)^13*((1-Supuestos!$B$11)*(1-Supuestos!$B$12)^12) | D55: =$G$38*$B$39*(1+Supuestos!$B$8)^13*(1-Supuestos!$B$13)^13*Supuestos!$B$10 | E55: =$H$38*$B$39*(1+Supuestos!$B$8)^13 | F55: =B55-C55-D55-E55 | G55: =C55+D55+E55-(IF(13<=Supuestos!$J$27,Supuestos!$B$19*Supuestos!$B$27*(1+Supuestos!$B$8)^12,0)+IF(13<=Supuestos!$B$22,Supuestos!$B$20*Supuestos!$D$27*(1+Supuestos!$B$8)^12,0)) | H55: =IF(13<=Supuestos!$J$27,$C$38*$B$39*((1-Supuestos!$B$11)*(1-Supuestos!$B$12)^12)*Supuestos!$I$27*(1+Supuestos!$B$9)^12,0) | I55: =IF(13<=Supuestos!$B$22,D55*Supuestos!$K$27,0) | J55: =C55+D55+E55-H55-I55 | K55: =H55+I55-(IF(13<=Supuestos!$J$27,Supuestos!$B$19*Supuestos!$B$27*(1+Supuestos!$B$8)^12,0)+IF(13<=Supuestos!$B$22,Supuestos!$B$20*Supuestos!$D$27*(1+Supuestos!$B$8)^12,0))-H55*Supuestos!$B$21 | L55: =L54+G55 | M55: =M54+J55
A56: 14 | B56: =$E$38*$B$39*(1+Supuestos!$B$8)^14 | C56: =$F$38*$B$39*(1+Supuestos!$B$8)^14*((1-Supuestos!$B$11)*(1-Supuestos!$B$12)^13) | D56: =$G$38*$B$39*(1+Supuestos!$B$8)^14*(1-Supuestos!$B$13)^14*Supuestos!$B$10 | E56: =$H$38*$B$39*(1+Supuestos!$B$8)^14 | F56: =B56-C56-D56-E56 | G56: =C56+D56+E56-(IF(14<=Supuestos!$J$27,Supuestos!$B$19*Supuestos!$B$27*(1+Supuestos!$B$8)^13,0)+IF(14<=Supuestos!$B$22,Supuestos!$B$20*Supuestos!$D$27*(1+Supuestos!$B$8)^13,0)) | H56: =IF(14<=Supuestos!$J$27,$C$38*$B$39*((1-Supuestos!$B$11)*(1-Supuestos!$B$12)^13)*Supuestos!$I$27*(1+Supuestos!$B$9)^13,0) | I56: =IF(14<=Supuestos!$B$22,D56*Supuestos!$K$27,0) | J56: =C56+D56+E56-H56-I56 | K56: =H56+I56-(IF(14<=Supuestos!$J$27,Supuestos!$B$19*Supuestos!$B$27*(1+Supuestos!$B$8)^13,0)+IF(14<=Supuestos!$B$22,Supuestos!$B$20*Supuestos!$D$27*(1+Supuestos!$B$8)^13,0))-H56*Supuestos!$B$21 | L56: =L55+G56 | M56: =M55+J56
A57: 15 | B57: =$E$38*$B$39*(1+Supuestos!$B$8)^15 | C57: =$F$38*$B$39*(1+Supuestos!$B$8)^15*((1-Supuestos!$B$11)*(1-Supuestos!$B$12)^14) | D57: =$G$38*$B$39*(1+Supuestos!$B$8)^15*(1-Supuestos!$B$13)^15*Supuestos!$B$10 | E57: =$H$38*$B$39*(1+Supuestos!$B$8)^15 | F57: =B57-C57-D57-E57 | G57: =C57+D57+E57-(IF(15<=Supuestos!$J$27,Supuestos!$B$19*Supuestos!$B$27*(1+Supuestos!$B$8)^14,0)+IF(15<=Supuestos!$B$22,Supuestos!$B$20*Supuestos!$D$27*(1+Supuestos!$B$8)^14,0)) | H57: =IF(15<=Supuestos!$J$27,$C$38*$B$39*((1-Supuestos!$B$11)*(1-Supuestos!$B$12)^14)*Supuestos!$I$27*(1+Supuestos!$B$9)^14,0) | I57: =IF(15<=Supuestos!$B$22,D57*Supuestos!$K$27,0) | J57: =C57+D57+E57-H57-I57 | K57: =H57+I57-(IF(15<=Supuestos!$J$27,Supuestos!$B$19*Supuestos!$B$27*(1+Supuestos!$B$8)^14,0)+IF(15<=Supuestos!$B$22,Supuestos!$B$20*Supuestos!$D$27*(1+Supuestos!$B$8)^14,0))-H57*Supuestos!$B$21 | L57: =L56+G57 | M57: =M56+J57
A58: 16 | B58: =$E$38*$B$39*(1+Supuestos!$B$8)^16 | C58: =$F$38*$B$39*(1+Supuestos!$B$8)^16*((1-Supuestos!$B$11)*(1-Supuestos!$B$12)^15) | D58: =$G$38*$B$39*(1+Supuestos!$B$8)^16*(1-Supuestos!$B$13)^16*Supuestos!$B$10 | E58: =$H$38*$B$39*(1+Supuestos!$B$8)^16 | F58: =B58-C58-D58-E58 | G58: =C58+D58+E58-(IF(16<=Supuestos!$J$27,Supuestos!$B$19*Supuestos!$B$27*(1+Supuestos!$B$8)^15,0)+IF(16<=Supuestos!$B$22,Supuestos!$B$20*Supuestos!$D$27*(1+Supuestos!$B$8)^15,0)) | H58: =IF(16<=Supuestos!$J$27,$C$38*$B$39*((1-Supuestos!$B$11)*(1-Supuestos!$B$12)^15)*Supuestos!$I$27*(1+Supuestos!$B$9)^15,0) | I58: =IF(16<=Supuestos!$B$22,D58*Supuestos!$K$27,0) | J58: =C58+D58+E58-H58-I58 | K58: =H58+I58-(IF(16<=Supuestos!$J$27,Supuestos!$B$19*Supuestos!$B$27*(1+Supuestos!$B$8)^15,0)+IF(16<=Supuestos!$B$22,Supuestos!$B$20*Supuestos!$D$27*(1+Supuestos!$B$8)^15,0))-H58*Supuestos!$B$21 | L58: =L57+G58 | M58: =M57+J58
A59: 17 | B59: =$E$38*$B$39*(1+Supuestos!$B$8)^17 | C59: =$F$38*$B$39*(1+Supuestos!$B$8)^17*((1-Supuestos!$B$11)*(1-Supuestos!$B$12)^16) | D59: =$G$38*$B$39*(1+Supuestos!$B$8)^17*(1-Supuestos!$B$13)^17*Supuestos!$B$10 | E59: =$H$38*$B$39*(1+Supuestos!$B$8)^17 | F59: =B59-C59-D59-E59 | G59: =C59+D59+E59-(IF(17<=Supuestos!$J$27,Supuestos!$B$19*Supuestos!$B$27*(1+Supuestos!$B$8)^16,0)+IF(17<=Supuestos!$B$22,Supuestos!$B$20*Supuestos!$D$27*(1+Supuestos!$B$8)^16,0)) | H59: =IF(17<=Supuestos!$J$27,$C$38*$B$39*((1-Supuestos!$B$11)*(1-Supuestos!$B$12)^16)*Supuestos!$I$27*(1+Supuestos!$B$9)^16,0) | I59: =IF(17<=Supuestos!$B$22,D59*Supuestos!$K$27,0) | J59: =C59+D59+E59-H59-I59 | K59: =H59+I59-(IF(17<=Supuestos!$J$27,Supuestos!$B$19*Supuestos!$B$27*(1+Supuestos!$B$8)^16,0)+IF(17<=Supuestos!$B$22,Supuestos!$B$20*Supuestos!$D$27*(1+Supuestos!$B$8)^16,0))-H59*Supuestos!$B$21 | L59: =L58+G59 | M59: =M58+J59
A60: 18 | B60: =$E$38*$B$39*(1+Supuestos!$B$8)^18 | C60: =$F$38*$B$39*(1+Supuestos!$B$8)^18*((1-Supuestos!$B$11)*(1-Supuestos!$B$12)^17) | D60: =$G$38*$B$39*(1+Supuestos!$B$8)^18*(1-Supuestos!$B$13)^18*Supuestos!$B$10 | E60: =$H$38*$B$39*(1+Supuestos!$B$8)^18 | F60: =B60-C60-D60-E60 | G60: =C60+D60+E60-(IF(18<=Supuestos!$J$27,Supuestos!$B$19*Supuestos!$B$27*(1+Supuestos!$B$8)^17,0)+IF(18<=Supuestos!$B$22,Supuestos!$B$20*Supuestos!$D$27*(1+Supuestos!$B$8)^17,0)) | H60: =IF(18<=Supuestos!$J$27,$C$38*$B$39*((1-Supuestos!$B$11)*(1-Supuestos!$B$12)^17)*Supuestos!$I$27*(1+Supuestos!$B$9)^17,0) | I60: =IF(18<=Supuestos!$B$22,D60*Supuestos!$K$27,0) | J60: =C60+D60+E60-H60-I60 | K60: =H60+I60-(IF(18<=Supuestos!$J$27,Supuestos!$B$19*Supuestos!$B$27*(1+Supuestos!$B$8)^17,0)+IF(18<=Supuestos!$B$22,Supuestos!$B$20*Supuestos!$D$27*(1+Supuestos!$B$8)^17,0))-H60*Supuestos!$B$21 | L60: =L59+G60 | M60: =M59+J60
A61: 19 | B61: =$E$38*$B$39*(1+Supuestos!$B$8)^19 | C61: =$F$38*$B$39*(1+Supuestos!$B$8)^19*((1-Supuestos!$B$11)*(1-Supuestos!$B$12)^18) | D61: =$G$38*$B$39*(1+Supuestos!$B$8)^19*(1-Supuestos!$B$13)^19*Supuestos!$B$10 | E61: =$H$38*$B$39*(1+Supuestos!$B$8)^19 | F61: =B61-C61-D61-E61 | G61: =C61+D61+E61-(IF(19<=Supuestos!$J$27,Supuestos!$B$19*Supuestos!$B$27*(1+Supuestos!$B$8)^18,0)+IF(19<=Supuestos!$B$22,Supuestos!$B$20*Supuestos!$D$27*(1+Supuestos!$B$8)^18,0)) | H61: =IF(19<=Supuestos!$J$27,$C$38*$B$39*((1-Supuestos!$B$11)*(1-Supuestos!$B$12)^18)*Supuestos!$I$27*(1+Supuestos!$B$9)^18,0) | I61: =IF(19<=Supuestos!$B$22,D61*Supuestos!$K$27,0) | J61: =C61+D61+E61-H61-I61 | K61: =H61+I61-(IF(19<=Supuestos!$J$27,Supuestos!$B$19*Supuestos!$B$27*(1+Supuestos!$B$8)^18,0)+IF(19<=Supuestos!$B$22,Supuestos!$B$20*Supuestos!$D$27*(1+Supuestos!$B$8)^18,0))-H61*Supuestos!$B$21 | L61: =L60+G61 | M61: =M60+J61
A62: 20 | B62: =$E$38*$B$39*(1+Supuestos!$B$8)^20 | C62: =$F$38*$B$39*(1+Supuestos!$B$8)^20*((1-Supuestos!$B$11)*(1-Supuestos!$B$12)^19) | D62: =$G$38*$B$39*(1+Supuestos!$B$8)^20*(1-Supuestos!$B$13)^20*Supuestos!$B$10 | E62: =$H$38*$B$39*(1+Supuestos!$B$8)^20 | F62: =B62-C62-D62-E62 | G62: =C62+D62+E62-(IF(20<=Supuestos!$J$27,Supuestos!$B$19*Supuestos!$B$27*(1+Supuestos!$B$8)^19,0)+IF(20<=Supuestos!$B$22,Supuestos!$B$20*Supuestos!$D$27*(1+Supuestos!$B$8)^19,0)) | H62: =IF(20<=Supuestos!$J$27,$C$38*$B$39*((1-Supuestos!$B$11)*(1-Supuestos!$B$12)^19)*Supuestos!$I$27*(1+Supuestos!$B$9)^19,0) | I62: =IF(20<=Supuestos!$B$22,D62*Supuestos!$K$27,0) | J62: =C62+D62+E62-H62-I62 | K62: =H62+I62-(IF(20<=Supuestos!$J$27,Supuestos!$B$19*Supuestos!$B$27*(1+Supuestos!$B$8)^19,0)+IF(20<=Supuestos!$B$22,Supuestos!$B$20*Supuestos!$D$27*(1+Supuestos!$B$8)^19,0))-H62*Supuestos!$B$21 | L62: =L61+G62 | M62: =M61+J62
A64: TIR compra (proyecto): | B64: =IRR(G42:G62) | C64: VPN compra @WACC: | D64: =G42+NPV(Supuestos!$B$7,G43:G62)
A65: TIR financiador: | B65: =IRR(K42:K62) | C65: VPN cliente PPA @WACC: | D65: =NPV(Supuestos!$B$7,J43:J62)
A66: Acumulado cliente PPA 20a: | B66: =SUM(J43:J62) | C66: Acumulado compra 20a: | D66: =SUM(G42:G62)
A68: 5. POR QUÉ ESTE DIMENSIONAMIENTO ES ÓPTIMO
A69: • PV 97 kWp — generador exento <0.7 MW (medición neta, sin permiso CNE). En SIN la generación solar cae en intermedio → recorta energía intermedia; no genera en punta, por lo que el BESS es la palanca de demanda.
A70: • BESS 186 kW / 743 kWh — recorta el pico de punta (arbitraje carga en base, descarga en punta, topado al kWh punta del recibo).
A71: • Dimensionado al consumo (rend. inputs.json); excedentes bajo medición neta expiran en 12 meses, por eso no se sobredimensiona el PV.
A72: • PV/BESS dimensionados por **barrido de máximo NPV del cliente** (NO se topó a 0.7 MW): el óptimo cae en 97 kWp / 186 kW de BESS (sweep NPV (exento)). Más allá del punto de autoconsumo solar el excedente se valúa ~$0 y el NPV cae; el barrido compara explícitamente quedarse exento <0.7 MW vs cruzar a autoconsumo.
A73: • Corrección de factor de potencia incluida — palanca separada, capacitores a cargo del financiador en el esquema PPA (el cliente conserva 100% del ahorro FP).
A74: • LIBRO 100% EN VIVO: motor mensual §3 = fórmulas sobre los datos del recibo (§6) y Supuestos (réplica exacta del motor determinista, verificada al peso) — edita kWp/BESS/FC/tarifas o cualquier mes y TODO recalcula hasta la TIR.
A78: 6. DATOS DEL RECIBO (editables — el motor mensual §3 se alimenta de aquí)
A79: Mes | B79: Días | C79: kWh B | D79: kWh I | E79: kWh P | F79: kW B | G79: kW I | H79: kW P | I79: FP % | J79: Gen B $ | K79: Gen I $ | L79: Gen P $ | M79: Distribución $ | N79: Capacidad $ | O79: Otros vol $ | P79: Suministro $ | Q79: 2%BT+FP neto $ | R79: Cargo FP $ | S79: Yield kWh/kWp | T79: Hrs punta | U79: Días punta | V79: kWh tot | W79: Vol $/kWh | X79: Tarifa B $/kWh | Y79: Tarifa I $/kWh | Z79: Tarifa P $/kWh | AA79: Umbral kW | AB79: $/kW cap
A80: Abr-25 | B80: 30 | C80: 34645 | D80: 72045 | E80: 9340 | F80: 222 | G80: 239 | H80: 215 | I80: 90.37 | J80: 33997.14 | K80: 125977.89 | L80: 19421.59 | M80: 21656.16 | N80: 93013.3 | O80: 22463.41 | P80: 563.57 | Q80: -317.09 | R80: 0 | S80: 150.72 | T80: 2 | U80: 22 | V80: =C80+D80+E80 | W80: =O80/V80 | X80: =IF(C80=0,Y80,J80/C80+W80) | Y80: =IF(D80=0,0,K80/D80+W80) | Z80: =IF(E80=0,0,L80/E80+W80) | AA80: =V80/(B80*24*$L$6) | AB80: =IFERROR(N80/MIN(H80,AA80),0)
A81: May-25 | B81: 31 | C81: 38237 | D81: 77568 | E81: 7295 | F81: 229 | G81: 241 | H81: 227 | I81: 89.37 | J81: 37521.97 | K81: 135635.4 | L81: 15169.22 | M81: 21959.92 | N81: 98204.74 | O81: 23832.16 | P81: 563.57 | Q81: 1331.55 | R81: 1331.55 | S81: 143.096 | T81: 2 | U81: 21 | V81: =C81+D81+E81 | W81: =O81/V81 | X81: =IF(C81=0,Y81,J81/C81+W81) | Y81: =IF(D81=0,0,K81/D81+W81) | Z81: =IF(E81=0,0,L81/E81+W81) | AA81: =V81/(B81*24*$L$6) | AB81: =IFERROR(N81/MIN(H81,AA81),0)
A82: Jun-25 | B82: 30 | C82: 32096 | D82: 61945 | E82: 5938 | F82: 210 | G82: 232 | H82: 195 | I82: 91.16 | J82: 32246.85 | K82: 110887.74 | L82: 12640.81 | M82: 21139.84 | N82: 86365.5 | O82: 19355.94 | P82: 563.57 | Q82: -849.6 | R82: 0 | S82: 133.92 | T82: 2 | U82: 21 | V82: =C82+D82+E82 | W82: =O82/V82 | X82: =IF(C82=0,Y82,J82/C82+W82) | Y82: =IF(D82=0,0,K82/D82+W82) | Z82: =IF(E82=0,0,L82/E82+W82) | AA82: =V82/(B82*24*$L$6) | AB82: =IFERROR(N82/MIN(H82,AA82),0)
A83: Jul-25 | B83: 31 | C83: 28818 | D83: 65053 | E83: 6374 | F83: 180 | G83: 199 | H83: 165 | I83: 91.11 | J83: 29385.71 | K83: 118201.3 | L83: 13772.94 | M83: 18132.88 | N83: 74174.1 | O83: 19407.44 | P83: 563.57 | Q83: -820.91 | R83: 0 | S83: 135.16 | T83: 2 | U83: 23 | V83: =C83+D83+E83 | W83: =O83/V83 | X83: =IF(C83=0,Y83,J83/C83+W83) | Y83: =IF(D83=0,0,K83/D83+W83) | Z83: =IF(E83=0,0,L83/E83+W83) | AA83: =V83/(B83*24*$L$6) | AB83: =IFERROR(N83/MIN(H83,AA83),0)
A84: Ago-25 | B84: 31 | C84: 33465 | D84: 67444 | E84: 6165 | F84: 202 | G84: 202 | H84: 197 | I84: 90.32 | J84: 34171.11 | K84: 122714.36 | L84: 13339.83 | M84: 18406.24 | N84: 88683.49 | O84: 20729.52 | P84: 563.57 | Q84: -298.61 | R84: 0 | S84: 126.728 | T84: 2 | U84: 21 | V84: =C84+D84+E84 | W84: =O84/V84 | X84: =IF(C84=0,Y84,J84/C84+W84) | Y84: =IF(D84=0,0,K84/D84+W84) | Z84: =IF(E84=0,0,L84/E84+W84) | AA84: =V84/(B84*24*$L$6) | AB84: =IFERROR(N84/MIN(H84,AA84),0)
A85: Sep-25 | B85: 30 | C85: 32056 | D85: 65338 | E85: 6085 | F85: 197 | G85: 221 | H85: 173 | I85: 90.51 | J85: 32434.26 | K85: 117791.35 | L85: 13046.24 | M85: 20137.52 | N85: 77166.65 | O85: 20457.8 | P85: 563.57 | Q85: -281.6 | R85: 0 | S85: 119.52 | T85: 2 | U85: 21 | V85: =C85+D85+E85 | W85: =O85/V85 | X85: =IF(C85=0,Y85,J85/C85+W85) | Y85: =IF(D85=0,0,K85/D85+W85) | Z85: =IF(E85=0,0,L85/E85+W85) | AA85: =V85/(B85*24*$L$6) | AB85: =IFERROR(N85/MIN(H85,AA85),0)
A86: Oct-25 | B86: 31 | C86: 29377 | D86: 64589 | E86: 8266 | F86: 189 | G86: 190 | H86: 186 | I86: 91.07 | J86: 29723.65 | K86: 116447.51 | L86: 17722.3 | M86: 17753.73 | N86: 82967.16 | O86: 20211.27 | P86: 563.57 | Q86: -856.17 | R86: 0 | S86: 131.936 | T86: 2 | U86: 23 | V86: =C86+D86+E86 | W86: =O86/V86 | X86: =IF(C86=0,Y86,J86/C86+W86) | Y86: =IF(D86=0,0,K86/D86+W86) | Z86: =IF(E86=0,0,L86/E86+W86) | AA86: =V86/(B86*24*$L$6) | AB86: =IFERROR(N86/MIN(H86,AA86),0)
A87: Nov-25 | B87: 30 | C87: 31370 | D87: 50643 | E87: 11895 | F87: 184 | G87: 183 | H87: 166 | I87: 91.75 | J87: 30786.52 | K87: 88559.41 | L87: 24736.84 | M87: 16766.08 | N87: 71821.56 | O87: 18565.62 | P87: 563.57 | Q87: -1259 | R87: 0 | S87: 136.56 | T87: 4 | U87: 19 | V87: =C87+D87+E87 | W87: =O87/V87 | X87: =IF(C87=0,Y87,J87/C87+W87) | Y87: =IF(D87=0,0,K87/D87+W87) | Z87: =IF(E87=0,0,L87/E87+W87) | AA87: =V87/(B87*24*$L$6) | AB87: =IFERROR(N87/MIN(H87,AA87),0)
A88: Dic-25 | B88: 31 | C88: 28064 | D88: 50519 | E88: 12433 | F88: 185 | G88: 154 | H88: 169 | I88: 91.94 | J88: 26166.87 | K88: 83927.21 | L88: 24563.88 | M88: 16857.2 | N88: 69464.07 | O88: 17993.87 | P88: 563.57 | Q88: -1197.68 | R88: 0 | S88: 131.192 | T88: 4 | U88: 22 | V88: =C88+D88+E88 | W88: =O88/V88 | X88: =IF(C88=0,Y88,J88/C88+W88) | Y88: =IF(D88=0,0,K88/D88+W88) | Z88: =IF(E88=0,0,L88/E88+W88) | AA88: =V88/(B88*24*$L$6) | AB88: =IFERROR(N88/MIN(H88,AA88),0)
A89: Ene-26 | B89: 31 | C89: 27003 | D89: 47763 | E89: 11813 | F89: 149 | G89: 180 | H89: 153 | I89: 92.01 | J89: 24610.53 | K89: 77562.34 | L89: 22813.27 | M89: 15507 | N89: 61472.34 | O89: 16848.27 | P89: 703.36 | Q89: -1097.59 | R89: 0 | S89: 143.096 | T89: 4 | U89: 21 | V89: =C89+D89+E89 | W89: =O89/V89 | X89: =IF(C89=0,Y89,J89/C89+W89) | Y89: =IF(D89=0,0,K89/D89+W89) | Z89: =IF(E89=0,0,L89/E89+W89) | AA89: =V89/(B89*24*$L$6) | AB89: =IFERROR(N89/MIN(H89,AA89),0)
A90: Feb-26 | B90: 28 | C90: 28532 | D90: 49886 | E90: 12871 | F90: 181 | G90: 200 | H90: 194 | I90: 90.64 | J90: 26018.33 | K90: 81054.77 | L90: 24870.63 | M90: 17230 | N90: 77989.94 | O90: 17764.83 | P90: 703.36 | Q90: -491.26 | R90: 0 | S90: 139.104 | T90: 4 | U90: 19 | V90: =C90+D90+E90 | W90: =O90/V90 | X90: =IF(C90=0,Y90,J90/C90+W90) | Y90: =IF(D90=0,0,K90/D90+W90) | Z90: =IF(E90=0,0,L90/E90+W90) | AA90: =V90/(B90*24*$L$6) | AB90: =IFERROR(N90/MIN(H90,AA90),0)
A91: Mar-26 | B91: 31 | C91: 33959 | D91: 55377 | E91: 13651 | F91: 193 | G91: 191 | H91: 190 | I91: 90.88 | J91: 30987.59 | K91: 90031.93 | L91: 26394.21 | M91: 16626.95 | N91: 76429.4 | O91: 20041.29 | P91: 703.36 | Q91: -522.43 | R91: 0 | S91: 170.376 | T91: 4 | U91: 21 | V91: =C91+D91+E91 | W91: =O91/V91 | X91: =IF(C91=0,Y91,J91/C91+W91) | Y91: =IF(D91=0,0,K91/D91+W91) | Z91: =IF(E91=0,0,L91/E91+W91) | AA91: =V91/(B91*24*$L$6) | AB91: =IFERROR(N91/MIN(H91,AA91),0)
A92: Filas = recibo ancla (parseado) + meses reconstruidos del CONSUMO HISTÓRICO (subtotal al peso; split TOU por shares del ancla). Capacidad a MIN(kW punta, umbral); tarifas por banda = concepto/kWh + vol/kWh; col Q<0 (bonificación FP) aplica claw-back al ahorro. Válido <700 kWp (medición neta). Excedentes PV a $0.
O94: Techo — referencia satelital (ruta HelioScope; cruz roja = punto verificado) · confianza ?

Sheet Fiesta Americana Condesa Can
A1: Fiesta Americana Condesa Cancún — Memoria de cálculo y propuesta energética
A2: RPU 780881200029 · GDMTH SIN · Demanda contratada 5,115 kW · 12 meses de recibo
A3: Régimen: GENERADOR EXENTO — Medición Neta (sin permiso; Art. 30 LSE; RES/142/2017)
A5: PARÁMETROS (desde Supuestos — edítalos ahí)
A6: PV kWp | B6: =Supuestos!$B$28 | C6: BESS kW | D6: =Supuestos!$C$28 | E6: BESS kWh | F6: =Supuestos!$D$28 | G6: FP corrección | H6: =Supuestos!$E$28 | I6: Entrega útil kWh | J6: =Supuestos!$D$28*Supuestos!$B$17*SQRT(Supuestos!$B$18) | K6: FC umbral | L6: 0.57
A8: 1. ESTRUCTURA DE COSTO Y AHORRO (pre-IVA, año base · fórmulas vivas ← §3)
A9: Concepto | B9: $ / año | C9: Nota
A10: Tarifa Actual (CFE pleno, sin proyecto) | B10: =$E$38*$B$39 | C10: Σ recibos × anualización
A11: (−) Ahorro PV (energía + demanda) | B11: =$F$38*$B$39 | C11: intermedio + umbral
A12: (−) Ahorro BESS (punta + arbitraje) | B12: =$G$38*$B$39 | C12: recorte punta + arbitraje (incl. claw)
A13: (−) Ahorro FP (corrección) | B13: =$H$38*$B$39 | C13: multa factor de potencia
A14: (=) Costo neto con proyecto | B14: =B10-B11-B12-B13
A15: Ahorro proyecto / año | B15: =B11+B12+B13
A16: Ahorro % | B16: =B15/B10
A18: 2. CAPEX (fórmulas vivas desde Supuestos)
A19: CAPEX PV | B19: =Supuestos!$B$28*1000*Supuestos!$F$28*Supuestos!$B$5
A20: CAPEX BESS | B20: =Supuestos!$D$28*Supuestos!$G$28*Supuestos!$B$5
A21: CAPEX capacitor (FP) | B21: =Supuestos!$H$28
A22: CAPEX TOTAL | B22: =B19+B20+B21
A24: 3. RESUMEN MENSUAL — Tarifa Actual vs Con Proyecto (fórmulas vivas ← §6 y Supuestos)
A25: Mes | B25: kWh Consumo | C25: Gen PV kWh | D25: BESS desc kWh | E25: Tarifa Actual $ | F25: Ah PV $ | G25: Ah BESS $ | H25: Ah FP $ | I25: Costo c/proy $ | J25: Ahorro $ | K25: Ahorro %
A26: =A80 | B26: =V80 | C26: =Supuestos!$B$28*S80 | D26: =MIN($J$6*U80,E80) | E26: =SUM(J80:Q80) | F26: =(MIN(C26,D80)*Y80+(MIN(H80,AA80)-MIN(H80,(V80-MIN(C26,D80))/($B$80*24*$L$6)))*AB80)*IF(Q80<0,1+Q80/SUM(J80:P80),1) | G26: =((MIN(H80,(V80-MIN(C26,D80))/($B$80*24*$L$6))-MIN(MAX(H80-MIN(Supuestos!$C$28,IF(T80>0,$J$6/T80,0)),0),(V80-MIN(C26,D80))/($B$80*24*$L$6)))*AB80+D26*Z80-D26/Supuestos!$B$18*X80)*IF(Q80<0,1+Q80/SUM(J80:P80),1) | H26: =IF(Supuestos!$E$28="Sí",R80,0) | I26: =E26-J26 | J26: =F26+G26+H26 | K26: =J26/E26
A27: =A81 | B27: =V81 | C27: =Supuestos!$B$28*S81 | D27: =MIN($J$6*U81,E81) | E27: =SUM(J81:Q81) | F27: =(MIN(C27,D81)*Y81+(MIN(H81,AA81)-MIN(H81,(V81-MIN(C27,D81))/($B$81*24*$L$6)))*AB81)*IF(Q81<0,1+Q81/SUM(J81:P81),1) | G27: =((MIN(H81,(V81-MIN(C27,D81))/($B$81*24*$L$6))-MIN(MAX(H81-MIN(Supuestos!$C$28,IF(T81>0,$J$6/T81,0)),0),(V81-MIN(C27,D81))/($B$81*24*$L$6)))*AB81+D27*Z81-D27/Supuestos!$B$18*X81)*IF(Q81<0,1+Q81/SUM(J81:P81),1) | H27: =IF(Supuestos!$E$28="Sí",R81,0) | I27: =E27-J27 | J27: =F27+G27+H27 | K27: =J27/E27
A28: =A82 | B28: =V82 | C28: =Supuestos!$B$28*S82 | D28: =MIN($J$6*U82,E82) | E28: =SUM(J82:Q82) | F28: =(MIN(C28,D82)*Y82+(MIN(H82,AA82)-MIN(H82,(V82-MIN(C28,D82))/($B$82*24*$L$6)))*AB82)*IF(Q82<0,1+Q82/SUM(J82:P82),1) | G28: =((MIN(H82,(V82-MIN(C28,D82))/($B$82*24*$L$6))-MIN(MAX(H82-MIN(Supuestos!$C$28,IF(T82>0,$J$6/T82,0)),0),(V82-MIN(C28,D82))/($B$82*24*$L$6)))*AB82+D28*Z82-D28/Supuestos!$B$18*X82)*IF(Q82<0,1+Q82/SUM(J82:P82),1) | H28: =IF(Supuestos!$E$28="Sí",R82,0) | I28: =E28-J28 | J28: =F28+G28+H28 | K28: =J28/E28
A29: =A83 | B29: =V83 | C29: =Supuestos!$B$28*S83 | D29: =MIN($J$6*U83,E83) | E29: =SUM(J83:Q83) | F29: =(MIN(C29,D83)*Y83+(MIN(H83,AA83)-MIN(H83,(V83-MIN(C29,D83))/($B$83*24*$L$6)))*AB83)*IF(Q83<0,1+Q83/SUM(J83:P83),1) | G29: =((MIN(H83,(V83-MIN(C29,D83))/($B$83*24*$L$6))-MIN(MAX(H83-MIN(Supuestos!$C$28,IF(T83>0,$J$6/T83,0)),0),(V83-MIN(C29,D83))/($B$83*24*$L$6)))*AB83+D29*Z83-D29/Supuestos!$B$18*X83)*IF(Q83<0,1+Q83/SUM(J83:P83),1) | H29: =IF(Supuestos!$E$28="Sí",R83,0) | I29: =E29-J29 | J29: =F29+G29+H29 | K29: =J29/E29
A30: =A84 | B30: =V84 | C30: =Supuestos!$B$28*S84 | D30: =MIN($J$6*U84,E84) | E30: =SUM(J84:Q84) | F30: =(MIN(C30,D84)*Y84+(MIN(H84,AA84)-MIN(H84,(V84-MIN(C30,D84))/($B$84*24*$L$6)))*AB84)*IF(Q84<0,1+Q84/SUM(J84:P84),1) | G30: =((MIN(H84,(V84-MIN(C30,D84))/($B$84*24*$L$6))-MIN(MAX(H84-MIN(Supuestos!$C$28,IF(T84>0,$J$6/T84,0)),0),(V84-MIN(C30,D84))/($B$84*24*$L$6)))*AB84+D30*Z84-D30/Supuestos!$B$18*X84)*IF(Q84<0,1+Q84/SUM(J84:P84),1) | H30: =IF(Supuestos!$E$28="Sí",R84,0) | I30: =E30-J30 | J30: =F30+G30+H30 | K30: =J30/E30
A31: =A85 | B31: =V85 | C31: =Supuestos!$B$28*S85 | D31: =MIN($J$6*U85,E85) | E31: =SUM(J85:Q85) | F31: =(MIN(C31,D85)*Y85+(MIN(H85,AA85)-MIN(H85,(V85-MIN(C31,D85))/($B$85*24*$L$6)))*AB85)*IF(Q85<0,1+Q85/SUM(J85:P85),1) | G31: =((MIN(H85,(V85-MIN(C31,D85))/($B$85*24*$L$6))-MIN(MAX(H85-MIN(Supuestos!$C$28,IF(T85>0,$J$6/T85,0)),0),(V85-MIN(C31,D85))/($B$85*24*$L$6)))*AB85+D31*Z85-D31/Supuestos!$B$18*X85)*IF(Q85<0,1+Q85/SUM(J85:P85),1) | H31: =IF(Supuestos!$E$28="Sí",R85,0) | I31: =E31-J31 | J31: =F31+G31+H31 | K31: =J31/E31
A32: =A86 | B32: =V86 | C32: =Supuestos!$B$28*S86 | D32: =MIN($J$6*U86,E86) | E32: =SUM(J86:Q86) | F32: =(MIN(C32,D86)*Y86+(MIN(H86,AA86)-MIN(H86,(V86-MIN(C32,D86))/($B$86*24*$L$6)))*AB86)*IF(Q86<0,1+Q86/SUM(J86:P86),1) | G32: =((MIN(H86,(V86-MIN(C32,D86))/($B$86*24*$L$6))-MIN(MAX(H86-MIN(Supuestos!$C$28,IF(T86>0,$J$6/T86,0)),0),(V86-MIN(C32,D86))/($B$86*24*$L$6)))*AB86+D32*Z86-D32/Supuestos!$B$18*X86)*IF(Q86<0,1+Q86/SUM(J86:P86),1) | H32: =IF(Supuestos!$E$28="Sí",R86,0) | I32: =E32-J32 | J32: =F32+G32+H32 | K32: =J32/E32
A33: =A87 | B33: =V87 | C33: =Supuestos!$B$28*S87 | D33: =MIN($J$6*U87,E87) | E33: =SUM(J87:Q87) | F33: =(MIN(C33,D87)*Y87+(MIN(H87,AA87)-MIN(H87,(V87-MIN(C33,D87))/($B$87*24*$L$6)))*AB87)*IF(Q87<0,1+Q87/SUM(J87:P87),1) | G33: =((MIN(H87,(V87-MIN(C33,D87))/($B$87*24*$L$6))-MIN(MAX(H87-MIN(Supuestos!$C$28,IF(T87>0,$J$6/T87,0)),0),(V87-MIN(C33,D87))/($B$87*24*$L$6)))*AB87+D33*Z87-D33/Supuestos!$B$18*X87)*IF(Q87<0,1+Q87/SUM(J87:P87),1) | H33: =IF(Supuestos!$E$28="Sí",R87,0) | I33: =E33-J33 | J33: =F33+G33+H33 | K33: =J33/E33
A34: =A88 | B34: =V88 | C34: =Supuestos!$B$28*S88 | D34: =MIN($J$6*U88,E88) | E34: =SUM(J88:Q88) | F34: =(MIN(C34,D88)*Y88+(MIN(H88,AA88)-MIN(H88,(V88-MIN(C34,D88))/($B$88*24*$L$6)))*AB88)*IF(Q88<0,1+Q88/SUM(J88:P88),1) | G34: =((MIN(H88,(V88-MIN(C34,D88))/($B$88*24*$L$6))-MIN(MAX(H88-MIN(Supuestos!$C$28,IF(T88>0,$J$6/T88,0)),0),(V88-MIN(C34,D88))/($B$88*24*$L$6)))*AB88+D34*Z88-D34/Supuestos!$B$18*X88)*IF(Q88<0,1+Q88/SUM(J88:P88),1) | H34: =IF(Supuestos!$E$28="Sí",R88,0) | I34: =E34-J34 | J34: =F34+G34+H34 | K34: =J34/E34
A35: =A89 | B35: =V89 | C35: =Supuestos!$B$28*S89 | D35: =MIN($J$6*U89,E89) | E35: =SUM(J89:Q89) | F35: =(MIN(C35,D89)*Y89+(MIN(H89,AA89)-MIN(H89,(V89-MIN(C35,D89))/($B$89*24*$L$6)))*AB89)*IF(Q89<0,1+Q89/SUM(J89:P89),1) | G35: =((MIN(H89,(V89-MIN(C35,D89))/($B$89*24*$L$6))-MIN(MAX(H89-MIN(Supuestos!$C$28,IF(T89>0,$J$6/T89,0)),0),(V89-MIN(C35,D89))/($B$89*24*$L$6)))*AB89+D35*Z89-D35/Supuestos!$B$18*X89)*IF(Q89<0,1+Q89/SUM(J89:P89),1) | H35: =IF(Supuestos!$E$28="Sí",R89,0) | I35: =E35-J35 | J35: =F35+G35+H35 | K35: =J35/E35
A36: =A90 | B36: =V90 | C36: =Supuestos!$B$28*S90 | D36: =MIN($J$6*U90,E90) | E36: =SUM(J90:Q90) | F36: =(MIN(C36,D90)*Y90+(MIN(H90,AA90)-MIN(H90,(V90-MIN(C36,D90))/($B$90*24*$L$6)))*AB90)*IF(Q90<0,1+Q90/SUM(J90:P90),1) | G36: =((MIN(H90,(V90-MIN(C36,D90))/($B$90*24*$L$6))-MIN(MAX(H90-MIN(Supuestos!$C$28,IF(T90>0,$J$6/T90,0)),0),(V90-MIN(C36,D90))/($B$90*24*$L$6)))*AB90+D36*Z90-D36/Supuestos!$B$18*X90)*IF(Q90<0,1+Q90/SUM(J90:P90),1) | H36: =IF(Supuestos!$E$28="Sí",R90,0) | I36: =E36-J36 | J36: =F36+G36+H36 | K36: =J36/E36
A37: =A91 | B37: =V91 | C37: =Supuestos!$B$28*S91 | D37: =MIN($J$6*U91,E91) | E37: =SUM(J91:Q91) | F37: =(MIN(C37,D91)*Y91+(MIN(H91,AA91)-MIN(H91,(V91-MIN(C37,D91))/($B$91*24*$L$6)))*AB91)*IF(Q91<0,1+Q91/SUM(J91:P91),1) | G37: =((MIN(H91,(V91-MIN(C37,D91))/($B$91*24*$L$6))-MIN(MAX(H91-MIN(Supuestos!$C$28,IF(T91>0,$J$6/T91,0)),0),(V91-MIN(C37,D91))/($B$91*24*$L$6)))*AB91+D37*Z91-D37/Supuestos!$B$18*X91)*IF(Q91<0,1+Q91/SUM(J91:P91),1) | H37: =IF(Supuestos!$E$28="Sí",R91,0) | I37: =E37-J37 | J37: =F37+G37+H37 | K37: =J37/E37
A38: TOTAL | B38: =SUM(B26:B37) | C38: =SUM(C26:C37) | D38: =SUM(D26:D37) | E38: =SUM(E26:E37) | F38: =SUM(F26:F37) | G38: =SUM(G26:G37) | H38: =SUM(H26:H37) | I38: =SUM(I26:I37) | J38: =SUM(J26:J37) | K38: =J38/E38
A39: Factor anualización (12/meses): | B39: 1
A40: 4. PROYECCIÓN 20 AÑOS — Comprar vs PPA/Ahorro compartido
A41: Año | B41: Tarifa Actual $ | C41: Ah PV $ | D41: Ah BESS $ | E41: Ah FP $ | F41: Costo c/proy $ | G41: Flujo Compra $ | H41: Pago PPA $ | I41: Comisión $ | J41: Flujo Cliente PPA $ | K41: Flujo Financiador $ | L41: Acum Compra $ | M41: Acum Cliente PPA $
A42: 0 | G42: =-B22 | K42: =-B22 | L42: =G42 | M42: 0
A43: 1 | B43: =$E$38*$B$39*(1+Supuestos!$B$8)^1 | C43: =$F$38*$B$39*(1+Supuestos!$B$8)^1*((1-Supuestos!$B$11)*(1-Supuestos!$B$12)^0) | D43: =$G$38*$B$39*(1+Supuestos!$B$8)^1*(1-Supuestos!$B$13)^1*Supuestos!$B$10 | E43: =$H$38*$B$39*(1+Supuestos!$B$8)^1 | F43: =B43-C43-D43-E43 | G43: =C43+D43+E43-(IF(1<=Supuestos!$J$28,Supuestos!$B$19*Supuestos!$B$28*(1+Supuestos!$B$8)^0,0)+IF(1<=Supuestos!$B$22,Supuestos!$B$20*Supuestos!$D$28*(1+Supuestos!$B$8)^0,0)) | H43: =IF(1<=Supuestos!$J$28,$C$38*$B$39*((1-Supuestos!$B$11)*(1-Supuestos!$B$12)^0)*Supuestos!$I$28*(1+Supuestos!$B$9)^0,0) | I43: =IF(1<=Supuestos!$B$22,D43*Supuestos!$K$28,0) | J43: =C43+D43+E43-H43-I43 | K43: =H43+I43-(IF(1<=Supuestos!$J$28,Supuestos!$B$19*Supuestos!$B$28*(1+Supuestos!$B$8)^0,0)+IF(1<=Supuestos!$B$22,Supuestos!$B$20*Supuestos!$D$28*(1+Supuestos!$B$8)^0,0))-H43*Supuestos!$B$21 | L43: =L42+G43 | M43: =M42+J43
A44: 2 | B44: =$E$38*$B$39*(1+Supuestos!$B$8)^2 | C44: =$F$38*$B$39*(1+Supuestos!$B$8)^2*((1-Supuestos!$B$11)*(1-Supuestos!$B$12)^1) | D44: =$G$38*$B$39*(1+Supuestos!$B$8)^2*(1-Supuestos!$B$13)^2*Supuestos!$B$10 | E44: =$H$38*$B$39*(1+Supuestos!$B$8)^2 | F44: =B44-C44-D44-E44 | G44: =C44+D44+E44-(IF(2<=Supuestos!$J$28,Supuestos!$B$19*Supuestos!$B$28*(1+Supuestos!$B$8)^1,0)+IF(2<=Supuestos!$B$22,Supuestos!$B$20*Supuestos!$D$28*(1+Supuestos!$B$8)^1,0)) | H44: =IF(2<=Supuestos!$J$28,$C$38*$B$39*((1-Supuestos!$B$11)*(1-Supuestos!$B$12)^1)*Supuestos!$I$28*(1+Supuestos!$B$9)^1,0) | I44: =IF(2<=Supuestos!$B$22,D44*Supuestos!$K$28,0) | J44: =C44+D44+E44-H44-I44 | K44: =H44+I44-(IF(2<=Supuestos!$J$28,Supuestos!$B$19*Supuestos!$B$28*(1+Supuestos!$B$8)^1,0)+IF(2<=Supuestos!$B$22,Supuestos!$B$20*Supuestos!$D$28*(1+Supuestos!$B$8)^1,0))-H44*Supuestos!$B$21 | L44: =L43+G44 | M44: =M43+J44
A45: 3 | B45: =$E$38*$B$39*(1+Supuestos!$B$8)^3 | C45: =$F$38*$B$39*(1+Supuestos!$B$8)^3*((1-Supuestos!$B$11)*(1-Supuestos!$B$12)^2) | D45: =$G$38*$B$39*(1+Supuestos!$B$8)^3*(1-Supuestos!$B$13)^3*Supuestos!$B$10 | E45: =$H$38*$B$39*(1+Supuestos!$B$8)^3 | F45: =B45-C45-D45-E45 | G45: =C45+D45+E45-(IF(3<=Supuestos!$J$28,Supuestos!$B$19*Supuestos!$B$28*(1+Supuestos!$B$8)^2,0)+IF(3<=Supuestos!$B$22,Supuestos!$B$20*Supuestos!$D$28*(1+Supuestos!$B$8)^2,0)) | H45: =IF(3<=Supuestos!$J$28,$C$38*$B$39*((1-Supuestos!$B$11)*(1-Supuestos!$B$12)^2)*Supuestos!$I$28*(1+Supuestos!$B$9)^2,0) | I45: =IF(3<=Supuestos!$B$22,D45*Supuestos!$K$28,0) | J45: =C45+D45+E45-H45-I45 | K45: =H45+I45-(IF(3<=Supuestos!$J$28,Supuestos!$B$19*Supuestos!$B$28*(1+Supuestos!$B$8)^2,0)+IF(3<=Supuestos!$B$22,Supuestos!$B$20*Supuestos!$D$28*(1+Supuestos!$B$8)^2,0))-H45*Supuestos!$B$21 | L45: =L44+G45 | M45: =M44+J45
A46: 4 | B46: =$E$38*$B$39*(1+Supuestos!$B$8)^4 | C46: =$F$38*$B$39*(1+Supuestos!$B$8)^4*((1-Supuestos!$B$11)*(1-Supuestos!$B$12)^3) | D46: =$G$38*$B$39*(1+Supuestos!$B$8)^4*(1-Supuestos!$B$13)^4*Supuestos!$B$10 | E46: =$H$38*$B$39*(1+Supuestos!$B$8)^4 | F46: =B46-C46-D46-E46 | G46: =C46+D46+E46-(IF(4<=Supuestos!$J$28,Supuestos!$B$19*Supuestos!$B$28*(1+Supuestos!$B$8)^3,0)+IF(4<=Supuestos!$B$22,Supuestos!$B$20*Supuestos!$D$28*(1+Supuestos!$B$8)^3,0)) | H46: =IF(4<=Supuestos!$J$28,$C$38*$B$39*((1-Supuestos!$B$11)*(1-Supuestos!$B$12)^3)*Supuestos!$I$28*(1+Supuestos!$B$9)^3,0) | I46: =IF(4<=Supuestos!$B$22,D46*Supuestos!$K$28,0) | J46: =C46+D46+E46-H46-I46 | K46: =H46+I46-(IF(4<=Supuestos!$J$28,Supuestos!$B$19*Supuestos!$B$28*(1+Supuestos!$B$8)^3,0)+IF(4<=Supuestos!$B$22,Supuestos!$B$20*Supuestos!$D$28*(1+Supuestos!$B$8)^3,0))-H46*Supuestos!$B$21 | L46: =L45+G46 | M46: =M45+J46
A47: 5 | B47: =$E$38*$B$39*(1+Supuestos!$B$8)^5 | C47: =$F$38*$B$39*(1+Supuestos!$B$8)^5*((1-Supuestos!$B$11)*(1-Supuestos!$B$12)^4) | D47: =$G$38*$B$39*(1+Supuestos!$B$8)^5*(1-Supuestos!$B$13)^5*Supuestos!$B$10 | E47: =$H$38*$B$39*(1+Supuestos!$B$8)^5 | F47: =B47-C47-D47-E47 | G47: =C47+D47+E47-(IF(5<=Supuestos!$J$28,Supuestos!$B$19*Supuestos!$B$28*(1+Supuestos!$B$8)^4,0)+IF(5<=Supuestos!$B$22,Supuestos!$B$20*Supuestos!$D$28*(1+Supuestos!$B$8)^4,0)) | H47: =IF(5<=Supuestos!$J$28,$C$38*$B$39*((1-Supuestos!$B$11)*(1-Supuestos!$B$12)^4)*Supuestos!$I$28*(1+Supuestos!$B$9)^4,0) | I47: =IF(5<=Supuestos!$B$22,D47*Supuestos!$K$28,0) | J47: =C47+D47+E47-H47-I47 | K47: =H47+I47-(IF(5<=Supuestos!$J$28,Supuestos!$B$19*Supuestos!$B$28*(1+Supuestos!$B$8)^4,0)+IF(5<=Supuestos!$B$22,Supuestos!$B$20*Supuestos!$D$28*(1+Supuestos!$B$8)^4,0))-H47*Supuestos!$B$21 | L47: =L46+G47 | M47: =M46+J47
A48: 6 | B48: =$E$38*$B$39*(1+Supuestos!$B$8)^6 | C48: =$F$38*$B$39*(1+Supuestos!$B$8)^6*((1-Supuestos!$B$11)*(1-Supuestos!$B$12)^5) | D48: =$G$38*$B$39*(1+Supuestos!$B$8)^6*(1-Supuestos!$B$13)^6*Supuestos!$B$10 | E48: =$H$38*$B$39*(1+Supuestos!$B$8)^6 | F48: =B48-C48-D48-E48 | G48: =C48+D48+E48-(IF(6<=Supuestos!$J$28,Supuestos!$B$19*Supuestos!$B$28*(1+Supuestos!$B$8)^5,0)+IF(6<=Supuestos!$B$22,Supuestos!$B$20*Supuestos!$D$28*(1+Supuestos!$B$8)^5,0)) | H48: =IF(6<=Supuestos!$J$28,$C$38*$B$39*((1-Supuestos!$B$11)*(1-Supuestos!$B$12)^5)*Supuestos!$I$28*(1+Supuestos!$B$9)^5,0) | I48: =IF(6<=Supuestos!$B$22,D48*Supuestos!$K$28,0) | J48: =C48+D48+E48-H48-I48 | K48: =H48+I48-(IF(6<=Supuestos!$J$28,Supuestos!$B$19*Supuestos!$B$28*(1+Supuestos!$B$8)^5,0)+IF(6<=Supuestos!$B$22,Supuestos!$B$20*Supuestos!$D$28*(1+Supuestos!$B$8)^5,0))-H48*Supuestos!$B$21 | L48: =L47+G48 | M48: =M47+J48
A49: 7 | B49: =$E$38*$B$39*(1+Supuestos!$B$8)^7 | C49: =$F$38*$B$39*(1+Supuestos!$B$8)^7*((1-Supuestos!$B$11)*(1-Supuestos!$B$12)^6) | D49: =$G$38*$B$39*(1+Supuestos!$B$8)^7*(1-Supuestos!$B$13)^7*Supuestos!$B$10 | E49: =$H$38*$B$39*(1+Supuestos!$B$8)^7 | F49: =B49-C49-D49-E49 | G49: =C49+D49+E49-(IF(7<=Supuestos!$J$28,Supuestos!$B$19*Supuestos!$B$28*(1+Supuestos!$B$8)^6,0)+IF(7<=Supuestos!$B$22,Supuestos!$B$20*Supuestos!$D$28*(1+Supuestos!$B$8)^6,0)) | H49: =IF(7<=Supuestos!$J$28,$C$38*$B$39*((1-Supuestos!$B$11)*(1-Supuestos!$B$12)^6)*Supuestos!$I$28*(1+Supuestos!$B$9)^6,0) | I49: =IF(7<=Supuestos!$B$22,D49*Supuestos!$K$28,0) | J49: =C49+D49+E49-H49-I49 | K49: =H49+I49-(IF(7<=Supuestos!$J$28,Supuestos!$B$19*Supuestos!$B$28*(1+Supuestos!$B$8)^6,0)+IF(7<=Supuestos!$B$22,Supuestos!$B$20*Supuestos!$D$28*(1+Supuestos!$B$8)^6,0))-H49*Supuestos!$B$21 | L49: =L48+G49 | M49: =M48+J49
A50: 8 | B50: =$E$38*$B$39*(1+Supuestos!$B$8)^8 | C50: =$F$38*$B$39*(1+Supuestos!$B$8)^8*((1-Supuestos!$B$11)*(1-Supuestos!$B$12)^7) | D50: =$G$38*$B$39*(1+Supuestos!$B$8)^8*(1-Supuestos!$B$13)^8*Supuestos!$B$10 | E50: =$H$38*$B$39*(1+Supuestos!$B$8)^8 | F50: =B50-C50-D50-E50 | G50: =C50+D50+E50-(IF(8<=Supuestos!$J$28,Supuestos!$B$19*Supuestos!$B$28*(1+Supuestos!$B$8)^7,0)+IF(8<=Supuestos!$B$22,Supuestos!$B$20*Supuestos!$D$28*(1+Supuestos!$B$8)^7,0)) | H50: =IF(8<=Supuestos!$J$28,$C$38*$B$39*((1-Supuestos!$B$11)*(1-Supuestos!$B$12)^7)*Supuestos!$I$28*(1+Supuestos!$B$9)^7,0) | I50: =IF(8<=Supuestos!$B$22,D50*Supuestos!$K$28,0) | J50: =C50+D50+E50-H50-I50 | K50: =H50+I50-(IF(8<=Supuestos!$J$28,Supuestos!$B$19*Supuestos!$B$28*(1+Supuestos!$B$8)^7,0)+IF(8<=Supuestos!$B$22,Supuestos!$B$20*Supuestos!$D$28*(1+Supuestos!$B$8)^7,0))-H50*Supuestos!$B$21 | L50: =L49+G50 | M50: =M49+J50
A51: 9 | B51: =$E$38*$B$39*(1+Supuestos!$B$8)^9 | C51: =$F$38*$B$39*(1+Supuestos!$B$8)^9*((1-Supuestos!$B$11)*(1-Supuestos!$B$12)^8) | D51: =$G$38*$B$39*(1+Supuestos!$B$8)^9*(1-Supuestos!$B$13)^9*Supuestos!$B$10 | E51: =$H$38*$B$39*(1+Supuestos!$B$8)^9 | F51: =B51-C51-D51-E51 | G51: =C51+D51+E51-(IF(9<=Supuestos!$J$28,Supuestos!$B$19*Supuestos!$B$28*(1+Supuestos!$B$8)^8,0)+IF(9<=Supuestos!$B$22,Supuestos!$B$20*Supuestos!$D$28*(1+Supuestos!$B$8)^8,0)) | H51: =IF(9<=Supuestos!$J$28,$C$38*$B$39*((1-Supuestos!$B$11)*(1-Supuestos!$B$12)^8)*Supuestos!$I$28*(1+Supuestos!$B$9)^8,0) | I51: =IF(9<=Supuestos!$B$22,D51*Supuestos!$K$28,0) | J51: =C51+D51+E51-H51-I51 | K51: =H51+I51-(IF(9<=Supuestos!$J$28,Supuestos!$B$19*Supuestos!$B$28*(1+Supuestos!$B$8)^8,0)+IF(9<=Supuestos!$B$22,Supuestos!$B$20*Supuestos!$D$28*(1+Supuestos!$B$8)^8,0))-H51*Supuestos!$B$21 | L51: =L50+G51 | M51: =M50+J51
A52: 10 | B52: =$E$38*$B$39*(1+Supuestos!$B$8)^10 | C52: =$F$38*$B$39*(1+Supuestos!$B$8)^10*((1-Supuestos!$B$11)*(1-Supuestos!$B$12)^9) | D52: =$G$38*$B$39*(1+Supuestos!$B$8)^10*(1-Supuestos!$B$13)^10*Supuestos!$B$10 | E52: =$H$38*$B$39*(1+Supuestos!$B$8)^10 | F52: =B52-C52-D52-E52 | G52: =C52+D52+E52-(IF(10<=Supuestos!$J$28,Supuestos!$B$19*Supuestos!$B$28*(1+Supuestos!$B$8)^9,0)+IF(10<=Supuestos!$B$22,Supuestos!$B$20*Supuestos!$D$28*(1+Supuestos!$B$8)^9,0)) | H52: =IF(10<=Supuestos!$J$28,$C$38*$B$39*((1-Supuestos!$B$11)*(1-Supuestos!$B$12)^9)*Supuestos!$I$28*(1+Supuestos!$B$9)^9,0) | I52: =IF(10<=Supuestos!$B$22,D52*Supuestos!$K$28,0) | J52: =C52+D52+E52-H52-I52 | K52: =H52+I52-(IF(10<=Supuestos!$J$28,Supuestos!$B$19*Supuestos!$B$28*(1+Supuestos!$B$8)^9,0)+IF(10<=Supuestos!$B$22,Supuestos!$B$20*Supuestos!$D$28*(1+Supuestos!$B$8)^9,0))-H52*Supuestos!$B$21 | L52: =L51+G52 | M52: =M51+J52
A53: 11 | B53: =$E$38*$B$39*(1+Supuestos!$B$8)^11 | C53: =$F$38*$B$39*(1+Supuestos!$B$8)^11*((1-Supuestos!$B$11)*(1-Supuestos!$B$12)^10) | D53: =$G$38*$B$39*(1+Supuestos!$B$8)^11*(1-Supuestos!$B$13)^11*Supuestos!$B$10 | E53: =$H$38*$B$39*(1+Supuestos!$B$8)^11 | F53: =B53-C53-D53-E53 | G53: =C53+D53+E53-(IF(11<=Supuestos!$J$28,Supuestos!$B$19*Supuestos!$B$28*(1+Supuestos!$B$8)^10,0)+IF(11<=Supuestos!$B$22,Supuestos!$B$20*Supuestos!$D$28*(1+Supuestos!$B$8)^10,0)) | H53: =IF(11<=Supuestos!$J$28,$C$38*$B$39*((1-Supuestos!$B$11)*(1-Supuestos!$B$12)^10)*Supuestos!$I$28*(1+Supuestos!$B$9)^10,0) | I53: =IF(11<=Supuestos!$B$22,D53*Supuestos!$K$28,0) | J53: =C53+D53+E53-H53-I53 | K53: =H53+I53-(IF(11<=Supuestos!$J$28,Supuestos!$B$19*Supuestos!$B$28*(1+Supuestos!$B$8)^10,0)+IF(11<=Supuestos!$B$22,Supuestos!$B$20*Supuestos!$D$28*(1+Supuestos!$B$8)^10,0))-H53*Supuestos!$B$21 | L53: =L52+G53 | M53: =M52+J53
A54: 12 | B54: =$E$38*$B$39*(1+Supuestos!$B$8)^12 | C54: =$F$38*$B$39*(1+Supuestos!$B$8)^12*((1-Supuestos!$B$11)*(1-Supuestos!$B$12)^11) | D54: =$G$38*$B$39*(1+Supuestos!$B$8)^12*(1-Supuestos!$B$13)^12*Supuestos!$B$10 | E54: =$H$38*$B$39*(1+Supuestos!$B$8)^12 | F54: =B54-C54-D54-E54 | G54: =C54+D54+E54-(IF(12<=Supuestos!$J$28,Supuestos!$B$19*Supuestos!$B$28*(1+Supuestos!$B$8)^11,0)+IF(12<=Supuestos!$B$22,Supuestos!$B$20*Supuestos!$D$28*(1+Supuestos!$B$8)^11,0)) | H54: =IF(12<=Supuestos!$J$28,$C$38*$B$39*((1-Supuestos!$B$11)*(1-Supuestos!$B$12)^11)*Supuestos!$I$28*(1+Supuestos!$B$9)^11,0) | I54: =IF(12<=Supuestos!$B$22,D54*Supuestos!$K$28,0) | J54: =C54+D54+E54-H54-I54 | K54: =H54+I54-(IF(12<=Supuestos!$J$28,Supuestos!$B$19*Supuestos!$B$28*(1+Supuestos!$B$8)^11,0)+IF(12<=Supuestos!$B$22,Supuestos!$B$20*Supuestos!$D$28*(1+Supuestos!$B$8)^11,0))-H54*Supuestos!$B$21 | L54: =L53+G54 | M54: =M53+J54
A55: 13 | B55: =$E$38*$B$39*(1+Supuestos!$B$8)^13 | C55: =$F$38*$B$39*(1+Supuestos!$B$8)^13*((1-Supuestos!$B$11)*(1-Supuestos!$B$12)^12) | D55: =$G$38*$B$39*(1+Supuestos!$B$8)^13*(1-Supuestos!$B$13)^13*Supuestos!$B$10 | E55: =$H$38*$B$39*(1+Supuestos!$B$8)^13 | F55: =B55-C55-D55-E55 | G55: =C55+D55+E55-(IF(13<=Supuestos!$J$28,Supuestos!$B$19*Supuestos!$B$28*(1+Supuestos!$B$8)^12,0)+IF(13<=Supuestos!$B$22,Supuestos!$B$20*Supuestos!$D$28*(1+Supuestos!$B$8)^12,0)) | H55: =IF(13<=Supuestos!$J$28,$C$38*$B$39*((1-Supuestos!$B$11)*(1-Supuestos!$B$12)^12)*Supuestos!$I$28*(1+Supuestos!$B$9)^12,0) | I55: =IF(13<=Supuestos!$B$22,D55*Supuestos!$K$28,0) | J55: =C55+D55+E55-H55-I55 | K55: =H55+I55-(IF(13<=Supuestos!$J$28,Supuestos!$B$19*Supuestos!$B$28*(1+Supuestos!$B$8)^12,0)+IF(13<=Supuestos!$B$22,Supuestos!$B$20*Supuestos!$D$28*(1+Supuestos!$B$8)^12,0))-H55*Supuestos!$B$21 | L55: =L54+G55 | M55: =M54+J55
A56: 14 | B56: =$E$38*$B$39*(1+Supuestos!$B$8)^14 | C56: =$F$38*$B$39*(1+Supuestos!$B$8)^14*((1-Supuestos!$B$11)*(1-Supuestos!$B$12)^13) | D56: =$G$38*$B$39*(1+Supuestos!$B$8)^14*(1-Supuestos!$B$13)^14*Supuestos!$B$10 | E56: =$H$38*$B$39*(1+Supuestos!$B$8)^14 | F56: =B56-C56-D56-E56 | G56: =C56+D56+E56-(IF(14<=Supuestos!$J$28,Supuestos!$B$19*Supuestos!$B$28*(1+Supuestos!$B$8)^13,0)+IF(14<=Supuestos!$B$22,Supuestos!$B$20*Supuestos!$D$28*(1+Supuestos!$B$8)^13,0)) | H56: =IF(14<=Supuestos!$J$28,$C$38*$B$39*((1-Supuestos!$B$11)*(1-Supuestos!$B$12)^13)*Supuestos!$I$28*(1+Supuestos!$B$9)^13,0) | I56: =IF(14<=Supuestos!$B$22,D56*Supuestos!$K$28,0) | J56: =C56+D56+E56-H56-I56 | K56: =H56+I56-(IF(14<=Supuestos!$J$28,Supuestos!$B$19*Supuestos!$B$28*(1+Supuestos!$B$8)^13,0)+IF(14<=Supuestos!$B$22,Supuestos!$B$20*Supuestos!$D$28*(1+Supuestos!$B$8)^13,0))-H56*Supuestos!$B$21 | L56: =L55+G56 | M56: =M55+J56
A57: 15 | B57: =$E$38*$B$39*(1+Supuestos!$B$8)^15 | C57: =$F$38*$B$39*(1+Supuestos!$B$8)^15*((1-Supuestos!$B$11)*(1-Supuestos!$B$12)^14) | D57: =$G$38*$B$39*(1+Supuestos!$B$8)^15*(1-Supuestos!$B$13)^15*Supuestos!$B$10 | E57: =$H$38*$B$39*(1+Supuestos!$B$8)^15 | F57: =B57-C57-D57-E57 | G57: =C57+D57+E57-(IF(15<=Supuestos!$J$28,Supuestos!$B$19*Supuestos!$B$28*(1+Supuestos!$B$8)^14,0)+IF(15<=Supuestos!$B$22,Supuestos!$B$20*Supuestos!$D$28*(1+Supuestos!$B$8)^14,0)) | H57: =IF(15<=Supuestos!$J$28,$C$38*$B$39*((1-Supuestos!$B$11)*(1-Supuestos!$B$12)^14)*Supuestos!$I$28*(1+Supuestos!$B$9)^14,0) | I57: =IF(15<=Supuestos!$B$22,D57*Supuestos!$K$28,0) | J57: =C57+D57+E57-H57-I57 | K57: =H57+I57-(IF(15<=Supuestos!$J$28,Supuestos!$B$19*Supuestos!$B$28*(1+Supuestos!$B$8)^14,0)+IF(15<=Supuestos!$B$22,Supuestos!$B$20*Supuestos!$D$28*(1+Supuestos!$B$8)^14,0))-H57*Supuestos!$B$21 | L57: =L56+G57 | M57: =M56+J57
A58: 16 | B58: =$E$38*$B$39*(1+Supuestos!$B$8)^16 | C58: =$F$38*$B$39*(1+Supuestos!$B$8)^16*((1-Supuestos!$B$11)*(1-Supuestos!$B$12)^15) | D58: =$G$38*$B$39*(1+Supuestos!$B$8)^16*(1-Supuestos!$B$13)^16*Supuestos!$B$10 | E58: =$H$38*$B$39*(1+Supuestos!$B$8)^16 | F58: =B58-C58-D58-E58 | G58: =C58+D58+E58-(IF(16<=Supuestos!$J$28,Supuestos!$B$19*Supuestos!$B$28*(1+Supuestos!$B$8)^15,0)+IF(16<=Supuestos!$B$22,Supuestos!$B$20*Supuestos!$D$28*(1+Supuestos!$B$8)^15,0)) | H58: =IF(16<=Supuestos!$J$28,$C$38*$B$39*((1-Supuestos!$B$11)*(1-Supuestos!$B$12)^15)*Supuestos!$I$28*(1+Supuestos!$B$9)^15,0) | I58: =IF(16<=Supuestos!$B$22,D58*Supuestos!$K$28,0) | J58: =C58+D58+E58-H58-I58 | K58: =H58+I58-(IF(16<=Supuestos!$J$28,Supuestos!$B$19*Supuestos!$B$28*(1+Supuestos!$B$8)^15,0)+IF(16<=Supuestos!$B$22,Supuestos!$B$20*Supuestos!$D$28*(1+Supuestos!$B$8)^15,0))-H58*Supuestos!$B$21 | L58: =L57+G58 | M58: =M57+J58
A59: 17 | B59: =$E$38*$B$39*(1+Supuestos!$B$8)^17 | C59: =$F$38*$B$39*(1+Supuestos!$B$8)^17*((1-Supuestos!$B$11)*(1-Supuestos!$B$12)^16) | D59: =$G$38*$B$39*(1+Supuestos!$B$8)^17*(1-Supuestos!$B$13)^17*Supuestos!$B$10 | E59: =$H$38*$B$39*(1+Supuestos!$B$8)^17 | F59: =B59-C59-D59-E59 | G59: =C59+D59+E59-(IF(17<=Supuestos!$J$28,Supuestos!$B$19*Supuestos!$B$28*(1+Supuestos!$B$8)^16,0)+IF(17<=Supuestos!$B$22,Supuestos!$B$20*Supuestos!$D$28*(1+Supuestos!$B$8)^16,0)) | H59: =IF(17<=Supuestos!$J$28,$C$38*$B$39*((1-Supuestos!$B$11)*(1-Supuestos!$B$12)^16)*Supuestos!$I$28*(1+Supuestos!$B$9)^16,0) | I59: =IF(17<=Supuestos!$B$22,D59*Supuestos!$K$28,0) | J59: =C59+D59+E59-H59-I59 | K59: =H59+I59-(IF(17<=Supuestos!$J$28,Supuestos!$B$19*Supuestos!$B$28*(1+Supuestos!$B$8)^16,0)+IF(17<=Supuestos!$B$22,Supuestos!$B$20*Supuestos!$D$28*(1+Supuestos!$B$8)^16,0))-H59*Supuestos!$B$21 | L59: =L58+G59 | M59: =M58+J59
A60: 18 | B60: =$E$38*$B$39*(1+Supuestos!$B$8)^18 | C60: =$F$38*$B$39*(1+Supuestos!$B$8)^18*((1-Supuestos!$B$11)*(1-Supuestos!$B$12)^17) | D60: =$G$38*$B$39*(1+Supuestos!$B$8)^18*(1-Supuestos!$B$13)^18*Supuestos!$B$10 | E60: =$H$38*$B$39*(1+Supuestos!$B$8)^18 | F60: =B60-C60-D60-E60 | G60: =C60+D60+E60-(IF(18<=Supuestos!$J$28,Supuestos!$B$19*Supuestos!$B$28*(1+Supuestos!$B$8)^17,0)+IF(18<=Supuestos!$B$22,Supuestos!$B$20*Supuestos!$D$28*(1+Supuestos!$B$8)^17,0)) | H60: =IF(18<=Supuestos!$J$28,$C$38*$B$39*((1-Supuestos!$B$11)*(1-Supuestos!$B$12)^17)*Supuestos!$I$28*(1+Supuestos!$B$9)^17,0) | I60: =IF(18<=Supuestos!$B$22,D60*Supuestos!$K$28,0) | J60: =C60+D60+E60-H60-I60 | K60: =H60+I60-(IF(18<=Supuestos!$J$28,Supuestos!$B$19*Supuestos!$B$28*(1+Supuestos!$B$8)^17,0)+IF(18<=Supuestos!$B$22,Supuestos!$B$20*Supuestos!$D$28*(1+Supuestos!$B$8)^17,0))-H60*Supuestos!$B$21 | L60: =L59+G60 | M60: =M59+J60
A61: 19 | B61: =$E$38*$B$39*(1+Supuestos!$B$8)^19 | C61: =$F$38*$B$39*(1+Supuestos!$B$8)^19*((1-Supuestos!$B$11)*(1-Supuestos!$B$12)^18) | D61: =$G$38*$B$39*(1+Supuestos!$B$8)^19*(1-Supuestos!$B$13)^19*Supuestos!$B$10 | E61: =$H$38*$B$39*(1+Supuestos!$B$8)^19 | F61: =B61-C61-D61-E61 | G61: =C61+D61+E61-(IF(19<=Supuestos!$J$28,Supuestos!$B$19*Supuestos!$B$28*(1+Supuestos!$B$8)^18,0)+IF(19<=Supuestos!$B$22,Supuestos!$B$20*Supuestos!$D$28*(1+Supuestos!$B$8)^18,0)) | H61: =IF(19<=Supuestos!$J$28,$C$38*$B$39*((1-Supuestos!$B$11)*(1-Supuestos!$B$12)^18)*Supuestos!$I$28*(1+Supuestos!$B$9)^18,0) | I61: =IF(19<=Supuestos!$B$22,D61*Supuestos!$K$28,0) | J61: =C61+D61+E61-H61-I61 | K61: =H61+I61-(IF(19<=Supuestos!$J$28,Supuestos!$B$19*Supuestos!$B$28*(1+Supuestos!$B$8)^18,0)+IF(19<=Supuestos!$B$22,Supuestos!$B$20*Supuestos!$D$28*(1+Supuestos!$B$8)^18,0))-H61*Supuestos!$B$21 | L61: =L60+G61 | M61: =M60+J61
A62: 20 | B62: =$E$38*$B$39*(1+Supuestos!$B$8)^20 | C62: =$F$38*$B$39*(1+Supuestos!$B$8)^20*((1-Supuestos!$B$11)*(1-Supuestos!$B$12)^19) | D62: =$G$38*$B$39*(1+Supuestos!$B$8)^20*(1-Supuestos!$B$13)^20*Supuestos!$B$10 | E62: =$H$38*$B$39*(1+Supuestos!$B$8)^20 | F62: =B62-C62-D62-E62 | G62: =C62+D62+E62-(IF(20<=Supuestos!$J$28,Supuestos!$B$19*Supuestos!$B$28*(1+Supuestos!$B$8)^19,0)+IF(20<=Supuestos!$B$22,Supuestos!$B$20*Supuestos!$D$28*(1+Supuestos!$B$8)^19,0)) | H62: =IF(20<=Supuestos!$J$28,$C$38*$B$39*((1-Supuestos!$B$11)*(1-Supuestos!$B$12)^19)*Supuestos!$I$28*(1+Supuestos!$B$9)^19,0) | I62: =IF(20<=Supuestos!$B$22,D62*Supuestos!$K$28,0) | J62: =C62+D62+E62-H62-I62 | K62: =H62+I62-(IF(20<=Supuestos!$J$28,Supuestos!$B$19*Supuestos!$B$28*(1+Supuestos!$B$8)^19,0)+IF(20<=Supuestos!$B$22,Supuestos!$B$20*Supuestos!$D$28*(1+Supuestos!$B$8)^19,0))-H62*Supuestos!$B$21 | L62: =L61+G62 | M62: =M61+J62
A64: TIR compra (proyecto): | B64: =IRR(G42:G62) | C64: VPN compra @WACC: | D64: =G42+NPV(Supuestos!$B$7,G43:G62)
A65: TIR financiador: | B65: =IRR(K42:K62) | C65: VPN cliente PPA @WACC: | D65: =NPV(Supuestos!$B$7,J43:J62)
A66: Acumulado cliente PPA 20a: | B66: =SUM(J43:J62) | C66: Acumulado compra 20a: | D66: =SUM(G42:G62)
A68: 5. POR QUÉ ESTE DIMENSIONAMIENTO ES ÓPTIMO
A69: • PV 194 kWp — generador exento <0.7 MW (medición neta, sin permiso CNE). En SIN la generación solar cae en intermedio → recorta energía intermedia; no genera en punta, por lo que el BESS es la palanca de demanda.
A70: • BESS 1,503 kW / 2,940 kWh — recorta el pico de punta (arbitraje carga en base, descarga en punta, topado al kWh punta del recibo).
A71: • Dimensionado al consumo (rend. inputs.json); excedentes bajo medición neta expiran en 12 meses, por eso no se sobredimensiona el PV.
A72: • Corrección de factor de potencia incluida — palanca separada, capacitores a cargo del financiador en el esquema PPA (el cliente conserva 100% del ahorro FP).
A73: • LIBRO 100% EN VIVO: motor mensual §3 = fórmulas sobre los datos del recibo (§6) y Supuestos (réplica exacta del motor determinista, verificada al peso) — edita kWp/BESS/FC/tarifas o cualquier mes y TODO recalcula hasta la TIR.
A78: 6. DATOS DEL RECIBO (editables — el motor mensual §3 se alimenta de aquí)
A79: Mes | B79: Días | C79: kWh B | D79: kWh I | E79: kWh P | F79: kW B | G79: kW I | H79: kW P | I79: FP % | J79: Gen B $ | K79: Gen I $ | L79: Gen P $ | M79: Distribución $ | N79: Capacidad $ | O79: Otros vol $ | P79: Suministro $ | Q79: 2%BT+FP neto $ | R79: Cargo FP $ | S79: Yield kWh/kWp | T79: Hrs punta | U79: Días punta | V79: kWh tot | W79: Vol $/kWh | X79: Tarifa B $/kWh | Y79: Tarifa I $/kWh | Z79: Tarifa P $/kWh | AA79: Umbral kW | AB79: $/kW cap
A80: Abr-25 | B80: 30 | C80: 214676 | D80: 441881 | E80: 40790 | F80: 1664 | G80: 1482 | H80: 1423 | I80: 99.8 | J80: 279739.71 | K80: 1088884.1 | L80: 150912.85 | M80: 155254.58 | N80: 606579.05 | O80: 165005.47 | P80: 421.57 | Q80: -29361.57 | R80: 0 | S80: 139.92 | T80: 2 | U80: 22 | V80: =C80+D80+E80 | W80: =O80/V80 | X80: =IF(C80=0,Y80,J80/C80+W80) | Y80: =IF(D80=0,0,K80/D80+W80) | Z80: =IF(E80=0,0,L80/E80+W80) | AA80: =V80/(B80*24*$L$6) | AB80: =IFERROR(N80/MIN(H80,AA80),0)
A81: May-25 | B81: 31 | C81: 295372 | D81: 603920 | E81: 56005 | F81: 1872 | G81: 1999 | H81: 1544 | I81: 99.78 | J81: 330875.71 | K81: 1225414.1 | L81: 128167.44 | M81: 189125.39 | N81: 652046.64 | O81: 184945.49 | P81: 421.57 | Q81: -32531.96 | R81: 0 | S81: 139.624 | T81: 2 | U81: 21 | V81: =C81+D81+E81 | W81: =O81/V81 | X81: =IF(C81=0,Y81,J81/C81+W81) | Y81: =IF(D81=0,0,K81/D81+W81) | Z81: =IF(E81=0,0,L81/E81+W81) | AA81: =V81/(B81*24*$L$6) | AB81: =IFERROR(N81/MIN(H81,AA81),0)
A82: Jun-25 | B82: 30 | C82: 303759 | D82: 583099 | E82: 57926 | F82: 1445 | G82: 1926 | H82: 1509 | I82: 99.66 | J82: 348350.82 | K82: 1211271.6 | L82: 135714.83 | M82: 182218.86 | N82: 652401.06 | O82: 182910.17 | P82: 421.57 | Q82: -32559.47 | R82: 0 | S82: 127.44 | T82: 2 | U82: 21 | V82: =C82+D82+E82 | W82: =O82/V82 | X82: =IF(C82=0,Y82,J82/C82+W82) | Y82: =IF(D82=0,0,K82/D82+W82) | Z82: =IF(E82=0,0,L82/E82+W82) | AA82: =V82/(B82*24*$L$6) | AB82: =IFERROR(N82/MIN(H82,AA82),0)
A83: Jul-25 | B83: 31 | C83: 298810 | D83: 641148 | E83: 63933 | F83: 1447 | G83: 1977 | H83: 1470 | I83: 99.52 | J83: 347814.84 | K83: 1351860.6 | L83: 152032.67 | M83: 187043.97 | N83: 645065.4 | O83: 194353.29 | P83: 421.57 | Q83: -31664.52 | R83: 0 | S83: 131.192 | T83: 2 | U83: 23 | V83: =C83+D83+E83 | W83: =O83/V83 | X83: =IF(C83=0,Y83,J83/C83+W83) | Y83: =IF(D83=0,0,K83/D83+W83) | Z83: =IF(E83=0,0,L83/E83+W83) | AA83: =V83/(B83*24*$L$6) | AB83: =IFERROR(N83/MIN(H83,AA83),0)
A84: Ago-25 | B84: 31 | C84: 312207 | D84: 627120 | E84: 57334 | F84: 1677 | G84: 1860 | H84: 1607 | I84: 99.49 | J84: 363939.7 | K84: 1324101.2 | L84: 136529.45 | M84: 175974.6 | N84: 706164.01 | O84: 192953.57 | P84: 421.57 | Q84: -31900.92 | R84: 0 | S84: 123.256 | T84: 2 | U84: 21 | V84: =C84+D84+E84 | W84: =O84/V84 | X84: =IF(C84=0,Y84,J84/C84+W84) | Y84: =IF(D84=0,0,K84/D84+W84) | Z84: =IF(E84=0,0,L84/E84+W84) | AA84: =V84/(B84*24*$L$6) | AB84: =IFERROR(N84/MIN(H84,AA84),0)
A85: Sep-25 | B85: 30 | C85: 278559 | D85: 532793 | E85: 48869 | F85: 1495 | G85: 1708 | H85: 1423 | I85: 99.74 | J85: 321735.65 | K85: 1114656.2 | L85: 115306.41 | M85: 161593.88 | N85: 619588.43 | O85: 170065.7 | P85: 421.57 | Q85: -30040.41 | R85: 0 | S85: 118.32 | T85: 2 | U85: 21 | V85: =C85+D85+E85 | W85: =O85/V85 | X85: =IF(C85=0,Y85,J85/C85+W85) | Y85: =IF(D85=0,0,K85/D85+W85) | Z85: =IF(E85=0,0,L85/E85+W85) | AA85: =V85/(B85*24*$L$6) | AB85: =IFERROR(N85/MIN(H85,AA85),0)
A86: Oct-25 | B86: 31 | C86: 249743 | D86: 543909 | E86: 67493 | F86: 1369 | G86: 1399 | H86: 1371 | I86: 99.85 | J86: 288453.17 | K86: 1137912 | L86: 159256.48 | M86: 148306.71 | N86: 619435.46 | O86: 170248.38 | P86: 421.57 | Q86: -30288.41 | R86: 0 | S86: 121.768 | T86: 2 | U86: 23 | V86: =C86+D86+E86 | W86: =O86/V86 | X86: =IF(C86=0,Y86,J86/C86+W86) | Y86: =IF(D86=0,0,K86/D86+W86) | Z86: =IF(E86=0,0,L86/E86+W86) | AA86: =V86/(B86*24*$L$6) | AB86: =IFERROR(N86/MIN(H86,AA86),0)
A87: Nov-25 | B87: 30 | C87: 268822 | D87: 440446 | E87: 104467 | F87: 1433 | G87: 1616 | H87: 1579 | I87: 99.95 | J87: 301161.29 | K87: 893797.07 | L87: 239093.62 | M87: 152889.76 | N87: 666874.86 | O87: 160875.42 | P87: 421.57 | Q87: -28981.36 | R87: 0 | S87: 114.96 | T87: 4 | U87: 19 | V87: =C87+D87+E87 | W87: =O87/V87 | X87: =IF(C87=0,Y87,J87/C87+W87) | Y87: =IF(D87=0,0,K87/D87+W87) | Z87: =IF(E87=0,0,L87/E87+W87) | AA87: =V87/(B87*24*$L$6) | AB87: =IFERROR(N87/MIN(H87,AA87),0)
A88: Dic-25 | B88: 31 | C88: 276320 | D88: 485482 | E88: 119171 | F88: 1591 | G88: 1453 | H88: 1583 | I88: 99.9 | J88: 294087.38 | K88: 935960.75 | L88: 259113.51 | M88: 150524.51 | N88: 635147.09 | O88: 174168.35 | P88: 421.57 | Q88: -29393.08 | R88: 0 | S88: 112.592 | T88: 4 | U88: 22 | V88: =C88+D88+E88 | W88: =O88/V88 | X88: =IF(C88=0,Y88,J88/C88+W88) | Y88: =IF(D88=0,0,K88/D88+W88) | Z88: =IF(E88=0,0,L88/E88+W88) | AA88: =V88/(B88*24*$L$6) | AB88: =IFERROR(N88/MIN(H88,AA88),0)
A89: Ene-26 | B89: 31 | C89: 268796 | D89: 477099 | E89: 114681 | F89: 1453 | G89: 1616 | H89: 1583 | I89: 99.9 | J89: 279655.36 | K89: 899093.07 | L89: 243743 | M89: 148461.92 | N89: 620852.6 | O89: 167468.09 | P89: 452.58 | Q89: -28316.72 | R89: 0 | S89: 116.312 | T89: 4 | U89: 21 | V89: =C89+D89+E89 | W89: =O89/V89 | X89: =IF(C89=0,Y89,J89/C89+W89) | Y89: =IF(D89=0,0,K89/D89+W89) | Z89: =IF(E89=0,0,L89/E89+W89) | AA89: =V89/(B89*24*$L$6) | AB89: =IFERROR(N89/MIN(H89,AA89),0)
A90: Feb-26 | B90: 28 | C90: 222447 | D90: 382846 | E90: 91302 | F90: 1414 | G90: 1518 | H90: 1476 | I90: 99.98 | J90: 231567.33 | K90: 721894.42 | L90: 194162.83 | M90: 139458.66 | N90: 579226.68 | O90: 135557.38 | P90: 452.58 | Q90: -24027.84 | R90: 0 | S90: 113.792 | T90: 4 | U90: 19 | V90: =C90+D90+E90 | W90: =O90/V90 | X90: =IF(C90=0,Y90,J90/C90+W90) | Y90: =IF(D90=0,0,K90/D90+W90) | Z90: =IF(E90=0,0,L90/E90+W90) | AA90: =V90/(B90*24*$L$6) | AB90: =IFERROR(N90/MIN(H90,AA90),0)
A91: Mar-26 | B91: 31 | C91: 281755 | D91: 452258 | E91: 108970 | F91: 1467 | G91: 1562 | H91: 1444 | I91: 99.97 | J91: 293476.01 | K91: 853275.17 | L91: 231877.26 | M91: 143500.94 | N91: 567001.04 | O91: 164044.5 | P91: 452.58 | Q91: -27043.53 | R91: 0 | S91: 140.616 | T91: 4 | U91: 21 | V91: =C91+D91+E91 | W91: =O91/V91 | X91: =IF(C91=0,Y91,J91/C91+W91) | Y91: =IF(D91=0,0,K91/D91+W91) | Z91: =IF(E91=0,0,L91/E91+W91) | AA91: =V91/(B91*24*$L$6) | AB91: =IFERROR(N91/MIN(H91,AA91),0)
A92: Filas = recibo ancla (parseado) + meses reconstruidos del CONSUMO HISTÓRICO (subtotal al peso; split TOU por shares del ancla). Capacidad a MIN(kW punta, umbral); tarifas por banda = concepto/kWh + vol/kWh; col Q<0 (bonificación FP) aplica claw-back al ahorro. Válido <700 kWp (medición neta). Excedentes PV a $0.
O94: Techo — referencia satelital (ruta HelioScope; cruz roja = punto verificado) · confianza ?

Sheet Fiesta Inn Periférico Sur (C
A1: Fiesta Inn Periférico Sur (CDMX) — Memoria de cálculo y propuesta energética
A2: RPU 968221200700 · GDMTH SIN · Demanda contratada 366 kW · 12 meses de recibo
A3: Régimen: GENERADOR EXENTO — Medición Neta (sin permiso; Art. 30 LSE; RES/142/2017)
A5: PARÁMETROS (desde Supuestos — edítalos ahí)
A6: PV kWp | B6: =Supuestos!$B$29 | C6: BESS kW | D6: =Supuestos!$C$29 | E6: BESS kWh | F6: =Supuestos!$D$29 | G6: FP corrección | H6: =Supuestos!$E$29 | I6: Entrega útil kWh | J6: =Supuestos!$D$29*Supuestos!$B$17*SQRT(Supuestos!$B$18) | K6: FC umbral | L6: 0.57
A8: 1. ESTRUCTURA DE COSTO Y AHORRO (pre-IVA, año base · fórmulas vivas ← §3)
A9: Concepto | B9: $ / año | C9: Nota
A10: Tarifa Actual (CFE pleno, sin proyecto) | B10: =$E$38*$B$39 | C10: Σ recibos × anualización
A11: (−) Ahorro PV (energía + demanda) | B11: =$F$38*$B$39 | C11: intermedio + umbral
A12: (−) Ahorro BESS (punta + arbitraje) | B12: =$G$38*$B$39 | C12: recorte punta + arbitraje (incl. claw)
A13: (−) Ahorro FP (corrección) | B13: =$H$38*$B$39 | C13: multa factor de potencia
A14: (=) Costo neto con proyecto | B14: =B10-B11-B12-B13
A15: Ahorro proyecto / año | B15: =B11+B12+B13
A16: Ahorro % | B16: =B15/B10
A18: 2. CAPEX (fórmulas vivas desde Supuestos)
A19: CAPEX PV | B19: =Supuestos!$B$29*1000*Supuestos!$F$29*Supuestos!$B$5
A20: CAPEX BESS | B20: =Supuestos!$D$29*Supuestos!$G$29*Supuestos!$B$5
A21: CAPEX capacitor (FP) | B21: =Supuestos!$H$29
A22: CAPEX TOTAL | B22: =B19+B20+B21
A24: 3. RESUMEN MENSUAL — Tarifa Actual vs Con Proyecto (fórmulas vivas ← §6 y Supuestos)
A25: Mes | B25: kWh Consumo | C25: Gen PV kWh | D25: BESS desc kWh | E25: Tarifa Actual $ | F25: Ah PV $ | G25: Ah BESS $ | H25: Ah FP $ | I25: Costo c/proy $ | J25: Ahorro $ | K25: Ahorro %
A26: =A80 | B26: =V80 | C26: =Supuestos!$B$29*S80 | D26: =MIN($J$6*U80,E80) | E26: =SUM(J80:Q80) | F26: =(MIN(C26,D80)*Y80+(MIN(H80,AA80)-MIN(H80,(V80-MIN(C26,D80))/($B$80*24*$L$6)))*AB80)*IF(Q80<0,1+Q80/SUM(J80:P80),1) | G26: =((MIN(H80,(V80-MIN(C26,D80))/($B$80*24*$L$6))-MIN(MAX(H80-MIN(Supuestos!$C$29,IF(T80>0,$J$6/T80,0)),0),(V80-MIN(C26,D80))/($B$80*24*$L$6)))*AB80+D26*Z80-D26/Supuestos!$B$18*X80)*IF(Q80<0,1+Q80/SUM(J80:P80),1) | H26: =IF(Supuestos!$E$29="Sí",R80,0) | I26: =E26-J26 | J26: =F26+G26+H26 | K26: =J26/E26
A27: =A81 | B27: =V81 | C27: =Supuestos!$B$29*S81 | D27: =MIN($J$6*U81,E81) | E27: =SUM(J81:Q81) | F27: =(MIN(C27,D81)*Y81+(MIN(H81,AA81)-MIN(H81,(V81-MIN(C27,D81))/($B$81*24*$L$6)))*AB81)*IF(Q81<0,1+Q81/SUM(J81:P81),1) | G27: =((MIN(H81,(V81-MIN(C27,D81))/($B$81*24*$L$6))-MIN(MAX(H81-MIN(Supuestos!$C$29,IF(T81>0,$J$6/T81,0)),0),(V81-MIN(C27,D81))/($B$81*24*$L$6)))*AB81+D27*Z81-D27/Supuestos!$B$18*X81)*IF(Q81<0,1+Q81/SUM(J81:P81),1) | H27: =IF(Supuestos!$E$29="Sí",R81,0) | I27: =E27-J27 | J27: =F27+G27+H27 | K27: =J27/E27
A28: =A82 | B28: =V82 | C28: =Supuestos!$B$29*S82 | D28: =MIN($J$6*U82,E82) | E28: =SUM(J82:Q82) | F28: =(MIN(C28,D82)*Y82+(MIN(H82,AA82)-MIN(H82,(V82-MIN(C28,D82))/($B$82*24*$L$6)))*AB82)*IF(Q82<0,1+Q82/SUM(J82:P82),1) | G28: =((MIN(H82,(V82-MIN(C28,D82))/($B$82*24*$L$6))-MIN(MAX(H82-MIN(Supuestos!$C$29,IF(T82>0,$J$6/T82,0)),0),(V82-MIN(C28,D82))/($B$82*24*$L$6)))*AB82+D28*Z82-D28/Supuestos!$B$18*X82)*IF(Q82<0,1+Q82/SUM(J82:P82),1) | H28: =IF(Supuestos!$E$29="Sí",R82,0) | I28: =E28-J28 | J28: =F28+G28+H28 | K28: =J28/E28
A29: =A83 | B29: =V83 | C29: =Supuestos!$B$29*S83 | D29: =MIN($J$6*U83,E83) | E29: =SUM(J83:Q83) | F29: =(MIN(C29,D83)*Y83+(MIN(H83,AA83)-MIN(H83,(V83-MIN(C29,D83))/($B$83*24*$L$6)))*AB83)*IF(Q83<0,1+Q83/SUM(J83:P83),1) | G29: =((MIN(H83,(V83-MIN(C29,D83))/($B$83*24*$L$6))-MIN(MAX(H83-MIN(Supuestos!$C$29,IF(T83>0,$J$6/T83,0)),0),(V83-MIN(C29,D83))/($B$83*24*$L$6)))*AB83+D29*Z83-D29/Supuestos!$B$18*X83)*IF(Q83<0,1+Q83/SUM(J83:P83),1) | H29: =IF(Supuestos!$E$29="Sí",R83,0) | I29: =E29-J29 | J29: =F29+G29+H29 | K29: =J29/E29
A30: =A84 | B30: =V84 | C30: =Supuestos!$B$29*S84 | D30: =MIN($J$6*U84,E84) | E30: =SUM(J84:Q84) | F30: =(MIN(C30,D84)*Y84+(MIN(H84,AA84)-MIN(H84,(V84-MIN(C30,D84))/($B$84*24*$L$6)))*AB84)*IF(Q84<0,1+Q84/SUM(J84:P84),1) | G30: =((MIN(H84,(V84-MIN(C30,D84))/($B$84*24*$L$6))-MIN(MAX(H84-MIN(Supuestos!$C$29,IF(T84>0,$J$6/T84,0)),0),(V84-MIN(C30,D84))/($B$84*24*$L$6)))*AB84+D30*Z84-D30/Supuestos!$B$18*X84)*IF(Q84<0,1+Q84/SUM(J84:P84),1) | H30: =IF(Supuestos!$E$29="Sí",R84,0) | I30: =E30-J30 | J30: =F30+G30+H30 | K30: =J30/E30
A31: =A85 | B31: =V85 | C31: =Supuestos!$B$29*S85 | D31: =MIN($J$6*U85,E85) | E31: =SUM(J85:Q85) | F31: =(MIN(C31,D85)*Y85+(MIN(H85,AA85)-MIN(H85,(V85-MIN(C31,D85))/($B$85*24*$L$6)))*AB85)*IF(Q85<0,1+Q85/SUM(J85:P85),1) | G31: =((MIN(H85,(V85-MIN(C31,D85))/($B$85*24*$L$6))-MIN(MAX(H85-MIN(Supuestos!$C$29,IF(T85>0,$J$6/T85,0)),0),(V85-MIN(C31,D85))/($B$85*24*$L$6)))*AB85+D31*Z85-D31/Supuestos!$B$18*X85)*IF(Q85<0,1+Q85/SUM(J85:P85),1) | H31: =IF(Supuestos!$E$29="Sí",R85,0) | I31: =E31-J31 | J31: =F31+G31+H31 | K31: =J31/E31
A32: =A86 | B32: =V86 | C32: =Supuestos!$B$29*S86 | D32: =MIN($J$6*U86,E86) | E32: =SUM(J86:Q86) | F32: =(MIN(C32,D86)*Y86+(MIN(H86,AA86)-MIN(H86,(V86-MIN(C32,D86))/($B$86*24*$L$6)))*AB86)*IF(Q86<0,1+Q86/SUM(J86:P86),1) | G32: =((MIN(H86,(V86-MIN(C32,D86))/($B$86*24*$L$6))-MIN(MAX(H86-MIN(Supuestos!$C$29,IF(T86>0,$J$6/T86,0)),0),(V86-MIN(C32,D86))/($B$86*24*$L$6)))*AB86+D32*Z86-D32/Supuestos!$B$18*X86)*IF(Q86<0,1+Q86/SUM(J86:P86),1) | H32: =IF(Supuestos!$E$29="Sí",R86,0) | I32: =E32-J32 | J32: =F32+G32+H32 | K32: =J32/E32
A33: =A87 | B33: =V87 | C33: =Supuestos!$B$29*S87 | D33: =MIN($J$6*U87,E87) | E33: =SUM(J87:Q87) | F33: =(MIN(C33,D87)*Y87+(MIN(H87,AA87)-MIN(H87,(V87-MIN(C33,D87))/($B$87*24*$L$6)))*AB87)*IF(Q87<0,1+Q87/SUM(J87:P87),1) | G33: =((MIN(H87,(V87-MIN(C33,D87))/($B$87*24*$L$6))-MIN(MAX(H87-MIN(Supuestos!$C$29,IF(T87>0,$J$6/T87,0)),0),(V87-MIN(C33,D87))/($B$87*24*$L$6)))*AB87+D33*Z87-D33/Supuestos!$B$18*X87)*IF(Q87<0,1+Q87/SUM(J87:P87),1) | H33: =IF(Supuestos!$E$29="Sí",R87,0) | I33: =E33-J33 | J33: =F33+G33+H33 | K33: =J33/E33
A34: =A88 | B34: =V88 | C34: =Supuestos!$B$29*S88 | D34: =MIN($J$6*U88,E88) | E34: =SUM(J88:Q88) | F34: =(MIN(C34,D88)*Y88+(MIN(H88,AA88)-MIN(H88,(V88-MIN(C34,D88))/($B$88*24*$L$6)))*AB88)*IF(Q88<0,1+Q88/SUM(J88:P88),1) | G34: =((MIN(H88,(V88-MIN(C34,D88))/($B$88*24*$L$6))-MIN(MAX(H88-MIN(Supuestos!$C$29,IF(T88>0,$J$6/T88,0)),0),(V88-MIN(C34,D88))/($B$88*24*$L$6)))*AB88+D34*Z88-D34/Supuestos!$B$18*X88)*IF(Q88<0,1+Q88/SUM(J88:P88),1) | H34: =IF(Supuestos!$E$29="Sí",R88,0) | I34: =E34-J34 | J34: =F34+G34+H34 | K34: =J34/E34
A35: =A89 | B35: =V89 | C35: =Supuestos!$B$29*S89 | D35: =MIN($J$6*U89,E89) | E35: =SUM(J89:Q89) | F35: =(MIN(C35,D89)*Y89+(MIN(H89,AA89)-MIN(H89,(V89-MIN(C35,D89))/($B$89*24*$L$6)))*AB89)*IF(Q89<0,1+Q89/SUM(J89:P89),1) | G35: =((MIN(H89,(V89-MIN(C35,D89))/($B$89*24*$L$6))-MIN(MAX(H89-MIN(Supuestos!$C$29,IF(T89>0,$J$6/T89,0)),0),(V89-MIN(C35,D89))/($B$89*24*$L$6)))*AB89+D35*Z89-D35/Supuestos!$B$18*X89)*IF(Q89<0,1+Q89/SUM(J89:P89),1) | H35: =IF(Supuestos!$E$29="Sí",R89,0) | I35: =E35-J35 | J35: =F35+G35+H35 | K35: =J35/E35
A36: =A90 | B36: =V90 | C36: =Supuestos!$B$29*S90 | D36: =MIN($J$6*U90,E90) | E36: =SUM(J90:Q90) | F36: =(MIN(C36,D90)*Y90+(MIN(H90,AA90)-MIN(H90,(V90-MIN(C36,D90))/($B$90*24*$L$6)))*AB90)*IF(Q90<0,1+Q90/SUM(J90:P90),1) | G36: =((MIN(H90,(V90-MIN(C36,D90))/($B$90*24*$L$6))-MIN(MAX(H90-MIN(Supuestos!$C$29,IF(T90>0,$J$6/T90,0)),0),(V90-MIN(C36,D90))/($B$90*24*$L$6)))*AB90+D36*Z90-D36/Supuestos!$B$18*X90)*IF(Q90<0,1+Q90/SUM(J90:P90),1) | H36: =IF(Supuestos!$E$29="Sí",R90,0) | I36: =E36-J36 | J36: =F36+G36+H36 | K36: =J36/E36
A37: =A91 | B37: =V91 | C37: =Supuestos!$B$29*S91 | D37: =MIN($J$6*U91,E91) | E37: =SUM(J91:Q91) | F37: =(MIN(C37,D91)*Y91+(MIN(H91,AA91)-MIN(H91,(V91-MIN(C37,D91))/($B$91*24*$L$6)))*AB91)*IF(Q91<0,1+Q91/SUM(J91:P91),1) | G37: =((MIN(H91,(V91-MIN(C37,D91))/($B$91*24*$L$6))-MIN(MAX(H91-MIN(Supuestos!$C$29,IF(T91>0,$J$6/T91,0)),0),(V91-MIN(C37,D91))/($B$91*24*$L$6)))*AB91+D37*Z91-D37/Supuestos!$B$18*X91)*IF(Q91<0,1+Q91/SUM(J91:P91),1) | H37: =IF(Supuestos!$E$29="Sí",R91,0) | I37: =E37-J37 | J37: =F37+G37+H37 | K37: =J37/E37
A38: TOTAL | B38: =SUM(B26:B37) | C38: =SUM(C26:C37) | D38: =SUM(D26:D37) | E38: =SUM(E26:E37) | F38: =SUM(F26:F37) | G38: =SUM(G26:G37) | H38: =SUM(H26:H37) | I38: =SUM(I26:I37) | J38: =SUM(J26:J37) | K38: =J38/E38
A39: Factor anualización (12/meses): | B39: 1
A40: 4. PROYECCIÓN 20 AÑOS — Comprar vs PPA/Ahorro compartido
A41: Año | B41: Tarifa Actual $ | C41: Ah PV $ | D41: Ah BESS $ | E41: Ah FP $ | F41: Costo c/proy $ | G41: Flujo Compra $ | H41: Pago PPA $ | I41: Comisión $ | J41: Flujo Cliente PPA $ | K41: Flujo Financiador $ | L41: Acum Compra $ | M41: Acum Cliente PPA $
A42: 0 | G42: =-B22 | K42: =-B22 | L42: =G42 | M42: 0
A43: 1 | B43: =$E$38*$B$39*(1+Supuestos!$B$8)^1 | C43: =$F$38*$B$39*(1+Supuestos!$B$8)^1*((1-Supuestos!$B$11)*(1-Supuestos!$B$12)^0) | D43: =$G$38*$B$39*(1+Supuestos!$B$8)^1*(1-Supuestos!$B$13)^1*Supuestos!$B$10 | E43: =$H$38*$B$39*(1+Supuestos!$B$8)^1 | F43: =B43-C43-D43-E43 | G43: =C43+D43+E43-(IF(1<=Supuestos!$J$29,Supuestos!$B$19*Supuestos!$B$29*(1+Supuestos!$B$8)^0,0)+IF(1<=Supuestos!$B$22,Supuestos!$B$20*Supuestos!$D$29*(1+Supuestos!$B$8)^0,0)) | H43: =IF(1<=Supuestos!$J$29,$C$38*$B$39*((1-Supuestos!$B$11)*(1-Supuestos!$B$12)^0)*Supuestos!$I$29*(1+Supuestos!$B$9)^0,0) | I43: =IF(1<=Supuestos!$B$22,D43*Supuestos!$K$29,0) | J43: =C43+D43+E43-H43-I43 | K43: =H43+I43-(IF(1<=Supuestos!$J$29,Supuestos!$B$19*Supuestos!$B$29*(1+Supuestos!$B$8)^0,0)+IF(1<=Supuestos!$B$22,Supuestos!$B$20*Supuestos!$D$29*(1+Supuestos!$B$8)^0,0))-H43*Supuestos!$B$21 | L43: =L42+G43 | M43: =M42+J43
A44: 2 | B44: =$E$38*$B$39*(1+Supuestos!$B$8)^2 | C44: =$F$38*$B$39*(1+Supuestos!$B$8)^2*((1-Supuestos!$B$11)*(1-Supuestos!$B$12)^1) | D44: =$G$38*$B$39*(1+Supuestos!$B$8)^2*(1-Supuestos!$B$13)^2*Supuestos!$B$10 | E44: =$H$38*$B$39*(1+Supuestos!$B$8)^2 | F44: =B44-C44-D44-E44 | G44: =C44+D44+E44-(IF(2<=Supuestos!$J$29,Supuestos!$B$19*Supuestos!$B$29*(1+Supuestos!$B$8)^1,0)+IF(2<=Supuestos!$B$22,Supuestos!$B$20*Supuestos!$D$29*(1+Supuestos!$B$8)^1,0)) | H44: =IF(2<=Supuestos!$J$29,$C$38*$B$39*((1-Supuestos!$B$11)*(1-Supuestos!$B$12)^1)*Supuestos!$I$29*(1+Supuestos!$B$9)^1,0) | I44: =IF(2<=Supuestos!$B$22,D44*Supuestos!$K$29,0) | J44: =C44+D44+E44-H44-I44 | K44: =H44+I44-(IF(2<=Supuestos!$J$29,Supuestos!$B$19*Supuestos!$B$29*(1+Supuestos!$B$8)^1,0)+IF(2<=Supuestos!$B$22,Supuestos!$B$20*Supuestos!$D$29*(1+Supuestos!$B$8)^1,0))-H44*Supuestos!$B$21 | L44: =L43+G44 | M44: =M43+J44
A45: 3 | B45: =$E$38*$B$39*(1+Supuestos!$B$8)^3 | C45: =$F$38*$B$39*(1+Supuestos!$B$8)^3*((1-Supuestos!$B$11)*(1-Supuestos!$B$12)^2) | D45: =$G$38*$B$39*(1+Supuestos!$B$8)^3*(1-Supuestos!$B$13)^3*Supuestos!$B$10 | E45: =$H$38*$B$39*(1+Supuestos!$B$8)^3 | F45: =B45-C45-D45-E45 | G45: =C45+D45+E45-(IF(3<=Supuestos!$J$29,Supuestos!$B$19*Supuestos!$B$29*(1+Supuestos!$B$8)^2,0)+IF(3<=Supuestos!$B$22,Supuestos!$B$20*Supuestos!$D$29*(1+Supuestos!$B$8)^2,0)) | H45: =IF(3<=Supuestos!$J$29,$C$38*$B$39*((1-Supuestos!$B$11)*(1-Supuestos!$B$12)^2)*Supuestos!$I$29*(1+Supuestos!$B$9)^2,0) | I45: =IF(3<=Supuestos!$B$22,D45*Supuestos!$K$29,0) | J45: =C45+D45+E45-H45-I45 | K45: =H45+I45-(IF(3<=Supuestos!$J$29,Supuestos!$B$19*Supuestos!$B$29*(1+Supuestos!$B$8)^2,0)+IF(3<=Supuestos!$B$22,Supuestos!$B$20*Supuestos!$D$29*(1+Supuestos!$B$8)^2,0))-H45*Supuestos!$B$21 | L45: =L44+G45 | M45: =M44+J45
A46: 4 | B46: =$E$38*$B$39*(1+Supuestos!$B$8)^4 | C46: =$F$38*$B$39*(1+Supuestos!$B$8)^4*((1-Supuestos!$B$11)*(1-Supuestos!$B$12)^3) | D46: =$G$38*$B$39*(1+Supuestos!$B$8)^4*(1-Supuestos!$B$13)^4*Supuestos!$B$10 | E46: =$H$38*$B$39*(1+Supuestos!$B$8)^4 | F46: =B46-C46-D46-E46 | G46: =C46+D46+E46-(IF(4<=Supuestos!$J$29,Supuestos!$B$19*Supuestos!$B$29*(1+Supuestos!$B$8)^3,0)+IF(4<=Supuestos!$B$22,Supuestos!$B$20*Supuestos!$D$29*(1+Supuestos!$B$8)^3,0)) | H46: =IF(4<=Supuestos!$J$29,$C$38*$B$39*((1-Supuestos!$B$11)*(1-Supuestos!$B$12)^3)*Supuestos!$I$29*(1+Supuestos!$B$9)^3,0) | I46: =IF(4<=Supuestos!$B$22,D46*Supuestos!$K$29,0) | J46: =C46+D46+E46-H46-I46 | K46: =H46+I46-(IF(4<=Supuestos!$J$29,Supuestos!$B$19*Supuestos!$B$29*(1+Supuestos!$B$8)^3,0)+IF(4<=Supuestos!$B$22,Supuestos!$B$20*Supuestos!$D$29*(1+Supuestos!$B$8)^3,0))-H46*Supuestos!$B$21 | L46: =L45+G46 | M46: =M45+J46
A47: 5 | B47: =$E$38*$B$39*(1+Supuestos!$B$8)^5 | C47: =$F$38*$B$39*(1+Supuestos!$B$8)^5*((1-Supuestos!$B$11)*(1-Supuestos!$B$12)^4) | D47: =$G$38*$B$39*(1+Supuestos!$B$8)^5*(1-Supuestos!$B$13)^5*Supuestos!$B$10 | E47: =$H$38*$B$39*(1+Supuestos!$B$8)^5 | F47: =B47-C47-D47-E47 | G47: =C47+D47+E47-(IF(5<=Supuestos!$J$29,Supuestos!$B$19*Supuestos!$B$29*(1+Supuestos!$B$8)^4,0)+IF(5<=Supuestos!$B$22,Supuestos!$B$20*Supuestos!$D$29*(1+Supuestos!$B$8)^4,0)) | H47: =IF(5<=Supuestos!$J$29,$C$38*$B$39*((1-Supuestos!$B$11)*(1-Supuestos!$B$12)^4)*Supuestos!$I$29*(1+Supuestos!$B$9)^4,0) | I47: =IF(5<=Supuestos!$B$22,D47*Supuestos!$K$29,0) | J47: =C47+D47+E47-H47-I47 | K47: =H47+I47-(IF(5<=Supuestos!$J$29,Supuestos!$B$19*Supuestos!$B$29*(1+Supuestos!$B$8)^4,0)+IF(5<=Supuestos!$B$22,Supuestos!$B$20*Supuestos!$D$29*(1+Supuestos!$B$8)^4,0))-H47*Supuestos!$B$21 | L47: =L46+G47 | M47: =M46+J47
A48: 6 | B48: =$E$38*$B$39*(1+Supuestos!$B$8)^6 | C48: =$F$38*$B$39*(1+Supuestos!$B$8)^6*((1-Supuestos!$B$11)*(1-Supuestos!$B$12)^5) | D48: =$G$38*$B$39*(1+Supuestos!$B$8)^6*(1-Supuestos!$B$13)^6*Supuestos!$B$10 | E48: =$H$38*$B$39*(1+Supuestos!$B$8)^6 | F48: =B48-C48-D48-E48 | G48: =C48+D48+E48-(IF(6<=Supuestos!$J$29,Supuestos!$B$19*Supuestos!$B$29*(1+Supuestos!$B$8)^5,0)+IF(6<=Supuestos!$B$22,Supuestos!$B$20*Supuestos!$D$29*(1+Supuestos!$B$8)^5,0)) | H48: =IF(6<=Supuestos!$J$29,$C$38*$B$39*((1-Supuestos!$B$11)*(1-Supuestos!$B$12)^5)*Supuestos!$I$29*(1+Supuestos!$B$9)^5,0) | I48: =IF(6<=Supuestos!$B$22,D48*Supuestos!$K$29,0) | J48: =C48+D48+E48-H48-I48 | K48: =H48+I48-(IF(6<=Supuestos!$J$29,Supuestos!$B$19*Supuestos!$B$29*(1+Supuestos!$B$8)^5,0)+IF(6<=Supuestos!$B$22,Supuestos!$B$20*Supuestos!$D$29*(1+Supuestos!$B$8)^5,0))-H48*Supuestos!$B$21 | L48: =L47+G48 | M48: =M47+J48
A49: 7 | B49: =$E$38*$B$39*(1+Supuestos!$B$8)^7 | C49: =$F$38*$B$39*(1+Supuestos!$B$8)^7*((1-Supuestos!$B$11)*(1-Supuestos!$B$12)^6) | D49: =$G$38*$B$39*(1+Supuestos!$B$8)^7*(1-Supuestos!$B$13)^7*Supuestos!$B$10 | E49: =$H$38*$B$39*(1+Supuestos!$B$8)^7 | F49: =B49-C49-D49-E49 | G49: =C49+D49+E49-(IF(7<=Supuestos!$J$29,Supuestos!$B$19*Supuestos!$B$29*(1+Supuestos!$B$8)^6,0)+IF(7<=Supuestos!$B$22,Supuestos!$B$20*Supuestos!$D$29*(1+Supuestos!$B$8)^6,0)) | H49: =IF(7<=Supuestos!$J$29,$C$38*$B$39*((1-Supuestos!$B$11)*(1-Supuestos!$B$12)^6)*Supuestos!$I$29*(1+Supuestos!$B$9)^6,0) | I49: =IF(7<=Supuestos!$B$22,D49*Supuestos!$K$29,0) | J49: =C49+D49+E49-H49-I49 | K49: =H49+I49-(IF(7<=Supuestos!$J$29,Supuestos!$B$19*Supuestos!$B$29*(1+Supuestos!$B$8)^6,0)+IF(7<=Supuestos!$B$22,Supuestos!$B$20*Supuestos!$D$29*(1+Supuestos!$B$8)^6,0))-H49*Supuestos!$B$21 | L49: =L48+G49 | M49: =M48+J49
A50: 8 | B50: =$E$38*$B$39*(1+Supuestos!$B$8)^8 | C50: =$F$38*$B$39*(1+Supuestos!$B$8)^8*((1-Supuestos!$B$11)*(1-Supuestos!$B$12)^7) | D50: =$G$38*$B$39*(1+Supuestos!$B$8)^8*(1-Supuestos!$B$13)^8*Supuestos!$B$10 | E50: =$H$38*$B$39*(1+Supuestos!$B$8)^8 | F50: =B50-C50-D50-E50 | G50: =C50+D50+E50-(IF(8<=Supuestos!$J$29,Supuestos!$B$19*Supuestos!$B$29*(1+Supuestos!$B$8)^7,0)+IF(8<=Supuestos!$B$22,Supuestos!$B$20*Supuestos!$D$29*(1+Supuestos!$B$8)^7,0)) | H50: =IF(8<=Supuestos!$J$29,$C$38*$B$39*((1-Supuestos!$B$11)*(1-Supuestos!$B$12)^7)*Supuestos!$I$29*(1+Supuestos!$B$9)^7,0) | I50: =IF(8<=Supuestos!$B$22,D50*Supuestos!$K$29,0) | J50: =C50+D50+E50-H50-I50 | K50: =H50+I50-(IF(8<=Supuestos!$J$29,Supuestos!$B$19*Supuestos!$B$29*(1+Supuestos!$B$8)^7,0)+IF(8<=Supuestos!$B$22,Supuestos!$B$20*Supuestos!$D$29*(1+Supuestos!$B$8)^7,0))-H50*Supuestos!$B$21 | L50: =L49+G50 | M50: =M49+J50
A51: 9 | B51: =$E$38*$B$39*(1+Supuestos!$B$8)^9 | C51: =$F$38*$B$39*(1+Supuestos!$B$8)^9*((1-Supuestos!$B$11)*(1-Supuestos!$B$12)^8) | D51: =$G$38*$B$39*(1+Supuestos!$B$8)^9*(1-Supuestos!$B$13)^9*Supuestos!$B$10 | E51: =$H$38*$B$39*(1+Supuestos!$B$8)^9 | F51: =B51-C51-D51-E51 | G51: =C51+D51+E51-(IF(9<=Supuestos!$J$29,Supuestos!$B$19*Supuestos!$B$29*(1+Supuestos!$B$8)^8,0)+IF(9<=Supuestos!$B$22,Supuestos!$B$20*Supuestos!$D$29*(1+Supuestos!$B$8)^8,0)) | H51: =IF(9<=Supuestos!$J$29,$C$38*$B$39*((1-Supuestos!$B$11)*(1-Supuestos!$B$12)^8)*Supuestos!$I$29*(1+Supuestos!$B$9)^8,0) | I51: =IF(9<=Supuestos!$B$22,D51*Supuestos!$K$29,0) | J51: =C51+D51+E51-H51-I51 | K51: =H51+I51-(IF(9<=Supuestos!$J$29,Supuestos!$B$19*Supuestos!$B$29*(1+Supuestos!$B$8)^8,0)+IF(9<=Supuestos!$B$22,Supuestos!$B$20*Supuestos!$D$29*(1+Supuestos!$B$8)^8,0))-H51*Supuestos!$B$21 | L51: =L50+G51 | M51: =M50+J51
A52: 10 | B52: =$E$38*$B$39*(1+Supuestos!$B$8)^10 | C52: =$F$38*$B$39*(1+Supuestos!$B$8)^10*((1-Supuestos!$B$11)*(1-Supuestos!$B$12)^9) | D52: =$G$38*$B$39*(1+Supuestos!$B$8)^10*(1-Supuestos!$B$13)^10*Supuestos!$B$10 | E52: =$H$38*$B$39*(1+Supuestos!$B$8)^10 | F52: =B52-C52-D52-E52 | G52: =C52+D52+E52-(IF(10<=Supuestos!$J$29,Supuestos!$B$19*Supuestos!$B$29*(1+Supuestos!$B$8)^9,0)+IF(10<=Supuestos!$B$22,Supuestos!$B$20*Supuestos!$D$29*(1+Supuestos!$B$8)^9,0)) | H52: =IF(10<=Supuestos!$J$29,$C$38*$B$39*((1-Supuestos!$B$11)*(1-Supuestos!$B$12)^9)*Supuestos!$I$29*(1+Supuestos!$B$9)^9,0) | I52: =IF(10<=Supuestos!$B$22,D52*Supuestos!$K$29,0) | J52: =C52+D52+E52-H52-I52 | K52: =H52+I52-(IF(10<=Supuestos!$J$29,Supuestos!$B$19*Supuestos!$B$29*(1+Supuestos!$B$8)^9,0)+IF(10<=Supuestos!$B$22,Supuestos!$B$20*Supuestos!$D$29*(1+Supuestos!$B$8)^9,0))-H52*Supuestos!$B$21 | L52: =L51+G52 | M52: =M51+J52
A53: 11 | B53: =$E$38*$B$39*(1+Supuestos!$B$8)^11 | C53: =$F$38*$B$39*(1+Supuestos!$B$8)^11*((1-Supuestos!$B$11)*(1-Supuestos!$B$12)^10) | D53: =$G$38*$B$39*(1+Supuestos!$B$8)^11*(1-Supuestos!$B$13)^11*Supuestos!$B$10 | E53: =$H$38*$B$39*(1+Supuestos!$B$8)^11 | F53: =B53-C53-D53-E53 | G53: =C53+D53+E53-(IF(11<=Supuestos!$J$29,Supuestos!$B$19*Supuestos!$B$29*(1+Supuestos!$B$8)^10,0)+IF(11<=Supuestos!$B$22,Supuestos!$B$20*Supuestos!$D$29*(1+Supuestos!$B$8)^10,0)) | H53: =IF(11<=Supuestos!$J$29,$C$38*$B$39*((1-Supuestos!$B$11)*(1-Supuestos!$B$12)^10)*Supuestos!$I$29*(1+Supuestos!$B$9)^10,0) | I53: =IF(11<=Supuestos!$B$22,D53*Supuestos!$K$29,0) | J53: =C53+D53+E53-H53-I53 | K53: =H53+I53-(IF(11<=Supuestos!$J$29,Supuestos!$B$19*Supuestos!$B$29*(1+Supuestos!$B$8)^10,0)+IF(11<=Supuestos!$B$22,Supuestos!$B$20*Supuestos!$D$29*(1+Supuestos!$B$8)^10,0))-H53*Supuestos!$B$21 | L53: =L52+G53 | M53: =M52+J53
A54: 12 | B54: =$E$38*$B$39*(1+Supuestos!$B$8)^12 | C54: =$F$38*$B$39*(1+Supuestos!$B$8)^12*((1-Supuestos!$B$11)*(1-Supuestos!$B$12)^11) | D54: =$G$38*$B$39*(1+Supuestos!$B$8)^12*(1-Supuestos!$B$13)^12*Supuestos!$B$10 | E54: =$H$38*$B$39*(1+Supuestos!$B$8)^12 | F54: =B54-C54-D54-E54 | G54: =C54+D54+E54-(IF(12<=Supuestos!$J$29,Supuestos!$B$19*Supuestos!$B$29*(1+Supuestos!$B$8)^11,0)+IF(12<=Supuestos!$B$22,Supuestos!$B$20*Supuestos!$D$29*(1+Supuestos!$B$8)^11,0)) | H54: =IF(12<=Supuestos!$J$29,$C$38*$B$39*((1-Supuestos!$B$11)*(1-Supuestos!$B$12)^11)*Supuestos!$I$29*(1+Supuestos!$B$9)^11,0) | I54: =IF(12<=Supuestos!$B$22,D54*Supuestos!$K$29,0) | J54: =C54+D54+E54-H54-I54 | K54: =H54+I54-(IF(12<=Supuestos!$J$29,Supuestos!$B$19*Supuestos!$B$29*(1+Supuestos!$B$8)^11,0)+IF(12<=Supuestos!$B$22,Supuestos!$B$20*Supuestos!$D$29*(1+Supuestos!$B$8)^11,0))-H54*Supuestos!$B$21 | L54: =L53+G54 | M54: =M53+J54
A55: 13 | B55: =$E$38*$B$39*(1+Supuestos!$B$8)^13 | C55: =$F$38*$B$39*(1+Supuestos!$B$8)^13*((1-Supuestos!$B$11)*(1-Supuestos!$B$12)^12) | D55: =$G$38*$B$39*(1+Supuestos!$B$8)^13*(1-Supuestos!$B$13)^13*Supuestos!$B$10 | E55: =$H$38*$B$39*(1+Supuestos!$B$8)^13 | F55: =B55-C55-D55-E55 | G55: =C55+D55+E55-(IF(13<=Supuestos!$J$29,Supuestos!$B$19*Supuestos!$B$29*(1+Supuestos!$B$8)^12,0)+IF(13<=Supuestos!$B$22,Supuestos!$B$20*Supuestos!$D$29*(1+Supuestos!$B$8)^12,0)) | H55: =IF(13<=Supuestos!$J$29,$C$38*$B$39*((1-Supuestos!$B$11)*(1-Supuestos!$B$12)^12)*Supuestos!$I$29*(1+Supuestos!$B$9)^12,0) | I55: =IF(13<=Supuestos!$B$22,D55*Supuestos!$K$29,0) | J55: =C55+D55+E55-H55-I55 | K55: =H55+I55-(IF(13<=Supuestos!$J$29,Supuestos!$B$19*Supuestos!$B$29*(1+Supuestos!$B$8)^12,0)+IF(13<=Supuestos!$B$22,Supuestos!$B$20*Supuestos!$D$29*(1+Supuestos!$B$8)^12,0))-H55*Supuestos!$B$21 | L55: =L54+G55 | M55: =M54+J55
A56: 14 | B56: =$E$38*$B$39*(1+Supuestos!$B$8)^14 | C56: =$F$38*$B$39*(1+Supuestos!$B$8)^14*((1-Supuestos!$B$11)*(1-Supuestos!$B$12)^13) | D56: =$G$38*$B$39*(1+Supuestos!$B$8)^14*(1-Supuestos!$B$13)^14*Supuestos!$B$10 | E56: =$H$38*$B$39*(1+Supuestos!$B$8)^14 | F56: =B56-C56-D56-E56 | G56: =C56+D56+E56-(IF(14<=Supuestos!$J$29,Supuestos!$B$19*Supuestos!$B$29*(1+Supuestos!$B$8)^13,0)+IF(14<=Supuestos!$B$22,Supuestos!$B$20*Supuestos!$D$29*(1+Supuestos!$B$8)^13,0)) | H56: =IF(14<=Supuestos!$J$29,$C$38*$B$39*((1-Supuestos!$B$11)*(1-Supuestos!$B$12)^13)*Supuestos!$I$29*(1+Supuestos!$B$9)^13,0) | I56: =IF(14<=Supuestos!$B$22,D56*Supuestos!$K$29,0) | J56: =C56+D56+E56-H56-I56 | K56: =H56+I56-(IF(14<=Supuestos!$J$29,Supuestos!$B$19*Supuestos!$B$29*(1+Supuestos!$B$8)^13,0)+IF(14<=Supuestos!$B$22,Supuestos!$B$20*Supuestos!$D$29*(1+Supuestos!$B$8)^13,0))-H56*Supuestos!$B$21 | L56: =L55+G56 | M56: =M55+J56
A57: 15 | B57: =$E$38*$B$39*(1+Supuestos!$B$8)^15 | C57: =$F$38*$B$39*(1+Supuestos!$B$8)^15*((1-Supuestos!$B$11)*(1-Supuestos!$B$12)^14) | D57: =$G$38*$B$39*(1+Supuestos!$B$8)^15*(1-Supuestos!$B$13)^15*Supuestos!$B$10 | E57: =$H$38*$B$39*(1+Supuestos!$B$8)^15 | F57: =B57-C57-D57-E57 | G57: =C57+D57+E57-(IF(15<=Supuestos!$J$29,Supuestos!$B$19*Supuestos!$B$29*(1+Supuestos!$B$8)^14,0)+IF(15<=Supuestos!$B$22,Supuestos!$B$20*Supuestos!$D$29*(1+Supuestos!$B$8)^14,0)) | H57: =IF(15<=Supuestos!$J$29,$C$38*$B$39*((1-Supuestos!$B$11)*(1-Supuestos!$B$12)^14)*Supuestos!$I$29*(1+Supuestos!$B$9)^14,0) | I57: =IF(15<=Supuestos!$B$22,D57*Supuestos!$K$29,0) | J57: =C57+D57+E57-H57-I57 | K57: =H57+I57-(IF(15<=Supuestos!$J$29,Supuestos!$B$19*Supuestos!$B$29*(1+Supuestos!$B$8)^14,0)+IF(15<=Supuestos!$B$22,Supuestos!$B$20*Supuestos!$D$29*(1+Supuestos!$B$8)^14,0))-H57*Supuestos!$B$21 | L57: =L56+G57 | M57: =M56+J57
A58: 16 | B58: =$E$38*$B$39*(1+Supuestos!$B$8)^16 | C58: =$F$38*$B$39*(1+Supuestos!$B$8)^16*((1-Supuestos!$B$11)*(1-Supuestos!$B$12)^15) | D58: =$G$38*$B$39*(1+Supuestos!$B$8)^16*(1-Supuestos!$B$13)^16*Supuestos!$B$10 | E58: =$H$38*$B$39*(1+Supuestos!$B$8)^16 | F58: =B58-C58-D58-E58 | G58: =C58+D58+E58-(IF(16<=Supuestos!$J$29,Supuestos!$B$19*Supuestos!$B$29*(1+Supuestos!$B$8)^15,0)+IF(16<=Supuestos!$B$22,Supuestos!$B$20*Supuestos!$D$29*(1+Supuestos!$B$8)^15,0)) | H58: =IF(16<=Supuestos!$J$29,$C$38*$B$39*((1-Supuestos!$B$11)*(1-Supuestos!$B$12)^15)*Supuestos!$I$29*(1+Supuestos!$B$9)^15,0) | I58: =IF(16<=Supuestos!$B$22,D58*Supuestos!$K$29,0) | J58: =C58+D58+E58-H58-I58 | K58: =H58+I58-(IF(16<=Supuestos!$J$29,Supuestos!$B$19*Supuestos!$B$29*(1+Supuestos!$B$8)^15,0)+IF(16<=Supuestos!$B$22,Supuestos!$B$20*Supuestos!$D$29*(1+Supuestos!$B$8)^15,0))-H58*Supuestos!$B$21 | L58: =L57+G58 | M58: =M57+J58
A59: 17 | B59: =$E$38*$B$39*(1+Supuestos!$B$8)^17 | C59: =$F$38*$B$39*(1+Supuestos!$B$8)^17*((1-Supuestos!$B$11)*(1-Supuestos!$B$12)^16) | D59: =$G$38*$B$39*(1+Supuestos!$B$8)^17*(1-Supuestos!$B$13)^17*Supuestos!$B$10 | E59: =$H$38*$B$39*(1+Supuestos!$B$8)^17 | F59: =B59-C59-D59-E59 | G59: =C59+D59+E59-(IF(17<=Supuestos!$J$29,Supuestos!$B$19*Supuestos!$B$29*(1+Supuestos!$B$8)^16,0)+IF(17<=Supuestos!$B$22,Supuestos!$B$20*Supuestos!$D$29*(1+Supuestos!$B$8)^16,0)) | H59: =IF(17<=Supuestos!$J$29,$C$38*$B$39*((1-Supuestos!$B$11)*(1-Supuestos!$B$12)^16)*Supuestos!$I$29*(1+Supuestos!$B$9)^16,0) | I59: =IF(17<=Supuestos!$B$22,D59*Supuestos!$K$29,0) | J59: =C59+D59+E59-H59-I59 | K59: =H59+I59-(IF(17<=Supuestos!$J$29,Supuestos!$B$19*Supuestos!$B$29*(1+Supuestos!$B$8)^16,0)+IF(17<=Supuestos!$B$22,Supuestos!$B$20*Supuestos!$D$29*(1+Supuestos!$B$8)^16,0))-H59*Supuestos!$B$21 | L59: =L58+G59 | M59: =M58+J59
A60: 18 | B60: =$E$38*$B$39*(1+Supuestos!$B$8)^18 | C60: =$F$38*$B$39*(1+Supuestos!$B$8)^18*((1-Supuestos!$B$11)*(1-Supuestos!$B$12)^17) | D60: =$G$38*$B$39*(1+Supuestos!$B$8)^18*(1-Supuestos!$B$13)^18*Supuestos!$B$10 | E60: =$H$38*$B$39*(1+Supuestos!$B$8)^18 | F60: =B60-C60-D60-E60 | G60: =C60+D60+E60-(IF(18<=Supuestos!$J$29,Supuestos!$B$19*Supuestos!$B$29*(1+Supuestos!$B$8)^17,0)+IF(18<=Supuestos!$B$22,Supuestos!$B$20*Supuestos!$D$29*(1+Supuestos!$B$8)^17,0)) | H60: =IF(18<=Supuestos!$J$29,$C$38*$B$39*((1-Supuestos!$B$11)*(1-Supuestos!$B$12)^17)*Supuestos!$I$29*(1+Supuestos!$B$9)^17,0) | I60: =IF(18<=Supuestos!$B$22,D60*Supuestos!$K$29,0) | J60: =C60+D60+E60-H60-I60 | K60: =H60+I60-(IF(18<=Supuestos!$J$29,Supuestos!$B$19*Supuestos!$B$29*(1+Supuestos!$B$8)^17,0)+IF(18<=Supuestos!$B$22,Supuestos!$B$20*Supuestos!$D$29*(1+Supuestos!$B$8)^17,0))-H60*Supuestos!$B$21 | L60: =L59+G60 | M60: =M59+J60
A61: 19 | B61: =$E$38*$B$39*(1+Supuestos!$B$8)^19 | C61: =$F$38*$B$39*(1+Supuestos!$B$8)^19*((1-Supuestos!$B$11)*(1-Supuestos!$B$12)^18) | D61: =$G$38*$B$39*(1+Supuestos!$B$8)^19*(1-Supuestos!$B$13)^19*Supuestos!$B$10 | E61: =$H$38*$B$39*(1+Supuestos!$B$8)^19 | F61: =B61-C61-D61-E61 | G61: =C61+D61+E61-(IF(19<=Supuestos!$J$29,Supuestos!$B$19*Supuestos!$B$29*(1+Supuestos!$B$8)^18,0)+IF(19<=Supuestos!$B$22,Supuestos!$B$20*Supuestos!$D$29*(1+Supuestos!$B$8)^18,0)) | H61: =IF(19<=Supuestos!$J$29,$C$38*$B$39*((1-Supuestos!$B$11)*(1-Supuestos!$B$12)^18)*Supuestos!$I$29*(1+Supuestos!$B$9)^18,0) | I61: =IF(19<=Supuestos!$B$22,D61*Supuestos!$K$29,0) | J61: =C61+D61+E61-H61-I61 | K61: =H61+I61-(IF(19<=Supuestos!$J$29,Supuestos!$B$19*Supuestos!$B$29*(1+Supuestos!$B$8)^18,0)+IF(19<=Supuestos!$B$22,Supuestos!$B$20*Supuestos!$D$29*(1+Supuestos!$B$8)^18,0))-H61*Supuestos!$B$21 | L61: =L60+G61 | M61: =M60+J61
A62: 20 | B62: =$E$38*$B$39*(1+Supuestos!$B$8)^20 | C62: =$F$38*$B$39*(1+Supuestos!$B$8)^20*((1-Supuestos!$B$11)*(1-Supuestos!$B$12)^19) | D62: =$G$38*$B$39*(1+Supuestos!$B$8)^20*(1-Supuestos!$B$13)^20*Supuestos!$B$10 | E62: =$H$38*$B$39*(1+Supuestos!$B$8)^20 | F62: =B62-C62-D62-E62 | G62: =C62+D62+E62-(IF(20<=Supuestos!$J$29,Supuestos!$B$19*Supuestos!$B$29*(1+Supuestos!$B$8)^19,0)+IF(20<=Supuestos!$B$22,Supuestos!$B$20*Supuestos!$D$29*(1+Supuestos!$B$8)^19,0)) | H62: =IF(20<=Supuestos!$J$29,$C$38*$B$39*((1-Supuestos!$B$11)*(1-Supuestos!$B$12)^19)*Supuestos!$I$29*(1+Supuestos!$B$9)^19,0) | I62: =IF(20<=Supuestos!$B$22,D62*Supuestos!$K$29,0) | J62: =C62+D62+E62-H62-I62 | K62: =H62+I62-(IF(20<=Supuestos!$J$29,Supuestos!$B$19*Supuestos!$B$29*(1+Supuestos!$B$8)^19,0)+IF(20<=Supuestos!$B$22,Supuestos!$B$20*Supuestos!$D$29*(1+Supuestos!$B$8)^19,0))-H62*Supuestos!$B$21 | L62: =L61+G62 | M62: =M61+J62
A64: TIR compra (proyecto): | B64: =IRR(G42:G62) | C64: VPN compra @WACC: | D64: =G42+NPV(Supuestos!$B$7,G43:G62)
A65: TIR financiador: | B65: =IRR(K42:K62) | C65: VPN cliente PPA @WACC: | D65: =NPV(Supuestos!$B$7,J43:J62)
A66: Acumulado cliente PPA 20a: | B66: =SUM(J43:J62) | C66: Acumulado compra 20a: | D66: =SUM(G42:G62)
A68: 5. POR QUÉ ESTE DIMENSIONAMIENTO ES ÓPTIMO
A69: • PV 349 kWp — generador exento <0.7 MW (medición neta, sin permiso CNE). En SIN la generación solar cae en intermedio → recorta energía intermedia; no genera en punta, por lo que el BESS es la palanca de demanda.
A70: • BESS 207 kW / 827 kWh — recorta el pico de punta (arbitraje carga en base, descarga en punta, topado al kWh punta del recibo).
A71: • Dimensionado al consumo (rend. inputs.json); excedentes bajo medición neta expiran en 12 meses, por eso no se sobredimensiona el PV.
A72: • PV/BESS dimensionados por **barrido de máximo NPV del cliente** (NO se topó a 0.7 MW): el óptimo cae en 349 kWp / 207 kW de BESS (sweep NPV (exento)). Más allá del punto de autoconsumo solar el excedente se valúa ~$0 y el NPV cae; el barrido compara explícitamente quedarse exento <0.7 MW vs cruzar a autoconsumo.
A73: • Corrección de factor de potencia incluida — palanca separada, capacitores a cargo del financiador en el esquema PPA (el cliente conserva 100% del ahorro FP).
A74: • LIBRO 100% EN VIVO: motor mensual §3 = fórmulas sobre los datos del recibo (§6) y Supuestos (réplica exacta del motor determinista, verificada al peso) — edita kWp/BESS/FC/tarifas o cualquier mes y TODO recalcula hasta la TIR.
A78: 6. DATOS DEL RECIBO (editables — el motor mensual §3 se alimenta de aquí)
A79: Mes | B79: Días | C79: kWh B | D79: kWh I | E79: kWh P | F79: kW B | G79: kW I | H79: kW P | I79: FP % | J79: Gen B $ | K79: Gen I $ | L79: Gen P $ | M79: Distribución $ | N79: Capacidad $ | O79: Otros vol $ | P79: Suministro $ | Q79: 2%BT+FP neto $ | R79: Cargo FP $ | S79: Yield kWh/kWp | T79: Hrs punta | U79: Días punta | V79: kWh tot | W79: Vol $/kWh | X79: Tarifa B $/kWh | Y79: Tarifa I $/kWh | Z79: Tarifa P $/kWh | AA79: Umbral kW | AB79: $/kW cap
A80: Abr-25 | B80: 30 | C80: 36275 | D80: 75914 | E80: 10018 | F80: 256 | G80: 248 | H80: 219 | I80: 99.82 | J80: 36028.33 | K80: 134648.66 | L80: 21133.98 | M80: 18317.01 | N80: 95969.78 | O80: 23659.29 | P80: 448.77 | Q80: -8193.85 | R80: 0 | S80: 150.72 | T80: 2 | U80: 22 | V80: =C80+D80+E80 | W80: =O80/V80 | X80: =IF(C80=0,Y80,J80/C80+W80) | Y80: =IF(D80=0,0,K80/D80+W80) | Z80: =IF(E80=0,0,L80/E80+W80) | AA80: =V80/(B80*24*$L$6) | AB80: =IFERROR(N80/MIN(H80,AA80),0)
A81: May-25 | B81: 31 | C81: 40107 | D81: 82925 | E81: 7789 | F81: 254 | G81: 273 | H81: 232 | I81: 99.77 | J81: 39834.27 | K81: 147084.07 | L81: 16431.67 | M81: 19432.14 | N81: 100367.84 | O81: 25326.95 | P81: 448.77 | Q81: -8374.22 | R81: 0 | S81: 143.096 | T81: 2 | U81: 21 | V81: =C81+D81+E81 | W81: =O81/V81 | X81: =IF(C81=0,Y81,J81/C81+W81) | Y81: =IF(D81=0,0,K81/D81+W81) | Z81: =IF(E81=0,0,L81/E81+W81) | AA81: =V81/(B81*24*$L$6) | AB81: =IFERROR(N81/MIN(H81,AA81),0)
A82: Jun-25 | B82: 30 | C82: 34900 | D82: 66165 | E82: 6756 | F82: 214 | G82: 242 | H82: 213 | I82: 99.98 | J82: 35486.32 | K82: 120142.41 | L82: 14591.61 | M82: 17225.56 | N82: 94337.7 | O82: 20874.14 | P82: 448.77 | Q82: -7577.66 | R82: 0 | S82: 133.92 | T82: 2 | U82: 21 | V82: =C82+D82+E82 | W82: =O82/V82 | X82: =IF(C82=0,Y82,J82/C82+W82) | Y82: =IF(D82=0,0,K82/D82+W82) | Z82: =IF(E82=0,0,L82/E82+W82) | AA82: =V82/(B82*24*$L$6) | AB82: =IFERROR(N82/MIN(H82,AA82),0)
A83: Jul-25 | B83: 31 | C83: 33959 | D83: 72608 | E83: 7443 | F83: 203 | G83: 254 | H83: 204 | I83: 99.96 | J83: 35045.69 | K83: 133823.8 | L83: 16316.54 | M83: 18079.72 | N83: 91706.16 | O83: 22072.34 | P83: 448.77 | Q83: -7937.33 | R83: 0 | S83: 135.16 | T83: 2 | U83: 23 | V83: =C83+D83+E83 | W83: =O83/V83 | X83: =IF(C83=0,Y83,J83/C83+W83) | Y83: =IF(D83=0,0,K83/D83+W83) | Z83: =IF(E83=0,0,L83/E83+W83) | AA83: =V83/(B83*24*$L$6) | AB83: =IFERROR(N83/MIN(H83,AA83),0)
A84: Ago-25 | B84: 31 | C84: 35967 | D84: 71098 | E84: 6735 | F84: 221 | G84: 290 | H84: 206 | I84: 99.96 | J84: 37168.3 | K84: 131218.47 | L84: 14784.67 | M84: 19147.42 | N84: 92735.02 | O84: 22031.7 | P84: 448.77 | Q84: -7938.36 | R84: 0 | S84: 126.728 | T84: 2 | U84: 21 | V84: =C84+D84+E84 | W84: =O84/V84 | X84: =IF(C84=0,Y84,J84/C84+W84) | Y84: =IF(D84=0,0,K84/D84+W84) | Z84: =IF(E84=0,0,L84/E84+W84) | AA84: =V84/(B84*24*$L$6) | AB84: =IFERROR(N84/MIN(H84,AA84),0)
A85: Sep-25 | B85: 30 | C85: 35687 | D85: 71078 | E85: 7280 | F85: 209 | G85: 264 | H85: 214 | I85: 99.96 | J85: 36543.49 | K85: 129987.45 | L85: 15834.73 | M85: 18791.52 | N85: 95454.7 | O85: 22546.7 | P85: 448.77 | Q85: -7990.18 | R85: 0 | S85: 119.52 | T85: 2 | U85: 21 | V85: =C85+D85+E85 | W85: =O85/V85 | X85: =IF(C85=0,Y85,J85/C85+W85) | Y85: =IF(D85=0,0,K85/D85+W85) | Z85: =IF(E85=0,0,L85/E85+W85) | AA85: =V85/(B85*24*$L$6) | AB85: =IFERROR(N85/MIN(H85,AA85),0)
A86: Oct-25 | B86: 31 | C86: 33507 | D86: 69418 | E86: 9060 | F86: 206 | G86: 195 | H86: 188 | I86: 99.99 | J86: 34311.17 | K86: 126951.64 | L86: 19707.31 | M86: 16500.1 | N86: 88895.74 | O86: 22139.43 | P86: 448.77 | Q86: -7723.85 | R86: 0 | S86: 131.936 | T86: 2 | U86: 23 | V86: =C86+D86+E86 | W86: =O86/V86 | X86: =IF(C86=0,Y86,J86/C86+W86) | Y86: =IF(D86=0,0,K86/D86+W86) | Z86: =IF(E86=0,0,L86/E86+W86) | AA86: =V86/(B86*24*$L$6) | AB86: =IFERROR(N86/MIN(H86,AA86),0)
A87: Nov-25 | B87: 30 | C87: 36171 | D87: 57690 | E87: 13831 | F87: 196 | G87: 213 | H87: 207 | I87: 99.99 | J87: 35928.65 | K87: 102336.29 | L87: 29180.64 | M87: 15161.34 | N87: 89560.62 | O87: 21290.7 | P87: 448.77 | Q87: -7347.68 | R87: 0 | S87: 136.56 | T87: 4 | U87: 19 | V87: =C87+D87+E87 | W87: =O87/V87 | X87: =IF(C87=0,Y87,J87/C87+W87) | Y87: =IF(D87=0,0,K87/D87+W87) | Z87: =IF(E87=0,0,L87/E87+W87) | AA87: =V87/(B87*24*$L$6) | AB87: =IFERROR(N87/MIN(H87,AA87),0)
A88: Dic-25 | B88: 31 | C88: 32620 | D88: 56907 | E88: 14364 | F88: 193 | G88: 196 | H88: 199 | I88: 100 | J88: 30780.23 | K88: 95899.68 | L88: 28791.2 | M88: 14164.82 | N88: 81794.97 | O88: 20539.25 | P88: 448.77 | Q88: -6810.47 | R88: 0 | S88: 131.192 | T88: 4 | U88: 22 | V88: =C88+D88+E88 | W88: =O88/V88 | X88: =IF(C88=0,Y88,J88/C88+W88) | Y88: =IF(D88=0,0,K88/D88+W88) | Z88: =IF(E88=0,0,L88/E88+W88) | AA88: =V88/(B88*24*$L$6) | AB88: =IFERROR(N88/MIN(H88,AA88),0)
A89: Ene-26 | B89: 31 | C89: 28810 | D89: 52377 | E89: 13454 | F89: 173 | G89: 186 | H89: 191 | I89: 100 | J89: 26574.34 | K89: 86280.63 | L89: 26359.08 | M89: 12926.88 | N89: 76739.98 | O89: 18417.15 | P89: 422.07 | Q89: -6193 | R89: 0 | S89: 143.096 | T89: 4 | U89: 21 | V89: =C89+D89+E89 | W89: =O89/V89 | X89: =IF(C89=0,Y89,J89/C89+W89) | Y89: =IF(D89=0,0,K89/D89+W89) | Z89: =IF(E89=0,0,L89/E89+W89) | AA89: =V89/(B89*24*$L$6) | AB89: =IFERROR(N89/MIN(H89,AA89),0)
A90: Feb-26 | B90: 28 | C90: 31053 | D90: 53500 | E90: 13511 | F90: 191 | G90: 227 | H90: 213 | I90: 99.99 | J90: 28658.81 | K90: 88178.7 | L90: 26486.96 | M90: 15363.36 | N90: 85628.13 | O90: 19083.26 | P90: 422.07 | Q90: -6595.53 | R90: 0 | S90: 139.104 | T90: 4 | U90: 19 | V90: =C90+D90+E90 | W90: =O90/V90 | X90: =IF(C90=0,Y90,J90/C90+W90) | Y90: =IF(D90=0,0,K90/D90+W90) | Z90: =IF(E90=0,0,L90/E90+W90) | AA90: =V90/(B90*24*$L$6) | AB90: =IFERROR(N90/MIN(H90,AA90),0)
A91: Mar-26 | B91: 31 | C91: 36252 | D91: 59101 | E91: 14087 | F91: 196 | G91: 209 | H91: 194 | I91: 100 | J91: 33478.72 | K91: 97469.37 | L91: 27633.06 | M91: 14145.12 | N91: 78038.44 | O91: 21297.04 | P91: 422.07 | Q91: -6812.1 | R91: 0 | S91: 170.376 | T91: 4 | U91: 21 | V91: =C91+D91+E91 | W91: =O91/V91 | X91: =IF(C91=0,Y91,J91/C91+W91) | Y91: =IF(D91=0,0,K91/D91+W91) | Z91: =IF(E91=0,0,L91/E91+W91) | AA91: =V91/(B91*24*$L$6) | AB91: =IFERROR(N91/MIN(H91,AA91),0)
A92: Filas = recibo ancla (parseado) + meses reconstruidos del CONSUMO HISTÓRICO (subtotal al peso; split TOU por shares del ancla). Capacidad a MIN(kW punta, umbral); tarifas por banda = concepto/kWh + vol/kWh; col Q<0 (bonificación FP) aplica claw-back al ahorro. Válido <700 kWp (medición neta). Excedentes PV a $0.
O94: Techo — referencia satelital (ruta HelioScope; cruz roja = punto verificado) · confianza ?

Sheet Fiesta Americana Viaducto Ae
A1: Fiesta Americana Viaducto Aeropuerto (CDMX) — Memoria de cálculo y propuesta energética
A2: RPU 986190901451 · GDMTH SIN · Demanda contratada 820 kW · 12 meses de recibo
A3: Régimen: GENERADOR EXENTO — Medición Neta (sin permiso; Art. 30 LSE; RES/142/2017)
A5: PARÁMETROS (desde Supuestos — edítalos ahí)
A6: PV kWp | B6: =Supuestos!$B$30 | C6: BESS kW | D6: =Supuestos!$C$30 | E6: BESS kWh | F6: =Supuestos!$D$30 | G6: FP corrección | H6: =Supuestos!$E$30 | I6: Entrega útil kWh | J6: =Supuestos!$D$30*Supuestos!$B$17*SQRT(Supuestos!$B$18) | K6: FC umbral | L6: 0.57
A8: 1. ESTRUCTURA DE COSTO Y AHORRO (pre-IVA, año base · fórmulas vivas ← §3)
A9: Concepto | B9: $ / año | C9: Nota
A10: Tarifa Actual (CFE pleno, sin proyecto) | B10: =$E$38*$B$39 | C10: Σ recibos × anualización
A11: (−) Ahorro PV (energía + demanda) | B11: =$F$38*$B$39 | C11: intermedio + umbral
A12: (−) Ahorro BESS (punta + arbitraje) | B12: =$G$38*$B$39 | C12: recorte punta + arbitraje (incl. claw)
A13: (−) Ahorro FP (corrección) | B13: =$H$38*$B$39 | C13: multa factor de potencia
A14: (=) Costo neto con proyecto | B14: =B10-B11-B12-B13
A15: Ahorro proyecto / año | B15: =B11+B12+B13
A16: Ahorro % | B16: =B15/B10
A18: 2. CAPEX (fórmulas vivas desde Supuestos)
A19: CAPEX PV | B19: =Supuestos!$B$30*1000*Supuestos!$F$30*Supuestos!$B$5
A20: CAPEX BESS | B20: =Supuestos!$D$30*Supuestos!$G$30*Supuestos!$B$5
A21: CAPEX capacitor (FP) | B21: =Supuestos!$H$30
A22: CAPEX TOTAL | B22: =B19+B20+B21
A24: 3. RESUMEN MENSUAL — Tarifa Actual vs Con Proyecto (fórmulas vivas ← §6 y Supuestos)
A25: Mes | B25: kWh Consumo | C25: Gen PV kWh | D25: BESS desc kWh | E25: Tarifa Actual $ | F25: Ah PV $ | G25: Ah BESS $ | H25: Ah FP $ | I25: Costo c/proy $ | J25: Ahorro $ | K25: Ahorro %
A26: =A80 | B26: =V80 | C26: =Supuestos!$B$30*S80 | D26: =MIN($J$6*U80,E80) | E26: =SUM(J80:Q80) | F26: =(MIN(C26,D80)*Y80+(MIN(H80,AA80)-MIN(H80,(V80-MIN(C26,D80))/($B$80*24*$L$6)))*AB80)*IF(Q80<0,1+Q80/SUM(J80:P80),1) | G26: =((MIN(H80,(V80-MIN(C26,D80))/($B$80*24*$L$6))-MIN(MAX(H80-MIN(Supuestos!$C$30,IF(T80>0,$J$6/T80,0)),0),(V80-MIN(C26,D80))/($B$80*24*$L$6)))*AB80+D26*Z80-D26/Supuestos!$B$18*X80)*IF(Q80<0,1+Q80/SUM(J80:P80),1) | H26: =IF(Supuestos!$E$30="Sí",R80,0) | I26: =E26-J26 | J26: =F26+G26+H26 | K26: =J26/E26
A27: =A81 | B27: =V81 | C27: =Supuestos!$B$30*S81 | D27: =MIN($J$6*U81,E81) | E27: =SUM(J81:Q81) | F27: =(MIN(C27,D81)*Y81+(MIN(H81,AA81)-MIN(H81,(V81-MIN(C27,D81))/($B$81*24*$L$6)))*AB81)*IF(Q81<0,1+Q81/SUM(J81:P81),1) | G27: =((MIN(H81,(V81-MIN(C27,D81))/($B$81*24*$L$6))-MIN(MAX(H81-MIN(Supuestos!$C$30,IF(T81>0,$J$6/T81,0)),0),(V81-MIN(C27,D81))/($B$81*24*$L$6)))*AB81+D27*Z81-D27/Supuestos!$B$18*X81)*IF(Q81<0,1+Q81/SUM(J81:P81),1) | H27: =IF(Supuestos!$E$30="Sí",R81,0) | I27: =E27-J27 | J27: =F27+G27+H27 | K27: =J27/E27
A28: =A82 | B28: =V82 | C28: =Supuestos!$B$30*S82 | D28: =MIN($J$6*U82,E82) | E28: =SUM(J82:Q82) | F28: =(MIN(C28,D82)*Y82+(MIN(H82,AA82)-MIN(H82,(V82-MIN(C28,D82))/($B$82*24*$L$6)))*AB82)*IF(Q82<0,1+Q82/SUM(J82:P82),1) | G28: =((MIN(H82,(V82-MIN(C28,D82))/($B$82*24*$L$6))-MIN(MAX(H82-MIN(Supuestos!$C$30,IF(T82>0,$J$6/T82,0)),0),(V82-MIN(C28,D82))/($B$82*24*$L$6)))*AB82+D28*Z82-D28/Supuestos!$B$18*X82)*IF(Q82<0,1+Q82/SUM(J82:P82),1) | H28: =IF(Supuestos!$E$30="Sí",R82,0) | I28: =E28-J28 | J28: =F28+G28+H28 | K28: =J28/E28
A29: =A83 | B29: =V83 | C29: =Supuestos!$B$30*S83 | D29: =MIN($J$6*U83,E83) | E29: =SUM(J83:Q83) | F29: =(MIN(C29,D83)*Y83+(MIN(H83,AA83)-MIN(H83,(V83-MIN(C29,D83))/($B$83*24*$L$6)))*AB83)*IF(Q83<0,1+Q83/SUM(J83:P83),1) | G29: =((MIN(H83,(V83-MIN(C29,D83))/($B$83*24*$L$6))-MIN(MAX(H83-MIN(Supuestos!$C$30,IF(T83>0,$J$6/T83,0)),0),(V83-MIN(C29,D83))/($B$83*24*$L$6)))*AB83+D29*Z83-D29/Supuestos!$B$18*X83)*IF(Q83<0,1+Q83/SUM(J83:P83),1) | H29: =IF(Supuestos!$E$30="Sí",R83,0) | I29: =E29-J29 | J29: =F29+G29+H29 | K29: =J29/E29
A30: =A84 | B30: =V84 | C30: =Supuestos!$B$30*S84 | D30: =MIN($J$6*U84,E84) | E30: =SUM(J84:Q84) | F30: =(MIN(C30,D84)*Y84+(MIN(H84,AA84)-MIN(H84,(V84-MIN(C30,D84))/($B$84*24*$L$6)))*AB84)*IF(Q84<0,1+Q84/SUM(J84:P84),1) | G30: =((MIN(H84,(V84-MIN(C30,D84))/($B$84*24*$L$6))-MIN(MAX(H84-MIN(Supuestos!$C$30,IF(T84>0,$J$6/T84,0)),0),(V84-MIN(C30,D84))/($B$84*24*$L$6)))*AB84+D30*Z84-D30/Supuestos!$B$18*X84)*IF(Q84<0,1+Q84/SUM(J84:P84),1) | H30: =IF(Supuestos!$E$30="Sí",R84,0) | I30: =E30-J30 | J30: =F30+G30+H30 | K30: =J30/E30
A31: =A85 | B31: =V85 | C31: =Supuestos!$B$30*S85 | D31: =MIN($J$6*U85,E85) | E31: =SUM(J85:Q85) | F31: =(MIN(C31,D85)*Y85+(MIN(H85,AA85)-MIN(H85,(V85-MIN(C31,D85))/($B$85*24*$L$6)))*AB85)*IF(Q85<0,1+Q85/SUM(J85:P85),1) | G31: =((MIN(H85,(V85-MIN(C31,D85))/($B$85*24*$L$6))-MIN(MAX(H85-MIN(Supuestos!$C$30,IF(T85>0,$J$6/T85,0)),0),(V85-MIN(C31,D85))/($B$85*24*$L$6)))*AB85+D31*Z85-D31/Supuestos!$B$18*X85)*IF(Q85<0,1+Q85/SUM(J85:P85),1) | H31: =IF(Supuestos!$E$30="Sí",R85,0) | I31: =E31-J31 | J31: =F31+G31+H31 | K31: =J31/E31
A32: =A86 | B32: =V86 | C32: =Supuestos!$B$30*S86 | D32: =MIN($J$6*U86,E86) | E32: =SUM(J86:Q86) | F32: =(MIN(C32,D86)*Y86+(MIN(H86,AA86)-MIN(H86,(V86-MIN(C32,D86))/($B$86*24*$L$6)))*AB86)*IF(Q86<0,1+Q86/SUM(J86:P86),1) | G32: =((MIN(H86,(V86-MIN(C32,D86))/($B$86*24*$L$6))-MIN(MAX(H86-MIN(Supuestos!$C$30,IF(T86>0,$J$6/T86,0)),0),(V86-MIN(C32,D86))/($B$86*24*$L$6)))*AB86+D32*Z86-D32/Supuestos!$B$18*X86)*IF(Q86<0,1+Q86/SUM(J86:P86),1) | H32: =IF(Supuestos!$E$30="Sí",R86,0) | I32: =E32-J32 | J32: =F32+G32+H32 | K32: =J32/E32
A33: =A87 | B33: =V87 | C33: =Supuestos!$B$30*S87 | D33: =MIN($J$6*U87,E87) | E33: =SUM(J87:Q87) | F33: =(MIN(C33,D87)*Y87+(MIN(H87,AA87)-MIN(H87,(V87-MIN(C33,D87))/($B$87*24*$L$6)))*AB87)*IF(Q87<0,1+Q87/SUM(J87:P87),1) | G33: =((MIN(H87,(V87-MIN(C33,D87))/($B$87*24*$L$6))-MIN(MAX(H87-MIN(Supuestos!$C$30,IF(T87>0,$J$6/T87,0)),0),(V87-MIN(C33,D87))/($B$87*24*$L$6)))*AB87+D33*Z87-D33/Supuestos!$B$18*X87)*IF(Q87<0,1+Q87/SUM(J87:P87),1) | H33: =IF(Supuestos!$E$30="Sí",R87,0) | I33: =E33-J33 | J33: =F33+G33+H33 | K33: =J33/E33
A34: =A88 | B34: =V88 | C34: =Supuestos!$B$30*S88 | D34: =MIN($J$6*U88,E88) | E34: =SUM(J88:Q88) | F34: =(MIN(C34,D88)*Y88+(MIN(H88,AA88)-MIN(H88,(V88-MIN(C34,D88))/($B$88*24*$L$6)))*AB88)*IF(Q88<0,1+Q88/SUM(J88:P88),1) | G34: =((MIN(H88,(V88-MIN(C34,D88))/($B$88*24*$L$6))-MIN(MAX(H88-MIN(Supuestos!$C$30,IF(T88>0,$J$6/T88,0)),0),(V88-MIN(C34,D88))/($B$88*24*$L$6)))*AB88+D34*Z88-D34/Supuestos!$B$18*X88)*IF(Q88<0,1+Q88/SUM(J88:P88),1) | H34: =IF(Supuestos!$E$30="Sí",R88,0) | I34: =E34-J34 | J34: =F34+G34+H34 | K34: =J34/E34
A35: =A89 | B35: =V89 | C35: =Supuestos!$B$30*S89 | D35: =MIN($J$6*U89,E89) | E35: =SUM(J89:Q89) | F35: =(MIN(C35,D89)*Y89+(MIN(H89,AA89)-MIN(H89,(V89-MIN(C35,D89))/($B$89*24*$L$6)))*AB89)*IF(Q89<0,1+Q89/SUM(J89:P89),1) | G35: =((MIN(H89,(V89-MIN(C35,D89))/($B$89*24*$L$6))-MIN(MAX(H89-MIN(Supuestos!$C$30,IF(T89>0,$J$6/T89,0)),0),(V89-MIN(C35,D89))/($B$89*24*$L$6)))*AB89+D35*Z89-D35/Supuestos!$B$18*X89)*IF(Q89<0,1+Q89/SUM(J89:P89),1) | H35: =IF(Supuestos!$E$30="Sí",R89,0) | I35: =E35-J35 | J35: =F35+G35+H35 | K35: =J35/E35
A36: =A90 | B36: =V90 | C36: =Supuestos!$B$30*S90 | D36: =MIN($J$6*U90,E90) | E36: =SUM(J90:Q90) | F36: =(MIN(C36,D90)*Y90+(MIN(H90,AA90)-MIN(H90,(V90-MIN(C36,D90))/($B$90*24*$L$6)))*AB90)*IF(Q90<0,1+Q90/SUM(J90:P90),1) | G36: =((MIN(H90,(V90-MIN(C36,D90))/($B$90*24*$L$6))-MIN(MAX(H90-MIN(Supuestos!$C$30,IF(T90>0,$J$6/T90,0)),0),(V90-MIN(C36,D90))/($B$90*24*$L$6)))*AB90+D36*Z90-D36/Supuestos!$B$18*X90)*IF(Q90<0,1+Q90/SUM(J90:P90),1) | H36: =IF(Supuestos!$E$30="Sí",R90,0) | I36: =E36-J36 | J36: =F36+G36+H36 | K36: =J36/E36
A37: =A91 | B37: =V91 | C37: =Supuestos!$B$30*S91 | D37: =MIN($J$6*U91,E91) | E37: =SUM(J91:Q91) | F37: =(MIN(C37,D91)*Y91+(MIN(H91,AA91)-MIN(H91,(V91-MIN(C37,D91))/($B$91*24*$L$6)))*AB91)*IF(Q91<0,1+Q91/SUM(J91:P91),1) | G37: =((MIN(H91,(V91-MIN(C37,D91))/($B$91*24*$L$6))-MIN(MAX(H91-MIN(Supuestos!$C$30,IF(T91>0,$J$6/T91,0)),0),(V91-MIN(C37,D91))/($B$91*24*$L$6)))*AB91+D37*Z91-D37/Supuestos!$B$18*X91)*IF(Q91<0,1+Q91/SUM(J91:P91),1) | H37: =IF(Supuestos!$E$30="Sí",R91,0) | I37: =E37-J37 | J37: =F37+G37+H37 | K37: =J37/E37
A38: TOTAL | B38: =SUM(B26:B37) | C38: =SUM(C26:C37) | D38: =SUM(D26:D37) | E38: =SUM(E26:E37) | F38: =SUM(F26:F37) | G38: =SUM(G26:G37) | H38: =SUM(H26:H37) | I38: =SUM(I26:I37) | J38: =SUM(J26:J37) | K38: =J38/E38
A39: Factor anualización (12/meses): | B39: 1
A40: 4. PROYECCIÓN 20 AÑOS — Comprar vs PPA/Ahorro compartido
A41: Año | B41: Tarifa Actual $ | C41: Ah PV $ | D41: Ah BESS $ | E41: Ah FP $ | F41: Costo c/proy $ | G41: Flujo Compra $ | H41: Pago PPA $ | I41: Comisión $ | J41: Flujo Cliente PPA $ | K41: Flujo Financiador $ | L41: Acum Compra $ | M41: Acum Cliente PPA $
A42: 0 | G42: =-B22 | K42: =-B22 | L42: =G42 | M42: 0
A43: 1 | B43: =$E$38*$B$39*(1+Supuestos!$B$8)^1 | C43: =$F$38*$B$39*(1+Supuestos!$B$8)^1*((1-Supuestos!$B$11)*(1-Supuestos!$B$12)^0) | D43: =$G$38*$B$39*(1+Supuestos!$B$8)^1*(1-Supuestos!$B$13)^1*Supuestos!$B$10 | E43: =$H$38*$B$39*(1+Supuestos!$B$8)^1 | F43: =B43-C43-D43-E43 | G43: =C43+D43+E43-(IF(1<=Supuestos!$J$30,Supuestos!$B$19*Supuestos!$B$30*(1+Supuestos!$B$8)^0,0)+IF(1<=Supuestos!$B$22,Supuestos!$B$20*Supuestos!$D$30*(1+Supuestos!$B$8)^0,0)) | H43: =IF(1<=Supuestos!$J$30,$C$38*$B$39*((1-Supuestos!$B$11)*(1-Supuestos!$B$12)^0)*Supuestos!$I$30*(1+Supuestos!$B$9)^0,0) | I43: =IF(1<=Supuestos!$B$22,D43*Supuestos!$K$30,0) | J43: =C43+D43+E43-H43-I43 | K43: =H43+I43-(IF(1<=Supuestos!$J$30,Supuestos!$B$19*Supuestos!$B$30*(1+Supuestos!$B$8)^0,0)+IF(1<=Supuestos!$B$22,Supuestos!$B$20*Supuestos!$D$30*(1+Supuestos!$B$8)^0,0))-H43*Supuestos!$B$21 | L43: =L42+G43 | M43: =M42+J43
A44: 2 | B44: =$E$38*$B$39*(1+Supuestos!$B$8)^2 | C44: =$F$38*$B$39*(1+Supuestos!$B$8)^2*((1-Supuestos!$B$11)*(1-Supuestos!$B$12)^1) | D44: =$G$38*$B$39*(1+Supuestos!$B$8)^2*(1-Supuestos!$B$13)^2*Supuestos!$B$10 | E44: =$H$38*$B$39*(1+Supuestos!$B$8)^2 | F44: =B44-C44-D44-E44 | G44: =C44+D44+E44-(IF(2<=Supuestos!$J$30,Supuestos!$B$19*Supuestos!$B$30*(1+Supuestos!$B$8)^1,0)+IF(2<=Supuestos!$B$22,Supuestos!$B$20*Supuestos!$D$30*(1+Supuestos!$B$8)^1,0)) | H44: =IF(2<=Supuestos!$J$30,$C$38*$B$39*((1-Supuestos!$B$11)*(1-Supuestos!$B$12)^1)*Supuestos!$I$30*(1+Supuestos!$B$9)^1,0) | I44: =IF(2<=Supuestos!$B$22,D44*Supuestos!$K$30,0) | J44: =C44+D44+E44-H44-I44 | K44: =H44+I44-(IF(2<=Supuestos!$J$30,Supuestos!$B$19*Supuestos!$B$30*(1+Supuestos!$B$8)^1,0)+IF(2<=Supuestos!$B$22,Supuestos!$B$20*Supuestos!$D$30*(1+Supuestos!$B$8)^1,0))-H44*Supuestos!$B$21 | L44: =L43+G44 | M44: =M43+J44
A45: 3 | B45: =$E$38*$B$39*(1+Supuestos!$B$8)^3 | C45: =$F$38*$B$39*(1+Supuestos!$B$8)^3*((1-Supuestos!$B$11)*(1-Supuestos!$B$12)^2) | D45: =$G$38*$B$39*(1+Supuestos!$B$8)^3*(1-Supuestos!$B$13)^3*Supuestos!$B$10 | E45: =$H$38*$B$39*(1+Supuestos!$B$8)^3 | F45: =B45-C45-D45-E45 | G45: =C45+D45+E45-(IF(3<=Supuestos!$J$30,Supuestos!$B$19*Supuestos!$B$30*(1+Supuestos!$B$8)^2,0)+IF(3<=Supuestos!$B$22,Supuestos!$B$20*Supuestos!$D$30*(1+Supuestos!$B$8)^2,0)) | H45: =IF(3<=Supuestos!$J$30,$C$38*$B$39*((1-Supuestos!$B$11)*(1-Supuestos!$B$12)^2)*Supuestos!$I$30*(1+Supuestos!$B$9)^2,0) | I45: =IF(3<=Supuestos!$B$22,D45*Supuestos!$K$30,0) | J45: =C45+D45+E45-H45-I45 | K45: =H45+I45-(IF(3<=Supuestos!$J$30,Supuestos!$B$19*Supuestos!$B$30*(1+Supuestos!$B$8)^2,0)+IF(3<=Supuestos!$B$22,Supuestos!$B$20*Supuestos!$D$30*(1+Supuestos!$B$8)^2,0))-H45*Supuestos!$B$21 | L45: =L44+G45 | M45: =M44+J45
A46: 4 | B46: =$E$38*$B$39*(1+Supuestos!$B$8)^4 | C46: =$F$38*$B$39*(1+Supuestos!$B$8)^4*((1-Supuestos!$B$11)*(1-Supuestos!$B$12)^3) | D46: =$G$38*$B$39*(1+Supuestos!$B$8)^4*(1-Supuestos!$B$13)^4*Supuestos!$B$10 | E46: =$H$38*$B$39*(1+Supuestos!$B$8)^4 | F46: =B46-C46-D46-E46 | G46: =C46+D46+E46-(IF(4<=Supuestos!$J$30,Supuestos!$B$19*Supuestos!$B$30*(1+Supuestos!$B$8)^3,0)+IF(4<=Supuestos!$B$22,Supuestos!$B$20*Supuestos!$D$30*(1+Supuestos!$B$8)^3,0)) | H46: =IF(4<=Supuestos!$J$30,$C$38*$B$39*((1-Supuestos!$B$11)*(1-Supuestos!$B$12)^3)*Supuestos!$I$30*(1+Supuestos!$B$9)^3,0) | I46: =IF(4<=Supuestos!$B$22,D46*Supuestos!$K$30,0) | J46: =C46+D46+E46-H46-I46 | K46: =H46+I46-(IF(4<=Supuestos!$J$30,Supuestos!$B$19*Supuestos!$B$30*(1+Supuestos!$B$8)^3,0)+IF(4<=Supuestos!$B$22,Supuestos!$B$20*Supuestos!$D$30*(1+Supuestos!$B$8)^3,0))-H46*Supuestos!$B$21 | L46: =L45+G46 | M46: =M45+J46
A47: 5 | B47: =$E$38*$B$39*(1+Supuestos!$B$8)^5 | C47: =$F$38*$B$39*(1+Supuestos!$B$8)^5*((1-Supuestos!$B$11)*(1-Supuestos!$B$12)^4) | D47: =$G$38*$B$39*(1+Supuestos!$B$8)^5*(1-Supuestos!$B$13)^5*Supuestos!$B$10 | E47: =$H$38*$B$39*(1+Supuestos!$B$8)^5 | F47: =B47-C47-D47-E47 | G47: =C47+D47+E47-(IF(5<=Supuestos!$J$30,Supuestos!$B$19*Supuestos!$B$30*(1+Supuestos!$B$8)^4,0)+IF(5<=Supuestos!$B$22,Supuestos!$B$20*Supuestos!$D$30*(1+Supuestos!$B$8)^4,0)) | H47: =IF(5<=Supuestos!$J$30,$C$38*$B$39*((1-Supuestos!$B$11)*(1-Supuestos!$B$12)^4)*Supuestos!$I$30*(1+Supuestos!$B$9)^4,0) | I47: =IF(5<=Supuestos!$B$22,D47*Supuestos!$K$30,0) | J47: =C47+D47+E47-H47-I47 | K47: =H47+I47-(IF(5<=Supuestos!$J$30,Supuestos!$B$19*Supuestos!$B$30*(1+Supuestos!$B$8)^4,0)+IF(5<=Supuestos!$B$22,Supuestos!$B$20*Supuestos!$D$30*(1+Supuestos!$B$8)^4,0))-H47*Supuestos!$B$21 | L47: =L46+G47 | M47: =M46+J47
A48: 6 | B48: =$E$38*$B$39*(1+Supuestos!$B$8)^6 | C48: =$F$38*$B$39*(1+Supuestos!$B$8)^6*((1-Supuestos!$B$11)*(1-Supuestos!$B$12)^5) | D48: =$G$38*$B$39*(1+Supuestos!$B$8)^6*(1-Supuestos!$B$13)^6*Supuestos!$B$10 | E48: =$H$38*$B$39*(1+Supuestos!$B$8)^6 | F48: =B48-C48-D48-E48 | G48: =C48+D48+E48-(IF(6<=Supuestos!$J$30,Supuestos!$B$19*Supuestos!$B$30*(1+Supuestos!$B$8)^5,0)+IF(6<=Supuestos!$B$22,Supuestos!$B$20*Supuestos!$D$30*(1+Supuestos!$B$8)^5,0)) | H48: =IF(6<=Supuestos!$J$30,$C$38*$B$39*((1-Supuestos!$B$11)*(1-Supuestos!$B$12)^5)*Supuestos!$I$30*(1+Supuestos!$B$9)^5,0) | I48: =IF(6<=Supuestos!$B$22,D48*Supuestos!$K$30,0) | J48: =C48+D48+E48-H48-I48 | K48: =H48+I48-(IF(6<=Supuestos!$J$30,Supuestos!$B$19*Supuestos!$B$30*(1+Supuestos!$B$8)^5,0)+IF(6<=Supuestos!$B$22,Supuestos!$B$20*Supuestos!$D$30*(1+Supuestos!$B$8)^5,0))-H48*Supuestos!$B$21 | L48: =L47+G48 | M48: =M47+J48
A49: 7 | B49: =$E$38*$B$39*(1+Supuestos!$B$8)^7 | C49: =$F$38*$B$39*(1+Supuestos!$B$8)^7*((1-Supuestos!$B$11)*(1-Supuestos!$B$12)^6) | D49: =$G$38*$B$39*(1+Supuestos!$B$8)^7*(1-Supuestos!$B$13)^7*Supuestos!$B$10 | E49: =$H$38*$B$39*(1+Supuestos!$B$8)^7 | F49: =B49-C49-D49-E49 | G49: =C49+D49+E49-(IF(7<=Supuestos!$J$30,Supuestos!$B$19*Supuestos!$B$30*(1+Supuestos!$B$8)^6,0)+IF(7<=Supuestos!$B$22,Supuestos!$B$20*Supuestos!$D$30*(1+Supuestos!$B$8)^6,0)) | H49: =IF(7<=Supuestos!$J$30,$C$38*$B$39*((1-Supuestos!$B$11)*(1-Supuestos!$B$12)^6)*Supuestos!$I$30*(1+Supuestos!$B$9)^6,0) | I49: =IF(7<=Supuestos!$B$22,D49*Supuestos!$K$30,0) | J49: =C49+D49+E49-H49-I49 | K49: =H49+I49-(IF(7<=Supuestos!$J$30,Supuestos!$B$19*Supuestos!$B$30*(1+Supuestos!$B$8)^6,0)+IF(7<=Supuestos!$B$22,Supuestos!$B$20*Supuestos!$D$30*(1+Supuestos!$B$8)^6,0))-H49*Supuestos!$B$21 | L49: =L48+G49 | M49: =M48+J49
A50: 8 | B50: =$E$38*$B$39*(1+Supuestos!$B$8)^8 | C50: =$F$38*$B$39*(1+Supuestos!$B$8)^8*((1-Supuestos!$B$11)*(1-Supuestos!$B$12)^7) | D50: =$G$38*$B$39*(1+Supuestos!$B$8)^8*(1-Supuestos!$B$13)^8*Supuestos!$B$10 | E50: =$H$38*$B$39*(1+Supuestos!$B$8)^8 | F50: =B50-C50-D50-E50 | G50: =C50+D50+E50-(IF(8<=Supuestos!$J$30,Supuestos!$B$19*Supuestos!$B$30*(1+Supuestos!$B$8)^7,0)+IF(8<=Supuestos!$B$22,Supuestos!$B$20*Supuestos!$D$30*(1+Supuestos!$B$8)^7,0)) | H50: =IF(8<=Supuestos!$J$30,$C$38*$B$39*((1-Supuestos!$B$11)*(1-Supuestos!$B$12)^7)*Supuestos!$I$30*(1+Supuestos!$B$9)^7,0) | I50: =IF(8<=Supuestos!$B$22,D50*Supuestos!$K$30,0) | J50: =C50+D50+E50-H50-I50 | K50: =H50+I50-(IF(8<=Supuestos!$J$30,Supuestos!$B$19*Supuestos!$B$30*(1+Supuestos!$B$8)^7,0)+IF(8<=Supuestos!$B$22,Supuestos!$B$20*Supuestos!$D$30*(1+Supuestos!$B$8)^7,0))-H50*Supuestos!$B$21 | L50: =L49+G50 | M50: =M49+J50
A51: 9 | B51: =$E$38*$B$39*(1+Supuestos!$B$8)^9 | C51: =$F$38*$B$39*(1+Supuestos!$B$8)^9*((1-Supuestos!$B$11)*(1-Supuestos!$B$12)^8) | D51: =$G$38*$B$39*(1+Supuestos!$B$8)^9*(1-Supuestos!$B$13)^9*Supuestos!$B$10 | E51: =$H$38*$B$39*(1+Supuestos!$B$8)^9 | F51: =B51-C51-D51-E51 | G51: =C51+D51+E51-(IF(9<=Supuestos!$J$30,Supuestos!$B$19*Supuestos!$B$30*(1+Supuestos!$B$8)^8,0)+IF(9<=Supuestos!$B$22,Supuestos!$B$20*Supuestos!$D$30*(1+Supuestos!$B$8)^8,0)) | H51: =IF(9<=Supuestos!$J$30,$C$38*$B$39*((1-Supuestos!$B$11)*(1-Supuestos!$B$12)^8)*Supuestos!$I$30*(1+Supuestos!$B$9)^8,0) | I51: =IF(9<=Supuestos!$B$22,D51*Supuestos!$K$30,0) | J51: =C51+D51+E51-H51-I51 | K51: =H51+I51-(IF(9<=Supuestos!$J$30,Supuestos!$B$19*Supuestos!$B$30*(1+Supuestos!$B$8)^8,0)+IF(9<=Supuestos!$B$22,Supuestos!$B$20*Supuestos!$D$30*(1+Supuestos!$B$8)^8,0))-H51*Supuestos!$B$21 | L51: =L50+G51 | M51: =M50+J51
A52: 10 | B52: =$E$38*$B$39*(1+Supuestos!$B$8)^10 | C52: =$F$38*$B$39*(1+Supuestos!$B$8)^10*((1-Supuestos!$B$11)*(1-Supuestos!$B$12)^9) | D52: =$G$38*$B$39*(1+Supuestos!$B$8)^10*(1-Supuestos!$B$13)^10*Supuestos!$B$10 | E52: =$H$38*$B$39*(1+Supuestos!$B$8)^10 | F52: =B52-C52-D52-E52 | G52: =C52+D52+E52-(IF(10<=Supuestos!$J$30,Supuestos!$B$19*Supuestos!$B$30*(1+Supuestos!$B$8)^9,0)+IF(10<=Supuestos!$B$22,Supuestos!$B$20*Supuestos!$D$30*(1+Supuestos!$B$8)^9,0)) | H52: =IF(10<=Supuestos!$J$30,$C$38*$B$39*((1-Supuestos!$B$11)*(1-Supuestos!$B$12)^9)*Supuestos!$I$30*(1+Supuestos!$B$9)^9,0) | I52: =IF(10<=Supuestos!$B$22,D52*Supuestos!$K$30,0) | J52: =C52+D52+E52-H52-I52 | K52: =H52+I52-(IF(10<=Supuestos!$J$30,Supuestos!$B$19*Supuestos!$B$30*(1+Supuestos!$B$8)^9,0)+IF(10<=Supuestos!$B$22,Supuestos!$B$20*Supuestos!$D$30*(1+Supuestos!$B$8)^9,0))-H52*Supuestos!$B$21 | L52: =L51+G52 | M52: =M51+J52
A53: 11 | B53: =$E$38*$B$39*(1+Supuestos!$B$8)^11 | C53: =$F$38*$B$39*(1+Supuestos!$B$8)^11*((1-Supuestos!$B$11)*(1-Supuestos!$B$12)^10) | D53: =$G$38*$B$39*(1+Supuestos!$B$8)^11*(1-Supuestos!$B$13)^11*Supuestos!$B$10 | E53: =$H$38*$B$39*(1+Supuestos!$B$8)^11 | F53: =B53-C53-D53-E53 | G53: =C53+D53+E53-(IF(11<=Supuestos!$J$30,Supuestos!$B$19*Supuestos!$B$30*(1+Supuestos!$B$8)^10,0)+IF(11<=Supuestos!$B$22,Supuestos!$B$20*Supuestos!$D$30*(1+Supuestos!$B$8)^10,0)) | H53: =IF(11<=Supuestos!$J$30,$C$38*$B$39*((1-Supuestos!$B$11)*(1-Supuestos!$B$12)^10)*Supuestos!$I$30*(1+Supuestos!$B$9)^10,0) | I53: =IF(11<=Supuestos!$B$22,D53*Supuestos!$K$30,0) | J53: =C53+D53+E53-H53-I53 | K53: =H53+I53-(IF(11<=Supuestos!$J$30,Supuestos!$B$19*Supuestos!$B$30*(1+Supuestos!$B$8)^10,0)+IF(11<=Supuestos!$B$22,Supuestos!$B$20*Supuestos!$D$30*(1+Supuestos!$B$8)^10,0))-H53*Supuestos!$B$21 | L53: =L52+G53 | M53: =M52+J53
A54: 12 | B54: =$E$38*$B$39*(1+Supuestos!$B$8)^12 | C54: =$F$38*$B$39*(1+Supuestos!$B$8)^12*((1-Supuestos!$B$11)*(1-Supuestos!$B$12)^11) | D54: =$G$38*$B$39*(1+Supuestos!$B$8)^12*(1-Supuestos!$B$13)^12*Supuestos!$B$10 | E54: =$H$38*$B$39*(1+Supuestos!$B$8)^12 | F54: =B54-C54-D54-E54 | G54: =C54+D54+E54-(IF(12<=Supuestos!$J$30,Supuestos!$B$19*Supuestos!$B$30*(1+Supuestos!$B$8)^11,0)+IF(12<=Supuestos!$B$22,Supuestos!$B$20*Supuestos!$D$30*(1+Supuestos!$B$8)^11,0)) | H54: =IF(12<=Supuestos!$J$30,$C$38*$B$39*((1-Supuestos!$B$11)*(1-Supuestos!$B$12)^11)*Supuestos!$I$30*(1+Supuestos!$B$9)^11,0) | I54: =IF(12<=Supuestos!$B$22,D54*Supuestos!$K$30,0) | J54: =C54+D54+E54-H54-I54 | K54: =H54+I54-(IF(12<=Supuestos!$J$30,Supuestos!$B$19*Supuestos!$B$30*(1+Supuestos!$B$8)^11,0)+IF(12<=Supuestos!$B$22,Supuestos!$B$20*Supuestos!$D$30*(1+Supuestos!$B$8)^11,0))-H54*Supuestos!$B$21 | L54: =L53+G54 | M54: =M53+J54
A55: 13 | B55: =$E$38*$B$39*(1+Supuestos!$B$8)^13 | C55: =$F$38*$B$39*(1+Supuestos!$B$8)^13*((1-Supuestos!$B$11)*(1-Supuestos!$B$12)^12) | D55: =$G$38*$B$39*(1+Supuestos!$B$8)^13*(1-Supuestos!$B$13)^13*Supuestos!$B$10 | E55: =$H$38*$B$39*(1+Supuestos!$B$8)^13 | F55: =B55-C55-D55-E55 | G55: =C55+D55+E55-(IF(13<=Supuestos!$J$30,Supuestos!$B$19*Supuestos!$B$30*(1+Supuestos!$B$8)^12,0)+IF(13<=Supuestos!$B$22,Supuestos!$B$20*Supuestos!$D$30*(1+Supuestos!$B$8)^12,0)) | H55: =IF(13<=Supuestos!$J$30,$C$38*$B$39*((1-Supuestos!$B$11)*(1-Supuestos!$B$12)^12)*Supuestos!$I$30*(1+Supuestos!$B$9)^12,0) | I55: =IF(13<=Supuestos!$B$22,D55*Supuestos!$K$30,0) | J55: =C55+D55+E55-H55-I55 | K55: =H55+I55-(IF(13<=Supuestos!$J$30,Supuestos!$B$19*Supuestos!$B$30*(1+Supuestos!$B$8)^12,0)+IF(13<=Supuestos!$B$22,Supuestos!$B$20*Supuestos!$D$30*(1+Supuestos!$B$8)^12,0))-H55*Supuestos!$B$21 | L55: =L54+G55 | M55: =M54+J55
A56: 14 | B56: =$E$38*$B$39*(1+Supuestos!$B$8)^14 | C56: =$F$38*$B$39*(1+Supuestos!$B$8)^14*((1-Supuestos!$B$11)*(1-Supuestos!$B$12)^13) | D56: =$G$38*$B$39*(1+Supuestos!$B$8)^14*(1-Supuestos!$B$13)^14*Supuestos!$B$10 | E56: =$H$38*$B$39*(1+Supuestos!$B$8)^14 | F56: =B56-C56-D56-E56 | G56: =C56+D56+E56-(IF(14<=Supuestos!$J$30,Supuestos!$B$19*Supuestos!$B$30*(1+Supuestos!$B$8)^13,0)+IF(14<=Supuestos!$B$22,Supuestos!$B$20*Supuestos!$D$30*(1+Supuestos!$B$8)^13,0)) | H56: =IF(14<=Supuestos!$J$30,$C$38*$B$39*((1-Supuestos!$B$11)*(1-Supuestos!$B$12)^13)*Supuestos!$I$30*(1+Supuestos!$B$9)^13,0) | I56: =IF(14<=Supuestos!$B$22,D56*Supuestos!$K$30,0) | J56: =C56+D56+E56-H56-I56 | K56: =H56+I56-(IF(14<=Supuestos!$J$30,Supuestos!$B$19*Supuestos!$B$30*(1+Supuestos!$B$8)^13,0)+IF(14<=Supuestos!$B$22,Supuestos!$B$20*Supuestos!$D$30*(1+Supuestos!$B$8)^13,0))-H56*Supuestos!$B$21 | L56: =L55+G56 | M56: =M55+J56
A57: 15 | B57: =$E$38*$B$39*(1+Supuestos!$B$8)^15 | C57: =$F$38*$B$39*(1+Supuestos!$B$8)^15*((1-Supuestos!$B$11)*(1-Supuestos!$B$12)^14) | D57: =$G$38*$B$39*(1+Supuestos!$B$8)^15*(1-Supuestos!$B$13)^15*Supuestos!$B$10 | E57: =$H$38*$B$39*(1+Supuestos!$B$8)^15 | F57: =B57-C57-D57-E57 | G57: =C57+D57+E57-(IF(15<=Supuestos!$J$30,Supuestos!$B$19*Supuestos!$B$30*(1+Supuestos!$B$8)^14,0)+IF(15<=Supuestos!$B$22,Supuestos!$B$20*Supuestos!$D$30*(1+Supuestos!$B$8)^14,0)) | H57: =IF(15<=Supuestos!$J$30,$C$38*$B$39*((1-Supuestos!$B$11)*(1-Supuestos!$B$12)^14)*Supuestos!$I$30*(1+Supuestos!$B$9)^14,0) | I57: =IF(15<=Supuestos!$B$22,D57*Supuestos!$K$30,0) | J57: =C57+D57+E57-H57-I57 | K57: =H57+I57-(IF(15<=Supuestos!$J$30,Supuestos!$B$19*Supuestos!$B$30*(1+Supuestos!$B$8)^14,0)+IF(15<=Supuestos!$B$22,Supuestos!$B$20*Supuestos!$D$30*(1+Supuestos!$B$8)^14,0))-H57*Supuestos!$B$21 | L57: =L56+G57 | M57: =M56+J57
A58: 16 | B58: =$E$38*$B$39*(1+Supuestos!$B$8)^16 | C58: =$F$38*$B$39*(1+Supuestos!$B$8)^16*((1-Supuestos!$B$11)*(1-Supuestos!$B$12)^15) | D58: =$G$38*$B$39*(1+Supuestos!$B$8)^16*(1-Supuestos!$B$13)^16*Supuestos!$B$10 | E58: =$H$38*$B$39*(1+Supuestos!$B$8)^16 | F58: =B58-C58-D58-E58 | G58: =C58+D58+E58-(IF(16<=Supuestos!$J$30,Supuestos!$B$19*Supuestos!$B$30*(1+Supuestos!$B$8)^15,0)+IF(16<=Supuestos!$B$22,Supuestos!$B$20*Supuestos!$D$30*(1+Supuestos!$B$8)^15,0)) | H58: =IF(16<=Supuestos!$J$30,$C$38*$B$39*((1-Supuestos!$B$11)*(1-Supuestos!$B$12)^15)*Supuestos!$I$30*(1+Supuestos!$B$9)^15,0) | I58: =IF(16<=Supuestos!$B$22,D58*Supuestos!$K$30,0) | J58: =C58+D58+E58-H58-I58 | K58: =H58+I58-(IF(16<=Supuestos!$J$30,Supuestos!$B$19*Supuestos!$B$30*(1+Supuestos!$B$8)^15,0)+IF(16<=Supuestos!$B$22,Supuestos!$B$20*Supuestos!$D$30*(1+Supuestos!$B$8)^15,0))-H58*Supuestos!$B$21 | L58: =L57+G58 | M58: =M57+J58
A59: 17 | B59: =$E$38*$B$39*(1+Supuestos!$B$8)^17 | C59: =$F$38*$B$39*(1+Supuestos!$B$8)^17*((1-Supuestos!$B$11)*(1-Supuestos!$B$12)^16) | D59: =$G$38*$B$39*(1+Supuestos!$B$8)^17*(1-Supuestos!$B$13)^17*Supuestos!$B$10 | E59: =$H$38*$B$39*(1+Supuestos!$B$8)^17 | F59: =B59-C59-D59-E59 | G59: =C59+D59+E59-(IF(17<=Supuestos!$J$30,Supuestos!$B$19*Supuestos!$B$30*(1+Supuestos!$B$8)^16,0)+IF(17<=Supuestos!$B$22,Supuestos!$B$20*Supuestos!$D$30*(1+Supuestos!$B$8)^16,0)) | H59: =IF(17<=Supuestos!$J$30,$C$38*$B$39*((1-Supuestos!$B$11)*(1-Supuestos!$B$12)^16)*Supuestos!$I$30*(1+Supuestos!$B$9)^16,0) | I59: =IF(17<=Supuestos!$B$22,D59*Supuestos!$K$30,0) | J59: =C59+D59+E59-H59-I59 | K59: =H59+I59-(IF(17<=Supuestos!$J$30,Supuestos!$B$19*Supuestos!$B$30*(1+Supuestos!$B$8)^16,0)+IF(17<=Supuestos!$B$22,Supuestos!$B$20*Supuestos!$D$30*(1+Supuestos!$B$8)^16,0))-H59*Supuestos!$B$21 | L59: =L58+G59 | M59: =M58+J59
A60: 18 | B60: =$E$38*$B$39*(1+Supuestos!$B$8)^18 | C60: =$F$38*$B$39*(1+Supuestos!$B$8)^18*((1-Supuestos!$B$11)*(1-Supuestos!$B$12)^17) | D60: =$G$38*$B$39*(1+Supuestos!$B$8)^18*(1-Supuestos!$B$13)^18*Supuestos!$B$10 | E60: =$H$38*$B$39*(1+Supuestos!$B$8)^18 | F60: =B60-C60-D60-E60 | G60: =C60+D60+E60-(IF(18<=Supuestos!$J$30,Supuestos!$B$19*Supuestos!$B$30*(1+Supuestos!$B$8)^17,0)+IF(18<=Supuestos!$B$22,Supuestos!$B$20*Supuestos!$D$30*(1+Supuestos!$B$8)^17,0)) | H60: =IF(18<=Supuestos!$J$30,$C$38*$B$39*((1-Supuestos!$B$11)*(1-Supuestos!$B$12)^17)*Supuestos!$I$30*(1+Supuestos!$B$9)^17,0) | I60: =IF(18<=Supuestos!$B$22,D60*Supuestos!$K$30,0) | J60: =C60+D60+E60-H60-I60 | K60: =H60+I60-(IF(18<=Supuestos!$J$30,Supuestos!$B$19*Supuestos!$B$30*(1+Supuestos!$B$8)^17,0)+IF(18<=Supuestos!$B$22,Supuestos!$B$20*Supuestos!$D$30*(1+Supuestos!$B$8)^17,0))-H60*Supuestos!$B$21 | L60: =L59+G60 | M60: =M59+J60
A61: 19 | B61: =$E$38*$B$39*(1+Supuestos!$B$8)^19 | C61: =$F$38*$B$39*(1+Supuestos!$B$8)^19*((1-Supuestos!$B$11)*(1-Supuestos!$B$12)^18) | D61: =$G$38*$B$39*(1+Supuestos!$B$8)^19*(1-Supuestos!$B$13)^19*Supuestos!$B$10 | E61: =$H$38*$B$39*(1+Supuestos!$B$8)^19 | F61: =B61-C61-D61-E61 | G61: =C61+D61+E61-(IF(19<=Supuestos!$J$30,Supuestos!$B$19*Supuestos!$B$30*(1+Supuestos!$B$8)^18,0)+IF(19<=Supuestos!$B$22,Supuestos!$B$20*Supuestos!$D$30*(1+Supuestos!$B$8)^18,0)) | H61: =IF(19<=Supuestos!$J$30,$C$38*$B$39*((1-Supuestos!$B$11)*(1-Supuestos!$B$12)^18)*Supuestos!$I$30*(1+Supuestos!$B$9)^18,0) | I61: =IF(19<=Supuestos!$B$22,D61*Supuestos!$K$30,0) | J61: =C61+D61+E61-H61-I61 | K61: =H61+I61-(IF(19<=Supuestos!$J$30,Supuestos!$B$19*Supuestos!$B$30*(1+Supuestos!$B$8)^18,0)+IF(19<=Supuestos!$B$22,Supuestos!$B$20*Supuestos!$D$30*(1+Supuestos!$B$8)^18,0))-H61*Supuestos!$B$21 | L61: =L60+G61 | M61: =M60+J61
A62: 20 | B62: =$E$38*$B$39*(1+Supuestos!$B$8)^20 | C62: =$F$38*$B$39*(1+Supuestos!$B$8)^20*((1-Supuestos!$B$11)*(1-Supuestos!$B$12)^19) | D62: =$G$38*$B$39*(1+Supuestos!$B$8)^20*(1-Supuestos!$B$13)^20*Supuestos!$B$10 | E62: =$H$38*$B$39*(1+Supuestos!$B$8)^20 | F62: =B62-C62-D62-E62 | G62: =C62+D62+E62-(IF(20<=Supuestos!$J$30,Supuestos!$B$19*Supuestos!$B$30*(1+Supuestos!$B$8)^19,0)+IF(20<=Supuestos!$B$22,Supuestos!$B$20*Supuestos!$D$30*(1+Supuestos!$B$8)^19,0)) | H62: =IF(20<=Supuestos!$J$30,$C$38*$B$39*((1-Supuestos!$B$11)*(1-Supuestos!$B$12)^19)*Supuestos!$I$30*(1+Supuestos!$B$9)^19,0) | I62: =IF(20<=Supuestos!$B$22,D62*Supuestos!$K$30,0) | J62: =C62+D62+E62-H62-I62 | K62: =H62+I62-(IF(20<=Supuestos!$J$30,Supuestos!$B$19*Supuestos!$B$30*(1+Supuestos!$B$8)^19,0)+IF(20<=Supuestos!$B$22,Supuestos!$B$20*Supuestos!$D$30*(1+Supuestos!$B$8)^19,0))-H62*Supuestos!$B$21 | L62: =L61+G62 | M62: =M61+J62
A64: TIR compra (proyecto): | B64: =IRR(G42:G62) | C64: VPN compra @WACC: | D64: =G42+NPV(Supuestos!$B$7,G43:G62)
A65: TIR financiador: | B65: =IRR(K42:K62) | C65: VPN cliente PPA @WACC: | D65: =NPV(Supuestos!$B$7,J43:J62)
A66: Acumulado cliente PPA 20a: | B66: =SUM(J43:J62) | C66: Acumulado compra 20a: | D66: =SUM(G42:G62)
A68: 5. POR QUÉ ESTE DIMENSIONAMIENTO ES ÓPTIMO
A69: • PV 234 kWp — generador exento <0.7 MW (medición neta, sin permiso CNE). En SIN la generación solar cae en intermedio → recorta energía intermedia; no genera en punta, por lo que el BESS es la palanca de demanda.
A70: • BESS 254 kW / 1,017 kWh — recorta el pico de punta (arbitraje carga en base, descarga en punta, topado al kWh punta del recibo).
A71: • Dimensionado al consumo (rend. inputs.json); excedentes bajo medición neta expiran en 12 meses, por eso no se sobredimensiona el PV.
A72: • PV/BESS dimensionados por **barrido de máximo NPV del cliente** (NO se topó a 0.7 MW): el óptimo cae en 234 kWp / 254 kW de BESS (sweep NPV (exento)). Más allá del punto de autoconsumo solar el excedente se valúa ~$0 y el NPV cae; el barrido compara explícitamente quedarse exento <0.7 MW vs cruzar a autoconsumo.
A73: • Corrección de factor de potencia incluida — palanca separada, capacitores a cargo del financiador en el esquema PPA (el cliente conserva 100% del ahorro FP).
A74: • LIBRO 100% EN VIVO: motor mensual §3 = fórmulas sobre los datos del recibo (§6) y Supuestos (réplica exacta del motor determinista, verificada al peso) — edita kWp/BESS/FC/tarifas o cualquier mes y TODO recalcula hasta la TIR.
A78: 6. DATOS DEL RECIBO (editables — el motor mensual §3 se alimenta de aquí)
A79: Mes | B79: Días | C79: kWh B | D79: kWh I | E79: kWh P | F79: kW B | G79: kW I | H79: kW P | I79: FP % | J79: Gen B $ | K79: Gen I $ | L79: Gen P $ | M79: Distribución $ | N79: Capacidad $ | O79: Otros vol $ | P79: Suministro $ | Q79: 2%BT+FP neto $ | R79: Cargo FP $ | S79: Yield kWh/kWp | T79: Hrs punta | U79: Días punta | V79: kWh tot | W79: Vol $/kWh | X79: Tarifa B $/kWh | Y79: Tarifa I $/kWh | Z79: Tarifa P $/kWh | AA79: Umbral kW | AB79: $/kW cap
A80: Abr-25 | B80: 30 | C80: 48186 | D80: 96049 | E80: 12039 | F80: 296 | G80: 296 | H80: 279 | I80: 100 | J80: 47439.12 | K80: 169267.15 | L80: 25196.42 | M80: 20091.15 | N80: 128633.94 | O80: 30254.65 | P80: 466.83 | Q80: -10533.73 | R80: 0 | S80: 150.72 | T80: 2 | U80: 22 | V80: =C80+D80+E80 | W80: =O80/V80 | X80: =IF(C80=0,Y80,J80/C80+W80) | Y80: =IF(D80=0,0,K80/D80+W80) | Z80: =IF(E80=0,0,L80/E80+W80) | AA80: =V80/(B80*24*$L$6) | AB80: =IFERROR(N80/MIN(H80,AA80),0)
A81: May-25 | B81: 31 | C81: 49117 | D81: 98185 | E81: 8816 | F81: 286 | G81: 322 | H81: 280 | I81: 100 | J81: 48355.69 | K81: 173031.43 | L81: 18451.01 | M81: 20646.64 | N81: 121133.6 | O81: 30224.45 | P81: 466.83 | Q81: -10307.74 | R81: 0 | S81: 143.096 | T81: 2 | U81: 21 | V81: =C81+D81+E81 | W81: =O81/V81 | X81: =IF(C81=0,Y81,J81/C81+W81) | Y81: =IF(D81=0,0,K81/D81+W81) | Z81: =IF(E81=0,0,L81/E81+W81) | AA81: =V81/(B81*24*$L$6) | AB81: =IFERROR(N81/MIN(H81,AA81),0)
A82: Jun-25 | B82: 30 | C82: 42769 | D82: 81384 | E82: 7642 | F82: 252 | G82: 363 | H82: 238 | I82: 100 | J82: 43106.88 | K82: 146824.87 | L82: 16374.51 | M82: 20646.64 | N82: 105410.2 | O82: 25515.52 | P82: 466.83 | Q82: -8958.64 | R82: 0 | S82: 133.92 | T82: 2 | U82: 21 | V82: =C82+D82+E82 | W82: =O82/V82 | X82: =IF(C82=0,Y82,J82/C82+W82) | Y82: =IF(D82=0,0,K82/D82+W82) | Z82: =IF(E82=0,0,L82/E82+W82) | AA82: =V82/(B82*24*$L$6) | AB82: =IFERROR(N82/MIN(H82,AA82),0)
A83: Jul-25 | B83: 31 | C83: 43308 | D83: 91399 | E83: 8743 | F83: 251 | G83: 295 | H83: 236 | I83: 100 | J83: 44304.08 | K83: 167369.85 | L83: 19014.28 | M83: 18915.4 | N83: 106091.44 | O83: 27771.92 | P83: 466.83 | Q83: -9598.35 | R83: 0 | S83: 135.16 | T83: 2 | U83: 23 | V83: =C83+D83+E83 | W83: =O83/V83 | X83: =IF(C83=0,Y83,J83/C83+W83) | Y83: =IF(D83=0,0,K83/D83+W83) | Z83: =IF(E83=0,0,L83/E83+W83) | AA83: =V83/(B83*24*$L$6) | AB83: =IFERROR(N83/MIN(H83,AA83),0)
A84: Ago-25 | B84: 31 | C84: 46345 | D84: 89977 | E84: 8099 | F84: 254 | G84: 281 | H84: 249 | I84: 100 | J84: 47480.45 | K84: 164990.82 | L84: 17638 | M84: 18017.72 | N84: 112092.33 | O84: 27959.9 | P84: 466.83 | Q84: -9716.15 | R84: 0 | S84: 126.728 | T84: 2 | U84: 21 | V84: =C84+D84+E84 | W84: =O84/V84 | X84: =IF(C84=0,Y84,J84/C84+W84) | Y84: =IF(D84=0,0,K84/D84+W84) | Z84: =IF(E84=0,0,L84/E84+W84) | AA84: =V84/(B84*24*$L$6) | AB84: =IFERROR(N84/MIN(H84,AA84),0)
A85: Sep-25 | B85: 30 | C85: 44334 | D85: 84898 | E85: 7852 | F85: 258 | G85: 271 | H85: 234 | I85: 100 | J85: 45003.44 | K85: 154259.67 | L85: 16943.83 | M85: 17376.52 | N85: 104375.7 | O85: 27101.51 | P85: 466.83 | Q85: -9138.19 | R85: 0 | S85: 119.52 | T85: 2 | U85: 21 | V85: =C85+D85+E85 | W85: =O85/V85 | X85: =IF(C85=0,Y85,J85/C85+W85) | Y85: =IF(D85=0,0,K85/D85+W85) | Z85: =IF(E85=0,0,L85/E85+W85) | AA85: =V85/(B85*24*$L$6) | AB85: =IFERROR(N85/MIN(H85,AA85),0)
A86: Oct-25 | B86: 31 | C86: 43349 | D86: 90173 | E86: 11101 | F86: 270 | G86: 249 | H86: 234 | I86: 100 | J86: 44003.57 | K86: 163844.34 | L86: 23954.85 | M86: 18398.37 | N86: 106536.52 | O86: 28591.98 | P86: 466.83 | Q86: -9644.92 | R86: 0 | S86: 131.936 | T86: 2 | U86: 23 | V86: =C86+D86+E86 | W86: =O86/V86 | X86: =IF(C86=0,Y86,J86/C86+W86) | Y86: =IF(D86=0,0,K86/D86+W86) | Z86: =IF(E86=0,0,L86/E86+W86) | AA86: =V86/(B86*24*$L$6) | AB86: =IFERROR(N86/MIN(H86,AA86),0)
A87: Nov-25 | B87: 30 | C87: 47603 | D87: 74526 | E87: 17103 | F87: 295 | G87: 251 | H87: 245 | I87: 100 | J87: 46869.91 | K87: 131344.62 | L87: 35798.29 | M87: 18915.4 | N87: 106001.7 | O87: 27526.16 | P87: 466.83 | Q87: -9173.07 | R87: 0 | S87: 136.56 | T87: 4 | U87: 19 | V87: =C87+D87+E87 | W87: =O87/V87 | X87: =IF(C87=0,Y87,J87/C87+W87) | Y87: =IF(D87=0,0,K87/D87+W87) | Z87: =IF(E87=0,0,L87/E87+W87) | AA87: =V87/(B87*24*$L$6) | AB87: =IFERROR(N87/MIN(H87,AA87),0)
A88: Dic-25 | B88: 31 | C88: 43085 | D88: 74065 | E88: 18253 | F88: 250 | G88: 264 | H88: 255 | I88: 100 | J88: 40301.71 | K88: 124007.03 | L88: 36296.09 | M88: 16927.68 | N88: 104812.65 | O88: 26769.18 | P88: 466.83 | Q88: -8739.53 | R88: 0 | S88: 131.192 | T88: 4 | U88: 22 | V88: =C88+D88+E88 | W88: =O88/V88 | X88: =IF(C88=0,Y88,J88/C88+W88) | Y88: =IF(D88=0,0,K88/D88+W88) | Z88: =IF(E88=0,0,L88/E88+W88) | AA88: =V88/(B88*24*$L$6) | AB88: =IFERROR(N88/MIN(H88,AA88),0)
A89: Ene-26 | B89: 31 | C89: 43042 | D89: 74276 | E89: 17893 | F89: 225 | G89: 255 | H89: 245 | I89: 99.99 | J89: 39357.6 | K89: 121560.1 | L89: 34778.62 | M89: 15509.1 | N89: 98436.1 | O89: 26312.06 | P89: 540.49 | Q89: -8412.35 | R89: 0 | S89: 143.096 | T89: 4 | U89: 21 | V89: =C89+D89+E89 | W89: =O89/V89 | X89: =IF(C89=0,Y89,J89/C89+W89) | Y89: =IF(D89=0,0,K89/D89+W89) | Z89: =IF(E89=0,0,L89/E89+W89) | AA89: =V89/(B89*24*$L$6) | AB89: =IFERROR(N89/MIN(H89,AA89),0)
A90: Feb-26 | B90: 28 | C90: 40334 | D90: 68136 | E90: 16606 | F90: 270 | G90: 302 | H90: 286 | I90: 100 | J90: 36901.58 | K90: 111579.51 | L90: 32297.01 | M90: 18367.64 | N90: 114974.86 | O90: 24339.78 | P90: 540.49 | Q90: -8475.02 | R90: 0 | S90: 139.104 | T90: 4 | U90: 19 | V90: =C90+D90+E90 | W90: =O90/V90 | X90: =IF(C90=0,Y90,J90/C90+W90) | Y90: =IF(D90=0,0,K90/D90+W90) | Z90: =IF(E90=0,0,L90/E90+W90) | AA90: =V90/(B90*24*$L$6) | AB90: =IFERROR(N90/MIN(H90,AA90),0)
A91: Mar-26 | B91: 31 | C91: 46954 | D91: 77134 | E91: 18613 | F91: 270 | G91: 294 | H91: 269 | I91: 100 | J91: 42981.69 | K91: 126391.77 | L91: 36220.9 | M91: 17881.08 | N91: 108207.94 | O91: 27769.61 | P91: 540.49 | Q91: -8999.84 | R91: 0 | S91: 170.376 | T91: 4 | U91: 21 | V91: =C91+D91+E91 | W91: =O91/V91 | X91: =IF(C91=0,Y91,J91/C91+W91) | Y91: =IF(D91=0,0,K91/D91+W91) | Z91: =IF(E91=0,0,L91/E91+W91) | AA91: =V91/(B91*24*$L$6) | AB91: =IFERROR(N91/MIN(H91,AA91),0)
A92: Filas = recibo ancla (parseado) + meses reconstruidos del CONSUMO HISTÓRICO (subtotal al peso; split TOU por shares del ancla). Capacidad a MIN(kW punta, umbral); tarifas por banda = concepto/kWh + vol/kWh; col Q<0 (bonificación FP) aplica claw-back al ahorro. Válido <700 kWp (medición neta). Excedentes PV a $0.
O94: Techo — referencia satelital (ruta HelioScope; cruz roja = punto verificado) · confianza ?

Sheet Comparativo Comercial
A1: Comparativo Comercial — Comprar vs PPA / Ahorro compartido
A3: RESULTADO POR PROYECTO (referencias vivas a cada hoja)
A4: Proyecto | B4: Compra benef/año $ | C4: Compra inversión $ | D4: Compra TIR | E4: PPA benef cliente a1 $ | F4: PPA TIR financiador | G4: Ahorro bruto/año $ | H4: Ahorro % | I4: Ahorro cliente % (PPA a1)
A5: Médano / Cabo San Lucas (Posadas F/1596) | B5: ='Médano - Cabo San Lucas (Pos'!$C$43+'Médano - Cabo San Lucas (Pos'!$D$43+'Médano - Cabo San Lucas (Pos'!$E$43 | C5: ='Médano - Cabo San Lucas (Pos'!$B$22 | D5: ='Médano - Cabo San Lucas (Pos'!$B$64 | E5: ='Médano - Cabo San Lucas (Pos'!$J$43 | F5: ='Médano - Cabo San Lucas (Pos'!$B$65 | G5: ='Médano - Cabo San Lucas (Pos'!$J$38*'Médano - Cabo San Lucas (Pos'!$B$39 | H5: =G5/('Médano - Cabo San Lucas (Pos'!$E$38*'Médano - Cabo San Lucas (Pos'!$B$39) | I5: ='Médano - Cabo San Lucas (Pos'!$J$43/'Médano - Cabo San Lucas (Pos'!$B$43
A6: Fairfield Inn Vallejo (F/1596) | B6: ='Fairfield Inn Vallejo (F-159'!$C$43+'Fairfield Inn Vallejo (F-159'!$D$43+'Fairfield Inn Vallejo (F-159'!$E$43 | C6: ='Fairfield Inn Vallejo (F-159'!$B$22 | D6: ='Fairfield Inn Vallejo (F-159'!$B$64 | E6: ='Fairfield Inn Vallejo (F-159'!$J$43 | F6: ='Fairfield Inn Vallejo (F-159'!$B$65 | G6: ='Fairfield Inn Vallejo (F-159'!$J$38*'Fairfield Inn Vallejo (F-159'!$B$39 | H6: =G6/('Fairfield Inn Vallejo (F-159'!$E$38*'Fairfield Inn Vallejo (F-159'!$B$39) | I6: ='Fairfield Inn Vallejo (F-159'!$J$43/'Fairfield Inn Vallejo (F-159'!$B$43
A7: Fiesta Americana Condesa Cancún | B7: ='Fiesta Americana Condesa Can'!$C$43+'Fiesta Americana Condesa Can'!$D$43+'Fiesta Americana Condesa Can'!$E$43 | C7: ='Fiesta Americana Condesa Can'!$B$22 | D7: ='Fiesta Americana Condesa Can'!$B$64 | E7: ='Fiesta Americana Condesa Can'!$J$43 | F7: ='Fiesta Americana Condesa Can'!$B$65 | G7: ='Fiesta Americana Condesa Can'!$J$38*'Fiesta Americana Condesa Can'!$B$39 | H7: =G7/('Fiesta Americana Condesa Can'!$E$38*'Fiesta Americana Condesa Can'!$B$39) | I7: ='Fiesta Americana Condesa Can'!$J$43/'Fiesta Americana Condesa Can'!$B$43
A8: Fiesta Inn Periférico Sur (CDMX) | B8: ='Fiesta Inn Periférico Sur (C'!$C$43+'Fiesta Inn Periférico Sur (C'!$D$43+'Fiesta Inn Periférico Sur (C'!$E$43 | C8: ='Fiesta Inn Periférico Sur (C'!$B$22 | D8: ='Fiesta Inn Periférico Sur (C'!$B$64 | E8: ='Fiesta Inn Periférico Sur (C'!$J$43 | F8: ='Fiesta Inn Periférico Sur (C'!$B$65 | G8: ='Fiesta Inn Periférico Sur (C'!$J$38*'Fiesta Inn Periférico Sur (C'!$B$39 | H8: =G8/('Fiesta Inn Periférico Sur (C'!$E$38*'Fiesta Inn Periférico Sur (C'!$B$39) | I8: ='Fiesta Inn Periférico Sur (C'!$J$43/'Fiesta Inn Periférico Sur (C'!$B$43
A9: Fiesta Americana Viaducto Aeropuerto (CDMX) | B9: ='Fiesta Americana Viaducto Ae'!$C$43+'Fiesta Americana Viaducto Ae'!$D$43+'Fiesta Americana Viaducto Ae'!$E$43 | C9: ='Fiesta Americana Viaducto Ae'!$B$22 | D9: ='Fiesta Americana Viaducto Ae'!$B$64 | E9: ='Fiesta Americana Viaducto Ae'!$J$43 | F9: ='Fiesta Americana Viaducto Ae'!$B$65 | G9: ='Fiesta Americana Viaducto Ae'!$J$38*'Fiesta Americana Viaducto Ae'!$B$39 | H9: =G9/('Fiesta Americana Viaducto Ae'!$E$38*'Fiesta Americana Viaducto Ae'!$B$39) | I9: ='Fiesta Americana Viaducto Ae'!$J$43/'Fiesta Americana Viaducto Ae'!$B$43
A10: PORTAFOLIO | B10: =SUM(B5:B9) | C10: =SUM(C5:C9) | E10: =SUM(E5:E9) | G10: =SUM(G5:G9)
A12: Comprar maximiza el ahorro (TIR proyecto supera el WACC); PPA = cero inversión: el financiador funda el CAPEX y cobra PPA+comisión a su TIR objetivo.

Sheet Proyección 20 años
A1: Proyección 20 años — Portafolio (suma de hojas por proyecto)
A3: Año | B3: Tarifa Actual $ | C3: Ahorro total $ | D3: Costo c/proy $ | E3: Flujo Compra $ | F3: Flujo Cliente PPA $ | G3: Acum. Compra $ | H3: Acum. Cliente PPA $
A4: 1 | B4: ='Médano - Cabo San Lucas (Pos'!B43+'Fairfield Inn Vallejo (F-159'!B43+'Fiesta Americana Condesa Can'!B43+'Fiesta Inn Periférico Sur (C'!B43+'Fiesta Americana Viaducto Ae'!B43 | C4: =('Médano - Cabo San Lucas (Pos'!C43+'Médano - Cabo San Lucas (Pos'!D43+'Médano - Cabo San Lucas (Pos'!E43)+('Fairfield Inn Vallejo (F-159'!C43+'Fairfield Inn Vallejo (F-159'!D43+'Fairfield Inn Vallejo (F-159'!E43)+('Fiesta Americana Condesa Can'!C43+'Fiesta Americana Condesa Can'!D43+'Fiesta Americana Condesa Can'!E43)+('Fiesta Inn Periférico Sur (C'!C43+'Fiesta Inn Periférico Sur (C'!D43+'Fiesta Inn Periférico Sur (C'!E43)+('Fiesta Americana Viaducto Ae'!C43+'Fiesta Americana Viaducto Ae'!D43+'Fiesta Americana Viaducto Ae'!E43) | D4: =B4-C4 | E4: ='Médano - Cabo San Lucas (Pos'!G43+'Fairfield Inn Vallejo (F-159'!G43+'Fiesta Americana Condesa Can'!G43+'Fiesta Inn Periférico Sur (C'!G43+'Fiesta Americana Viaducto Ae'!G43 | F4: ='Médano - Cabo San Lucas (Pos'!J43+'Fairfield Inn Vallejo (F-159'!J43+'Fiesta Americana Condesa Can'!J43+'Fiesta Inn Periférico Sur (C'!J43+'Fiesta Americana Viaducto Ae'!J43 | G4: =E4 | H4: =F4
A5: 2 | B5: ='Médano - Cabo San Lucas (Pos'!B44+'Fairfield Inn Vallejo (F-159'!B44+'Fiesta Americana Condesa Can'!B44+'Fiesta Inn Periférico Sur (C'!B44+'Fiesta Americana Viaducto Ae'!B44 | C5: =('Médano - Cabo San Lucas (Pos'!C44+'Médano - Cabo San Lucas (Pos'!D44+'Médano - Cabo San Lucas (Pos'!E44)+('Fairfield Inn Vallejo (F-159'!C44+'Fairfield Inn Vallejo (F-159'!D44+'Fairfield Inn Vallejo (F-159'!E44)+('Fiesta Americana Condesa Can'!C44+'Fiesta Americana Condesa Can'!D44+'Fiesta Americana Condesa Can'!E44)+('Fiesta Inn Periférico Sur (C'!C44+'Fiesta Inn Periférico Sur (C'!D44+'Fiesta Inn Periférico Sur (C'!E44)+('Fiesta Americana Viaducto Ae'!C44+'Fiesta Americana Viaducto Ae'!D44+'Fiesta Americana Viaducto Ae'!E44) | D5: =B5-C5 | E5: ='Médano - Cabo San Lucas (Pos'!G44+'Fairfield Inn Vallejo (F-159'!G44+'Fiesta Americana Condesa Can'!G44+'Fiesta Inn Periférico Sur (C'!G44+'Fiesta Americana Viaducto Ae'!G44 | F5: ='Médano - Cabo San Lucas (Pos'!J44+'Fairfield Inn Vallejo (F-159'!J44+'Fiesta Americana Condesa Can'!J44+'Fiesta Inn Periférico Sur (C'!J44+'Fiesta Americana Viaducto Ae'!J44 | G5: =G4+E5 | H5: =H4+F5
A6: 3 | B6: ='Médano - Cabo San Lucas (Pos'!B45+'Fairfield Inn Vallejo (F-159'!B45+'Fiesta Americana Condesa Can'!B45+'Fiesta Inn Periférico Sur (C'!B45+'Fiesta Americana Viaducto Ae'!B45 | C6: =('Médano - Cabo San Lucas (Pos'!C45+'Médano - Cabo San Lucas (Pos'!D45+'Médano - Cabo San Lucas (Pos'!E45)+('Fairfield Inn Vallejo (F-159'!C45+'Fairfield Inn Vallejo (F-159'!D45+'Fairfield Inn Vallejo (F-159'!E45)+('Fiesta Americana Condesa Can'!C45+'Fiesta Americana Condesa Can'!D45+'Fiesta Americana Condesa Can'!E45)+('Fiesta Inn Periférico Sur (C'!C45+'Fiesta Inn Periférico Sur (C'!D45+'Fiesta Inn Periférico Sur (C'!E45)+('Fiesta Americana Viaducto Ae'!C45+'Fiesta Americana Viaducto Ae'!D45+'Fiesta Americana Viaducto Ae'!E45) | D6: =B6-C6 | E6: ='Médano - Cabo San Lucas (Pos'!G45+'Fairfield Inn Vallejo (F-159'!G45+'Fiesta Americana Condesa Can'!G45+'Fiesta Inn Periférico Sur (C'!G45+'Fiesta Americana Viaducto Ae'!G45 | F6: ='Médano - Cabo San Lucas (Pos'!J45+'Fairfield Inn Vallejo (F-159'!J45+'Fiesta Americana Condesa Can'!J45+'Fiesta Inn Periférico Sur (C'!J45+'Fiesta Americana Viaducto Ae'!J45 | G6: =G5+E6 | H6: =H5+F6
A7: 4 | B7: ='Médano - Cabo San Lucas (Pos'!B46+'Fairfield Inn Vallejo (F-159'!B46+'Fiesta Americana Condesa Can'!B46+'Fiesta Inn Periférico Sur (C'!B46+'Fiesta Americana Viaducto Ae'!B46 | C7: =('Médano - Cabo San Lucas (Pos'!C46+'Médano - Cabo San Lucas (Pos'!D46+'Médano - Cabo San Lucas (Pos'!E46)+('Fairfield Inn Vallejo (F-159'!C46+'Fairfield Inn Vallejo (F-159'!D46+'Fairfield Inn Vallejo (F-159'!E46)+('Fiesta Americana Condesa Can'!C46+'Fiesta Americana Condesa Can'!D46+'Fiesta Americana Condesa Can'!E46)+('Fiesta Inn Periférico Sur (C'!C46+'Fiesta Inn Periférico Sur (C'!D46+'Fiesta Inn Periférico Sur (C'!E46)+('Fiesta Americana Viaducto Ae'!C46+'Fiesta Americana Viaducto Ae'!D46+'Fiesta Americana Viaducto Ae'!E46) | D7: =B7-C7 | E7: ='Médano - Cabo San Lucas (Pos'!G46+'Fairfield Inn Vallejo (F-159'!G46+'Fiesta Americana Condesa Can'!G46+'Fiesta Inn Periférico Sur (C'!G46+'Fiesta Americana Viaducto Ae'!G46 | F7: ='Médano - Cabo San Lucas (Pos'!J46+'Fairfield Inn Vallejo (F-159'!J46+'Fiesta Americana Condesa Can'!J46+'Fiesta Inn Periférico Sur (C'!J46+'Fiesta Americana Viaducto Ae'!J46 | G7: =G6+E7 | H7: =H6+F7
A8: 5 | B8: ='Médano - Cabo San Lucas (Pos'!B47+'Fairfield Inn Vallejo (F-159'!B47+'Fiesta Americana Condesa Can'!B47+'Fiesta Inn Periférico Sur (C'!B47+'Fiesta Americana Viaducto Ae'!B47 | C8: =('Médano - Cabo San Lucas (Pos'!C47+'Médano - Cabo San Lucas (Pos'!D47+'Médano - Cabo San Lucas (Pos'!E47)+('Fairfield Inn Vallejo (F-159'!C47+'Fairfield Inn Vallejo (F-159'!D47+'Fairfield Inn Vallejo (F-159'!E47)+('Fiesta Americana Condesa Can'!C47+'Fiesta Americana Condesa Can'!D47+'Fiesta Americana Condesa Can'!E47)+('Fiesta Inn Periférico Sur (C'!C47+'Fiesta Inn Periférico Sur (C'!D47+'Fiesta Inn Periférico Sur (C'!E47)+('Fiesta Americana Viaducto Ae'!C47+'Fiesta Americana Viaducto Ae'!D47+'Fiesta Americana Viaducto Ae'!E47) | D8: =B8-C8 | E8: ='Médano - Cabo San Lucas (Pos'!G47+'Fairfield Inn Vallejo (F-159'!G47+'Fiesta Americana Condesa Can'!G47+'Fiesta Inn Periférico Sur (C'!G47+'Fiesta Americana Viaducto Ae'!G47 | F8: ='Médano - Cabo San Lucas (Pos'!J47+'Fairfield Inn Vallejo (F-159'!J47+'Fiesta Americana Condesa Can'!J47+'Fiesta Inn Periférico Sur (C'!J47+'Fiesta Americana Viaducto Ae'!J47 | G8: =G7+E8 | H8: =H7+F8
A9: 6 | B9: ='Médano - Cabo San Lucas (Pos'!B48+'Fairfield Inn Vallejo (F-159'!B48+'Fiesta Americana Condesa Can'!B48+'Fiesta Inn Periférico Sur (C'!B48+'Fiesta Americana Viaducto Ae'!B48 | C9: =('Médano - Cabo San Lucas (Pos'!C48+'Médano - Cabo San Lucas (Pos'!D48+'Médano - Cabo San Lucas (Pos'!E48)+('Fairfield Inn Vallejo (F-159'!C48+'Fairfield Inn Vallejo (F-159'!D48+'Fairfield Inn Vallejo (F-159'!E48)+('Fiesta Americana Condesa Can'!C48+'Fiesta Americana Condesa Can'!D48+'Fiesta Americana Condesa Can'!E48)+('Fiesta Inn Periférico Sur (C'!C48+'Fiesta Inn Periférico Sur (C'!D48+'Fiesta Inn Periférico Sur (C'!E48)+('Fiesta Americana Viaducto Ae'!C48+'Fiesta Americana Viaducto Ae'!D48+'Fiesta Americana Viaducto Ae'!E48) | D9: =B9-C9 | E9: ='Médano - Cabo San Lucas (Pos'!G48+'Fairfield Inn Vallejo (F-159'!G48+'Fiesta Americana Condesa Can'!G48+'Fiesta Inn Periférico Sur (C'!G48+'Fiesta Americana Viaducto Ae'!G48 | F9: ='Médano - Cabo San Lucas (Pos'!J48+'Fairfield Inn Vallejo (F-159'!J48+'Fiesta Americana Condesa Can'!J48+'Fiesta Inn Periférico Sur (C'!J48+'Fiesta Americana Viaducto Ae'!J48 | G9: =G8+E9 | H9: =H8+F9
A10: 7 | B10: ='Médano - Cabo San Lucas (Pos'!B49+'Fairfield Inn Vallejo (F-159'!B49+'Fiesta Americana Condesa Can'!B49+'Fiesta Inn Periférico Sur (C'!B49+'Fiesta Americana Viaducto Ae'!B49 | C10: =('Médano - Cabo San Lucas (Pos'!C49+'Médano - Cabo San Lucas (Pos'!D49+'Médano - Cabo San Lucas (Pos'!E49)+('Fairfield Inn Vallejo (F-159'!C49+'Fairfield Inn Vallejo (F-159'!D49+'Fairfield Inn Vallejo (F-159'!E49)+('Fiesta Americana Condesa Can'!C49+'Fiesta Americana Condesa Can'!D49+'Fiesta Americana Condesa Can'!E49)+('Fiesta Inn Periférico Sur (C'!C49+'Fiesta Inn Periférico Sur (C'!D49+'Fiesta Inn Periférico Sur (C'!E49)+('Fiesta Americana Viaducto Ae'!C49+'Fiesta Americana Viaducto Ae'!D49+'Fiesta Americana Viaducto Ae'!E49) | D10: =B10-C10 | E10: ='Médano - Cabo San Lucas (Pos'!G49+'Fairfield Inn Vallejo (F-159'!G49+'Fiesta Americana Condesa Can'!G49+'Fiesta Inn Periférico Sur (C'!G49+'Fiesta Americana Viaducto Ae'!G49 | F10: ='Médano - Cabo San Lucas (Pos'!J49+'Fairfield Inn Vallejo (F-159'!J49+'Fiesta Americana Condesa Can'!J49+'Fiesta Inn Periférico Sur (C'!J49+'Fiesta Americana Viaducto Ae'!J49 | G10: =G9+E10 | H10: =H9+F10
A11: 8 | B11: ='Médano - Cabo San Lucas (Pos'!B50+'Fairfield Inn Vallejo (F-159'!B50+'Fiesta Americana Condesa Can'!B50+'Fiesta Inn Periférico Sur (C'!B50+'Fiesta Americana Viaducto Ae'!B50 | C11: =('Médano - Cabo San Lucas (Pos'!C50+'Médano - Cabo San Lucas (Pos'!D50+'Médano - Cabo San Lucas (Pos'!E50)+('Fairfield Inn Vallejo (F-159'!C50+'Fairfield Inn Vallejo (F-159'!D50+'Fairfield Inn Vallejo (F-159'!E50)+('Fiesta Americana Condesa Can'!C50+'Fiesta Americana Condesa Can'!D50+'Fiesta Americana Condesa Can'!E50)+('Fiesta Inn Periférico Sur (C'!C50+'Fiesta Inn Periférico Sur (C'!D50+'Fiesta Inn Periférico Sur (C'!E50)+('Fiesta Americana Viaducto Ae'!C50+'Fiesta Americana Viaducto Ae'!D50+'Fiesta Americana Viaducto Ae'!E50) | D11: =B11-C11 | E11: ='Médano - Cabo San Lucas (Pos'!G50+'Fairfield Inn Vallejo (F-159'!G50+'Fiesta Americana Condesa Can'!G50+'Fiesta Inn Periférico Sur (C'!G50+'Fiesta Americana Viaducto Ae'!G50 | F11: ='Médano - Cabo San Lucas (Pos'!J50+'Fairfield Inn Vallejo (F-159'!J50+'Fiesta Americana Condesa Can'!J50+'Fiesta Inn Periférico Sur (C'!J50+'Fiesta Americana Viaducto Ae'!J50 | G11: =G10+E11 | H11: =H10+F11
A12: 9 | B12: ='Médano - Cabo San Lucas (Pos'!B51+'Fairfield Inn Vallejo (F-159'!B51+'Fiesta Americana Condesa Can'!B51+'Fiesta Inn Periférico Sur (C'!B51+'Fiesta Americana Viaducto Ae'!B51 | C12: =('Médano - Cabo San Lucas (Pos'!C51+'Médano - Cabo San Lucas (Pos'!D51+'Médano - Cabo San Lucas (Pos'!E51)+('Fairfield Inn Vallejo (F-159'!C51+'Fairfield Inn Vallejo (F-159'!D51+'Fairfield Inn Vallejo (F-159'!E51)+('Fiesta Americana Condesa Can'!C51+'Fiesta Americana Condesa Can'!D51+'Fiesta Americana Condesa Can'!E51)+('Fiesta Inn Periférico Sur (C'!C51+'Fiesta Inn Periférico Sur (C'!D51+'Fiesta Inn Periférico Sur (C'!E51)+('Fiesta Americana Viaducto Ae'!C51+'Fiesta Americana Viaducto Ae'!D51+'Fiesta Americana Viaducto Ae'!E51) | D12: =B12-C12 | E12: ='Médano - Cabo San Lucas (Pos'!G51+'Fairfield Inn Vallejo (F-159'!G51+'Fiesta Americana Condesa Can'!G51+'Fiesta Inn Periférico Sur (C'!G51+'Fiesta Americana Viaducto Ae'!G51 | F12: ='Médano - Cabo San Lucas (Pos'!J51+'Fairfield Inn Vallejo (F-159'!J51+'Fiesta Americana Condesa Can'!J51+'Fiesta Inn Periférico Sur (C'!J51+'Fiesta Americana Viaducto Ae'!J51 | G12: =G11+E12 | H12: =H11+F12
A13: 10 | B13: ='Médano - Cabo San Lucas (Pos'!B52+'Fairfield Inn Vallejo (F-159'!B52+'Fiesta Americana Condesa Can'!B52+'Fiesta Inn Periférico Sur (C'!B52+'Fiesta Americana Viaducto Ae'!B52 | C13: =('Médano - Cabo San Lucas (Pos'!C52+'Médano - Cabo San Lucas (Pos'!D52+'Médano - Cabo San Lucas (Pos'!E52)+('Fairfield Inn Vallejo (F-159'!C52+'Fairfield Inn Vallejo (F-159'!D52+'Fairfield Inn Vallejo (F-159'!E52)+('Fiesta Americana Condesa Can'!C52+'Fiesta Americana Condesa Can'!D52+'Fiesta Americana Condesa Can'!E52)+('Fiesta Inn Periférico Sur (C'!C52+'Fiesta Inn Periférico Sur (C'!D52+'Fiesta Inn Periférico Sur (C'!E52)+('Fiesta Americana Viaducto Ae'!C52+'Fiesta Americana Viaducto Ae'!D52+'Fiesta Americana Viaducto Ae'!E52) | D13: =B13-C13 | E13: ='Médano - Cabo San Lucas (Pos'!G52+'Fairfield Inn Vallejo (F-159'!G52+'Fiesta Americana Condesa Can'!G52+'Fiesta Inn Periférico Sur (C'!G52+'Fiesta Americana Viaducto Ae'!G52 | F13: ='Médano - Cabo San Lucas (Pos'!J52+'Fairfield Inn Vallejo (F-159'!J52+'Fiesta Americana Condesa Can'!J52+'Fiesta Inn Periférico Sur (C'!J52+'Fiesta Americana Viaducto Ae'!J52 | G13: =G12+E13 | H13: =H12+F13
A14: 11 | B14: ='Médano - Cabo San Lucas (Pos'!B53+'Fairfield Inn Vallejo (F-159'!B53+'Fiesta Americana Condesa Can'!B53+'Fiesta Inn Periférico Sur (C'!B53+'Fiesta Americana Viaducto Ae'!B53 | C14: =('Médano - Cabo San Lucas (Pos'!C53+'Médano - Cabo San Lucas (Pos'!D53+'Médano - Cabo San Lucas (Pos'!E53)+('Fairfield Inn Vallejo (F-159'!C53+'Fairfield Inn Vallejo (F-159'!D53+'Fairfield Inn Vallejo (F-159'!E53)+('Fiesta Americana Condesa Can'!C53+'Fiesta Americana Condesa Can'!D53+'Fiesta Americana Condesa Can'!E53)+('Fiesta Inn Periférico Sur (C'!C53+'Fiesta Inn Periférico Sur (C'!D53+'Fiesta Inn Periférico Sur (C'!E53)+('Fiesta Americana Viaducto Ae'!C53+'Fiesta Americana Viaducto Ae'!D53+'Fiesta Americana Viaducto Ae'!E53) | D14: =B14-C14 | E14: ='Médano - Cabo San Lucas (Pos'!G53+'Fairfield Inn Vallejo (F-159'!G53+'Fiesta Americana Condesa Can'!G53+'Fiesta Inn Periférico Sur (C'!G53+'Fiesta Americana Viaducto Ae'!G53 | F14: ='Médano - Cabo San Lucas (Pos'!J53+'Fairfield Inn Vallejo (F-159'!J53+'Fiesta Americana Condesa Can'!J53+'Fiesta Inn Periférico Sur (C'!J53+'Fiesta Americana Viaducto Ae'!J53 | G14: =G13+E14 | H14: =H13+F14
A15: 12 | B15: ='Médano - Cabo San Lucas (Pos'!B54+'Fairfield Inn Vallejo (F-159'!B54+'Fiesta Americana Condesa Can'!B54+'Fiesta Inn Periférico Sur (C'!B54+'Fiesta Americana Viaducto Ae'!B54 | C15: =('Médano - Cabo San Lucas (Pos'!C54+'Médano - Cabo San Lucas (Pos'!D54+'Médano - Cabo San Lucas (Pos'!E54)+('Fairfield Inn Vallejo (F-159'!C54+'Fairfield Inn Vallejo (F-159'!D54+'Fairfield Inn Vallejo (F-159'!E54)+('Fiesta Americana Condesa Can'!C54+'Fiesta Americana Condesa Can'!D54+'Fiesta Americana Condesa Can'!E54)+('Fiesta Inn Periférico Sur (C'!C54+'Fiesta Inn Periférico Sur (C'!D54+'Fiesta Inn Periférico Sur (C'!E54)+('Fiesta Americana Viaducto Ae'!C54+'Fiesta Americana Viaducto Ae'!D54+'Fiesta Americana Viaducto Ae'!E54) | D15: =B15-C15 | E15: ='Médano - Cabo San Lucas (Pos'!G54+'Fairfield Inn Vallejo (F-159'!G54+'Fiesta Americana Condesa Can'!G54+'Fiesta Inn Periférico Sur (C'!G54+'Fiesta Americana Viaducto Ae'!G54 | F15: ='Médano - Cabo San Lucas (Pos'!J54+'Fairfield Inn Vallejo (F-159'!J54+'Fiesta Americana Condesa Can'!J54+'Fiesta Inn Periférico Sur (C'!J54+'Fiesta Americana Viaducto Ae'!J54 | G15: =G14+E15 | H15: =H14+F15
