Workbook

Sheet Resumen
A1: GEPP — PROPUESTA PROPLASA (3 SITIOS: Preforma 1, Preforma 2, Tapa) | MXN sin IVA | jul-2026
A3: Sitio | B3: Opción / Esquema | C3: PV (kWp) | D3: BESS (kW) | E3: BESS (kWh) | F3: Gen (kWh/año) | G3: Gasto real hoy ($/año) | H3: Beneficio autoab. ($/año, →2032) | I3: Ahorro bruto ($) | J3: Pago PPA ($) | K3: Pago partic. ($) | L3: AHORRO NETO GEPP ($) | M3: % bruto | N3: % neto | O3: PPA (MXN/kWh) | P3: TIR PV | Q3: TIR BESS @50%
A4: Proplasa · Preforma 1 | B4: Op1: Autoconsumo | C4: ='Preforma 1'!C26 -> 681.2 | D4: ='Preforma 1'!C28 -> 2080 | E4: ='Preforma 1'!C29 -> 4159 | F4: ='Preforma 1'!C41 -> 1130906.4 | G4: ='Preforma 1'!N19 -> 32178329 | H4: ='Preforma 1'!C38 -> 7886060.9 | I4: ='Preforma 1'!C45 -> 8780166.5 | J4: ='Preforma 1'!C46 -> 1249199.3 | K4: ='Preforma 1'!C47 -> 3367873.7 | L4: ='Preforma 1'!C48 -> 4163093.5 | M4: ='Preforma 1'!C49 -> 0.27285961 | N4: ='Preforma 1'!C50 -> 0.12937569 | O4: ='Preforma 1'!C31 -> 1.1046 | P4: ='Preforma 1'!C51 -> 0.14109903 | Q4: ='Preforma 1'!C52 -> 0.13491917
B5: Op2: GD Medición Neta | C5: ='Preforma 1'!D26 -> 839.45 | D5: ='Preforma 1'!D28 -> 2080 | E5: ='Preforma 1'!D29 -> 4159 | F5: ='Preforma 1'!D41 -> 1393628 | G5: ='Preforma 1'!N19 -> 32178329 | H5: ='Preforma 1'!C38 -> 7886060.9 | I5: ='Preforma 1'!D45 -> 9255107.2 | J5: ='Preforma 1'!D46 -> 1539401.5 | K5: ='Preforma 1'!D47 -> 3367873.7 | L5: ='Preforma 1'!D48 -> 4347832 | M5: ='Preforma 1'!D49 -> 0.28761926 | N5: ='Preforma 1'!D50 -> 0.13511677 | O5: ='Preforma 1'!D31 -> 1.1046 | P5: ='Preforma 1'!D51 -> 0.14109903 | Q5: ='Preforma 1'!D52 -> 0.13491917
A6: Proplasa · Preforma 2 | B6: Op1: Autoconsumo | C6: ='Preforma 2'!C26 -> 1912 | D6: ='Preforma 2'!C28 -> 5837 | E6: ='Preforma 2'!C29 -> 11674 | F6: ='Preforma 2'!C41 -> 3174241.2 | G6: ='Preforma 2'!N19 -> 1.0213677e+08 | H6: ='Preforma 2'!C38 -> 27268065 | I6: ='Preforma 2'!C45 -> 24644122 | J6: ='Preforma 2'!C46 -> 3506266.8 | K6: ='Preforma 2'!C47 -> 9452911.4 | L6: ='Preforma 2'!C48 -> 11684944 | M6: ='Preforma 2'!C49 -> 0.2412855 | N6: ='Preforma 2'!C50 -> 0.11440487 | O6: ='Preforma 2'!C31 -> 1.1046 | P6: ='Preforma 2'!C51 -> 0.14109903 | Q6: ='Preforma 2'!C52 -> 0.13490802
B7: Op2: GD Medición Neta | C7: ='Preforma 2'!D26 -> 839.45 | D7: ='Preforma 2'!D28 -> 5837 | E7: ='Preforma 2'!D29 -> 11674 | F7: ='Preforma 2'!D41 -> 1393628 | G7: ='Preforma 2'!N19 -> 1.0213677e+08 | H7: ='Preforma 2'!C38 -> 27268065 | I7: ='Preforma 2'!D45 -> 21425183 | J7: ='Preforma 2'!D46 -> 1539401.5 | K7: ='Preforma 2'!D47 -> 9452911.4 | L7: ='Preforma 2'!D48 -> 10432870 | M7: ='Preforma 2'!D49 -> 0.20976954 | N7: ='Preforma 2'!D50 -> 0.10214607 | O7: ='Preforma 2'!D31 -> 1.1046 | P7: ='Preforma 2'!D51 -> 0.14109903 | Q7: ='Preforma 2'!D52 -> 0.13490802
A8: Proplasa · Tapa | B8: Op1: Autoconsumo | C8: =Tapa!C26 -> 1255.7 | D8: =Tapa!C28 -> 3870 | E8: =Tapa!C29 -> 7741 | F8: =Tapa!C41 -> 2084673 | G8: =Tapa!N19 -> 63523603 | H8: =Tapa!C38 -> 22509980 | I8: =Tapa!C45 -> 16298623 | J8: =Tapa!C46 -> 2302729.7 | K8: =Tapa!C47 -> 6265006.5 | L8: =Tapa!C48 -> 7730886.6 | M8: =Tapa!C49 -> 0.25657586 | N8: =Tapa!C50 -> 0.12170101 | O8: =Tapa!C31 -> 1.1046 | P8: =Tapa!C51 -> 0.14109903 | Q8: =Tapa!C52 -> 0.13479034
B9: Op2: GD Medición Neta | C9: =Tapa!D26 -> 839.45 | D9: =Tapa!D28 -> 3870 | E9: =Tapa!D29 -> 7741 | F9: =Tapa!D41 -> 1393628 | G9: =Tapa!N19 -> 63523603 | H9: =Tapa!C38 -> 22509980 | I9: =Tapa!D45 -> 15049373 | J9: =Tapa!D46 -> 1539401.5 | K9: =Tapa!D47 -> 6265006.5 | L9: =Tapa!D48 -> 7244964.9 | M9: =Tapa!D49 -> 0.23690994 | N9: =Tapa!D50 -> 0.11405154 | O9: =Tapa!D31 -> 1.1046 | P9: =Tapa!D51 -> 0.14109903 | Q9: =Tapa!D52 -> 0.13479034
A11: PORTAFOLIO | B11: Suma Opción 1 | C11: =C4+C6+C8 -> 3848.9 | D11: =D4+D6+D8 -> 11787 | E11: =E4+E6+E8 -> 23574 | F11: =F4+F6+F8 -> 6389820.6 | G11: =G4+G6+G8 -> 1.978387e+08 | H11: =H4+H6+H8 -> 57664106 | I11: =I4+I6+I8 -> 49722911 | J11: =J4+J6+J8 -> 7058195.9 | ... L11: =L4+L6+L8 -> 23578924
B12: Suma Opción 2 | C12: =C5+C7+C9 -> 2518.35 | D12: =D5+D7+D9 -> 11787 | E12: =E5+E7+E9 -> 23574 | F12: =F5+F7+F9 -> 4180884.1 | G12: =G5+G7+G9 -> 1.978387e+08 | H12: =H5+H7+H9 -> 57664106 | I12: =I5+I7+I9 -> 45729663 | J12: =J5+J7+J9 -> 4618204.6 | ... L12: =L5+L7+L9 -> 22025667
A14: Nota: "Gasto real hoy" ya refleja el descuento de autoabasto; el "Beneficio autoab." (naranja) se pierde en 2032 → el gasto real del cliente salta en 2033 (ver proyección 20 años de cada sitio). Nuestro ahorro $ es el hedge.

Sheet Supuestos
A1: SUPUESTOS DEL MODELO — editar celdas amarillas (todo sin IVA)
A4: Tipo de cambio (MXN/USD) | B4: 17.55 | C4: MXN/USD
A5: Precio de venta PV (USD/Wp) | B5: 0.65 | C5: USD/Wp
A6: Costo duro PV — informativo (USD/Wp) | B6: 0.5 | C6: USD/Wp
A7: Precio BESS instalado (USD/Wh) | B7: 0.28 | C7: USD/Wh
A8: Costo FOB BESS — informativo (USD/Wh) | B8: 0.18 | C8: USD/Wh
A9: Escalación tarifas CFE (anual) | B9: 0.04 | C9: %
A10: Escalación precio PPA (anual) | B10: 0.04 | C10: %
A11: Degradación PV (anual) | B11: 0.005 | C11: %
A12: Degradación BESS (anual) | B12: 0.0125 | C12: %
A13: Profundidad de descarga BESS (DoD) | B13: 0.96
A14: Eficiencia round-trip BESS (RTE) | B14: 0.96
A15: Factor de carga p/ umbral de demanda | B15: 0.57
A16: Meses sin ahorro BESS al año (merma de riesgo) | B16: 2 | C16: meses
A17: Participación del inversionista en ahorro BESS | B17: 0.5 | C17: %
A18: Plazo PPA / venta de energía PV (años) | B18: 15 | C18: años
A19: Plazo BESS / participación en ahorro (años) | B19: 15 | C19: años
A20: Horizonte de análisis (años) | B20: 20 | C20: años
A21: Tasa de descuento / WACC | B21: 0.12 | C21: %
A22: O&M PV (MXN/kWp·año) | B22: 310 | C22: MXN/kWp
A23: O&M BESS (MXN/kWh·año) | B23: 180 | C23: MXN/kWh
A24: Densidad de instalación (m²/kWp) | B24: 4 | C24: m²/kWp
A25: Año base del modelo (Año 1) | B25: 2026 | C25: año
A26: Año de término autoabasto TALA / ENEL | B26: 2032 | C26: año
A29: SITIOS — recurso solar y superficie
A30: Sitio | B30: Municipio | C30: Tarifa | D30: Yield (kWh/kWp·año) | E30: Superficie disp. (m²)
A31: Proplasa · Preforma 1 | B31: Cuautitlán Izcalli, Méx. | C31: GDMTH (V. de México Norte) | D31: 1660 | E31: —
A32: Proplasa · Preforma 2 | B32: Cuautitlán Izcalli, Méx. | C32: GDMTH (V. de México Norte) | D32: 1660 | E32: —
A33: Proplasa · Tapa | B33: Cuautitlán Izcalli, Méx. | C33: GDMTH (V. de México Norte) | D33: 1660 | E33: —
A36: SUPUESTOS Y NOTAS CLAVE
A37: • Baseline: últimos 12 meses reales may-25 → abr-26 (recibos CFE, sin IVA).
A38: • Autoabasto TALA (Ixtlahuacán, zafra) y ENEL (Proplasa) vencen 2032. Su beneficio actual se
A39: cuantifica por sitio (fila "Beneficio autoabasto") y aparece en la proyección 20 años como la
A40: brecha entre "Gasto CFE pleno" y "Gasto real"; esa brecha se cierra en 2033 → el gasto real del
A41: cliente DA UN SALTO. El ahorro $ de nuestro sistema (PPA fijo) no cambia, por lo que cubre un %
A42: menor de un recibo mayor, pero es justo el hedge que amortigua ese salto. Editar beneficio y año.
A43: • Plazo PPA y plazo BESS ahora son independientes (celdas B18/B19). Ej.: 12 años PPA + 20 de
A44: participación en ahorro BESS. Tras el plazo PPA el ahorro PV queda 100% para GEPP (pago=0).
A45: • TIR nominal MXN, pre-IVA, sin apalancamiento, sobre precio de venta. PPA resuelto p/ TIR PV ~14%.
A46: • Marco legal: Ley del Sector Eléctrico (DOF 18-mar-2025). GD Exento <0.7 MW sin permiso (Art. 30).
A47: • Módulo Tongwei TWMNF-66HD715 (715 Wp, η 23.0%). Densidad 4.0 m²/kWp.
A48: • Ahorros de demanda calibrados con simulación horaria al tamaño de diseño; escalan linealmente.

Sheet Preforma 1
A1: GEPP Proplasa · Preforma 1 — Propuesta Solar + BESS | GDMTH (V. de México Norte) | Cuautitlán Izcalli, Méx. (MXN sin IVA)
A3: 1. DATOS BASE — últimos 12 meses reales (recibos CFE, sin IVA)
A4: Mes | B4: may-25 | C4: jun-25 | D4: jul-25 | E4: ago-25 | F4: sep-25 | G4: oct-25 | H4: nov-25 | I4: dic-25 | J4: ene-26 | K4: feb-26 | L4: mar-26 | M4: abr-26 | N4: TOTAL
A5: Consumo Base (kWh) | B5: 546627 | C5: 467527 | D5: 414209 | E5: 511027 | F5: 471225 | G5: 435183 | H5: 431457 | I5: 395911 | J5: 455237 | K5: 476589 | L5: 535513 | M5: 497333 | N5: =SUM(B5:M5) -> 5637838
A6: Consumo Intermedia (kWh) | B6: 924218 | C6: 810870 | D6: 746631 | E6: 868483 | F6: 799977 | G6: 788394 | H6: 617240 | I6: 618556 | J6: 729971 | K6: 681958 | L6: 750251 | M6: 867045 | N6: =SUM(B6:M6) -> 9203594
A7: Consumo Punta (kWh) | B7: 89553 | C7: 82141 | D7: 74300 | E7: 84864 | F7: 80458 | G7: 98384 | H7: 150654 | I7: 146212 | J7: 183178 | K7: 167798 | L7: 182294 | M7: 108027 | N7: =SUM(B7:M7) -> 1447863
A8: Consumo Total (kWh) | B8: =SUM(B5:B7) -> 1560398 | C8: =SUM(C5:C7) -> 1360538 | D8: =SUM(D5:D7) -> 1235140 | E8: =SUM(E5:E7) -> 1464374 | F8: =SUM(F5:F7) -> 1351660 | G8: =SUM(G5:G7) -> 1321961 | H8: =SUM(H5:H7) -> 1199351 | I8: =SUM(I5:I7) -> 1160679 | ... M8: =SUM(M5:M7) -> 1472405 | N8: =SUM(B8:M8) -> 16289295
A9: Dem. máx. en punta (kW) | B9: 1654 | C9: 1465 | D9: 1582 | E9: 1515 | F9: 2279 | G9: 1750 | H9: 2026 | I9: 2124 | J9: 1892 | K9: 1903 | L9: 1771 | M9: 1579 | N9: =MAX(B9:M9) -> 2279
A10: Dem. máx. mensual (kW) | B10: 1700 | C10: 1532 | D10: 1672 | E10: 1568 | F10: 2356 | G10: 1832 | H10: 2026 | I10: 2124 | J10: 1930 | K10: 1936 | L10: 1793 | M10: 1622 | N10: =MAX(B10:M10) -> 2356
A11: Días con punta | B11: 22 | C11: 21 | D11: 23 | E11: 21 | F11: 22 | G11: 23 | H11: 25 | I11: 27 | J11: 27 | K11: 24 | L11: 26 | M11: 23
A12: Horas punta/día | B12: 2 | C12: 2 | D12: 2 | E12: 2 | F12: 2 | G12: 2.43 | H12: 3.6 | I12: 3.7 | J12: 3.63 | K12: 3.67 | L12: 3.69 | M12: 2.26
A13: Días del mes | B13: 31 | C13: 30 | D13: 31 | E13: 31 | F13: 30 | G13: 31 | H13: 30 | I13: 31 | J13: 31 | K13: 28 | L13: 31 | M13: 30
A14: Tarifa Base ($/kWh) | B14: 1.1749 | C14: 1.1983 | D14: 1.2133 | E14: 1.2147 | F14: 1.2095 | G14: 1.2095 | H14: 1.1791 | I14: 1.1301 | J14: 1.106 | K14: 1.1065 | L14: 1.1071 | M14: 1.107
A15: Tarifa Intermedia ($/kWh) | B15: 1.9422 | C15: 1.9837 | D15: 2.0106 | E15: 2.0131 | F15: 2.0005 | G15: 2.0006 | H15: 1.9464 | I15: 1.859 | J15: 1.8185 | K15: 1.8194 | L15: 1.8204 | M15: 1.8204
A16: Tarifa Punta ($/kWh) | B16: 2.273 | C16: 2.3224 | D16: 2.3544 | E16: 2.3574 | F16: 2.3417 | G16: 2.3417 | H16: 2.2773 | I16: 2.1734 | J16: 2.1258 | K16: 2.1269 | L16: 2.1281 | M16: 2.128
A17: Tarifa Capacidad ($/kW·mes) | B17: 432.62 | C17: 442.9 | D17: 449.54 | E17: 450.17 | F17: 446.05 | G17: 446.05 | H17: 432.66 | I17: 411.03 | J17: 401.78 | K17: 402.01 | L17: 402.26 | M17: 402.24
A18: Tarifa Distribución ($/kW·mes) | B18: 91.12 | C18: 91.12 | D18: 91.12 | E18: 91.12 | F18: 91.12 | G18: 91.12 | H18: 91.12 | I18: 91.12 | J18: 86.15 | K18: 86.15 | L18: 86.15 | M18: 86.15
A19: Gasto actual facturado ($ MXN) | B19: 3302499.8 | C19: 2709232.8 | D19: 2381024.9 | E19: 2985577.8 | F19: 2695900.3 | G19: 2651342.2 | H19: 2280746.1 | I19: 2132953.9 | J19: 2570565.3 | K19: 2521062.4 | L19: 2806680.9 | M19: 3140742.8 | N19: =SUM(B19:M19) -> 32178329
A20: Umbral de demanda (kW) | B20: =B8/(24*B13*Supuestos!$B$15) -> 3679.4897 | C20: =C8/(24*C13*Supuestos!$B$15) -> 3315.1511 | D20: =D8/(24*D13*Supuestos!$B$15) -> 2912.5165 | E20: =E8/(24*E13*Supuestos!$B$15) -> 3453.0607 | F20: =F8/(24*F13*Supuestos!$B$15) -> 3293.5185 | G20: =G8/(24*G13*Supuestos!$B$15) -> 3117.2444 | H20: =H8/(24*H13*Supuestos!$B$15) -> 2922.3952 | I20: =I8/(24*I13*Supuestos!$B$15) -> 2736.9341 | ... M20: =M8/(24*M13*Supuestos!$B$15) -> 3587.7315
A21: Yield PV (kWh/kWp) | B21: 143.096 | C21: 133.92 | D21: 135.16 | E21: 126.48 | F21: 119.52 | G21: 131.688 | H21: 136.56 | I21: 130.944 | J21: 142.848 | K21: 139.104 | L21: 170.128 | M21: 150.72 | N21: =SUM(B21:M21) -> 1660.168
A23: 2. SISTEMA PROPUESTO — Opción 1 y Opción 2 (amarillo = editable)
A24: Concepto | C24: OPCIÓN 1 — Autoconsumo | D24: OPCIÓN 2 — GD Medición Neta
A25: Esquema legal | C25: Autoconsumo interconectado (permiso CNE simplificado) | D25: Generación Distribuida <0.7 MW (sin permiso)
A26: Potencia PV (kWp DC) | C26: 681.2 | D26: 839.45
A27: Superficie requerida (m²) | C27: =C26*Supuestos!$B$24 -> 2724.8 | D27: =D26*Supuestos!$B$24 -> 3357.8
A28: BESS potencia (kW) | C28: 2080 | D28: 2080
A29: BESS capacidad (kWh) | C29: 4159 | D29: 4159
A30: Energía útil BESS (kWh) | C30: =C29*Supuestos!$B$13*SQRT(Supuestos!$B$14) -> 3911.9723 | D30: =D29*Supuestos!$B$13*SQRT(Supuestos!$B$14) -> 3911.9723
A31: Precio PPA (MXN/kWh, año 1) | C31: 1.3526645 | D31: 1.6148562
A32: Participación inversionista BESS (%) | C32: =Supuestos!$B$17 -> 0.5 | D32: =Supuestos!$B$17 -> 0.5
A33: CAPEX PV (USD) | C33: =C26*1000*Supuestos!$B$5 -> 442780 | D33: =D26*1000*Supuestos!$B$5 -> 545642.5
A34: CAPEX PV (MXN) | C34: =C33*Supuestos!$B$4 -> 7770789 | D34: =D33*Supuestos!$B$4 -> 9576025.9
A35: CAPEX BESS (USD) | C35: =C29*1000*Supuestos!$B$7 -> 1164520 | D35: =D29*1000*Supuestos!$B$7 -> 1164520
A36: CAPEX BESS (MXN) | C36: =C35*Supuestos!$B$4 -> 20437326 | D36: =D35*Supuestos!$B$4 -> 20437326
A37: — Autoabasto TALA / ENEL (vence 2032) —
A38: Beneficio autoabasto actual ($/año) | C38: 7886060.9 | D38: =C38 -> 7886060.9
A39: Gasto sin autoabasto — CFE pleno ($/año) | C39: =$N$19+C38 -> 40064390 | D39: =$N$19+D38 -> 40064390
A40: Gasto real hoy (con autoabasto) ($/año) | C40: =C39-C38 -> 32178329 | D40: =D39-D38 -> 32178329
A41: Generación PV año 1 (kWh) | C41: =C72 -> 1130906.4 | D41: =C89 -> 1393628
A42: Energía facturada al PPA (kWh) | C42: =K72 -> 1130906.4 | D42: =K89 -> 1393628
A43: Ahorro bruto PV año 1 ($) | C43: =M72 -> 2044419.1 | D43: =M89 -> 2519359.8
A44: Ahorro bruto BESS año 1 c/merma ($) | C44: =R72*(12-Supuestos!$B$16)/12 -> 6735747.4 | D44: =R89*(12-Supuestos!$B$16)/12 -> 6735747.4
A45: Ahorro bruto total ($) | C45: =C43+C44 -> 8780166.5 | D45: =D43+D44 -> 9255107.2
A46: Pago PPA año 1 ($) | C46: =C42*C31 -> 1249199.3 | D46: =D42*D31 -> 1539401.5
A47: Pago participación BESS ($) | C47: =C44*C32 -> 3367873.7 | D47: =D44*D32 -> 3367873.7
A48: AHORRO NETO GEPP año 1 ($) | C48: =C45-C46-C47 -> 4163093.5 | D48: =D45-D46-D47 -> 4347832
A49: % ahorro bruto (vs gasto real hoy) | C49: =C45/$N$19 -> 0.27285961 | D49: =D45/$N$19 -> 0.28761926
A50: % ahorro neto (vs gasto real hoy) | C50: =C48/$N$19 -> 0.12937569 | D50: =D48/$N$19 -> 0.13511677
A51: TIR inversionista PV | C51: =IRR(M94:M114) -> 0.14109903 | D51: =IRR(M119:M139) -> 0.14109903
A52: TIR inversionista BESS | C52: =IRR(N94:N114) -> 0.13491917 | D52: =IRR(N119:N139) -> 0.13491917
A53: Participación req. p/ TIR BESS 16% | C53: 0.5655 | D53: 0.5655
A54: Payback simple inversionista PV (años) | C54: =COUNTIF(O94:O114,"<0") -> 7 | D54: =COUNTIF(O119:O139,"<0") -> 7
A55: VAN GEPP del ahorro neto 20a (@WACC) | C55: =NPV(Supuestos!$B$21,J95:J114) -> 50014372 | D55: =NPV(Supuestos!$B$21,J120:J139) -> 52602249
A58: 3. MODELO MENSUAL AÑO 1 — OPCIÓN 1 — Autoconsumo (vertical)
B59: Mes | C59: Gen PV (kWh) | D59: %Base | E59: %Int | F59: %Punta | G59: PV→Base | H59: PV→Int | I59: PV→Punta | J59: Ahorro energía PV $ | K59: Energía PPA (kWh) | L59: Ahorro distrib/umbral $ (motor) | M59: Ahorro PV total $ | N59: BESS despl. punta kWh | O59: Costo carga base $ | P59: Ahorro arbitraje $ | Q59: Ahorro capacidad $ (motor) | R59: Ahorro BESS bruto $ | S59: Reducción dem. punta (kW) | T59: Dem. punta después (kW)
B60: may-25 | C60: =$C$26*B$21 -> 97476.995 | D60: 0.12903214 | E60: 0.87096786 | F60: 0 | G60: =C60*D60 -> 12577.665 | H60: =C60*E60 -> 84899.33 | I60: =C60*F60 -> 0 | J60: =G60*B$14+H60*B$15+I60*B$16 -> 179668.98 | K60: =G60+H60+I60 -> 97476.995 | L60: 0 | M60: =J60+L60*$C$26/681.2 -> 179668.98 | N60: =MIN($C$30*B$11,$C$28*B$12*B$11,B$7) -> 86063.39 | O60: =N60/Supuestos!$B$14*B$14 -> 105329.04 | P60: =N60*B$16-O60 -> 90293.047 | Q60: =846206.697484428*MIN(1,$C$30/3911.97229065033) -> 846206.7 | R60: =P60+Q60 -> 936499.74 | S60: =Q60/B$17 -> 1956.0046 | T60: =B$9-S60 -> -302.00457
B61: jun-25 | C61: =$C$26*C$21 -> 91226.304 | D61: 0.1666657 | E61: 0.83333236 | F61: 0 | G61: =C61*D61 -> 15204.296 | H61: =C61*E61 -> 76021.832 | I61: =C61*F61 -> 0 | J61: =G61*C$14+H61*C$15+I61*C$16 -> 169023.81 | K61: =G61+H61+I61 -> 91226.127 | L61: 0 | M61: =J61+L61*$C$26/681.2 -> 169023.81 | N61: =MIN($C$30*C$11,$C$28*C$12*C$11,C$7) -> 82141 | O61: =N61/Supuestos!$B$14*C$14 -> 102530.79 | P61: =N61*C$16-O61 -> 88233.466 | Q61: =866314.36455085*MIN(1,$C$30/3911.97229065033) -> 866314.36 | R61: =P61+Q61 -> 954547.83 | S61: =Q61/C$17 -> 1956.0044 | T61: =C$9-S61 -> -491.00444
B62: jul-25 | C62: =$C$26*D$21 -> 92070.992 | D62: 0.12903269 | E62: 0.87096923 | F62: 0 | G62: =C62*D62 -> 11880.168 | H62: =C62*E62 -> 80191.001 | I62: =C62*F62 -> 0 | J62: =G62*D$14+H62*D$15+I62*D$16 -> 175646.23 | K62: =G62+H62+I62 -> 92071.169 | L62: 0 | M62: =J62+L62*$C$26/681.2 -> 175646.23 | N62: =MIN($C$30*D$11,$C$28*D$12*D$11,D$7) -> 74300 | O62: =N62/Supuestos!$B$14*D$14 -> 93904.365 | P62: =N62*D$16-O62 -> 81027.555 | Q62: =782888.179108982*MIN(1,$C$30/3911.97229065033) -> 782888.18 | R62: =P62+Q62 -> 863915.73 | S62: =Q62/D$17 -> 1741.5317 | T62: =D$9-S62 -> -159.53174
B63: ago-25 | C63: =$C$26*E$21 -> 86158.176 | D63: 0.16129118 | E63: 0.83870882 | F63: 0 | G63: =C63*D63 -> 13896.554 | H63: =C63*E63 -> 72261.622 | I63: =C63*F63 -> 0 | J63: =G63*E$14+H63*E$15+I63*E$16 -> 162350.02 | K63: =G63+H63+I63 -> 86158.176 | L63: 0 | M63: =J63+L63*$C$26/681.2 -> 162350.02 | N63: =MIN($C$30*E$11,$C$28*E$12*E$11,E$7) -> 82151.418 | O63: =N63/Supuestos!$B$14*E$14 -> 103947.22 | P63: =N63*E$16-O63 -> 89716.537 | Q63: =879944.946860273*MIN(1,$C$30/3911.97229065033) -> 879944.95 | R63: =P63+Q63 -> 969661.48 | S63: =Q63/E$17 -> 1954.6948 | T63: =E$9-S63 -> -439.69477
B64: sep-25 | C64: =$C$26*F$21 -> 81417.024 | D64: 0.13333304 | E64: 0.86666478 | F64: 0 | G64: =C64*D64 -> 10855.58 | H64: =C64*E64 -> 70561.267 | I64: =C64*F64 -> 0 | J64: =G64*F$14+H64*F$15+I64*F$16 -> 154287.64 | K64: =G64+H64+I64 -> 81416.847 | L64: 0 | M64: =J64+L64*$C$26/681.2 -> 154287.64 | N64: =MIN($C$30*F$11,$C$28*F$12*F$11,F$7) -> 80458 | O64: =N64/Supuestos!$B$14*F$14 -> 101368.7 | P64: =N64*F$16-O64 -> 87039.8 | Q64: =750604.023175983*MIN(1,$C$30/3911.97229065033) -> 750604.02 | R64: =P64+Q64 -> 837643.82 | S64: =Q64/F$17 -> 1682.78 | T64: =F$9-S64 -> 596.21999
B65: oct-25 | C65: =$C$26*G$21 -> 89705.866 | D65: 0.12852419 | E65: 0.86893267 | F65: 0.0025431387 | G65: =C65*D65 -> 11529.374 | H65: =C65*E65 -> 77948.357 | I65: =C65*F65 -> 228.13445 | J65: =G65*G$14+H65*G$15+I65*G$16 -> 170422.48 | K65: =G65+H65+I65 -> 89705.866 | L65: 0 | M65: =J65+L65*$C$26/681.2 -> 170422.48 | N65: =MIN($C$30*G$11,$C$28*G$12*G$11,G$7) -> 89975.363 | O65: =N65/Supuestos!$B$14*G$14 -> 113359.58 | P65: =N65*G$16-O65 -> 97335.722 | Q65: =436237.736219313*MIN(1,$C$30/3911.97229065033) -> 436237.74 | R65: =P65+Q65 -> 533573.46 | S65: =Q65/G$17 -> 978.00187 | T65: =G$9-S65 -> 771.99813
B66: nov-25 | C66: =$C$26*H$21 -> 93024.672 | D66: 0.16925416 | E66: 0.82023227 | F66: 0.010513579 | G66: =C66*D66 -> 15744.812 | H66: =C66*E66 -> 76301.837 | I66: =C66*F66 -> 978.0222 | J66: =G66*H$14+H66*H$15+I66*H$16 -> 169305.85 | K66: =G66+H66+I66 -> 93024.672 | L66: 0 | M66: =J66+L66*$C$26/681.2 -> 169305.85 | N66: =MIN($C$30*H$11,$C$28*H$12*H$11,H$7) -> 97799.307 | O66: =N66/Supuestos!$B$14*H$14 -> 120119.96 | P66: =N66*H$16-O66 -> 102598.4 | Q66: =423142.426841897*MIN(1,$C$30/3911.97229065033) -> 423142.43 | R66: =P66+Q66 -> 525740.83 | S66: =Q66/H$17 -> 978.00219 | T66: =H$9-S66 -> 1047.9978
B67: dic-25 | C67: =$C$26*I$21 -> 89199.053 | D67: 0.13103435 | E67: 0.85726503 | F67: 0.011700629 | G67: =C67*D67 -> 11688.14 | H67: =C67*E67 -> 76467.228 | I67: =C67*F67 -> 1043.685 | J67: =G67*I$14+H67*I$15+I67*I$16 -> 157629.69 | K67: =G67+H67+I67 -> 89199.053 | L67: 0 | M67: =J67+L67*$C$26/681.2 -> 157629.69 | N67: =MIN($C$30*I$11,$C$28*I$12*I$11,I$7) -> 105623.25 | O67: =N67/Supuestos!$B$14*I$14 -> 124338.37 | P67: =N67*I$16-O67 -> 105223.2 | Q67: =401988.207688244*MIN(1,$C$30/3911.97229065033) -> 401988.21 | R67: =P67+Q67 -> 507211.41 | S67: =Q67/I$17 -> 978.00211 | T67: =I$9-S67 -> 1145.9979
B68: ene-26 | C68: =$C$26*J$21 -> 97308.058 | D68: 0.13204428 | E68: 0.85676272 | F68: 0.011191179 | G68: =C68*D68 -> 12848.972 | H68: =C68*E68 -> 83369.917 | I68: =C68*F68 -> 1088.9919 | J68: =G68*J$14+H68*J$15+I68*J$16 -> 168134.14 | K68: =G68+H68+I68 -> 97307.881 | L68: 0 | M68: =J68+L68*$C$26/681.2 -> 168134.14 | N68: =MIN($C$30*J$11,$C$28*J$12*J$11,J$7) -> 105623.25 | O68: =N68/Supuestos!$B$14*J$14 -> 121686.79 | P68: =N68*J$16-O68 -> 102847.12 | Q68: =392941.671717752*MIN(1,$C$30/3911.97229065033) -> 392941.67 | R68: =P68+Q68 -> 495788.79 | S68: =Q68/J$17 -> 978.00207 | T68: =J$9-S68 -> 913.99793
B69: feb-26 | C69: =$C$26*K$21 -> 94757.645 | D69: 0.14507552 | E69: 0.84366181 | F69: 0.011264538 | G69: =C69*D69 -> 13747.015 | H69: =C69*E69 -> 79943.406 | I69: =C69*F69 -> 1067.4011 | J69: =G69*K$14+H69*K$15+I69*K$16 -> 162930.36 | K69: =G69+H69+I69 -> 94757.822 | L69: 0 | M69: =J69+L69*$C$26/681.2 -> 162930.36 | N69: =MIN($C$30*K$11,$C$28*K$12*K$11,K$7) -> 93887.335 | O69: =N69/Supuestos!$B$14*K$14 -> 108214.93 | P69: =N69*K$16-O69 -> 91474.039 | Q69: =393166.7897999*MIN(1,$C$30/3911.97229065033) -> 393166.79 | R69: =P69+Q69 -> 484640.83 | S69: =Q69/K$17 -> 978.00251 | T69: =K$9-S69 -> 924.99749
B70: mar-26 | C70: =$C$26*L$21 -> 115891.19 | D70: 0.16278409 | E70: 0.82602328 | F70: 0.011192628 | G70: =C70*D70 -> 18865.243 | H70: =C70*E70 -> 95728.824 | I70: =C70*F70 -> 1297.127 | J70: =G70*L$14+H70*L$15+I70*L$16 -> 197910.88 | K70: =G70+H70+I70 -> 115891.19 | L70: 0 | M70: =J70+L70*$C$26/681.2 -> 197910.88 | N70: =MIN($C$30*L$11,$C$28*L$12*L$11,L$7) -> 101711.28 | O70: =N70/Supuestos!$B$14*L$14 -> 117296.41 | P70: =N70*L$16-O70 -> 99155.36 | Q70: =393411.13818844*MIN(1,$C$30/3911.97229065033) -> 393411.14 | R70: =P70+Q70 -> 492566.5 | S70: =Q70/L$17 -> 978.00213 | T70: =L$9-S70 -> 792.99787
B71: abr-26 | C71: =$C$26*M$21 -> 102670.46 | D71: 0.13437717 | E71: 0.86404726 | F71: 0.0015772979 | G71: =C71*D71 -> 13796.566 | H71: =C71*E71 -> 88712.133 | I71: =C71*F71 -> 161.94191 | J71: =G71*M$14+H71*M$15+I71*M$16 -> 177108.98 | K71: =G71+H71+I71 -> 102670.64 | L71: 0 | M71: =J71+L71*$C$26/681.2 -> 177108.98 | N71: =MIN($C$30*M$11,$C$28*M$12*M$11,M$7) -> 89975.363 | O71: =N71/Supuestos!$B$14*M$14 -> 103752.84 | P71: =N71*M$16-O71 -> 87714.732 | Q71: =393391.73145722*MIN(1,$C$30/3911.97229065033) -> 393391.73 | R71: =P71+Q71 -> 481106.46 | S71: =Q71/M$17 -> 978.00251 | T71: =M$9-S71 -> 600.99749
B72: TOTAL | C72: =SUM(C60:C71) -> 1130906.4 | G72: =SUM(G60:G71) -> 162634.38 | H72: =SUM(H60:H71) -> 962406.75 | I72: =SUM(I60:I71) -> 5865.3037 | J72: =SUM(J60:J71) -> 2044419.1 | K72: =SUM(K60:K71) -> 1130906.4 | M72: =SUM(M60:M71) -> 2044419.1 | N72: =SUM(N60:N71) -> 1089709 | O72: =SUM(O60:O71) -> 1315849 | P72: =SUM(P60:P71) -> 1122659 | Q72: =SUM(Q60:Q71) -> 6960237.9 | R72: =SUM(R60:R71) -> 8082896.9 | S72: =AVERAGE(S60:S71) -> 1344.7526 | T72: =AVERAGE(T60:T71) -> 450.24742
A73: Q (Ahorro capacidad → flujo BESS) y L (Ahorro distrib/umbral → flujo PV) provienen de la simulación horaria al tamaño de diseño (memoria MC-GEPP-4SITIOS-2026-07 §4); escalan con MIN(1, E_útil/E_diseño). El rasurado que los sustenta se ilustra abajo (Despacho día típico, rasurado plano). Columnas S–T: demanda de punta facturable resultante mes a mes (Reducción = Q ÷ tarifa capacidad; Después = Dmáx punta − Reducción).
A75: 4. MODELO MENSUAL AÑO 1 — OPCIÓN 2 — GD Medición Neta (vertical)
B76: Mes | C76: Gen PV (kWh) | D76: %Base | E76: %Int | F76: %Punta | G76: PV→Base | H76: PV→Int | I76: PV→Punta | J76: Ahorro energía PV $ | K76: Energía PPA (kWh) | L76: Ahorro distrib/umbral $ (motor) | M76: Ahorro PV total $ | N76: BESS despl. punta kWh | O76: Costo carga base $ | P76: Ahorro arbitraje $ | Q76: Ahorro capacidad $ (motor) | R76: Ahorro BESS bruto $ | S76: Reducción dem. punta (kW) | T76: Dem. punta después (kW)
B77: may-25 | C77: =$D$26*B$21 -> 120121.94 | D77: 0.12903271 | E77: 0.87096729 | F77: 0 | G77: =C77*D77 -> 15499.659 | H77: =C77*E77 -> 104622.28 | I77: =C77*F77 -> 0 | J77: =G77*B$14+H77*B$15+I77*B$16 -> 221407.94 | K77: =G77+H77+I77 -> 120121.94 | L77: 0 | M77: =J77+L77*$D$26/839.45 -> 221407.94 | N77: =MIN($D$30*B$11,$D$28*B$12*B$11,B$7) -> 86063.39 | O77: =N77/Supuestos!$B$14*B$14 -> 105329.04 | P77: =N77*B$16-O77 -> 90293.047 | Q77: =846206.697484428*MIN(1,$D$30/3911.97229065033) -> 846206.7 | R77: =P77+Q77 -> 936499.74 | S77: =Q77/B$17 -> 1956.0046 | T77: =B$9-S77 -> -302.00457
B78: jun-25 | C78: =$D$26*C$21 -> 112419.14 | D78: 0.16666815 | E78: 0.83333482 | F78: 0 | G78: =C78*D78 -> 18736.691 | H78: =C78*E78 -> 93682.787 | I78: =C78*F78 -> 0 | J78: =G78*C$14+H78*C$15+I78*C$16 -> 208290.72 | K78: =G78+H78+I78 -> 112419.48 | L78: 0 | M78: =J78+L78*$D$26/839.45 -> 208290.72 | N78: =MIN($D$30*C$11,$D$28*C$12*C$11,C$7) -> 82141 | O78: =N78/Supuestos!$B$14*C$14 -> 102530.79 | P78: =N78*C$16-O78 -> 88233.466 | Q78: =866314.36455085*MIN(1,$D$30/3911.97229065033) -> 866314.36 | R78: =P78+Q78 -> 954547.83 | S78: =Q78/C$17 -> 1956.0044 | T78: =C$9-S78 -> -491.00444
B79: jul-25 | C79: =$D$26*D$21 -> 113460.06 | D79: 0.12903226 | E79: 0.87096774 | F79: 0 | G79: =C79*D79 -> 14640.008 | H79: =C79*E79 -> 98820.054 | I79: =C79*F79 -> 0 | J79: =G79*D$14+H79*D$15+I79*D$16 -> 216450.32 | K79: =G79+H79+I79 -> 113460.06 | L79: 0 | M79: =J79+L79*$D$26/839.45 -> 216450.32 | N79: =MIN($D$30*D$11,$D$28*D$12*D$11,D$7) -> 74300 | O79: =N79/Supuestos!$B$14*D$14 -> 93904.365 | P79: =N79*D$16-O79 -> 81027.555 | Q79: =782888.179108982*MIN(1,$D$30/3911.97229065033) -> 782888.18 | R79: =P79+Q79 -> 863915.73 | S79: =Q79/D$17 -> 1741.5317 | T79: =D$9-S79 -> -159.53174
B80: ago-25 | C80: =$D$26*E$21 -> 106173.64 | D80: 0.16128921 | E80: 0.83871079 | F80: 0 | G80: =C80*D80 -> 17124.662 | H80: =C80*E80 -> 89048.974 | I80: =C80*F80 -> 0 | J80: =G80*E$14+H80*E$15+I80*E$16 -> 200065.82 | K80: =G80+H80+I80 -> 106173.64 | L80: 0 | M80: =J80+L80*$D$26/839.45 -> 200065.82 | N80: =MIN($D$30*E$11,$D$28*E$12*E$11,E$7) -> 82151.418 | O80: =N80/Supuestos!$B$14*E$14 -> 103947.22 | P80: =N80*E$16-O80 -> 89716.537 | Q80: =879944.946860273*MIN(1,$D$30/3911.97229065033) -> 879944.95 | R80: =P80+Q80 -> 969661.48 | S80: =Q80/E$17 -> 1954.6948 | T80: =E$9-S80 -> -439.69477
B81: sep-25 | C81: =$D$26*F$21 -> 100331.06 | D81: 0.133332 | E81: 0.866668 | F81: 0 | G81: =C81*D81 -> 13377.342 | H81: =C81*E81 -> 86953.722 | I81: =C81*F81 -> 0 | J81: =G81*F$14+H81*F$15+I81*F$16 -> 190130.82 | K81: =G81+H81+I81 -> 100331.06 | L81: 0 | M81: =J81+L81*$D$26/839.45 -> 190130.82 | N81: =MIN($D$30*F$11,$D$28*F$12*F$11,F$7) -> 80458 | O81: =N81/Supuestos!$B$14*F$14 -> 101368.7 | P81: =N81*F$16-O81 -> 87039.8 | Q81: =750604.023175983*MIN(1,$D$30/3911.97229065033) -> 750604.02 | R81: =P81+Q81 -> 837643.82 | S81: =Q81/F$17 -> 1682.78 | T81: =F$9-S81 -> 596.21999
B82: oct-25 | C82: =$D$26*G$21 -> 110545.49 | D82: 0.12852344 | E82: 0.86893462 | F82: 0.0025449589 | G82: =C82*D82 -> 14207.687 | H82: =C82*E82 -> 96056.804 | I82: =C82*F82 -> 281.33374 | J82: =G82*G$14+H82*G$15+I82*G$16 -> 210014.24 | K82: =G82+H82+I82 -> 110545.82 | L82: 0 | M82: =J82+L82*$D$26/839.45 -> 210014.24 | N82: =MIN($D$30*G$11,$D$28*G$12*G$11,G$7) -> 89975.363 | O82: =N82/Supuestos!$B$14*G$14 -> 113359.58 | P82: =N82*G$16-O82 -> 97335.722 | Q82: =436237.736219313*MIN(1,$D$30/3911.97229065033) -> 436237.74 | R82: =P82+Q82 -> 533573.46 | S82: =Q82/G$17 -> 978.00187 | T82: =G$9-S82 -> 771.99813
B83: nov-25 | C83: =$D$26*H$21 -> 114635.29 | D83: 0.16925264 | E83: 0.82023285 | F83: 0.010514501 | G83: =C83*D83 -> 19402.326 | H83: =C83*E83 -> 94027.633 | I83: =C83*F83 -> 1205.3329 | J83: =G83*H$14+H83*H$15+I83*H$16 -> 208637.57 | K83: =G83+H83+I83 -> 114635.29 | L83: 0 | M83: =J83+L83*$D$26/839.45 -> 208637.57 | N83: =MIN($D$30*H$11,$D$28*H$12*H$11,H$7) -> 97799.307 | O83: =N83/Supuestos!$B$14*H$14 -> 120119.96 | P83: =N83*H$16-O83 -> 102598.4 | Q83: =423142.426841897*MIN(1,$D$30/3911.97229065033) -> 423142.43 | R83: =P83+Q83 -> 525740.83 | S83: =Q83/H$17 -> 978.00219 | T83: =H$9-S83 -> 1047.9978
B84: dic-25 | C84: =$D$26*I$21 -> 109920.94 | D84: 0.1310335 | E84: 0.85726416 | F84: 0.011699311 | G84: =C84*D84 -> 14403.326 | H84: =C84*E84 -> 94231.283 | I84: =C84*F84 -> 1285.9993 | J84: =G84*I$14+H84*I$15+I84*I$16 -> 194248.14 | K84: =G84+H84+I84 -> 109920.61 | L84: 0 | M84: =J84+L84*$D$26/839.45 -> 194248.14 | N84: =MIN($D$30*I$11,$D$28*I$12*I$11,I$7) -> 105623.25 | O84: =N84/Supuestos!$B$14*I$14 -> 124338.37 | P84: =N84*I$16-O84 -> 105223.2 | Q84: =401988.207688244*MIN(1,$D$30/3911.97229065033) -> 401988.21 | R84: =P84+Q84 -> 507211.41 | S84: =Q84/I$17 -> 978.00211 | T84: =I$9-S84 -> 1145.9979
B85: ene-26 | C85: =$D$26*J$21 -> 119913.75 | D85: 0.132045 | E85: 0.85676362 | F85: 0.011191385 | G85: =C85*D85 -> 15834.011 | H85: =C85*E85 -> 102737.74 | I85: =C85*F85 -> 1342.001 | J85: =G85*J$14+H85*J$15+I85*J$16 -> 207193.82 | K85: =G85+H85+I85 -> 119913.75 | L85: 0 | M85: =J85+L85*$D$26/839.45 -> 207193.82 | N85: =MIN($D$30*J$11,$D$28*J$12*J$11,J$7) -> 105623.25 | O85: =N85/Supuestos!$B$14*J$14 -> 121686.79 | P85: =N85*J$16-O85 -> 102847.12 | Q85: =392941.671717752*MIN(1,$D$30/3911.97229065033) -> 392941.67 | R85: =P85+Q85 -> 495788.79 | S85: =Q85/J$17 -> 978.00207 | T85: =J$9-S85 -> 913.99793
B86: feb-26 | C86: =$D$26*K$21 -> 116770.85 | D86: 0.14507312 | E86: 0.84365981 | F86: 0.011264212 | G86: =C86*D86 -> 16940.312 | H86: =C86*E86 -> 98514.876 | I86: =C86*F86 -> 1315.3317 | J86: =G86*K$14+H86*K$15+I86*K$16 -> 200780 | K86: =G86+H86+I86 -> 116770.52 | L86: 0 | M86: =J86+L86*$D$26/839.45 -> 200780 | N86: =MIN($D$30*K$11,$D$28*K$12*K$11,K$7) -> 93887.335 | O86: =N86/Supuestos!$B$14*K$14 -> 108214.93 | P86: =N86*K$16-O86 -> 91474.039 | Q86: =393166.7897999*MIN(1,$D$30/3911.97229065033) -> 393166.79 | R86: =P86+Q86 -> 484640.83 | S86: =Q86/K$17 -> 978.00251 | T86: =K$9-S86 -> 924.99749
B87: mar-26 | C87: =$D$26*L$21 -> 142813.95 | D87: 0.16278516 | E87: 0.82602313 | F87: 0.011191713 | G87: =C87*D87 -> 23247.992 | H87: =C87*E87 -> 117967.63 | I87: =C87*F87 -> 1598.3328 | J87: =G87*L$14+H87*L$15+I87*L$16 -> 243887.53 | K87: =G87+H87+I87 -> 142813.95 | L87: 0 | M87: =J87+L87*$D$26/839.45 -> 243887.53 | N87: =MIN($D$30*L$11,$D$28*L$12*L$11,L$7) -> 101711.28 | O87: =N87/Supuestos!$B$14*L$14 -> 117296.41 | P87: =N87*L$16-O87 -> 99155.36 | Q87: =393411.13818844*MIN(1,$D$30/3911.97229065033) -> 393411.14 | R87: =P87+Q87 -> 492566.5 | S87: =Q87/L$17 -> 978.00213 | T87: =L$9-S87 -> 792.99787
B88: abr-26 | C88: =$D$26*M$21 -> 126521.9 | D88: 0.13437716 | E88: 0.86404472 | F88: 0.0015781182 | G88: =C88*D88 -> 17001.654 | H88: =C88*E88 -> 109320.58 | I88: =C88*F88 -> 199.66652 | J88: =G88*M$14+H88*M$15+I88*M$16 -> 218252.91 | K88: =G88+H88+I88 -> 126521.9 | L88: 0 | M88: =J88+L88*$D$26/839.45 -> 218252.91 | N88: =MIN($D$30*M$11,$D$28*M$12*M$11,M$7) -> 89975.363 | O88: =N88/Supuestos!$B$14*M$14 -> 103752.84 | P88: =N88*M$16-O88 -> 87714.732 | Q88: =393391.73145722*MIN(1,$D$30/3911.97229065033) -> 393391.73 | R88: =P88+Q88 -> 481106.46 | S88: =Q88/M$17 -> 978.00251 | T88: =M$9-S88 -> 600.99749
B89: TOTAL | C89: =SUM(C77:C88) -> 1393628 | G89: =SUM(G77:G88) -> 200415.67 | H89: =SUM(H77:H88) -> 1185984.4 | I89: =SUM(I77:I88) -> 7227.9979 | J89: =SUM(J77:J88) -> 2519359.8 | K89: =SUM(K77:K88) -> 1393628 | M89: =SUM(M77:M88) -> 2519359.8 | N89: =SUM(N77:N88) -> 1089709 | O89: =SUM(O77:O88) -> 1315849 | P89: =SUM(P77:P88) -> 1122659 | Q89: =SUM(Q77:Q88) -> 6960237.9 | R89: =SUM(R77:R88) -> 8082896.9 | S89: =AVERAGE(S77:S88) -> 1344.7526 | T89: =AVERAGE(T77:T88) -> 450.24742
A92: 5. PROYECCIÓN 20 AÑOS — OPCIÓN 1 — Autoconsumo (vertical, con cliff autoabasto 2032)
B93: Año | C93: Gasto CFE pleno $ | D93: Beneficio autoabasto $ | E93: Gasto real sin sistema $ | F93: Ahorro PV $ | G93: Ahorro BESS $ | H93: Pago PPA $ | I93: Pago particip. BESS $ | J93: Ahorro neto GEPP $ | K93: Acumulado GEPP $ | L93: % ahorro | M93: Flujo inv. PV $ | N93: Flujo inv. BESS $ | O93: Flujo inv. PV acum $ | P93: Flujo inv. BESS acum $
B94: Año 0 | C94: 0 | D94: 0 | E94: 0 | F94: 0 | G94: 0 | H94: 0 | I94: 0 | J94: 0 | K94: 0 | L94: 0 | M94: =-$C$34 -> -7770789 | N94: =-$C$36 -> -20437326 | O94: =M94 -> -7770789 | P94: =N94 -> -20437326
B95: =Supuestos!$B$25+1-1 -> 2026 | C95: =$C$39*(1+Supuestos!$B$9)^(1-1) -> 40064390 | D95: =IF(B95<=Supuestos!$B$26,$C$38*(1+Supuestos!$B$9)^(1-1),0) -> 7886060.9 | E95: =C95-D95 -> 32178329 | F95: =$C$43*(1+Supuestos!$B$9)^(1-1)*(1-Supuestos!$B$11)^(1-1) -> 2044419.1 | G95: =$C$44*(1+Supuestos!$B$9)^(1-1)*(1-Supuestos!$B$12)^(1-1) -> 6735747.4 | H95: =IF(1<=Supuestos!$B$18,$C$42*$C$31*(1+Supuestos!$B$10)^(1-1)*(1-Supuestos!$B$11)^(1-1),0) -> 1249199.3 | I95: =IF(1<=Supuestos!$B$19,G95*$C$32,0) -> 3367873.7 | J95: =F95+G95-H95-I95 -> 4163093.5 | K95: =K94+J95 -> 4163093.5 | L95: =IF(E95>0,J95/E95,0) -> 0.12937569 | M95: =IF(1<=Supuestos!$B$18,H95-Supuestos!$B$22*$C$26*(1+Supuestos!$B$9)^(1-1),0) -> 1038027.3 | N95: =IF(1<=Supuestos!$B$19,I95-Supuestos!$B$23*$C$29*(1+Supuestos!$B$9)^(1-1),0) -> 2619253.7 | O95: =O94+M95 -> -6732761.7 | P95: =P94+N95 -> -17818072
B96: =Supuestos!$B$25+2-1 -> 2027 | C96: =$C$39*(1+Supuestos!$B$9)^(2-1) -> 42468254 | D96: =IF(B96<=Supuestos!$B$26,$C$38*(1+Supuestos!$B$9)^(2-1),0) -> 8359224.6 | E96: =C96-D96 -> 34109029 | F96: =$C$43*(1+Supuestos!$B$9)^(2-1)*(1-Supuestos!$B$11)^(2-1) -> 2156248.8 | G96: =$C$44*(1+Supuestos!$B$9)^(2-1)*(1-Supuestos!$B$12)^(2-1) -> 7050643.6 | H96: =IF(2<=Supuestos!$B$18,$C$42*$C$31*(1+Supuestos!$B$10)^(2-1)*(1-Supuestos!$B$11)^(2-1),0) -> 1305100.9 | I96: =IF(2<=Supuestos!$B$19,G96*$C$32,0) -> 3525321.8 | J96: =F96+G96-H96-I96 -> 4376469.7 | K96: =K95+J96 -> 8539563.2 | L96: =IF(E96>0,J96/E96,0) -> 0.12830825 | M96: =IF(2<=Supuestos!$B$18,H96-Supuestos!$B$22*$C$26*(1+Supuestos!$B$9)^(2-1),0) -> 1081258.6 | N96: =IF(2<=Supuestos!$B$19,I96-Supuestos!$B$23*$C$29*(1+Supuestos!$B$9)^(2-1),0) -> 2731784.6 | O96: =O95+M96 -> -5651503.1 | P96: =P95+N96 -> -15086288
B97: =Supuestos!$B$25+3-1 -> 2028 | C97: =$C$39*(1+Supuestos!$B$9)^(3-1) -> 45016349 | D97: =IF(B97<=Supuestos!$B$26,$C$38*(1+Supuestos!$B$9)^(3-1),0) -> 8860778 | E97: =C97-D97 -> 36155571 | F97: =$C$43*(1+Supuestos!$B$9)^(3-1)*(1-Supuestos!$B$11)^(3-1) -> 2274195.6 | G97: =$C$44*(1+Supuestos!$B$9)^(3-1)*(1-Supuestos!$B$12)^(3-1) -> 7380261.2 | H97: =IF(3<=Supuestos!$B$18,$C$42*$C$31*(1+Supuestos!$B$10)^(3-1)*(1-Supuestos!$B$11)^(3-1),0) -> 1363504.2 | I97: =IF(3<=Supuestos!$B$19,G97*$C$32,0) -> 3690130.6 | J97: =F97+G97-H97-I97 -> 4600822 | K97: =K96+J97 -> 13140385 | L97: =IF(E97>0,J97/E97,0) -> 0.12725071 | M97: =IF(3<=Supuestos!$B$18,H97-Supuestos!$B$22*$C$26*(1+Supuestos!$B$9)^(3-1),0) -> 1126231.3 | N97: =IF(3<=Supuestos!$B$19,I97-Supuestos!$B$23*$C$29*(1+Supuestos!$B$9)^(3-1),0) -> 2848981.2 | O97: =O96+M97 -> -4525271.8 | P97: =P96+N97 -> -12237307
B98: =Supuestos!$B$25+4-1 -> 2029 | C98: =$C$39*(1+Supuestos!$B$9)^(4-1) -> 47717330 | D98: =IF(B98<=Supuestos!$B$26,$C$38*(1+Supuestos!$B$9)^(4-1),0) -> 9392424.7 | E98: =C98-D98 -> 38324905 | F98: =$C$43*(1+Supuestos!$B$9)^(4-1)*(1-Supuestos!$B$11)^(4-1) -> 2398594.1 | G98: =$C$44*(1+Supuestos!$B$9)^(4-1)*(1-Supuestos!$B$12)^(4-1) -> 7725288.4 | H98: =IF(4<=Supuestos!$B$18,$C$42*$C$31*(1+Supuestos!$B$10)^(4-1)*(1-Supuestos!$B$11)^(4-1),0) -> 1424521 | I98: =IF(4<=Supuestos!$B$19,G98*$C$32,0) -> 3862644.2 | J98: =F98+G98-H98-I98 -> 4836717.3 | K98: =K97+J98 -> 17977102 | L98: =IF(E98>0,J98/E98,0) -> 0.12620298 | M98: =IF(4<=Supuestos!$B$18,H98-Supuestos!$B$22*$C$26*(1+Supuestos!$B$9)^(4-1),0) -> 1173011.8 | N98: =IF(4<=Supuestos!$B$19,I98-Supuestos!$B$23*$C$29*(1+Supuestos!$B$9)^(4-1),0) -> 2971025.8 | O98: =O97+M98 -> -3352260 | P98: =P97+N98 -> -9266280.7
B99: =Supuestos!$B$25+5-1 -> 2030 | C99: =$C$39*(1+Supuestos!$B$9)^(5-1) -> 50580369 | D99: =IF(B99<=Supuestos!$B$26,$C$38*(1+Supuestos!$B$9)^(5-1),0) -> 9955970.2 | E99: =C99-D99 -> 40624399 | F99: =$C$43*(1+Supuestos!$B$9)^(5-1)*(1-Supuestos!$B$11)^(5-1) -> 2529797.2 | G99: =$C$44*(1+Supuestos!$B$9)^(5-1)*(1-Supuestos!$B$12)^(5-1) -> 8086445.6 | H99: =IF(5<=Supuestos!$B$18,$C$42*$C$31*(1+Supuestos!$B$10)^(5-1)*(1-Supuestos!$B$11)^(5-1),0) -> 1488268.3 | I99: =IF(5<=Supuestos!$B$19,G99*$C$32,0) -> 4043222.8 | J99: =F99+G99-H99-I99 -> 5084751.7 | K99: =K98+J99 -> 23061854 | L99: =IF(E99>0,J99/E99,0) -> 0.12516497 | M99: =IF(5<=Supuestos!$B$18,H99-Supuestos!$B$22*$C$26*(1+Supuestos!$B$9)^(5-1),0) -> 1221668.5 | N99: =IF(5<=Supuestos!$B$19,I99-Supuestos!$B$23*$C$29*(1+Supuestos!$B$9)^(5-1),0) -> 3098107.3 | O99: =O98+M99 -> -2130591.5 | P99: =P98+N99 -> -6168173.4
B100: =Supuestos!$B$25+6-1 -> 2031 | C100: =$C$39*(1+Supuestos!$B$9)^(6-1) -> 53615192 | D100: =IF(B100<=Supuestos!$B$26,$C$38*(1+Supuestos!$B$9)^(6-1),0) -> 10553328 | E100: =C100-D100 -> 43061863 | F100: =$C$43*(1+Supuestos!$B$9)^(6-1)*(1-Supuestos!$B$11)^(6-1) -> 2668177.1 | G100: =$C$44*(1+Supuestos!$B$9)^(6-1)*(1-Supuestos!$B$12)^(6-1) -> 8464487 | H100: =IF(6<=Supuestos!$B$18,$C$42*$C$31*(1+Supuestos!$B$10)^(6-1)*(1-Supuestos!$B$11)^(6-1),0) -> 1554868.3 | I100: =IF(6<=Supuestos!$B$19,G100*$C$32,0) -> 4232243.5 | J100: =F100+G100-H100-I100 -> 5345552.3 | K100: =K99+J100 -> 28407406 | L100: =IF(E100>0,J100/E100,0) -> 0.12413658 | M100: =IF(6<=Supuestos!$B$18,H100-Supuestos!$B$22*$C$26*(1+Supuestos!$B$9)^(6-1),0) -> 1272272.6 | N100: =IF(6<=Supuestos!$B$19,I100-Supuestos!$B$23*$C$29*(1+Supuestos!$B$9)^(6-1),0) -> 3230421.1 | O100: =O99+M100 -> -858318.96 | P100: =P99+N100 -> -2937752.3
B101: =Supuestos!$B$25+7-1 -> 2032 | C101: =$C$39*(1+Supuestos!$B$9)^(7-1) -> 56832103 | D101: =IF(B101<=Supuestos!$B$26,$C$38*(1+Supuestos!$B$9)^(7-1),0) -> 11186528 | E101: =C101-D101 -> 45645575 | F101: =$C$43*(1+Supuestos!$B$9)^(7-1)*(1-Supuestos!$B$11)^(7-1) -> 2814126.4 | G101: =$C$44*(1+Supuestos!$B$9)^(7-1)*(1-Supuestos!$B$12)^(7-1) -> 8860201.7 | H101: =IF(7<=Supuestos!$B$18,$C$42*$C$31*(1+Supuestos!$B$10)^(7-1)*(1-Supuestos!$B$11)^(7-1),0) -> 1624448.7 | I101: =IF(7<=Supuestos!$B$19,G101*$C$32,0) -> 4430100.9 | J101: =F101+G101-H101-I101 -> 5619778.6 | K101: =K100+J101 -> 34027185 | L101: =IF(E101>0,J101/E101,0) -> 0.12311771 | M101: =IF(7<=Supuestos!$B$18,H101-Supuestos!$B$22*$C$26*(1+Supuestos!$B$9)^(7-1),0) -> 1324897.2 | N101: =IF(7<=Supuestos!$B$19,I101-Supuestos!$B$23*$C$29*(1+Supuestos!$B$9)^(7-1),0) -> 3368169.1 | O101: =O100+M101 -> 466578.2 | P101: =P100+N101 -> 430416.74
B102: =Supuestos!$B$25+8-1 -> 2033 | C102: =$C$39*(1+Supuestos!$B$9)^(8-1) -> 60242029 | D102: =IF(B102<=Supuestos!$B$26,$C$38*(1+Supuestos!$B$9)^(8-1),0) -> 0 | E102: =C102-D102 -> 60242029 | F102: =$C$43*(1+Supuestos!$B$9)^(8-1)*(1-Supuestos!$B$11)^(8-1) -> 2968059.1 | G102: =$C$44*(1+Supuestos!$B$9)^(8-1)*(1-Supuestos!$B$12)^(8-1) -> 9274416.2 | H102: =IF(8<=Supuestos!$B$18,$C$42*$C$31*(1+Supuestos!$B$10)^(8-1)*(1-Supuestos!$B$11)^(8-1),0) -> 1697142.8 | I102: =IF(8<=Supuestos!$B$19,G102*$C$32,0) -> 4637208.1 | J102: =F102+G102-H102-I102 -> 5908124.4 | K102: =K101+J102 -> 39935309 | L102: =IF(E102>0,J102/E102,0) -> 0.098073131 | M102: =IF(8<=Supuestos!$B$18,H102-Supuestos!$B$22*$C$26*(1+Supuestos!$B$9)^(8-1),0) -> 1379618.1 | N102: =IF(8<=Supuestos!$B$19,I102-Supuestos!$B$23*$C$29*(1+Supuestos!$B$9)^(8-1),0) -> 3511560.4 | O102: =O101+M102 -> 1846196.4 | P102: =P101+N102 -> 3941977.1
B103: =Supuestos!$B$25+9-1 -> 2034 | C103: =$C$39*(1+Supuestos!$B$9)^(9-1) -> 63856551 | D103: =IF(B103<=Supuestos!$B$26,$C$38*(1+Supuestos!$B$9)^(9-1),0) -> 0 | E103: =C103-D103 -> 63856551 | F103: =$C$43*(1+Supuestos!$B$9)^(9-1)*(1-Supuestos!$B$11)^(9-1) -> 3130411.9 | G103: =$C$44*(1+Supuestos!$B$9)^(9-1)*(1-Supuestos!$B$12)^(9-1) -> 9707995.1 | H103: =IF(9<=Supuestos!$B$18,$C$42*$C$31*(1+Supuestos!$B$10)^(9-1)*(1-Supuestos!$B$11)^(9-1),0) -> 1773089.9 | I103: =IF(9<=Supuestos!$B$19,G103*$C$32,0) -> 4853997.6 | J103: =F103+G103-H103-I103 -> 6211319.6 | K103: =K102+J103 -> 46146629 | L103: =IF(E103>0,J103/E103,0) -> 0.097269888 | M103: =IF(9<=Supuestos!$B$18,H103-Supuestos!$B$22*$C$26*(1+Supuestos!$B$9)^(9-1),0) -> 1436513.8 | N103: =IF(9<=Supuestos!$B$19,I103-Supuestos!$B$23*$C$29*(1+Supuestos!$B$9)^(9-1),0) -> 3660811 | O103: =O102+M103 -> 3282710.2 | P103: =P102+N103 -> 7602788.2
B104: =Supuestos!$B$25+10-1 -> 2035 | C104: =$C$39*(1+Supuestos!$B$9)^(10-1) -> 67687944 | D104: =IF(B104<=Supuestos!$B$26,$C$38*(1+Supuestos!$B$9)^(10-1),0) -> 0 | E104: =C104-D104 -> 67687944 | F104: =$C$43*(1+Supuestos!$B$9)^(10-1)*(1-Supuestos!$B$11)^(10-1) -> 3301645.5 | G104: =$C$44*(1+Supuestos!$B$9)^(10-1)*(1-Supuestos!$B$12)^(10-1) -> 10161844 | H104: =IF(10<=Supuestos!$B$18,$C$42*$C$31*(1+Supuestos!$B$10)^(10-1)*(1-Supuestos!$B$11)^(10-1),0) -> 1852435.7 | I104: =IF(10<=Supuestos!$B$19,G104*$C$32,0) -> 5080921.9 | J104: =F104+G104-H104-I104 -> 6530131.7 | K104: =K103+J104 -> 52676761 | L104: =IF(E104>0,J104/E104,0) -> 0.096474074 | M104: =IF(10<=Supuestos!$B$18,H104-Supuestos!$B$22*$C$26*(1+Supuestos!$B$9)^(10-1),0) -> 1495665 | N104: =IF(10<=Supuestos!$B$19,I104-Supuestos!$B$23*$C$29*(1+Supuestos!$B$9)^(10-1),0) -> 3816144.2 | O104: =O103+M104 -> 4778375.2 | P104: =P103+N104 -> 11418932
B105: =Supuestos!$B$25+11-1 -> 2036 | C105: =$C$39*(1+Supuestos!$B$9)^(11-1) -> 71749221 | D105: =IF(B105<=Supuestos!$B$26,$C$38*(1+Supuestos!$B$9)^(11-1),0) -> 0 | E105: =C105-D105 -> 71749221 | F105: =$C$43*(1+Supuestos!$B$9)^(11-1)*(1-Supuestos!$B$11)^(11-1) -> 3482245.5 | G105: =$C$44*(1+Supuestos!$B$9)^(11-1)*(1-Supuestos!$B$12)^(11-1) -> 10636910 | H105: =IF(11<=Supuestos!$B$18,$C$42*$C$31*(1+Supuestos!$B$10)^(11-1)*(1-Supuestos!$B$11)^(11-1),0) -> 1935332.2 | I105: =IF(11<=Supuestos!$B$19,G105*$C$32,0) -> 5318455 | J105: =F105+G105-H105-I105 -> 6865368.3 | K105: =K104+J105 -> 59542129 | L105: =IF(E105>0,J105/E105,0) -> 0.095685615 | M105: =IF(11<=Supuestos!$B$18,H105-Supuestos!$B$22*$C$26*(1+Supuestos!$B$9)^(11-1),0) -> 1557155.3 | N105: =IF(11<=Supuestos!$B$19,I105-Supuestos!$B$23*$C$29*(1+Supuestos!$B$9)^(11-1),0) -> 3977790.6 | O105: =O104+M105 -> 6335530.5 | P105: =P104+N105 -> 15396723
B106: =Supuestos!$B$25+12-1 -> 2037 | C106: =$C$39*(1+Supuestos!$B$9)^(12-1) -> 76054174 | D106: =IF(B106<=Supuestos!$B$26,$C$38*(1+Supuestos!$B$9)^(12-1),0) -> 0 | E106: =C106-D106 -> 76054174 | F106: =$C$43*(1+Supuestos!$B$9)^(12-1)*(1-Supuestos!$B$11)^(12-1) -> 3672724.3 | G106: =$C$44*(1+Supuestos!$B$9)^(12-1)*(1-Supuestos!$B$12)^(12-1) -> 11134186 | H106: =IF(12<=Supuestos!$B$18,$C$42*$C$31*(1+Supuestos!$B$10)^(12-1)*(1-Supuestos!$B$11)^(12-1),0) -> 2021938.3 | I106: =IF(12<=Supuestos!$B$19,G106*$C$32,0) -> 5567092.8 | J106: =F106+G106-H106-I106 -> 7217878.8 | K106: =K105+J106 -> 66760008 | L106: =IF(E106>0,J106/E106,0) -> 0.09490444 | M106: =IF(12<=Supuestos!$B$18,H106-Supuestos!$B$22*$C$26*(1+Supuestos!$B$9)^(12-1),0) -> 1621070.8 | N106: =IF(12<=Supuestos!$B$19,I106-Supuestos!$B$23*$C$29*(1+Supuestos!$B$9)^(12-1),0) -> 4145988.6 | O106: =O105+M106 -> 7956601.2 | P106: =P105+N106 -> 19542712
B107: =Supuestos!$B$25+13-1 -> 2038 | C107: =$C$39*(1+Supuestos!$B$9)^(13-1) -> 80617424 | D107: =IF(B107<=Supuestos!$B$26,$C$38*(1+Supuestos!$B$9)^(13-1),0) -> 0 | E107: =C107-D107 -> 80617424 | F107: =$C$43*(1+Supuestos!$B$9)^(13-1)*(1-Supuestos!$B$11)^(13-1) -> 3873622.3 | G107: =$C$44*(1+Supuestos!$B$9)^(13-1)*(1-Supuestos!$B$12)^(13-1) -> 11654709 | H107: =IF(13<=Supuestos!$B$18,$C$42*$C$31*(1+Supuestos!$B$10)^(13-1)*(1-Supuestos!$B$11)^(13-1),0) -> 2112420 | I107: =IF(13<=Supuestos!$B$19,G107*$C$32,0) -> 5827354.4 | J107: =F107+G107-H107-I107 -> 7588556.7 | K107: =K106+J107 -> 74348565 | L107: =IF(E107>0,J107/E107,0) -> 0.094130478 | M107: =IF(13<=Supuestos!$B$18,H107-Supuestos!$B$22*$C$26*(1+Supuestos!$B$9)^(13-1),0) -> 1687500.5 | N107: =IF(13<=Supuestos!$B$19,I107-Supuestos!$B$23*$C$29*(1+Supuestos!$B$9)^(13-1),0) -> 4320983.9 | O107: =O106+M107 -> 9644101.7 | P107: =P106+N107 -> 23863695
...

Sheet Preforma 2
A1: GEPP Proplasa · Preforma 2 — Propuesta Solar + BESS | GDMTH (V. de México Norte) | Cuautitlán Izcalli, Méx. (MXN sin IVA)
A3: 1. DATOS BASE — últimos 12 meses reales (recibos CFE, sin IVA)
A4: Mes | B4: may-25 | C4: jun-25 | D4: jul-25 | E4: ago-25 | F4: sep-25 | G4: oct-25 | H4: nov-25 | I4: dic-25 | J4: ene-26 | K4: feb-26 | L4: mar-26 | M4: abr-26 | N4: TOTAL
A5: Consumo Base (kWh) | B5: 1554976 | C5: 1461034 | D5: 1213977 | E5: 1460355 | F5: 1257774 | G5: 1080780 | H5: 1215444 | I5: 1136000 | J5: 1127389 | K5: 1258745 | L5: 1582579 | M5: 1391931 | N5: =SUM(B5:M5) -> 15740984
A6: Consumo Intermedia (kWh) | B6: 2674916 | C6: 2511016 | D6: 2229430 | E6: 2480903 | F6: 2130853 | G6: 2010757 | H6: 1781412 | I6: 1717671 | J6: 1795542 | K6: 1870728 | L6: 2238743 | M6: 2472488 | N6: =SUM(B6:M6) -> 25914459
A7: Consumo Punta (kWh) | B7: 252409 | C7: 251483 | D7: 229493 | E7: 235656 | F7: 208228 | G7: 247787 | H7: 435452 | I7: 418355 | J7: 466031 | K7: 471567 | L7: 538917 | M7: 308716 | N7: =SUM(B7:M7) -> 4064094
A8: Consumo Total (kWh) | B8: =SUM(B5:B7) -> 4482301 | C8: =SUM(C5:C7) -> 4223533 | D8: =SUM(D5:D7) -> 3672900 | E8: =SUM(E5:E7) -> 4176914 | F8: =SUM(F5:F7) -> 3596855 | G8: =SUM(G5:G7) -> 3339324 | H8: =SUM(H5:H7) -> 3432308 | I8: =SUM(I5:I7) -> 3272026 | ... M8: =SUM(M5:M7) -> 4173135 | N8: =SUM(B8:M8) -> 45719537
A9: Dem. máx. en punta (kW) | B9: 6509 | C9: 6634 | D9: 5851 | E9: 6354 | F9: 5562 | G9: 4470 | H9: 6123 | I9: 5588 | J9: 6670 | K9: 6525 | L9: 6470 | M9: 6489 | N9: =MAX(B9:M9) -> 6670
A10: Dem. máx. mensual (kW) | B10: 6565 | C10: 6744 | D10: 5873 | E10: 6492 | F10: 6311 | G10: 4522 | H10: 6215 | I10: 6070 | J10: 6718 | K10: 6557 | L10: 6470 | M10: 6597 | N10: =MAX(B10:M10) -> 6744
A11: Días con punta | B11: 22 | C11: 21 | D11: 23 | E11: 21 | F11: 22 | G11: 23 | H11: 25 | I11: 27 | J11: 27 | K11: 24 | L11: 26 | M11: 23
A12: Horas punta/día | B12: 2 | C12: 2 | D12: 2 | E12: 2 | F12: 2 | G12: 2.43 | H12: 3.6 | I12: 3.7 | J12: 3.63 | K12: 3.67 | L12: 3.69 | M12: 2.26
A13: Días del mes | B13: 31 | C13: 30 | D13: 31 | E13: 31 | F13: 30 | G13: 31 | H13: 30 | I13: 31 | J13: 31 | K13: 28 | L13: 31 | M13: 30
A14: Tarifa Base ($/kWh) | B14: 1.1749 | C14: 1.1983 | D14: 1.2133 | E14: 1.2147 | F14: 1.2095 | G14: 1.2095 | H14: 1.1791 | I14: 1.1301 | J14: 1.106 | K14: 1.1065 | L14: 1.1071 | M14: 1.107
A15: Tarifa Intermedia ($/kWh) | B15: 1.9422 | C15: 1.9837 | D15: 2.0106 | E15: 2.0131 | F15: 2.0005 | G15: 2.0006 | H15: 1.9464 | I15: 1.859 | J15: 1.8185 | K15: 1.8194 | L15: 1.8204 | M15: 1.8204
A16: Tarifa Punta ($/kWh) | B16: 2.273 | C16: 2.3224 | D16: 2.3544 | E16: 2.3574 | F16: 2.3417 | G16: 2.3417 | H16: 2.2773 | I16: 2.1734 | J16: 2.1258 | K16: 2.1269 | L16: 2.1281 | M16: 2.128
A17: Tarifa Capacidad ($/kW·mes) | B17: 432.62 | C17: 442.9 | D17: 449.54 | E17: 450.17 | F17: 446.05 | G17: 446.05 | H17: 432.66 | I17: 411.03 | J17: 401.78 | K17: 402.01 | L17: 402.26 | M17: 402.24
A18: Tarifa Distribución ($/kW·mes) | B18: 91.12 | C18: 91.12 | D18: 91.12 | E18: 91.12 | F18: 91.12 | G18: 91.12 | H18: 91.12 | I18: 91.12 | J18: 86.15 | K18: 86.15 | L18: 86.15 | M18: 86.15
A19: Gasto actual facturado ($ MXN) | B19: 8530453.4 | C19: 10067365 | D19: 9371204.3 | E19: 10432413 | F19: 9148607.8 | G19: 8701905.6 | H19: 8980129.9 | I19: 8145664.8 | J19: 6171336.9 | K19: 6424180.2 | L19: 8245044 | M19: 7918464.6 | N19: =SUM(B19:M19) -> 1.0213677e+08
A20: Umbral de demanda (kW) | B20: =B8/(24*B13*Supuestos!$B$15) -> 10569.47 | C20: =C8/(24*C13*Supuestos!$B$15) -> 10291.26 | D20: =D8/(24*D13*Supuestos!$B$15) -> 8660.8659 | E20: =E8/(24*E13*Supuestos!$B$15) -> 9849.3539 | F20: =F8/(24*F13*Supuestos!$B$15) -> 8764.2666 | G20: =G8/(24*G13*Supuestos!$B$15) -> 7874.2784 | H20: =H8/(24*H13*Supuestos!$B$15) -> 8363.3236 | I20: =I8/(24*I13*Supuestos!$B$15) -> 7715.5867 | ... M20: =M8/(24*M13*Supuestos!$B$15) -> 10168.458
A21: Yield PV (kWh/kWp) | B21: 143.096 | C21: 133.92 | D21: 135.16 | E21: 126.48 | F21: 119.52 | G21: 131.688 | H21: 136.56 | I21: 130.944 | J21: 142.848 | K21: 139.104 | L21: 170.128 | M21: 150.72 | N21: =SUM(B21:M21) -> 1660.168
A23: 2. SISTEMA PROPUESTO — Opción 1 y Opción 2 (amarillo = editable)
A24: Concepto | C24: OPCIÓN 1 — Autoconsumo | D24: OPCIÓN 2 — GD Medición Neta
A25: Esquema legal | C25: Autoconsumo interconectado (permiso CNE simplificado) | D25: Generación Distribuida <0.7 MW (sin permiso)
A26: Potencia PV (kWp DC) | C26: 1912 | D26: 839.45
A27: Superficie requerida (m²) | C27: =C26*Supuestos!$B$24 -> 7648 | D27: =D26*Supuestos!$B$24 -> 3357.8
A28: BESS potencia (kW) | C28: 5837 | D28: 5837
A29: BESS capacidad (kWh) | C29: 11674 | D29: 11674
A30: Energía útil BESS (kWh) | C30: =C29*Supuestos!$B$13*SQRT(Supuestos!$B$14) -> 10980.612 | D30: =D29*Supuestos!$B$13*SQRT(Supuestos!$B$14) -> 10980.612
A31: Precio PPA (MXN/kWh, año 1) | C31: 1.3526645 | D31: 1.6148562
A32: Participación inversionista BESS (%) | C32: =Supuestos!$B$17 -> 0.5 | D32: =Supuestos!$B$17 -> 0.5
A33: CAPEX PV (USD) | C33: =C26*1000*Supuestos!$B$5 -> 1242800 | D33: =D26*1000*Supuestos!$B$5 -> 545642.5
A34: CAPEX PV (MXN) | C34: =C33*Supuestos!$B$4 -> 21811140 | D34: =D33*Supuestos!$B$4 -> 9576025.9
A35: CAPEX BESS (USD) | C35: =C29*1000*Supuestos!$B$7 -> 3268720 | D35: =D29*1000*Supuestos!$B$7 -> 3268720
A36: CAPEX BESS (MXN) | C36: =C35*Supuestos!$B$4 -> 57366036 | D36: =D35*Supuestos!$B$4 -> 57366036
A37: — Autoabasto TALA / ENEL (vence 2032) —
A38: Beneficio autoabasto actual ($/año) | C38: 27268065 | D38: =C38 -> 27268065
A39: Gasto sin autoabasto — CFE pleno ($/año) | C39: =$N$19+C38 -> 1.2940483e+08 | D39: =$N$19+D38 -> 1.2940483e+08
A40: Gasto real hoy (con autoabasto) ($/año) | C40: =C39-C38 -> 1.0213677e+08 | D40: =D39-D38 -> 1.0213677e+08
A41: Generación PV año 1 (kWh) | C41: =C72 -> 3174241.2 | D41: =C89 -> 1393628
A42: Energía facturada al PPA (kWh) | C42: =K72 -> 3174241.2 | D42: =K89 -> 1393628
A43: Ahorro bruto PV año 1 ($) | C43: =M72 -> 5738298.9 | D43: =M89 -> 2519359.8
A44: Ahorro bruto BESS año 1 c/merma ($) | C44: =R72*(12-Supuestos!$B$16)/12 -> 18905823 | D44: =R89*(12-Supuestos!$B$16)/12 -> 18905823
A45: Ahorro bruto total ($) | C45: =C43+C44 -> 24644122 | D45: =D43+D44 -> 21425183
A46: Pago PPA año 1 ($) | C46: =C42*C31 -> 3506266.8 | D46: =D42*D31 -> 1539401.5
A47: Pago participación BESS ($) | C47: =C44*C32 -> 9452911.4 | D47: =D44*D32 -> 9452911.4
A48: AHORRO NETO GEPP año 1 ($) | C48: =C45-C46-C47 -> 11684944 | D48: =D45-D46-D47 -> 10432870
A49: % ahorro bruto (vs gasto real hoy) | C49: =C45/$N$19 -> 0.2412855 | D49: =D45/$N$19 -> 0.20976954
A50: % ahorro neto (vs gasto real hoy) | C50: =C48/$N$19 -> 0.11440487 | D50: =D48/$N$19 -> 0.10214607
A51: TIR inversionista PV | C51: =IRR(M94:M114) -> 0.14109903 | D51: =IRR(M119:M139) -> 0.14109903
A52: TIR inversionista BESS | C52: =IRR(N94:N114) -> 0.13490802 | D52: =IRR(N119:N139) -> 0.13490802
A53: Participación req. p/ TIR BESS 16% | C53: 0.5655 | D53: 0.5655
A54: Payback simple inversionista PV (años) | C54: =COUNTIF(O94:O114,"<0") -> 7 | D54: =COUNTIF(O119:O139,"<0") -> 7
A55: VAN GEPP del ahorro neto 20a (@WACC) | C55: =NPV(Supuestos!$B$21,J95:J114) -> 1.4038005e+08 | D55: =NPV(Supuestos!$B$21,J120:J139) -> 1.2284058e+08
A58: 3. MODELO MENSUAL AÑO 1 — OPCIÓN 1 — Autoconsumo (vertical)
B59: Mes | C59: Gen PV (kWh) | D59: %Base | E59: %Int | F59: %Punta | G59: PV→Base | H59: PV→Int | I59: PV→Punta | J59: Ahorro energía PV $ | K59: Energía PPA (kWh) | L59: Ahorro distrib/umbral $ (motor) | M59: Ahorro PV total $ | N59: BESS despl. punta kWh | O59: Costo carga base $ | P59: Ahorro arbitraje $ | Q59: Ahorro capacidad $ (motor) | R59: Ahorro BESS bruto $ | S59: Reducción dem. punta (kW) | T59: Dem. punta después (kW)
B60: may-25 | C60: =$C$26*B$21 -> 273599.55 | D60: 0.12903214 | E60: 0.87096786 | F60: 0 | G60: =C60*D60 -> 35303.136 | H60: =C60*E60 -> 238296.42 | I60: =C60*F60 -> 0 | J60: =G60*B$14+H60*B$15+I60*B$16 -> 504296.95 | K60: =G60+H60+I60 -> 273599.55 | L60: 0 | M60: =J60+L60*$C$26/1912 -> 504296.95 | N60: =MIN($C$30*B$11,$C$28*B$12*B$11,B$7) -> 241573.46 | O60: =N60/Supuestos!$B$14*B$14 -> 295650.69 | P60: =N60*B$16-O60 -> 253445.79 | Q60: =2375268.62832069*MIN(1,$C$30/10980.6118107843) -> 2375268.6 | R60: =P60+Q60 -> 2628714.4 | S60: =Q60/B$17 -> 5490.4272 | T60: =B$9-S60 -> 1018.5728
B61: jun-25 | C61: =$C$26*C$21 -> 256055.04 | D61: 0.1666657 | E61: 0.83333236 | F61: 0 | G61: =C61*D61 -> 42675.592 | H61: =C61*E61 -> 213378.95 | I61: =C61*F61 -> 0 | J61: =G61*C$14+H61*C$15+I61*C$16 -> 474417.99 | K61: =G61+H61+I61 -> 256054.54 | L61: 0 | M61: =J61+L61*$C$26/1912 -> 474417.99 | N61: =MIN($C$30*C$11,$C$28*C$12*C$11,C$7) -> 230592.85 | O61: =N61/Supuestos!$B$14*C$14 -> 287832.72 | P61: =N61*C$16-O61 -> 247696.11 | Q61: =2431710.05204561*MIN(1,$C$30/10980.6118107843) -> 2431710.1 | R61: =P61+Q61 -> 2679406.2 | S61: =Q61/C$17 -> 5490.4269 | T61: =C$9-S61 -> 1143.5731
B62: jul-25 | C62: =$C$26*D$21 -> 258425.92 | D62: 0.12903269 | E62: 0.87096923 | F62: 0 | G62: =C62*D62 -> 33345.392 | H62: =C62*E62 -> 225081.02 | I62: =C62*F62 -> 0 | J62: =G62*D$14+H62*D$15+I62*D$16 -> 493005.87 | K62: =G62+H62+I62 -> 258426.42 | L62: 0 | M62: =J62+L62*$C$26/1912 -> 493005.87 | N62: =MIN($C$30*D$11,$C$28*D$12*D$11,D$7) -> 229493 | O62: =N62/Supuestos!$B$14*D$14 -> 290045.68 | P62: =N62*D$16-O62 -> 250272.63 | Q62: =2197536.05927338*MIN(1,$C$30/10980.6118107843) -> 2197536.1 | R62: =P62+Q62 -> 2447808.7 | S62: =Q62/D$17 -> 4888.4105 | T62: =D$9-S62 -> 962.58949
B63: ago-25 | C63: =$C$26*E$21 -> 241829.76 | D63: 0.16129118 | E63: 0.83870882 | F63: 0 | G63: =C63*D63 -> 39005.008 | H63: =C63*E63 -> 202824.75 | I63: =C63*F63 -> 0 | J63: =G63*E$14+H63*E$15+I63*E$16 -> 455685.89 | K63: =G63+H63+I63 -> 241829.76 | L63: 0 | M63: =J63+L63*$C$26/1912 -> 455685.89 | N63: =MIN($C$30*E$11,$C$28*E$12*E$11,E$7) -> 230592.85 | O63: =N63/Supuestos!$B$14*E$14 -> 291772.01 | P63: =N63*E$16-O63 -> 251827.57 | Q63: =2469970.55582272*MIN(1,$C$30/10980.6118107843) -> 2469970.6 | R63: =P63+Q63 -> 2721798.1 | S63: =Q63/E$17 -> 5486.7507 | T63: =E$9-S63 -> 867.24932
B64: sep-25 | C64: =$C$26*F$21 -> 228522.24 | D64: 0.13333304 | E64: 0.86666478 | F64: 0 | G64: =C64*D64 -> 30469.566 | H64: =C64*E64 -> 198052.18 | I64: =C64*F64 -> 0 | J64: =G64*F$14+H64*F$15+I64*F$16 -> 433056.32 | K64: =G64+H64+I64 -> 228521.74 | L64: 0 | M64: =J64+L64*$C$26/1912 -> 433056.32 | N64: =MIN($C$30*F$11,$C$28*F$12*F$11,F$7) -> 208228 | O64: =N64/Supuestos!$B$14*F$14 -> 262345.59 | P64: =N64*F$16-O64 -> 225261.92 | Q64: =2106915.71437724*MIN(1,$C$30/10980.6118107843) -> 2106915.7 | R64: =P64+Q64 -> 2332177.6 | S64: =Q64/F$17 -> 4723.4967 | T64: =F$9-S64 -> 838.50327
B65: oct-25 | C65: =$C$26*G$21 -> 251787.46 | D65: 0.12852419 | E65: 0.86893267 | F65: 0.0025431387 | G65: =C65*D65 -> 32360.779 | H65: =C65*E65 -> 218786.35 | I65: =C65*F65 -> 640.33041 | J65: =G65*G$14+H65*G$15+I65*G$16 -> 478343.79 | K65: =G65+H65+I65 -> 251787.46 | L65: 0 | M65: =J65+L65*$C$26/1912 -> 478343.79 | N65: =MIN($C$30*G$11,$C$28*G$12*G$11,G$7) -> 247787 | O65: =N65/Supuestos!$B$14*G$14 -> 312185.81 | P65: =N65*G$16-O65 -> 268057.01 | Q65: =1224502.01872863*MIN(1,$C$30/10980.6118107843) -> 1224502 | R65: =P65+Q65 -> 1492559 | S65: =Q65/G$17 -> 2745.2125 | T65: =G$9-S65 -> 1724.7875
B66: nov-25 | C66: =$C$26*H$21 -> 261102.72 | D66: 0.16925416 | E66: 0.82023227 | F66: 0.010513579 | G66: =C66*D66 -> 44192.721 | H66: =C66*E66 -> 214164.88 | I66: =C66*F66 -> 2745.124 | J66: =G66*H$14+H66*H$15+I66*H$16 -> 475209.62 | K66: =G66+H66+I66 -> 261102.72 | L66: 0 | M66: =J66+L66*$C$26/1912 -> 475209.62 | N66: =MIN($C$30*H$11,$C$28*H$12*H$11,H$7) -> 274515.3 | O66: =N66/Supuestos!$B$14*H$14 -> 337167.69 | P66: =N66*H$16-O66 -> 287985.99 | Q66: =1187744.00483581*MIN(1,$C$30/10980.6118107843) -> 1187744 | R66: =P66+Q66 -> 1475730 | S66: =Q66/H$17 -> 2745.2133 | T66: =H$9-S66 -> 3377.7867
B67: dic-25 | C67: =$C$26*I$21 -> 250364.93 | D67: 0.13103435 | E67: 0.85726503 | F67: 0.011700629 | G67: =C67*D67 -> 32806.405 | H67: =C67*E67 -> 214629.1 | I67: =C67*F67 -> 2929.4271 | J67: =G67*I$14+H67*I$15+I67*I$16 -> 442436.82 | K67: =G67+H67+I67 -> 250364.93 | L67: 0 | M67: =J67+L67*$C$26/1912 -> 442436.82 | N67: =MIN($C$30*I$11,$C$28*I$12*I$11,I$7) -> 296476.52 | O67: =N67/Supuestos!$B$14*I$14 -> 349008.45 | P67: =N67*I$16-O67 -> 295353.61 | Q67: =1128364.95092183*MIN(1,$C$30/10980.6118107843) -> 1128365 | R67: =P67+Q67 -> 1423718.6 | S67: =Q67/I$17 -> 2745.2131 | T67: =I$9-S67 -> 2842.7869
B68: ene-26 | C68: =$C$26*J$21 -> 273125.38 | D68: 0.13204428 | E68: 0.85676272 | F68: 0.011191179 | G68: =C68*D68 -> 36064.643 | H68: =C68*E68 -> 234003.64 | I68: =C68*F68 -> 3056.5951 | J68: =G68*J$14+H68*J$15+I68*J$16 -> 471920.83 | K68: =G68+H68+I68 -> 273124.88 | L68: 0 | M68: =J68+L68*$C$26/1912 -> 471920.83 | N68: =MIN($C$30*J$11,$C$28*J$12*J$11,J$7) -> 296476.52 | O68: =N68/Supuestos!$B$14*J$14 -> 341565.66 | P68: =N68*J$16-O68 -> 288684.13 | Q68: =1102971.68335545*MIN(1,$C$30/10980.6118107843) -> 1102971.7 | R68: =P68+Q68 -> 1391655.8 | S68: =Q68/J$17 -> 2745.213 | T68: =J$9-S68 -> 3924.787
B69: feb-26 | C69: =$C$26*K$21 -> 265966.85 | D69: 0.14507552 | E69: 0.84366181 | F69: 0.011264538 | G69: =C69*D69 -> 38585.28 | H69: =C69*E69 -> 224386.07 | I69: =C69*F69 -> 2995.9937 | J69: =G69*K$14+H69*K$15+I69*K$16 -> 457314.81 | K69: =G69+H69+I69 -> 265967.34 | L69: 0 | M69: =J69+L69*$C$26/1912 -> 457314.81 | N69: =MIN($C$30*K$11,$C$28*K$12*K$11,K$7) -> 263534.68 | O69: =N69/Supuestos!$B$14*K$14 -> 303751.17 | P69: =N69*K$16-O69 -> 256760.74 | Q69: =1103603.58088095*MIN(1,$C$30/10980.6118107843) -> 1103603.6 | R69: =P69+Q69 -> 1360364.3 | S69: =Q69/K$17 -> 2745.2143 | T69: =K$9-S69 -> 3779.7857
B70: mar-26 | C70: =$C$26*L$21 -> 325284.74 | D70: 0.16278409 | E70: 0.82602328 | F70: 0.011192628 | G70: =C70*D70 -> 52951.18 | H70: =C70*E70 -> 268692.76 | I70: =C70*F70 -> 3640.7911 | J70: =G70*L$14+H70*L$15+I70*L$16 -> 555498.53 | K70: =G70+H70+I70 -> 325284.74 | L70: 0 | M70: =J70+L70*$C$26/1912 -> 555498.53 | N70: =MIN($C$30*L$11,$C$28*L$12*L$11,L$7) -> 285495.91 | O70: =N70/Supuestos!$B$14*L$14 -> 329242.21 | P70: =N70*L$16-O70 -> 278321.63 | Q70: =1104289.45711356*MIN(1,$C$30/10980.6118107843) -> 1104289.5 | R70: =P70+Q70 -> 1382611.1 | S70: =Q70/L$17 -> 2745.2132 | T70: =L$9-S70 -> 3724.7868
B71: abr-26 | C71: =$C$26*M$21 -> 288176.64 | D71: 0.13437717 | E71: 0.86404726 | F71: 0.0015772979 | G71: =C71*D71 -> 38724.36 | H71: =C71*E71 -> 248998.24 | I71: =C71*F71 -> 454.54042 | J71: =G71*M$14+H71*M$15+I71*M$16 -> 497111.52 | K71: =G71+H71+I71 -> 288177.14 | L71: 0 | M71: =J71+L71*$C$26/1912 -> 497111.52 | N71: =MIN($C$30*M$11,$C$28*M$12*M$11,M$7) -> 252554.07 | O71: =N71/Supuestos!$B$14*M$14 -> 291226.41 | P71: =N71*M$16-O71 -> 246208.65 | Q71: =1104234.98318894*MIN(1,$C$30/10980.6118107843) -> 1104235 | R71: =P71+Q71 -> 1350443.6 | S71: =Q71/M$17 -> 2745.2143 | T71: =M$9-S71 -> 3743.7857
B72: TOTAL | C72: =SUM(C60:C71) -> 3174241.2 | G72: =SUM(G60:G71) -> 456484.06 | H72: =SUM(H60:H71) -> 2701294.4 | I72: =SUM(I60:I71) -> 16462.802 | J72: =SUM(J60:J71) -> 5738298.9 | K72: =SUM(K60:K71) -> 3174241.2 | M72: =SUM(M60:M71) -> 5738298.9 | N72: =SUM(N60:N71) -> 3057320.2 | O72: =SUM(O60:O71) -> 3691794.1 | P72: =SUM(P60:P71) -> 3149875.8 | Q72: =SUM(Q60:Q71) -> 19537112 | R72: =SUM(R60:R71) -> 22686987 | S72: =AVERAGE(S60:S71) -> 3774.6671 | T72: =AVERAGE(T60:T71) -> 2329.0829
A73: Q (Ahorro capacidad → flujo BESS) y L (Ahorro distrib/umbral → flujo PV) provienen de la simulación horaria al tamaño de diseño (memoria MC-GEPP-4SITIOS-2026-07 §4); escalan con MIN(1, E_útil/E_diseño). El rasurado que los sustenta se ilustra abajo (Despacho día típico, rasurado plano). Columnas S–T: demanda de punta facturable resultante mes a mes (Reducción = Q ÷ tarifa capacidad; Después = Dmáx punta − Reducción).
A75: 4. MODELO MENSUAL AÑO 1 — OPCIÓN 2 — GD Medición Neta (vertical)
B76: Mes | C76: Gen PV (kWh) | D76: %Base | E76: %Int | F76: %Punta | G76: PV→Base | H76: PV→Int | I76: PV→Punta | J76: Ahorro energía PV $ | K76: Energía PPA (kWh) | L76: Ahorro distrib/umbral $ (motor) | M76: Ahorro PV total $ | N76: BESS despl. punta kWh | O76: Costo carga base $ | P76: Ahorro arbitraje $ | Q76: Ahorro capacidad $ (motor) | R76: Ahorro BESS bruto $ | S76: Reducción dem. punta (kW) | T76: Dem. punta después (kW)
B77: may-25 | C77: =$D$26*B$21 -> 120121.94 | D77: 0.12903271 | E77: 0.87096729 | F77: 0 | G77: =C77*D77 -> 15499.659 | H77: =C77*E77 -> 104622.28 | I77: =C77*F77 -> 0 | J77: =G77*B$14+H77*B$15+I77*B$16 -> 221407.94 | K77: =G77+H77+I77 -> 120121.94 | L77: 0 | M77: =J77+L77*$D$26/839.45 -> 221407.94 | N77: =MIN($D$30*B$11,$D$28*B$12*B$11,B$7) -> 241573.46 | O77: =N77/Supuestos!$B$14*B$14 -> 295650.69 | P77: =N77*B$16-O77 -> 253445.79 | Q77: =2375268.62832069*MIN(1,$D$30/10980.6118107843) -> 2375268.6 | R77: =P77+Q77 -> 2628714.4 | S77: =Q77/B$17 -> 5490.4272 | T77: =B$9-S77 -> 1018.5728
B78: jun-25 | C78: =$D$26*C$21 -> 112419.14 | D78: 0.16666815 | E78: 0.83333482 | F78: 0 | G78: =C78*D78 -> 18736.691 | H78: =C78*E78 -> 93682.787 | I78: =C78*F78 -> 0 | J78: =G78*C$14+H78*C$15+I78*C$16 -> 208290.72 | K78: =G78+H78+I78 -> 112419.48 | L78: 0 | M78: =J78+L78*$D$26/839.45 -> 208290.72 | N78: =MIN($D$30*C$11,$D$28*C$12*C$11,C$7) -> 230592.85 | O78: =N78/Supuestos!$B$14*C$14 -> 287832.72 | P78: =N78*C$16-O78 -> 247696.11 | Q78: =2431710.05204561*MIN(1,$D$30/10980.6118107843) -> 2431710.1 | R78: =P78+Q78 -> 2679406.2 | S78: =Q78/C$17 -> 5490.4269 | T78: =C$9-S78 -> 1143.5731
B79: jul-25 | C79: =$D$26*D$21 -> 113460.06 | D79: 0.12903226 | E79: 0.87096774 | F79: 0 | G79: =C79*D79 -> 14640.008 | H79: =C79*E79 -> 98820.054 | I79: =C79*F79 -> 0 | J79: =G79*D$14+H79*D$15+I79*D$16 -> 216450.32 | K79: =G79+H79+I79 -> 113460.06 | L79: 0 | M79: =J79+L79*$D$26/839.45 -> 216450.32 | N79: =MIN($D$30*D$11,$D$28*D$12*D$11,D$7) -> 229493 | O79: =N79/Supuestos!$B$14*D$14 -> 290045.68 | P79: =N79*D$16-O79 -> 250272.63 | Q79: =2197536.05927338*MIN(1,$D$30/10980.6118107843) -> 2197536.1 | R79: =P79+Q79 -> 2447808.7 | S79: =Q79/D$17 -> 4888.4105 | T79: =D$9-S79 -> 962.58949
B80: ago-25 | C80: =$D$26*E$21 -> 106173.64 | D80: 0.16128921 | E80: 0.83871079 | F80: 0 | G80: =C80*D80 -> 17124.662 | H80: =C80*E80 -> 89048.974 | I80: =C80*F80 -> 0 | J80: =G80*E$14+H80*E$15+I80*E$16 -> 200065.82 | K80: =G80+H80+I80 -> 106173.64 | L80: 0 | M80: =J80+L80*$D$26/839.45 -> 200065.82 | N80: =MIN($D$30*E$11,$D$28*E$12*E$11,E$7) -> 230592.85 | O80: =N80/Supuestos!$B$14*E$14 -> 291772.01 | P80: =N80*E$16-O80 -> 251827.57 | Q80: =2469970.55582272*MIN(1,$D$30/10980.6118107843) -> 2469970.6 | R80: =P80+Q80 -> 2721798.1 | S80: =Q80/E$17 -> 5486.7507 | T80: =E$9-S80 -> 867.24932
B81: sep-25 | C81: =$D$26*F$21 -> 100331.06 | D81: 0.133332 | E81: 0.866668 | F81: 0 | G81: =C81*D81 -> 13377.342 | H81: =C81*E81 -> 86953.722 | I81: =C81*F81 -> 0 | J81: =G81*F$14+H81*F$15+I81*F$16 -> 190130.82 | K81: =G81+H81+I81 -> 100331.06 | L81: 0 | M81: =J81+L81*$D$26/839.45 -> 190130.82 | N81: =MIN($D$30*F$11,$D$28*F$12*F$11,F$7) -> 208228 | O81: =N81/Supuestos!$B$14*F$14 -> 262345.59 | P81: =N81*F$16-O81 -> 225261.92 | Q81: =2106915.71437724*MIN(1,$D$30/10980.6118107843) -> 2106915.7 | R81: =P81+Q81 -> 2332177.6 | S81: =Q81/F$17 -> 4723.4967 | T81: =F$9-S81 -> 838.50327
B82: oct-25 | C82: =$D$26*G$21 -> 110545.49 | D82: 0.12852344 | E82: 0.86893462 | F82: 0.0025449589 | G82: =C82*D82 -> 14207.687 | H82: =C82*E82 -> 96056.804 | I82: =C82*F82 -> 281.33374 | J82: =G82*G$14+H82*G$15+I82*G$16 -> 210014.24 | K82: =G82+H82+I82 -> 110545.82 | L82: 0 | M82: =J82+L82*$D$26/839.45 -> 210014.24 | N82: =MIN($D$30*G$11,$D$28*G$12*G$11,G$7) -> 247787 | O82: =N82/Supuestos!$B$14*G$14 -> 312185.81 | P82: =N82*G$16-O82 -> 268057.01 | Q82: =1224502.01872863*MIN(1,$D$30/10980.6118107843) -> 1224502 | R82: =P82+Q82 -> 1492559 | S82: =Q82/G$17 -> 2745.2125 | T82: =G$9-S82 -> 1724.7875
B83: nov-25 | C83: =$D$26*H$21 -> 114635.29 | D83: 0.16925264 | E83: 0.82023285 | F83: 0.010514501 | G83: =C83*D83 -> 19402.326 | H83: =C83*E83 -> 94027.633 | I83: =C83*F83 -> 1205.3329 | J83: =G83*H$14+H83*H$15+I83*H$16 -> 208637.57 | K83: =G83+H83+I83 -> 114635.29 | L83: 0 | M83: =J83+L83*$D$26/839.45 -> 208637.57 | N83: =MIN($D$30*H$11,$D$28*H$12*H$11,H$7) -> 274515.3 | O83: =N83/Supuestos!$B$14*H$14 -> 337167.69 | P83: =N83*H$16-O83 -> 287985.99 | Q83: =1187744.00483581*MIN(1,$D$30/10980.6118107843) -> 1187744 | R83: =P83+Q83 -> 1475730 | S83: =Q83/H$17 -> 2745.2133 | T83: =H$9-S83 -> 3377.7867
B84: dic-25 | C84: =$D$26*I$21 -> 109920.94 | D84: 0.1310335 | E84: 0.85726416 | F84: 0.011699311 | G84: =C84*D84 -> 14403.326 | H84: =C84*E84 -> 94231.283 | I84: =C84*F84 -> 1285.9993 | J84: =G84*I$14+H84*I$15+I84*I$16 -> 194248.14 | K84: =G84+H84+I84 -> 109920.61 | L84: 0 | M84: =J84+L84*$D$26/839.45 -> 194248.14 | N84: =MIN($D$30*I$11,$D$28*I$12*I$11,I$7) -> 296476.52 | O84: =N84/Supuestos!$B$14*I$14 -> 349008.45 | P84: =N84*I$16-O84 -> 295353.61 | Q84: =1128364.95092183*MIN(1,$D$30/10980.6118107843) -> 1128365 | R84: =P84+Q84 -> 1423718.6 | S84: =Q84/I$17 -> 2745.2131 | T84: =I$9-S84 -> 2842.7869
B85: ene-26 | C85: =$D$26*J$21 -> 119913.75 | D85: 0.132045 | E85: 0.85676362 | F85: 0.011191385 | G85: =C85*D85 -> 15834.011 | H85: =C85*E85 -> 102737.74 | I85: =C85*F85 -> 1342.001 | J85: =G85*J$14+H85*J$15+I85*J$16 -> 207193.82 | K85: =G85+H85+I85 -> 119913.75 | L85: 0 | M85: =J85+L85*$D$26/839.45 -> 207193.82 | N85: =MIN($D$30*J$11,$D$28*J$12*J$11,J$7) -> 296476.52 | O85: =N85/Supuestos!$B$14*J$14 -> 341565.66 | P85: =N85*J$16-O85 -> 288684.13 | Q85: =1102971.68335545*MIN(1,$D$30/10980.6118107843) -> 1102971.7 | R85: =P85+Q85 -> 1391655.8 | S85: =Q85/J$17 -> 2745.213 | T85: =J$9-S85 -> 3924.787
B86: feb-26 | C86: =$D$26*K$21 -> 116770.85 | D86: 0.14507312 | E86: 0.84365981 | F86: 0.011264212 | G86: =C86*D86 -> 16940.312 | H86: =C86*E86 -> 98514.876 | I86: =C86*F86 -> 1315.3317 | J86: =G86*K$14+H86*K$15+I86*K$16 -> 200780 | K86: =G86+H86+I86 -> 116770.52 | L86: 0 | M86: =J86+L86*$D$26/839.45 -> 200780 | N86: =MIN($D$30*K$11,$D$28*K$12*K$11,K$7) -> 263534.68 | O86: =N86/Supuestos!$B$14*K$14 -> 303751.17 | P86: =N86*K$16-O86 -> 256760.74 | Q86: =1103603.58088095*MIN(1,$D$30/10980.6118107843) -> 1103603.6 | R86: =P86+Q86 -> 1360364.3 | S86: =Q86/K$17 -> 2745.2143 | T86: =K$9-S86 -> 3779.7857
B87: mar-26 | C87: =$D$26*L$21 -> 142813.95 | D87: 0.16278516 | E87: 0.82602313 | F87: 0.011191713 | G87: =C87*D87 -> 23247.992 | H87: =C87*E87 -> 117967.63 | I87: =C87*F87 -> 1598.3328 | J87: =G87*L$14+H87*L$15+I87*L$16 -> 243887.53 | K87: =G87+H87+I87 -> 142813.95 | L87: 0 | M87: =J87+L87*$D$26/839.45 -> 243887.53 | N87: =MIN($D$30*L$11,$D$28*L$12*L$11,L$7) -> 285495.91 | O87: =N87/Supuestos!$B$14*L$14 -> 329242.21 | P87: =N87*L$16-O87 -> 278321.63 | Q87: =1104289.45711356*MIN(1,$D$30/10980.6118107843) -> 1104289.5 | R87: =P87+Q87 -> 1382611.1 | S87: =Q87/L$17 -> 2745.2132 | T87: =L$9-S87 -> 3724.7868
B88: abr-26 | C88: =$D$26*M$21 -> 126521.9 | D88: 0.13437716 | E88: 0.86404472 | F88: 0.0015781182 | G88: =C88*D88 -> 17001.654 | H88: =C88*E88 -> 109320.58 | I88: =C88*F88 -> 199.66652 | J88: =G88*M$14+H88*M$15+I88*M$16 -> 218252.91 | K88: =G88+H88+I88 -> 126521.9 | L88: 0 | M88: =J88+L88*$D$26/839.45 -> 218252.91 | N88: =MIN($D$30*M$11,$D$28*M$12*M$11,M$7) -> 252554.07 | O88: =N88/Supuestos!$B$14*M$14 -> 291226.41 | P88: =N88*M$16-O88 -> 246208.65 | Q88: =1104234.98318894*MIN(1,$D$30/10980.6118107843) -> 1104235 | R88: =P88+Q88 -> 1350443.6 | S88: =Q88/M$17 -> 2745.2143 | T88: =M$9-S88 -> 3743.7857
B89: TOTAL | C89: =SUM(C77:C88) -> 1393628 | G89: =SUM(G77:G88) -> 200415.67 | H89: =SUM(H77:H88) -> 1185984.4 | I89: =SUM(I77:I88) -> 7227.9979 | J89: =SUM(J77:J88) -> 2519359.8 | K89: =SUM(K77:K88) -> 1393628 | M89: =SUM(M77:M88) -> 2519359.8 | N89: =SUM(N77:N88) -> 3057320.2 | O89: =SUM(O77:O88) -> 3691794.1 | P89: =SUM(P77:P88) -> 3149875.8 | Q89: =SUM(Q77:Q88) -> 19537112 | R89: =SUM(R77:R88) -> 22686987 | S89: =AVERAGE(S77:S88) -> 3774.6671 | T89: =AVERAGE(T77:T88) -> 2329.0829
A92: 5. PROYECCIÓN 20 AÑOS — OPCIÓN 1 — Autoconsumo (vertical, con cliff autoabasto 2032)
B93: Año | C93: Gasto CFE pleno $ | D93: Beneficio autoabasto $ | E93: Gasto real sin sistema $ | F93: Ahorro PV $ | G93: Ahorro BESS $ | H93: Pago PPA $ | I93: Pago particip. BESS $ | J93: Ahorro neto GEPP $ | K93: Acumulado GEPP $ | L93: % ahorro | M93: Flujo inv. PV $ | N93: Flujo inv. BESS $ | O93: Flujo inv. PV acum $ | P93: Flujo inv. BESS acum $
B94: Año 0 | C94: 0 | D94: 0 | E94: 0 | F94: 0 | G94: 0 | H94: 0 | I94: 0 | J94: 0 | K94: 0 | L94: 0 | M94: =-$C$34 -> -21811140 | N94: =-$C$36 -> -57366036 | O94: =M94 -> -21811140 | P94: =N94 -> -57366036
B95: =Supuestos!$B$25+1-1 -> 2026 | C95: =$C$39*(1+Supuestos!$B$9)^(1-1) -> 1.2940483e+08 | D95: =IF(B95<=Supuestos!$B$26,$C$38*(1+Supuestos!$B$9)^(1-1),0) -> 27268065 | E95: =C95-D95 -> 1.0213677e+08 | F95: =$C$43*(1+Supuestos!$B$9)^(1-1)*(1-Supuestos!$B$11)^(1-1) -> 5738298.9 | G95: =$C$44*(1+Supuestos!$B$9)^(1-1)*(1-Supuestos!$B$12)^(1-1) -> 18905823 | H95: =IF(1<=Supuestos!$B$18,$C$42*$C$31*(1+Supuestos!$B$10)^(1-1)*(1-Supuestos!$B$11)^(1-1),0) -> 3506266.8 | I95: =IF(1<=Supuestos!$B$19,G95*$C$32,0) -> 9452911.4 | J95: =F95+G95-H95-I95 -> 11684944 | K95: =K94+J95 -> 11684944 | L95: =IF(E95>0,J95/E95,0) -> 0.11440487 | M95: =IF(1<=Supuestos!$B$18,H95-Supuestos!$B$22*$C$26*(1+Supuestos!$B$9)^(1-1),0) -> 2913546.8 | N95: =IF(1<=Supuestos!$B$19,I95-Supuestos!$B$23*$C$29*(1+Supuestos!$B$9)^(1-1),0) -> 7351591.4 | O95: =O94+M95 -> -18897593 | P95: =P94+N95 -> -50014445
B96: =Supuestos!$B$25+2-1 -> 2027 | C96: =$C$39*(1+Supuestos!$B$9)^(2-1) -> 1.3716912e+08 | D96: =IF(B96<=Supuestos!$B$26,$C$38*(1+Supuestos!$B$9)^(2-1),0) -> 28904149 | E96: =C96-D96 -> 1.0826498e+08 | F96: =$C$43*(1+Supuestos!$B$9)^(2-1)*(1-Supuestos!$B$11)^(2-1) -> 6052183.9 | G96: =$C$44*(1+Supuestos!$B$9)^(2-1)*(1-Supuestos!$B$12)^(2-1) -> 19789670 | H96: =IF(2<=Supuestos!$B$18,$C$42*$C$31*(1+Supuestos!$B$10)^(2-1)*(1-Supuestos!$B$11)^(2-1),0) -> 3663172.3 | I96: =IF(2<=Supuestos!$B$19,G96*$C$32,0) -> 9894835.1 | J96: =F96+G96-H96-I96 -> 12283847 | K96: =K95+J96 -> 23968790 | L96: =IF(E96>0,J96/E96,0) -> 0.11346095 | M96: =IF(2<=Supuestos!$B$18,H96-Supuestos!$B$22*$C$26*(1+Supuestos!$B$9)^(2-1),0) -> 3034889.1 | N96: =IF(2<=Supuestos!$B$19,I96-Supuestos!$B$23*$C$29*(1+Supuestos!$B$9)^(2-1),0) -> 7667435.9 | O96: =O95+M96 -> -15862704 | P96: =P95+N96 -> -42347009
B97: =Supuestos!$B$25+3-1 -> 2028 | C97: =$C$39*(1+Supuestos!$B$9)^(3-1) -> 1.4539927e+08 | D97: =IF(B97<=Supuestos!$B$26,$C$38*(1+Supuestos!$B$9)^(3-1),0) -> 30638398 | E97: =C97-D97 -> 1.1476087e+08 | F97: =$C$43*(1+Supuestos!$B$9)^(3-1)*(1-Supuestos!$B$11)^(3-1) -> 6383238.4 | G97: =$C$44*(1+Supuestos!$B$9)^(3-1)*(1-Supuestos!$B$12)^(3-1) -> 20714837 | H97: =IF(3<=Supuestos!$B$18,$C$42*$C$31*(1+Supuestos!$B$10)^(3-1)*(1-Supuestos!$B$11)^(3-1),0) -> 3827099.2 | I97: =IF(3<=Supuestos!$B$19,G97*$C$32,0) -> 10357419 | J97: =F97+G97-H97-I97 -> 12913558 | K97: =K96+J97 -> 36882348 | L97: =IF(E97>0,J97/E97,0) -> 0.11252579 | M97: =IF(3<=Supuestos!$B$18,H97-Supuestos!$B$22*$C$26*(1+Supuestos!$B$9)^(3-1),0) -> 3161119.1 | N97: =IF(3<=Supuestos!$B$19,I97-Supuestos!$B$23*$C$29*(1+Supuestos!$B$9)^(3-1),0) -> 7996375.4 | O97: =O96+M97 -> -12701585 | P97: =P96+N97 -> -34350633
B98: =Supuestos!$B$25+4-1 -> 2029 | C98: =$C$39*(1+Supuestos!$B$9)^(4-1) -> 1.5412323e+08 | D98: =IF(B98<=Supuestos!$B$26,$C$38*(1+Supuestos!$B$9)^(4-1),0) -> 32476702 | E98: =C98-D98 -> 1.2164653e+08 | F98: =$C$43*(1+Supuestos!$B$9)^(4-1)*(1-Supuestos!$B$11)^(4-1) -> 6732401.5 | G98: =$C$44*(1+Supuestos!$B$9)^(4-1)*(1-Supuestos!$B$12)^(4-1) -> 21683256 | H98: =IF(4<=Supuestos!$B$18,$C$42*$C$31*(1+Supuestos!$B$10)^(4-1)*(1-Supuestos!$B$11)^(4-1),0) -> 3998361.9 | I98: =IF(4<=Supuestos!$B$19,G98*$C$32,0) -> 10841628 | J98: =F98+G98-H98-I98 -> 13575667 | K98: =K97+J98 -> 50458015 | L98: =IF(E98>0,J98/E98,0) -> 0.1115993 | M98: =IF(4<=Supuestos!$B$18,H98-Supuestos!$B$22*$C$26*(1+Supuestos!$B$9)^(4-1),0) -> 3292422.9 | N98: =IF(4<=Supuestos!$B$19,I98-Supuestos!$B$23*$C$29*(1+Supuestos!$B$9)^(4-1),0) -> 8338922.2 | O98: =O97+M98 -> -9409162.1 | P98: =P97+N98 -> -26011711
B99: =Supuestos!$B$25+5-1 -> 2030 | C99: =$C$39*(1+Supuestos!$B$9)^(5-1) -> 1.6337062e+08 | D99: =IF(B99<=Supuestos!$B$26,$C$38*(1+Supuestos!$B$9)^(5-1),0) -> 34425304 | E99: =C99-D99 -> 1.2894532e+08 | F99: =$C$43*(1+Supuestos!$B$9)^(5-1)*(1-Supuestos!$B$11)^(5-1) -> 7100663.9 | G99: =$C$44*(1+Supuestos!$B$9)^(5-1)*(1-Supuestos!$B$12)^(5-1) -> 22696948 | H99: =IF(5<=Supuestos!$B$18,$C$42*$C$31*(1+Supuestos!$B$10)^(5-1)*(1-Supuestos!$B$11)^(5-1),0) -> 4177288.6 | I99: =IF(5<=Supuestos!$B$19,G99*$C$32,0) -> 11348474 | J99: =F99+G99-H99-I99 -> 14271849 | K99: =K98+J99 -> 64729865 | L99: =IF(E99>0,J99/E99,0) -> 0.11068141 | M99: =IF(5<=Supuestos!$B$18,H99-Supuestos!$B$22*$C$26*(1+Supuestos!$B$9)^(5-1),0) -> 3428993.3 | N99: =IF(5<=Supuestos!$B$19,I99-Supuestos!$B$23*$C$29*(1+Supuestos!$B$9)^(5-1),0) -> 8695605.9 | O99: =O98+M99 -> -5980168.8 | P99: =P98+N99 -> -17316105
B100: =Supuestos!$B$25+6-1 -> 2031 | C100: =$C$39*(1+Supuestos!$B$9)^(6-1) -> 1.7317286e+08 | D100: =IF(B100<=Supuestos!$B$26,$C$38*(1+Supuestos!$B$9)^(6-1),0) -> 36490822 | E100: =C100-D100 -> 1.3668204e+08 | F100: =$C$43*(1+Supuestos!$B$9)^(6-1)*(1-Supuestos!$B$11)^(6-1) -> 7489070.2 | G100: =$C$44*(1+Supuestos!$B$9)^(6-1)*(1-Supuestos!$B$12)^(6-1) -> 23758030 | H100: =IF(6<=Supuestos!$B$18,$C$42*$C$31*(1+Supuestos!$B$10)^(6-1)*(1-Supuestos!$B$11)^(6-1),0) -> 4364222.3 | I100: =IF(6<=Supuestos!$B$19,G100*$C$32,0) -> 11879015 | J100: =F100+G100-H100-I100 -> 15003863 | K100: =K99+J100 -> 79733728 | L100: =IF(E100>0,J100/E100,0) -> 0.10977202 | M100: =IF(6<=Supuestos!$B$18,H100-Supuestos!$B$22*$C$26*(1+Supuestos!$B$9)^(6-1),0) -> 3571029.2 | N100: =IF(6<=Supuestos!$B$19,I100-Supuestos!$B$23*$C$29*(1+Supuestos!$B$9)^(6-1),0) -> 9066975 | O100: =O99+M100 -> -2409139.5 | P100: =P99+N100 -> -8249130.1
B101: =Supuestos!$B$25+7-1 -> 2032 | C101: =$C$39*(1+Supuestos!$B$9)^(7-1) -> 1.8356323e+08 | D101: =IF(B101<=Supuestos!$B$26,$C$38*(1+Supuestos!$B$9)^(7-1),0) -> 38680271 | E101: =C101-D101 -> 1.4488296e+08 | F101: =$C$43*(1+Supuestos!$B$9)^(7-1)*(1-Supuestos!$B$11)^(7-1) -> 7898722.3 | G101: =$C$44*(1+Supuestos!$B$9)^(7-1)*(1-Supuestos!$B$12)^(7-1) -> 24868718 | H101: =IF(7<=Supuestos!$B$18,$C$42*$C$31*(1+Supuestos!$B$10)^(7-1)*(1-Supuestos!$B$11)^(7-1),0) -> 4559521.3 | I101: =IF(7<=Supuestos!$B$19,G101*$C$32,0) -> 12434359 | J101: =F101+G101-H101-I101 -> 15773560 | K101: =K100+J101 -> 95507288 | L101: =IF(E101>0,J101/E101,0) -> 0.10887105 | M101: =IF(7<=Supuestos!$B$18,H101-Supuestos!$B$22*$C$26*(1+Supuestos!$B$9)^(7-1),0) -> 3718736.6 | N101: =IF(7<=Supuestos!$B$19,I101-Supuestos!$B$23*$C$29*(1+Supuestos!$B$9)^(7-1),0) -> 9453596.6 | O101: =O100+M101 -> 1309597.1 | P101: =P100+N101 -> 1204466.4
B102: =Supuestos!$B$25+8-1 -> 2033 | C102: =$C$39*(1+Supuestos!$B$9)^(8-1) -> 1.9457703e+08 | D102: =IF(B102<=Supuestos!$B$26,$C$38*(1+Supuestos!$B$9)^(8-1),0) -> 0 | E102: =C102-D102 -> 1.9457703e+08 | F102: =$C$43*(1+Supuestos!$B$9)^(8-1)*(1-Supuestos!$B$11)^(8-1) -> 8330782.4 | G102: =$C$44*(1+Supuestos!$B$9)^(8-1)*(1-Supuestos!$B$12)^(8-1) -> 26031331 | H102: =IF(8<=Supuestos!$B$18,$C$42*$C$31*(1+Supuestos!$B$10)^(8-1)*(1-Supuestos!$B$11)^(8-1),0) -> 4763559.8 | I102: =IF(8<=Supuestos!$B$19,G102*$C$32,0) -> 13015665 | J102: =F102+G102-H102-I102 -> 16582888 | K102: =K101+J102 -> 1.1209018e+08 | L102: =IF(E102>0,J102/E102,0) -> 0.085225314 | M102: =IF(8<=Supuestos!$B$18,H102-Supuestos!$B$22*$C$26*(1+Supuestos!$B$9)^(8-1),0) -> 3872328.1 | N102: =IF(8<=Supuestos!$B$19,I102-Supuestos!$B$23*$C$29*(1+Supuestos!$B$9)^(8-1),0) -> 9856057.1 | O102: =O101+M102 -> 5181925.2 | P102: =P101+N102 -> 11060524
B103: =Supuestos!$B$25+9-1 -> 2034 | C103: =$C$39*(1+Supuestos!$B$9)^(9-1) -> 2.0625165e+08 | D103: =IF(B103<=Supuestos!$B$26,$C$38*(1+Supuestos!$B$9)^(9-1),0) -> 0 | E103: =C103-D103 -> 2.0625165e+08 | F103: =$C$43*(1+Supuestos!$B$9)^(9-1)*(1-Supuestos!$B$11)^(9-1) -> 8786476.2 | G103: =$C$44*(1+Supuestos!$B$9)^(9-1)*(1-Supuestos!$B$12)^(9-1) -> 27248296 | H103: =IF(9<=Supuestos!$B$18,$C$42*$C$31*(1+Supuestos!$B$10)^(9-1)*(1-Supuestos!$B$11)^(9-1),0) -> 4976729.1 | I103: =IF(9<=Supuestos!$B$19,G103*$C$32,0) -> 13624148 | J103: =F103+G103-H103-I103 -> 17433895 | K103: =K102+J103 -> 1.2952407e+08 | L103: =IF(E103>0,J103/E103,0) -> 0.0845273 | M103: =IF(9<=Supuestos!$B$18,H103-Supuestos!$B$22*$C$26*(1+Supuestos!$B$9)^(9-1),0) -> 4032023.5 | N103: =IF(9<=Supuestos!$B$19,I103-Supuestos!$B$23*$C$29*(1+Supuestos!$B$9)^(9-1),0) -> 10274963 | O103: =O102+M103 -> 9213948.7 | P103: =P102+N103 -> 21335486
B104: =Supuestos!$B$25+10-1 -> 2035 | C104: =$C$39*(1+Supuestos!$B$9)^(10-1) -> 2.1862675e+08 | D104: =IF(B104<=Supuestos!$B$26,$C$38*(1+Supuestos!$B$9)^(10-1),0) -> 0 | E104: =C104-D104 -> 2.1862675e+08 | F104: =$C$43*(1+Supuestos!$B$9)^(10-1)*(1-Supuestos!$B$11)^(10-1) -> 9267096.5 | G104: =$C$44*(1+Supuestos!$B$9)^(10-1)*(1-Supuestos!$B$12)^(10-1) -> 28522153 | H104: =IF(10<=Supuestos!$B$18,$C$42*$C$31*(1+Supuestos!$B$10)^(10-1)*(1-Supuestos!$B$11)^(10-1),0) -> 5199437.8 | I104: =IF(10<=Supuestos!$B$19,G104*$C$32,0) -> 14261077 | J104: =F104+G104-H104-I104 -> 18328735 | K104: =K103+J104 -> 1.4785281e+08 | L104: =IF(E104>0,J104/E104,0) -> 0.083835742 | M104: =IF(10<=Supuestos!$B$18,H104-Supuestos!$B$22*$C$26*(1+Supuestos!$B$9)^(10-1),0) -> 4198049.8 | N104: =IF(10<=Supuestos!$B$19,I104-Supuestos!$B$23*$C$29*(1+Supuestos!$B$9)^(10-1),0) -> 10710941 | O104: =O103+M104 -> 13411998 | P104: =P103+N104 -> 32046427
B105: =Supuestos!$B$25+11-1 -> 2036 | C105: =$C$39*(1+Supuestos!$B$9)^(11-1) -> 2.3174435e+08 | D105: =IF(B105<=Supuestos!$B$26,$C$38*(1+Supuestos!$B$9)^(11-1),0) -> 0 | E105: =C105-D105 -> 2.3174435e+08 | F105: =$C$43*(1+Supuestos!$B$9)^(11-1)*(1-Supuestos!$B$11)^(11-1) -> 9774006.6 | G105: =$C$44*(1+Supuestos!$B$9)^(11-1)*(1-Supuestos!$B$12)^(11-1) -> 29855564 | H105: =IF(11<=Supuestos!$B$18,$C$42*$C$31*(1+Supuestos!$B$10)^(11-1)*(1-Supuestos!$B$11)^(11-1),0) -> 5432112.6 | I105: =IF(11<=Supuestos!$B$19,G105*$C$32,0) -> 14927782 | J105: =F105+G105-H105-I105 -> 19269676 | K105: =K104+J105 -> 1.6712248e+08 | L105: =IF(E105>0,J105/E105,0) -> 0.083150575 | M105: =IF(11<=Supuestos!$B$18,H105-Supuestos!$B$22*$C$26*(1+Supuestos!$B$9)^(11-1),0) -> 4370641.4 | N105: =IF(11<=Supuestos!$B$19,I105-Supuestos!$B$23*$C$29*(1+Supuestos!$B$9)^(11-1),0) -> 11164638 | O105: =O104+M105 -> 17782640 | P105: =P104+N105 -> 43211065
B106: =Supuestos!$B$25+12-1 -> 2037 | C106: =$C$39*(1+Supuestos!$B$9)^(12-1) -> 2.4564901e+08 | D106: =IF(B106<=Supuestos!$B$26,$C$38*(1+Supuestos!$B$9)^(12-1),0) -> 0 | E106: =C106-D106 -> 2.4564901e+08 | F106: =$C$43*(1+Supuestos!$B$9)^(12-1)*(1-Supuestos!$B$11)^(12-1) -> 10308645 | G106: =$C$44*(1+Supuestos!$B$9)^(12-1)*(1-Supuestos!$B$12)^(12-1) -> 31251312 | H106: =IF(12<=Supuestos!$B$18,$C$42*$C$31*(1+Supuestos!$B$10)^(12-1)*(1-Supuestos!$B$11)^(12-1),0) -> 5675199.6 | I106: =IF(12<=Supuestos!$B$19,G106*$C$32,0) -> 15625656 | J106: =F106+G106-H106-I106 -> 20259101 | K106: =K105+J106 -> 1.8738158e+08 | L106: =IF(E106>0,J106/E106,0) -> 0.082471738 | M106: =IF(12<=Supuestos!$B$18,H106-Supuestos!$B$22*$C$26*(1+Supuestos!$B$9)^(12-1),0) -> 4550040.1 | N106: =IF(12<=Supuestos!$B$19,I106-Supuestos!$B$23*$C$29*(1+Supuestos!$B$9)^(12-1),0) -> 11636723 | O106: =O105+M106 -> 22332680 | P106: =P105+N106 -> 54847788
B107: =Supuestos!$B$25+13-1 -> 2038 | C107: =$C$39*(1+Supuestos!$B$9)^(13-1) -> 2.6038795e+08 | D107: =IF(B107<=Supuestos!$B$26,$C$38*(1+Supuestos!$B$9)^(13-1),0) -> 0 | E107: =C107-D107 -> 2.6038795e+08 | F107: =$C$43*(1+Supuestos!$B$9)^(13-1)*(1-Supuestos!$B$11)^(13-1) -> 10872528 | G107: =$C$44*(1+Supuestos!$B$9)^(13-1)*(1-Supuestos!$B$12)^(13-1) -> 32712311 | H107: =IF(13<=Supuestos!$B$18,$C$42*$C$31*(1+Supuestos!$B$10)^(13-1)*(1-Supuestos!$B$11)^(13-1),0) -> 5929164.8 | I107: =IF(13<=Supuestos!$B$19,G107*$C$32,0) -> 16356155 | J107: =F107+G107-H107-I107 -> 21299518 | K107: =K106+J107 -> 2.086811e+08 | L107: =IF(E107>0,J107/E107,0) -> 0.081799169 | M107: =IF(13<=Supuestos!$B$18,H107-Supuestos!$B$22*$C$26*(1+Supuestos!$B$9)^(13-1),0) -> 4736495.7 | N107: =IF(13<=Supuestos!$B$19,I107-Supuestos!$B$23*$C$29*(1+Supuestos!$B$9)^(13-1),0) -> 12127887 | O107: =O106+M107 -> 27069176 | P107: =P106+N107 -> 66975675
...

Sheet Tapa
A1: GEPP Proplasa · Tapa — Propuesta Solar + BESS | GDMTH (V. de México Norte) | Cuautitlán Izcalli, Méx. (MXN sin IVA)
A3: 1. DATOS BASE — últimos 12 meses reales (recibos CFE, sin IVA)
A4: Mes | B4: may-25 | C4: jun-25 | D4: jul-25 | E4: ago-25 | F4: sep-25 | G4: oct-25 | H4: nov-25 | I4: dic-25 | J4: ene-26 | K4: feb-26 | L4: mar-26 | M4: abr-26 | N4: TOTAL
A5: Consumo Base (kWh) | B5: 960467 | C5: 923339 | D5: 765377 | E5: 900504 | F5: 746286 | G5: 754528 | H5: 756600 | I5: 741947 | J5: 881325 | K5: 805606 | L5: 960995 | M5: 891289 | N5: =SUM(B5:M5) -> 10088263
A6: Consumo Intermedia (kWh) | B6: 1696392 | C6: 1593739 | D6: 1464549 | E6: 1602297 | F6: 1358643 | G6: 1417944 | H6: 1150215 | I6: 1178280 | J6: 1481542 | K6: 1252899 | L6: 1426117 | M6: 1620825 | N6: =SUM(B6:M6) -> 17243442
A7: Consumo Punta (kWh) | B7: 162699 | C7: 157968 | D7: 150284 | E7: 152370 | F7: 130996 | G7: 176270 | H7: 278429 | I7: 273186 | J7: 365971 | K7: 303074 | L7: 335764 | M7: 207717 | N7: =SUM(B7:M7) -> 2694728
A8: Consumo Total (kWh) | B8: =SUM(B5:B7) -> 2819558 | C8: =SUM(C5:C7) -> 2675046 | D8: =SUM(D5:D7) -> 2380210 | E8: =SUM(E5:E7) -> 2655171 | F8: =SUM(F5:F7) -> 2235925 | G8: =SUM(G5:G7) -> 2348742 | H8: =SUM(H5:H7) -> 2185244 | I8: =SUM(I5:I7) -> 2193413 | ... M8: =SUM(M5:M7) -> 2719831 | N8: =SUM(B8:M8) -> 30026433
A9: Dem. máx. en punta (kW) | B9: 4081 | C9: 4146 | D9: 3935 | E9: 3868 | F9: 3761 | G9: 3121 | H9: 3661 | I9: 3968 | J9: 4272 | K9: 4136 | L9: 4183 | M9: 4106 | N9: =MAX(B9:M9) -> 4272
A10: Dem. máx. mensual (kW) | B10: 4308 | C10: 4228 | D10: 3987 | E10: 4012 | F10: 3791 | G10: 3433 | H10: 3772 | I10: 3985 | J10: 4350 | K10: 4251 | L10: 4350 | M10: 4250 | N10: =MAX(B10:M10) -> 4350
A11: Días con punta | B11: 22 | C11: 21 | D11: 23 | E11: 21 | F11: 22 | G11: 23 | H11: 25 | I11: 27 | J11: 27 | K11: 24 | L11: 26 | M11: 23
A12: Horas punta/día | B12: 2 | C12: 2 | D12: 2 | E12: 2 | F12: 2 | G12: 2.43 | H12: 3.6 | I12: 3.7 | J12: 3.63 | K12: 3.67 | L12: 3.69 | M12: 2.26
A13: Días del mes | B13: 31 | C13: 30 | D13: 31 | E13: 31 | F13: 30 | G13: 31 | H13: 30 | I13: 31 | J13: 31 | K13: 28 | L13: 31 | M13: 30
A14: Tarifa Base ($/kWh) | B14: 1.1749 | C14: 1.1983 | D14: 1.2133 | E14: 1.2147 | F14: 1.2095 | G14: 1.2095 | H14: 1.1791 | I14: 1.1301 | J14: 1.106 | K14: 1.1065 | L14: 1.1071 | M14: 1.107
A15: Tarifa Intermedia ($/kWh) | B15: 1.9422 | C15: 1.9837 | D15: 2.0106 | E15: 2.0131 | F15: 2.0005 | G15: 2.0006 | H15: 1.9464 | I15: 1.859 | J15: 1.8185 | K15: 1.8194 | L15: 1.8204 | M15: 1.8204
A16: Tarifa Punta ($/kWh) | B16: 2.273 | C16: 2.3224 | D16: 2.3544 | E16: 2.3574 | F16: 2.3417 | G16: 2.3417 | H16: 2.2773 | I16: 2.1734 | J16: 2.1258 | K16: 2.1269 | L16: 2.1281 | M16: 2.128
A17: Tarifa Capacidad ($/kW·mes) | B17: 432.62 | C17: 442.9 | D17: 449.54 | E17: 450.17 | F17: 446.05 | G17: 446.05 | H17: 432.66 | I17: 411.03 | J17: 401.78 | K17: 402.01 | L17: 402.26 | M17: 402.24
A18: Tarifa Distribución ($/kW·mes) | B18: 91.12 | C18: 91.12 | D18: 91.12 | E18: 91.12 | F18: 91.12 | G18: 91.12 | H18: 91.12 | I18: 91.12 | J18: 86.15 | K18: 86.15 | L18: 86.15 | M18: 86.15
A19: Gasto actual facturado ($ MXN) | B19: 6541898 | C19: 6373529.9 | D19: 4791535.4 | E19: 5398272.1 | F19: 4614409.2 | G19: 4790415.4 | H19: 4274575.5 | I19: 4286090.2 | J19: 5344856.9 | K19: 4464979.3 | L19: 6189354.3 | M19: 6453686.4 | N19: =SUM(B19:M19) -> 63523603
A20: Umbral de demanda (kW) | B20: =B8/(24*B13*Supuestos!$B$15) -> 6648.6465 | C20: =C8/(24*C13*Supuestos!$B$15) -> 6518.1433 | D20: =D8/(24*D13*Supuestos!$B$15) -> 5612.6438 | E20: =E8/(24*E13*Supuestos!$B$15) -> 6261.0144 | F20: =F8/(24*F13*Supuestos!$B$15) -> 5448.1603 | G20: =G8/(24*G13*Supuestos!$B$15) -> 5538.4409 | H20: =H8/(24*H13*Supuestos!$B$15) -> 5324.6686 | I20: =I8/(24*I13*Supuestos!$B$15) -> 5172.168 | ... M20: =M8/(24*M13*Supuestos!$B$15) -> 6627.2685
A21: Yield PV (kWh/kWp) | B21: 143.096 | C21: 133.92 | D21: 135.16 | E21: 126.48 | F21: 119.52 | G21: 131.688 | H21: 136.56 | I21: 130.944 | J21: 142.848 | K21: 139.104 | L21: 170.128 | M21: 150.72 | N21: =SUM(B21:M21) -> 1660.168
A23: 2. SISTEMA PROPUESTO — Opción 1 y Opción 2 (amarillo = editable)
A24: Concepto | C24: OPCIÓN 1 — Autoconsumo | D24: OPCIÓN 2 — GD Medición Neta
A25: Esquema legal | C25: Autoconsumo interconectado (permiso CNE simplificado) | D25: Generación Distribuida <0.7 MW (sin permiso)
A26: Potencia PV (kWp DC) | C26: 1255.7 | D26: 839.45
A27: Superficie requerida (m²) | C27: =C26*Supuestos!$B$24 -> 5022.8 | D27: =D26*Supuestos!$B$24 -> 3357.8
A28: BESS potencia (kW) | C28: 3870 | D28: 3870
A29: BESS capacidad (kWh) | C29: 7741 | D29: 7741
A30: Energía útil BESS (kWh) | C30: =C29*Supuestos!$B$13*SQRT(Supuestos!$B$14) -> 7281.216 | D30: =D29*Supuestos!$B$13*SQRT(Supuestos!$B$14) -> 7281.216
A31: Precio PPA (MXN/kWh, año 1) | C31: 1.3526645 | D31: 1.6148562
A32: Participación inversionista BESS (%) | C32: =Supuestos!$B$17 -> 0.5 | D32: =Supuestos!$B$17 -> 0.5
A33: CAPEX PV (USD) | C33: =C26*1000*Supuestos!$B$5 -> 816205 | D33: =D26*1000*Supuestos!$B$5 -> 545642.5
A34: CAPEX PV (MXN) | C34: =C33*Supuestos!$B$4 -> 14324398 | D34: =D33*Supuestos!$B$4 -> 9576025.9
A35: CAPEX BESS (USD) | C35: =C29*1000*Supuestos!$B$7 -> 2167480 | D35: =D29*1000*Supuestos!$B$7 -> 2167480
A36: CAPEX BESS (MXN) | C36: =C35*Supuestos!$B$4 -> 38039274 | D36: =D35*Supuestos!$B$4 -> 38039274
A37: — Autoabasto TALA / ENEL (vence 2032) —
A38: Beneficio autoabasto actual ($/año) | C38: 22509980 | D38: =C38 -> 22509980
A39: Gasto sin autoabasto — CFE pleno ($/año) | C39: =$N$19+C38 -> 86033582 | D39: =$N$19+D38 -> 86033582
A40: Gasto real hoy (con autoabasto) ($/año) | C40: =C39-C38 -> 63523603 | D40: =D39-D38 -> 63523603
A41: Generación PV año 1 (kWh) | C41: =C72 -> 2084673 | D41: =C89 -> 1393628
A42: Energía facturada al PPA (kWh) | C42: =K72 -> 2084673 | D42: =K89 -> 1393628
A43: Ahorro bruto PV año 1 ($) | C43: =M72 -> 3768609.8 | D43: =M89 -> 2519359.8
A44: Ahorro bruto BESS año 1 c/merma ($) | C44: =R72*(12-Supuestos!$B$16)/12 -> 12530013 | D44: =R89*(12-Supuestos!$B$16)/12 -> 12530013
A45: Ahorro bruto total ($) | C45: =C43+C44 -> 16298623 | D45: =D43+D44 -> 15049373
A46: Pago PPA año 1 ($) | C46: =C42*C31 -> 2302729.7 | D46: =D42*D31 -> 1539401.5
A47: Pago participación BESS ($) | C47: =C44*C32 -> 6265006.5 | D47: =D44*D32 -> 6265006.5
A48: AHORRO NETO GEPP año 1 ($) | C48: =C45-C46-C47 -> 7730886.6 | D48: =D45-D46-D47 -> 7244964.9
A49: % ahorro bruto (vs gasto real hoy) | C49: =C45/$N$19 -> 0.25657586 | D49: =D45/$N$19 -> 0.23690994
A50: % ahorro neto (vs gasto real hoy) | C50: =C48/$N$19 -> 0.12170101 | D50: =D48/$N$19 -> 0.11405154
A51: TIR inversionista PV | C51: =IRR(M94:M114) -> 0.14109903 | D51: =IRR(M119:M139) -> 0.14109903
A52: TIR inversionista BESS | C52: =IRR(N94:N114) -> 0.13479034 | D52: =IRR(N119:N139) -> 0.13479034
A53: Participación req. p/ TIR BESS 16% | C53: 0.5655 | D53: 0.5655
A54: Payback simple inversionista PV (años) | C54: =COUNTIF(O94:O114,"<0") -> 7 | D54: =COUNTIF(O119:O139,"<0") -> 7
A55: VAN GEPP del ahorro neto 20a (@WACC) | C55: =NPV(Supuestos!$B$21,J95:J114) -> 92850208 | D55: =NPV(Supuestos!$B$21,J120:J139) -> 86043252
A58: 3. MODELO MENSUAL AÑO 1 — OPCIÓN 1 — Autoconsumo (vertical)
B59: Mes | C59: Gen PV (kWh) | D59: %Base | E59: %Int | F59: %Punta | G59: PV→Base | H59: PV→Int | I59: PV→Punta | J59: Ahorro energía PV $ | K59: Energía PPA (kWh) | L59: Ahorro distrib/umbral $ (motor) | M59: Ahorro PV total $ | N59: BESS despl. punta kWh | O59: Costo carga base $ | P59: Ahorro arbitraje $ | Q59: Ahorro capacidad $ (motor) | R59: Ahorro BESS bruto $ | S59: Reducción dem. punta (kW) | T59: Dem. punta después (kW)
B60: may-25 | C60: =$C$26*B$21 -> 179685.65 | D60: 0.12903214 | E60: 0.87096786 | F60: 0 | G60: =C60*D60 -> 23185.224 | H60: =C60*E60 -> 156500.42 | I60: =C60*F60 -> 0 | J60: =G60*B$14+H60*B$15+I60*B$16 -> 331195.44 | K60: =G60+H60+I60 -> 179685.65 | L60: 0 | M60: =J60+L60*$C$26/1255.7 -> 331195.44 | N60: =MIN($C$30*B$11,$C$28*B$12*B$11,B$7) -> 160186.75 | O60: =N60/Supuestos!$B$14*B$14 -> 196045.22 | P60: =N60*B$16-O60 -> 168059.26 | Q60: =1574939.67419487*MIN(1,$C$30/7281.21603797167) -> 1574939.7 | R60: =P60+Q60 -> 1742998.9 | S60: =Q60/B$17 -> 3640.4689 | T60: =B$9-S60 -> 440.53106
B61: jun-25 | C61: =$C$26*C$21 -> 168163.34 | D61: 0.1666657 | E61: 0.83333236 | F61: 0 | G61: =C61*D61 -> 28027.061 | H61: =C61*E61 -> 140135.96 | I61: =C61*F61 -> 0 | J61: =G61*C$14+H61*C$15+I61*C$16 -> 311572.52 | K61: =G61+H61+I61 -> 168163.02 | L61: 0 | M61: =J61+L61*$C$26/1255.7 -> 311572.52 | N61: =MIN($C$30*C$11,$C$28*C$12*C$11,C$7) -> 152905.54 | O61: =N61/Supuestos!$B$14*C$14 -> 190861.15 | P61: =N61*C$16-O61 -> 164246.67 | Q61: =1612363.58340353*MIN(1,$C$30/7281.21603797167) -> 1612363.6 | R61: =P61+Q61 -> 1776610.3 | S61: =Q61/C$17 -> 3640.4687 | T61: =C$9-S61 -> 505.53131
B62: jul-25 | C62: =$C$26*D$21 -> 169720.41 | D62: 0.12903269 | E62: 0.87096923 | F62: 0 | G62: =C62*D62 -> 21899.482 | H62: =C62*E62 -> 147821.26 | I62: =C62*F62 -> 0 | J62: =G62*D$14+H62*D$15+I62*D$16 -> 323780.06 | K62: =G62+H62+I62 -> 169720.74 | L62: 0 | M62: =J62+L62*$C$26/1255.7 -> 323780.06 | N62: =MIN($C$30*D$11,$C$28*D$12*D$11,D$7) -> 150284 | O62: =N62/Supuestos!$B$14*D$14 -> 189937.06 | P62: =N62*D$16-O62 -> 163891.59 | Q62: =1457092.76161763*MIN(1,$C$30/7281.21603797167) -> 1457092.8 | R62: =P62+Q62 -> 1620984.4 | S62: =Q62/D$17 -> 3241.2972 | T62: =D$9-S62 -> 693.70276
B63: ago-25 | C63: =$C$26*E$21 -> 158820.94 | D63: 0.16129118 | E63: 0.83870882 | F63: 0 | G63: =C63*D63 -> 25616.417 | H63: =C63*E63 -> 133204.52 | I63: =C63*F63 -> 0 | J63: =G63*E$14+H63*E$15+I63*E$16 -> 299270.28 | K63: =G63+H63+I63 -> 158820.94 | L63: 0 | M63: =J63+L63*$C$26/1255.7 -> 299270.28 | N63: =MIN($C$30*E$11,$C$28*E$12*E$11,E$7) -> 152370 | O63: =N63/Supuestos!$B$14*E$14 -> 192795.67 | P63: =N63*E$16-O63 -> 166401.37 | Q63: =1637732.497317*MIN(1,$C$30/7281.21603797167) -> 1637732.5 | R63: =P63+Q63 -> 1804133.9 | S63: =Q63/E$17 -> 3638.0312 | T63: =E$9-S63 -> 229.96882
B64: sep-25 | C64: =$C$26*F$21 -> 150081.26 | D64: 0.13333304 | E64: 0.86666478 | F64: 0 | G64: =C64*D64 -> 20010.792 | H64: =C64*E64 -> 130070.15 | I64: =C64*F64 -> 0 | J64: =G64*F$14+H64*F$15+I64*F$16 -> 284408.38 | K64: =G64+H64+I64 -> 150080.94 | L64: 0 | M64: =J64+L64*$C$26/1255.7 -> 284408.38 | N64: =MIN($C$30*F$11,$C$28*F$12*F$11,F$7) -> 130996 | O64: =N64/Supuestos!$B$14*F$14 -> 165041.31 | P64: =N64*F$16-O64 -> 141712.02 | Q64: =1397006.26244677*MIN(1,$C$30/7281.21603797167) -> 1397006.3 | R64: =P64+Q64 -> 1538718.3 | S64: =Q64/F$17 -> 3131.9499 | T64: =F$9-S64 -> 629.05008
B65: oct-25 | C65: =$C$26*G$21 -> 165360.62 | D65: 0.12852419 | E65: 0.86893267 | F65: 0.0025431387 | G65: =C65*D65 -> 21252.84 | H65: =C65*E65 -> 143687.25 | I65: =C65*F65 -> 420.53499 | J65: =G65*G$14+H65*G$15+I65*G$16 -> 314150.78 | K65: =G65+H65+I65 -> 165360.62 | L65: 0 | M65: =J65+L65*$C$26/1255.7 -> 314150.78 | N65: =MIN($C$30*G$11,$C$28*G$12*G$11,G$7) -> 167467.97 | O65: =N65/Supuestos!$B$14*G$14 -> 210992.2 | P65: =N65*G$16-O65 -> 181167.55 | Q65: =811915.245052052*MIN(1,$C$30/7281.21603797167) -> 811915.25 | R65: =P65+Q65 -> 993082.79 | S65: =Q65/G$17 -> 1820.2337 | T65: =G$9-S65 -> 1300.7663
B66: nov-25 | C66: =$C$26*H$21 -> 171478.39 | D66: 0.16925416 | E66: 0.82023227 | F66: 0.010513579 | G66: =C66*D66 -> 29023.431 | H66: =C66*E66 -> 140652.11 | I66: =C66*F66 -> 1802.8516 | J66: =G66*H$14+H66*H$15+I66*H$16 -> 312092.43 | K66: =G66+H66+I66 -> 171478.39 | L66: 0 | M66: =J66+L66*$C$26/1255.7 -> 312092.43 | N66: =MIN($C$30*H$11,$C$28*H$12*H$11,H$7) -> 182030.4 | O66: =N66/Supuestos!$B$14*H$14 -> 223575.05 | P66: =N66*H$16-O66 -> 190962.78 | Q66: =787542.568322288*MIN(1,$C$30/7281.21603797167) -> 787542.57 | R66: =P66+Q66 -> 978505.35 | S66: =Q66/H$17 -> 1820.2343 | T66: =H$9-S66 -> 1840.7657
B67: dic-25 | C67: =$C$26*I$21 -> 164426.38 | D67: 0.13103435 | E67: 0.85726503 | F67: 0.011700629 | G67: =C67*D67 -> 21545.503 | H67: =C67*E67 -> 140956.99 | I67: =C67*F67 -> 1923.8921 | J67: =G67*I$14+H67*I$15+I67*I$16 -> 290569 | K67: =G67+H67+I67 -> 164426.38 | L67: 0 | M67: =J67+L67*$C$26/1255.7 -> 290569 | N67: =MIN($C$30*I$11,$C$28*I$12*I$11,I$7) -> 196592.83 | O67: =N67/Supuestos!$B$14*I$14 -> 231426.63 | P67: =N67*I$16-O67 -> 195848.24 | Q67: =748170.841389915*MIN(1,$C$30/7281.21603797167) -> 748170.84 | R67: =P67+Q67 -> 944019.08 | S67: =Q67/I$17 -> 1820.2341 | T67: =I$9-S67 -> 2147.7659
B68: ene-26 | C68: =$C$26*J$21 -> 179374.23 | D68: 0.13204428 | E68: 0.85676272 | F68: 0.011191179 | G68: =C68*D68 -> 23685.341 | H68: =C68*E68 -> 153681.16 | I68: =C68*F68 -> 2007.4092 | J68: =G68*J$14+H68*J$15+I68*J$16 -> 309932.52 | K68: =G68+H68+I68 -> 179373.91 | L68: 0 | M68: =J68+L68*$C$26/1255.7 -> 309932.52 | N68: =MIN($C$30*J$11,$C$28*J$12*J$11,J$7) -> 196592.83 | O68: =N68/Supuestos!$B$14*J$14 -> 226491.33 | P68: =N68*J$16-O68 -> 191425.72 | Q68: =731333.644926788*MIN(1,$C$30/7281.21603797167) -> 731333.64 | R68: =P68+Q68 -> 922759.36 | S68: =Q68/J$17 -> 1820.2341 | T68: =J$9-S68 -> 2451.7659
B69: feb-26 | C69: =$C$26*K$21 -> 174672.89 | D69: 0.14507552 | E69: 0.84366181 | F69: 0.011264538 | G69: =C69*D69 -> 25340.761 | H69: =C69*E69 -> 147364.85 | I69: =C69*F69 -> 1967.6095 | J69: =G69*K$14+H69*K$15+I69*K$16 -> 300340.07 | K69: =G69+H69+I69 -> 174673.22 | L69: 0 | M69: =J69+L69*$C$26/1255.7 -> 300340.07 | N69: =MIN($C$30*K$11,$C$28*K$12*K$11,K$7) -> 174749.18 | O69: =N69/Supuestos!$B$14*K$14 -> 201416.64 | P69: =N69*K$16-O69 -> 170257.4 | Q69: =731752.629319146*MIN(1,$C$30/7281.21603797167) -> 731752.63 | R69: =P69+Q69 -> 902010.03 | S69: =Q69/K$17 -> 1820.2349 | T69: =K$9-S69 -> 2315.7651
B70: mar-26 | C70: =$C$26*L$21 -> 213629.73 | D70: 0.16278409 | E70: 0.82602328 | F70: 0.011192628 | G70: =C70*D70 -> 34775.522 | H70: =C70*E70 -> 176463.13 | I70: =C70*F70 -> 2391.0781 | J70: =G70*L$14+H70*L$15+I70*L$16 -> 364821.92 | K70: =G70+H70+I70 -> 213629.73 | L70: 0 | M70: =J70+L70*$C$26/1255.7 -> 364821.92 | N70: =MIN($C$30*L$11,$C$28*L$12*L$11,L$7) -> 189311.62 | O70: =N70/Supuestos!$B$14*L$14 -> 218319.68 | P70: =N70*L$16-O70 -> 184554.37 | Q70: =732207.404697999*MIN(1,$C$30/7281.21603797167) -> 732207.4 | R70: =P70+Q70 -> 916761.78 | S70: =Q70/L$17 -> 1820.2342 | T70: =L$9-S70 -> 2362.7658
B71: abr-26 | C71: =$C$26*M$21 -> 189259.1 | D71: 0.13437717 | E71: 0.86404726 | F71: 0.0015772979 | G71: =C71*D71 -> 25432.102 | H71: =C71*E71 -> 163528.81 | I71: =C71*F71 -> 298.518 | J71: =G71*M$14+H71*M$15+I71*M$16 -> 326476.43 | K71: =G71+H71+I71 -> 189259.43 | L71: 0 | M71: =J71+L71*$C$26/1255.7 -> 326476.43 | N71: =MIN($C$30*M$11,$C$28*M$12*M$11,M$7) -> 167467.97 | O71: =N71/Supuestos!$B$14*M$14 -> 193111.5 | P71: =N71*M$16-O71 -> 163260.34 | Q71: =732171.28535383*MIN(1,$C$30/7281.21603797167) -> 732171.29 | R71: =P71+Q71 -> 895431.62 | S71: =Q71/M$17 -> 1820.2349 | T71: =M$9-S71 -> 2285.7651
B72: TOTAL | C72: =SUM(C60:C71) -> 2084673 | G72: =SUM(G60:G71) -> 299794.47 | H72: =SUM(H60:H71) -> 1774066.6 | I72: =SUM(I60:I71) -> 10811.893 | J72: =SUM(J60:J71) -> 3768609.8 | K72: =SUM(K60:K71) -> 2084673 | M72: =SUM(M60:M71) -> 3768609.8 | N72: =SUM(N60:N71) -> 2020955.1 | O72: =SUM(O60:O71) -> 2440013.4 | P72: =SUM(P60:P71) -> 2081787.3 | Q72: =SUM(Q60:Q71) -> 12954228 | R72: =SUM(R60:R71) -> 15036016 | S72: =AVERAGE(S60:S71) -> 2502.8213 | T72: =AVERAGE(T60:T71) -> 1433.6787
A73: Q (Ahorro capacidad → flujo BESS) y L (Ahorro distrib/umbral → flujo PV) provienen de la simulación horaria al tamaño de diseño (memoria MC-GEPP-4SITIOS-2026-07 §4); escalan con MIN(1, E_útil/E_diseño). El rasurado que los sustenta se ilustra abajo (Despacho día típico, rasurado plano). Columnas S–T: demanda de punta facturable resultante mes a mes (Reducción = Q ÷ tarifa capacidad; Después = Dmáx punta − Reducción).
A75: 4. MODELO MENSUAL AÑO 1 — OPCIÓN 2 — GD Medición Neta (vertical)
B76: Mes | C76: Gen PV (kWh) | D76: %Base | E76: %Int | F76: %Punta | G76: PV→Base | H76: PV→Int | I76: PV→Punta | J76: Ahorro energía PV $ | K76: Energía PPA (kWh) | L76: Ahorro distrib/umbral $ (motor) | M76: Ahorro PV total $ | N76: BESS despl. punta kWh | O76: Costo carga base $ | P76: Ahorro arbitraje $ | Q76: Ahorro capacidad $ (motor) | R76: Ahorro BESS bruto $ | S76: Reducción dem. punta (kW) | T76: Dem. punta después (kW)
B77: may-25 | C77: =$D$26*B$21 -> 120121.94 | D77: 0.12903271 | E77: 0.87096729 | F77: 0 | G77: =C77*D77 -> 15499.659 | H77: =C77*E77 -> 104622.28 | I77: =C77*F77 -> 0 | J77: =G77*B$14+H77*B$15+I77*B$16 -> 221407.94 | K77: =G77+H77+I77 -> 120121.94 | L77: 0 | M77: =J77+L77*$D$26/839.45 -> 221407.94 | N77: =MIN($D$30*B$11,$D$28*B$12*B$11,B$7) -> 160186.75 | O77: =N77/Supuestos!$B$14*B$14 -> 196045.22 | P77: =N77*B$16-O77 -> 168059.26 | Q77: =1574939.67419487*MIN(1,$D$30/7281.21603797167) -> 1574939.7 | R77: =P77+Q77 -> 1742998.9 | S77: =Q77/B$17 -> 3640.4689 | T77: =B$9-S77 -> 440.53106
B78: jun-25 | C78: =$D$26*C$21 -> 112419.14 | D78: 0.16666815 | E78: 0.83333482 | F78: 0 | G78: =C78*D78 -> 18736.691 | H78: =C78*E78 -> 93682.787 | I78: =C78*F78 -> 0 | J78: =G78*C$14+H78*C$15+I78*C$16 -> 208290.72 | K78: =G78+H78+I78 -> 112419.48 | L78: 0 | M78: =J78+L78*$D$26/839.45 -> 208290.72 | N78: =MIN($D$30*C$11,$D$28*C$12*C$11,C$7) -> 152905.54 | O78: =N78/Supuestos!$B$14*C$14 -> 190861.15 | P78: =N78*C$16-O78 -> 164246.67 | Q78: =1612363.58340353*MIN(1,$D$30/7281.21603797167) -> 1612363.6 | R78: =P78+Q78 -> 1776610.3 | S78: =Q78/C$17 -> 3640.4687 | T78: =C$9-S78 -> 505.53131
B79: jul-25 | C79: =$D$26*D$21 -> 113460.06 | D79: 0.12903226 | E79: 0.87096774 | F79: 0 | G79: =C79*D79 -> 14640.008 | H79: =C79*E79 -> 98820.054 | I79: =C79*F79 -> 0 | J79: =G79*D$14+H79*D$15+I79*D$16 -> 216450.32 | K79: =G79+H79+I79 -> 113460.06 | L79: 0 | M79: =J79+L79*$D$26/839.45 -> 216450.32 | N79: =MIN($D$30*D$11,$D$28*D$12*D$11,D$7) -> 150284 | O79: =N79/Supuestos!$B$14*D$14 -> 189937.06 | P79: =N79*D$16-O79 -> 163891.59 | Q79: =1457092.76161763*MIN(1,$D$30/7281.21603797167) -> 1457092.8 | R79: =P79+Q79 -> 1620984.4 | S79: =Q79/D$17 -> 3241.2972 | T79: =D$9-S79 -> 693.70276
B80: ago-25 | C80: =$D$26*E$21 -> 106173.64 | D80: 0.16128921 | E80: 0.83871079 | F80: 0 | G80: =C80*D80 -> 17124.662 | H80: =C80*E80 -> 89048.974 | I80: =C80*F80 -> 0 | J80: =G80*E$14+H80*E$15+I80*E$16 -> 200065.82 | K80: =G80+H80+I80 -> 106173.64 | L80: 0 | M80: =J80+L80*$D$26/839.45 -> 200065.82 | N80: =MIN($D$30*E$11,$D$28*E$12*E$11,E$7) -> 152370 | O80: =N80/Supuestos!$B$14*E$14 -> 192795.67 | P80: =N80*E$16-O80 -> 166401.37 | Q80: =1637732.497317*MIN(1,$D$30/7281.21603797167) -> 1637732.5 | R80: =P80+Q80 -> 1804133.9 | S80: =Q80/E$17 -> 3638.0312 | T80: =E$9-S80 -> 229.96882
B81: sep-25 | C81: =$D$26*F$21 -> 100331.06 | D81: 0.133332 | E81: 0.866668 | F81: 0 | G81: =C81*D81 -> 13377.342 | H81: =C81*E81 -> 86953.722 | I81: =C81*F81 -> 0 | J81: =G81*F$14+H81*F$15+I81*F$16 -> 190130.82 | K81: =G81+H81+I81 -> 100331.06 | L81: 0 | M81: =J81+L81*$D$26/839.45 -> 190130.82 | N81: =MIN($D$30*F$11,$D$28*F$12*F$11,F$7) -> 130996 | O81: =N81/Supuestos!$B$14*F$14 -> 165041.31 | P81: =N81*F$16-O81 -> 141712.02 | Q81: =1397006.26244677*MIN(1,$D$30/7281.21603797167) -> 1397006.3 | R81: =P81+Q81 -> 1538718.3 | S81: =Q81/F$17 -> 3131.9499 | T81: =F$9-S81 -> 629.05008
B82: oct-25 | C82: =$D$26*G$21 -> 110545.49 | D82: 0.12852344 | E82: 0.86893462 | F82: 0.0025449589 | G82: =C82*D82 -> 14207.687 | H82: =C82*E82 -> 96056.804 | I82: =C82*F82 -> 281.33374 | J82: =G82*G$14+H82*G$15+I82*G$16 -> 210014.24 | K82: =G82+H82+I82 -> 110545.82 | L82: 0 | M82: =J82+L82*$D$26/839.45 -> 210014.24 | N82: =MIN($D$30*G$11,$D$28*G$12*G$11,G$7) -> 167467.97 | O82: =N82/Supuestos!$B$14*G$14 -> 210992.2 | P82: =N82*G$16-O82 -> 181167.55 | Q82: =811915.245052052*MIN(1,$D$30/7281.21603797167) -> 811915.25 | R82: =P82+Q82 -> 993082.79 | S82: =Q82/G$17 -> 1820.2337 | T82: =G$9-S82 -> 1300.7663
B83: nov-25 | C83: =$D$26*H$21 -> 114635.29 | D83: 0.16925264 | E83: 0.82023285 | F83: 0.010514501 | G83: =C83*D83 -> 19402.326 | H83: =C83*E83 -> 94027.633 | I83: =C83*F83 -> 1205.3329 | J83: =G83*H$14+H83*H$15+I83*H$16 -> 208637.57 | K83: =G83+H83+I83 -> 114635.29 | L83: 0 | M83: =J83+L83*$D$26/839.45 -> 208637.57 | N83: =MIN($D$30*H$11,$D$28*H$12*H$11,H$7) -> 182030.4 | O83: =N83/Supuestos!$B$14*H$14 -> 223575.05 | P83: =N83*H$16-O83 -> 190962.78 | Q83: =787542.568322288*MIN(1,$D$30/7281.21603797167) -> 787542.57 | R83: =P83+Q83 -> 978505.35 | S83: =Q83/H$17 -> 1820.2343 | T83: =H$9-S83 -> 1840.7657
B84: dic-25 | C84: =$D$26*I$21 -> 109920.94 | D84: 0.1310335 | E84: 0.85726416 | F84: 0.011699311 | G84: =C84*D84 -> 14403.326 | H84: =C84*E84 -> 94231.283 | I84: =C84*F84 -> 1285.9993 | J84: =G84*I$14+H84*I$15+I84*I$16 -> 194248.14 | K84: =G84+H84+I84 -> 109920.61 | L84: 0 | M84: =J84+L84*$D$26/839.45 -> 194248.14 | N84: =MIN($D$30*I$11,$D$28*I$12*I$11,I$7) -> 196592.83 | O84: =N84/Supuestos!$B$14*I$14 -> 231426.63 | P84: =N84*I$16-O84 -> 195848.24 | Q84: =748170.841389915*MIN(1,$D$30/7281.21603797167) -> 748170.84 | R84: =P84+Q84 -> 944019.08 | S84: =Q84/I$17 -> 1820.2341 | T84: =I$9-S84 -> 2147.7659
B85: ene-26 | C85: =$D$26*J$21 -> 119913.75 | D85: 0.132045 | E85: 0.85676362 | F85: 0.011191385 | G85: =C85*D85 -> 15834.011 | H85: =C85*E85 -> 102737.74 | I85: =C85*F85 -> 1342.001 | J85: =G85*J$14+H85*J$15+I85*J$16 -> 207193.82 | K85: =G85+H85+I85 -> 119913.75 | L85: 0 | M85: =J85+L85*$D$26/839.45 -> 207193.82 | N85: =MIN($D$30*J$11,$D$28*J$12*J$11,J$7) -> 196592.83 | O85: =N85/Supuestos!$B$14*J$14 -> 226491.33 | P85: =N85*J$16-O85 -> 191425.72 | Q85: =731333.644926788*MIN(1,$D$30/7281.21603797167) -> 731333.64 | R85: =P85+Q85 -> 922759.36 | S85: =Q85/J$17 -> 1820.2341 | T85: =J$9-S85 -> 2451.7659
B86: feb-26 | C86: =$D$26*K$21 -> 116770.85 | D86: 0.14507312 | E86: 0.84365981 | F86: 0.011264212 | G86: =C86*D86 -> 16940.312 | H86: =C86*E86 -> 98514.876 | I86: =C86*F86 -> 1315.3317 | J86: =G86*K$14+H86*K$15+I86*K$16 -> 200780 | K86: =G86+H86+I86 -> 116770.52 | L86: 0 | M86: =J86+L86*$D$26/839.45 -> 200780 | N86: =MIN($D$30*K$11,$D$28*K$12*K$11,K$7) -> 174749.18 | O86: =N86/Supuestos!$B$14*K$14 -> 201416.64 | P86: =N86*K$16-O86 -> 170257.4 | Q86: =731752.629319146*MIN(1,$D$30/7281.21603797167) -> 731752.63 | R86: =P86+Q86 -> 902010.03 | S86: =Q86/K$17 -> 1820.2349 | T86: =K$9-S86 -> 2315.7651
B87: mar-26 | C87: =$D$26*L$21 -> 142813.95 | D87: 0.16278516 | E87: 0.82602313 | F87: 0.011191713 | G87: =C87*D87 -> 23247.992 | H87: =C87*E87 -> 117967.63 | I87: =C87*F87 -> 1598.3328 | J87: =G87*L$14+H87*L$15+I87*L$16 -> 243887.53 | K87: =G87+H87+I87 -> 142813.95 | L87: 0 | M87: =J87+L87*$D$26/839.45 -> 243887.53 | N87: =MIN($D$30*L$11,$D$28*L$12*L$11,L$7) -> 189311.62 | O87: =N87/Supuestos!$B$14*L$14 -> 218319.68 | P87: =N87*L$16-O87 -> 184554.37 | Q87: =732207.404697999*MIN(1,$D$30/7281.21603797167) -> 732207.4 | R87: =P87+Q87 -> 916761.78 | S87: =Q87/L$17 -> 1820.2342 | T87: =L$9-S87 -> 2362.7658
B88: abr-26 | C88: =$D$26*M$21 -> 126521.9 | D88: 0.13437716 | E88: 0.86404472 | F88: 0.0015781182 | G88: =C88*D88 -> 17001.654 | H88: =C88*E88 -> 109320.58 | I88: =C88*F88 -> 199.66652 | J88: =G88*M$14+H88*M$15+I88*M$16 -> 218252.91 | K88: =G88+H88+I88 -> 126521.9 | L88: 0 | M88: =J88+L88*$D$26/839.45 -> 218252.91 | N88: =MIN($D$30*M$11,$D$28*M$12*M$11,M$7) -> 167467.97 | O88: =N88/Supuestos!$B$14*M$14 -> 193111.5 | P88: =N88*M$16-O88 -> 163260.34 | Q88: =732171.28535383*MIN(1,$D$30/7281.21603797167) -> 732171.29 | R88: =P88+Q88 -> 895431.62 | S88: =Q88/M$17 -> 1820.2349 | T88: =M$9-S88 -> 2285.7651
B89: TOTAL | C89: =SUM(C77:C88) -> 1393628 | G89: =SUM(G77:G88) -> 200415.67 | H89: =SUM(H77:H88) -> 1185984.4 | I89: =SUM(I77:I88) -> 7227.9979 | J89: =SUM(J77:J88) -> 2519359.8 | K89: =SUM(K77:K88) -> 1393628 | M89: =SUM(M77:M88) -> 2519359.8 | N89: =SUM(N77:N88) -> 2020955.1 | O89: =SUM(O77:O88) -> 2440013.4 | P89: =SUM(P77:P88) -> 2081787.3 | Q89: =SUM(Q77:Q88) -> 12954228 | R89: =SUM(R77:R88) -> 15036016 | S89: =AVERAGE(S77:S88) -> 2502.8213 | T89: =AVERAGE(T77:T88) -> 1433.6787
A92: 5. PROYECCIÓN 20 AÑOS — OPCIÓN 1 — Autoconsumo (vertical, con cliff autoabasto 2032)
B93: Año | C93: Gasto CFE pleno $ | D93: Beneficio autoabasto $ | E93: Gasto real sin sistema $ | F93: Ahorro PV $ | G93: Ahorro BESS $ | H93: Pago PPA $ | I93: Pago particip. BESS $ | J93: Ahorro neto GEPP $ | K93: Acumulado GEPP $ | L93: % ahorro | M93: Flujo inv. PV $ | N93: Flujo inv. BESS $ | O93: Flujo inv. PV acum $ | P93: Flujo inv. BESS acum $
B94: Año 0 | C94: 0 | D94: 0 | E94: 0 | F94: 0 | G94: 0 | H94: 0 | I94: 0 | J94: 0 | K94: 0 | L94: 0 | M94: =-$C$34 -> -14324398 | N94: =-$C$36 -> -38039274 | O94: =M94 -> -14324398 | P94: =N94 -> -38039274
B95: =Supuestos!$B$25+1-1 -> 2026 | C95: =$C$39*(1+Supuestos!$B$9)^(1-1) -> 86033582 | D95: =IF(B95<=Supuestos!$B$26,$C$38*(1+Supuestos!$B$9)^(1-1),0) -> 22509980 | E95: =C95-D95 -> 63523603 | F95: =$C$43*(1+Supuestos!$B$9)^(1-1)*(1-Supuestos!$B$11)^(1-1) -> 3768609.8 | G95: =$C$44*(1+Supuestos!$B$9)^(1-1)*(1-Supuestos!$B$12)^(1-1) -> 12530013 | H95: =IF(1<=Supuestos!$B$18,$C$42*$C$31*(1+Supuestos!$B$10)^(1-1)*(1-Supuestos!$B$11)^(1-1),0) -> 2302729.7 | I95: =IF(1<=Supuestos!$B$19,G95*$C$32,0) -> 6265006.5 | J95: =F95+G95-H95-I95 -> 7730886.6 | K95: =K94+J95 -> 7730886.6 | L95: =IF(E95>0,J95/E95,0) -> 0.12170101 | M95: =IF(1<=Supuestos!$B$18,H95-Supuestos!$B$22*$C$26*(1+Supuestos!$B$9)^(1-1),0) -> 1913462.7 | N95: =IF(1<=Supuestos!$B$19,I95-Supuestos!$B$23*$C$29*(1+Supuestos!$B$9)^(1-1),0) -> 4871626.5 | O95: =O94+M95 -> -12410935 | P95: =P94+N95 -> -33167647
B96: =Supuestos!$B$25+2-1 -> 2027 | C96: =$C$39*(1+Supuestos!$B$9)^(2-1) -> 91195597 | D96: =IF(B96<=Supuestos!$B$26,$C$38*(1+Supuestos!$B$9)^(2-1),0) -> 23860578 | E96: =C96-D96 -> 67335019 | F96: =$C$43*(1+Supuestos!$B$9)^(2-1)*(1-Supuestos!$B$11)^(2-1) -> 3974752.8 | G96: =$C$44*(1+Supuestos!$B$9)^(2-1)*(1-Supuestos!$B$12)^(2-1) -> 13115791 | H96: =IF(2<=Supuestos!$B$18,$C$42*$C$31*(1+Supuestos!$B$10)^(2-1)*(1-Supuestos!$B$11)^(2-1),0) -> 2405776.9 | I96: =IF(2<=Supuestos!$B$19,G96*$C$32,0) -> 6557895.6 | J96: =F96+G96-H96-I96 -> 8126871.5 | K96: =K95+J96 -> 15857758 | L96: =IF(E96>0,J96/E96,0) -> 0.12069309 | M96: =IF(2<=Supuestos!$B$18,H96-Supuestos!$B$22*$C$26*(1+Supuestos!$B$9)^(2-1),0) -> 1993153.9 | N96: =IF(2<=Supuestos!$B$19,I96-Supuestos!$B$23*$C$29*(1+Supuestos!$B$9)^(2-1),0) -> 5080912.8 | O96: =O95+M96 -> -10417781 | P96: =P95+N96 -> -28086735
B97: =Supuestos!$B$25+3-1 -> 2028 | C97: =$C$39*(1+Supuestos!$B$9)^(3-1) -> 96667333 | D97: =IF(B97<=Supuestos!$B$26,$C$38*(1+Supuestos!$B$9)^(3-1),0) -> 25292213 | E97: =C97-D97 -> 71375120 | F97: =$C$43*(1+Supuestos!$B$9)^(3-1)*(1-Supuestos!$B$11)^(3-1) -> 4192171.8 | G97: =$C$44*(1+Supuestos!$B$9)^(3-1)*(1-Supuestos!$B$12)^(3-1) -> 13728954 | H97: =IF(3<=Supuestos!$B$18,$C$42*$C$31*(1+Supuestos!$B$10)^(3-1)*(1-Supuestos!$B$11)^(3-1),0) -> 2513435.4 | I97: =IF(3<=Supuestos!$B$19,G97*$C$32,0) -> 6864477.2 | J97: =F97+G97-H97-I97 -> 8543213.6 | K97: =K96+J97 -> 24400972 | L97: =IF(E97>0,J97/E97,0) -> 0.11969456 | M97: =IF(3<=Supuestos!$B$18,H97-Supuestos!$B$22*$C$26*(1+Supuestos!$B$9)^(3-1),0) -> 2076055 | N97: =IF(3<=Supuestos!$B$19,I97-Supuestos!$B$23*$C$29*(1+Supuestos!$B$9)^(3-1),0) -> 5298875.5 | O97: =O96+M97 -> -8341726.1 | P97: =P96+N97 -> -22787859
B98: =Supuestos!$B$25+4-1 -> 2029 | C98: =$C$39*(1+Supuestos!$B$9)^(4-1) -> 1.0246737e+08 | D98: =IF(B98<=Supuestos!$B$26,$C$38*(1+Supuestos!$B$9)^(4-1),0) -> 26809746 | E98: =C98-D98 -> 75657627 | F98: =$C$43*(1+Supuestos!$B$9)^(4-1)*(1-Supuestos!$B$11)^(4-1) -> 4421483.6 | G98: =$C$44*(1+Supuestos!$B$9)^(4-1)*(1-Supuestos!$B$12)^(4-1) -> 14370783 | H98: =IF(4<=Supuestos!$B$18,$C$42*$C$31*(1+Supuestos!$B$10)^(4-1)*(1-Supuestos!$B$11)^(4-1),0) -> 2625911.7 | I98: =IF(4<=Supuestos!$B$19,G98*$C$32,0) -> 7185391.5 | J98: =F98+G98-H98-I98 -> 8980963.4 | K98: =K97+J98 -> 33381935 | L98: =IF(E98>0,J98/E98,0) -> 0.11870533 | M98: =IF(4<=Supuestos!$B$18,H98-Supuestos!$B$22*$C$26*(1+Supuestos!$B$9)^(4-1),0) -> 2162288.4 | N98: =IF(4<=Supuestos!$B$19,I98-Supuestos!$B$23*$C$29*(1+Supuestos!$B$9)^(4-1),0) -> 5525853.7 | O98: =O97+M98 -> -6179437.7 | P98: =P97+N98 -> -17262006
B99: =Supuestos!$B$25+5-1 -> 2030 | C99: =$C$39*(1+Supuestos!$B$9)^(5-1) -> 1.0861542e+08 | D99: =IF(B99<=Supuestos!$B$26,$C$38*(1+Supuestos!$B$9)^(5-1),0) -> 28418331 | E99: =C99-D99 -> 80197085 | F99: =$C$43*(1+Supuestos!$B$9)^(5-1)*(1-Supuestos!$B$11)^(5-1) -> 4663338.7 | G99: =$C$44*(1+Supuestos!$B$9)^(5-1)*(1-Supuestos!$B$12)^(5-1) -> 15042617 | H99: =IF(5<=Supuestos!$B$18,$C$42*$C$31*(1+Supuestos!$B$10)^(5-1)*(1-Supuestos!$B$11)^(5-1),0) -> 2743421.2 | I99: =IF(5<=Supuestos!$B$19,G99*$C$32,0) -> 7521308.6 | J99: =F99+G99-H99-I99 -> 9441226.1 | K99: =K98+J99 -> 42823161 | L99: =IF(E99>0,J99/E99,0) -> 0.1177253 | M99: =IF(5<=Supuestos!$B$18,H99-Supuestos!$B$22*$C$26*(1+Supuestos!$B$9)^(5-1),0) -> 2251980.6 | N99: =IF(5<=Supuestos!$B$19,I99-Supuestos!$B$23*$C$29*(1+Supuestos!$B$9)^(5-1),0) -> 5762198.4 | O99: =O98+M99 -> -3927457.1 | P99: =P98+N99 -> -11499807
B100: =Supuestos!$B$25+6-1 -> 2031 | C100: =$C$39*(1+Supuestos!$B$9)^(6-1) -> 1.1513234e+08 | D100: =IF(B100<=Supuestos!$B$26,$C$38*(1+Supuestos!$B$9)^(6-1),0) -> 30123431 | E100: =C100-D100 -> 85008910 | F100: =$C$43*(1+Supuestos!$B$9)^(6-1)*(1-Supuestos!$B$11)^(6-1) -> 4918423.3 | G100: =$C$44*(1+Supuestos!$B$9)^(6-1)*(1-Supuestos!$B$12)^(6-1) -> 15745860 | H100: =IF(6<=Supuestos!$B$18,$C$42*$C$31*(1+Supuestos!$B$10)^(6-1)*(1-Supuestos!$B$11)^(6-1),0) -> 2866189.3 | I100: =IF(6<=Supuestos!$B$19,G100*$C$32,0) -> 7872929.8 | J100: =F100+G100-H100-I100 -> 9925163.8 | K100: =K99+J100 -> 52748325 | L100: =IF(E100>0,J100/E100,0) -> 0.11675439 | M100: =IF(6<=Supuestos!$B$18,H100-Supuestos!$B$22*$C$26*(1+Supuestos!$B$9)^(6-1),0) -> 2345262.2 | N100: =IF(6<=Supuestos!$B$19,I100-Supuestos!$B$23*$C$29*(1+Supuestos!$B$9)^(6-1),0) -> 6008273 | O100: =O99+M100 -> -1582194.8 | P100: =P99+N100 -> -5491534.1
B101: =Supuestos!$B$25+7-1 -> 2032 | C101: =$C$39*(1+Supuestos!$B$9)^(7-1) -> 1.2204028e+08 | D101: =IF(B101<=Supuestos!$B$26,$C$38*(1+Supuestos!$B$9)^(7-1),0) -> 31930836 | E101: =C101-D101 -> 90109444 | F101: =$C$43*(1+Supuestos!$B$9)^(7-1)*(1-Supuestos!$B$11)^(7-1) -> 5187461.1 | G101: =$C$44*(1+Supuestos!$B$9)^(7-1)*(1-Supuestos!$B$12)^(7-1) -> 16481978 | H101: =IF(7<=Supuestos!$B$18,$C$42*$C$31*(1+Supuestos!$B$10)^(7-1)*(1-Supuestos!$B$11)^(7-1),0) -> 2994451.3 | I101: =IF(7<=Supuestos!$B$19,G101*$C$32,0) -> 8240989.2 | J101: =F101+G101-H101-I101 -> 10433999 | K101: =K100+J101 -> 63182324 | L101: =IF(E101>0,J101/E101,0) -> 0.11579251 | M101: =IF(7<=Supuestos!$B$18,H101-Supuestos!$B$22*$C$26*(1+Supuestos!$B$9)^(7-1),0) -> 2442268.6 | N101: =IF(7<=Supuestos!$B$19,I101-Supuestos!$B$23*$C$29*(1+Supuestos!$B$9)^(7-1),0) -> 6264453.1 | O101: =O100+M101 -> 860073.76 | P101: =P100+N101 -> 772918.97
B102: =Supuestos!$B$25+8-1 -> 2033 | C102: =$C$39*(1+Supuestos!$B$9)^(8-1) -> 1.293627e+08 | D102: =IF(B102<=Supuestos!$B$26,$C$38*(1+Supuestos!$B$9)^(8-1),0) -> 0 | E102: =C102-D102 -> 1.293627e+08 | F102: =$C$43*(1+Supuestos!$B$9)^(8-1)*(1-Supuestos!$B$11)^(8-1) -> 5471215.2 | G102: =$C$44*(1+Supuestos!$B$9)^(8-1)*(1-Supuestos!$B$12)^(8-1) -> 17252511 | H102: =IF(8<=Supuestos!$B$18,$C$42*$C$31*(1+Supuestos!$B$10)^(8-1)*(1-Supuestos!$B$11)^(8-1),0) -> 3128453 | I102: =IF(8<=Supuestos!$B$19,G102*$C$32,0) -> 8626255.5 | J102: =F102+G102-H102-I102 -> 10969018 | K102: =K101+J102 -> 74151342 | L102: =IF(E102>0,J102/E102,0) -> 0.084792741 | M102: =IF(8<=Supuestos!$B$18,H102-Supuestos!$B$22*$C$26*(1+Supuestos!$B$9)^(8-1),0) -> 2543139.3 | N102: =IF(8<=Supuestos!$B$19,I102-Supuestos!$B$23*$C$29*(1+Supuestos!$B$9)^(8-1),0) -> 6531127.1 | O102: =O101+M102 -> 3403213.1 | P102: =P101+N102 -> 7304046.1
B103: =Supuestos!$B$25+9-1 -> 2034 | C103: =$C$39*(1+Supuestos!$B$9)^(9-1) -> 1.3712446e+08 | D103: =IF(B103<=Supuestos!$B$26,$C$38*(1+Supuestos!$B$9)^(9-1),0) -> 0 | E103: =C103-D103 -> 1.3712446e+08 | F103: =$C$43*(1+Supuestos!$B$9)^(9-1)*(1-Supuestos!$B$11)^(9-1) -> 5770490.7 | G103: =$C$44*(1+Supuestos!$B$9)^(9-1)*(1-Supuestos!$B$12)^(9-1) -> 18059066 | H103: =IF(9<=Supuestos!$B$18,$C$42*$C$31*(1+Supuestos!$B$10)^(9-1)*(1-Supuestos!$B$11)^(9-1),0) -> 3268451.2 | I103: =IF(9<=Supuestos!$B$19,G103*$C$32,0) -> 9029532.9 | J103: =F103+G103-H103-I103 -> 11531572 | K103: =K102+J103 -> 85682914 | L103: =IF(E103>0,J103/E103,0) -> 0.084095663 | M103: =IF(9<=Supuestos!$B$18,H103-Supuestos!$B$22*$C$26*(1+Supuestos!$B$9)^(9-1),0) -> 2648018.8 | N103: =IF(9<=Supuestos!$B$19,I103-Supuestos!$B$23*$C$29*(1+Supuestos!$B$9)^(9-1),0) -> 6808696.9 | O103: =O102+M103 -> 6051231.9 | P103: =P102+N103 -> 14112743
B104: =Supuestos!$B$25+10-1 -> 2035 | C104: =$C$39*(1+Supuestos!$B$9)^(10-1) -> 1.4535193e+08 | D104: =IF(B104<=Supuestos!$B$26,$C$38*(1+Supuestos!$B$9)^(10-1),0) -> 0 | E104: =C104-D104 -> 1.4535193e+08 | F104: =$C$43*(1+Supuestos!$B$9)^(10-1)*(1-Supuestos!$B$11)^(10-1) -> 6086136.5 | G104: =$C$44*(1+Supuestos!$B$9)^(10-1)*(1-Supuestos!$B$12)^(10-1) -> 18903327 | H104: =IF(10<=Supuestos!$B$18,$C$42*$C$31*(1+Supuestos!$B$10)^(10-1)*(1-Supuestos!$B$11)^(10-1),0) -> 3414714.4 | I104: =IF(10<=Supuestos!$B$19,G104*$C$32,0) -> 9451663.6 | J104: =F104+G104-H104-I104 -> 12123086 | K104: =K103+J104 -> 97806000 | L104: =IF(E104>0,J104/E104,0) -> 0.083405056 | M104: =IF(10<=Supuestos!$B$18,H104-Supuestos!$B$22*$C$26*(1+Supuestos!$B$9)^(10-1),0) -> 2757056 | N104: =IF(10<=Supuestos!$B$19,I104-Supuestos!$B$23*$C$29*(1+Supuestos!$B$9)^(10-1),0) -> 7097577.4 | O104: =O103+M104 -> 8808287.9 | P104: =P103+N104 -> 21210320
B105: =Supuestos!$B$25+11-1 -> 2036 | C105: =$C$39*(1+Supuestos!$B$9)^(11-1) -> 1.5407304e+08 | D105: =IF(B105<=Supuestos!$B$26,$C$38*(1+Supuestos!$B$9)^(11-1),0) -> 0 | E105: =C105-D105 -> 1.5407304e+08 | F105: =$C$43*(1+Supuestos!$B$9)^(11-1)*(1-Supuestos!$B$11)^(11-1) -> 6419048.2 | G105: =$C$44*(1+Supuestos!$B$9)^(11-1)*(1-Supuestos!$B$12)^(11-1) -> 19787058 | H105: =IF(11<=Supuestos!$B$18,$C$42*$C$31*(1+Supuestos!$B$10)^(11-1)*(1-Supuestos!$B$11)^(11-1),0) -> 3567522.9 | I105: =IF(11<=Supuestos!$B$19,G105*$C$32,0) -> 9893528.9 | J105: =F105+G105-H105-I105 -> 12745054 | K105: =K104+J105 -> 1.1055105e+08 | L105: =IF(E105>0,J105/E105,0) -> 0.082720857 | M105: =IF(11<=Supuestos!$B$18,H105-Supuestos!$B$22*$C$26*(1+Supuestos!$B$9)^(11-1),0) -> 2870405 | N105: =IF(11<=Supuestos!$B$19,I105-Supuestos!$B$23*$C$29*(1+Supuestos!$B$9)^(11-1),0) -> 7398197.5 | O105: =O104+M105 -> 11678693 | P105: =P104+N105 -> 28608518
B106: =Supuestos!$B$25+12-1 -> 2037 | C106: =$C$39*(1+Supuestos!$B$9)^(12-1) -> 1.6331743e+08 | D106: =IF(B106<=Supuestos!$B$26,$C$38*(1+Supuestos!$B$9)^(12-1),0) -> 0 | E106: =C106-D106 -> 1.6331743e+08 | F106: =$C$43*(1+Supuestos!$B$9)^(12-1)*(1-Supuestos!$B$11)^(12-1) -> 6770170.1 | G106: =$C$44*(1+Supuestos!$B$9)^(12-1)*(1-Supuestos!$B$12)^(12-1) -> 20712103 | H106: =IF(12<=Supuestos!$B$18,$C$42*$C$31*(1+Supuestos!$B$10)^(12-1)*(1-Supuestos!$B$11)^(12-1),0) -> 3727169.6 | I106: =IF(12<=Supuestos!$B$19,G106*$C$32,0) -> 10356051 | J106: =F106+G106-H106-I106 -> 13399052 | K106: =K105+J106 -> 1.2395011e+08 | L106: =IF(E106>0,J106/E106,0) -> 0.082043002 | M106: =IF(12<=Supuestos!$B$18,H106-Supuestos!$B$22*$C$26*(1+Supuestos!$B$9)^(12-1),0) -> 2988224.6 | N106: =IF(12<=Supuestos!$B$19,I106-Supuestos!$B$23*$C$29*(1+Supuestos!$B$9)^(12-1),0) -> 7711000.1 | O106: =O105+M106 -> 14666917 | P106: =P105+N106 -> 36319518
B107: =Supuestos!$B$25+13-1 -> 2038 | C107: =$C$39*(1+Supuestos!$B$9)^(13-1) -> 1.7311647e+08 | D107: =IF(B107<=Supuestos!$B$26,$C$38*(1+Supuestos!$B$9)^(13-1),0) -> 0 | E107: =C107-D107 -> 1.7311647e+08 | F107: =$C$43*(1+Supuestos!$B$9)^(13-1)*(1-Supuestos!$B$11)^(13-1) -> 7140498.4 | G107: =$C$44*(1+Supuestos!$B$9)^(13-1)*(1-Supuestos!$B$12)^(13-1) -> 21680393 | H107: =IF(13<=Supuestos!$B$18,$C$42*$C$31*(1+Supuestos!$B$10)^(13-1)*(1-Supuestos!$B$11)^(13-1),0) -> 3893960.4 | I107: =IF(13<=Supuestos!$B$19,G107*$C$32,0) -> 10840197 | J107: =F107+G107-H107-I107 -> 14086735 | K107: =K106+J107 -> 1.3803684e+08 | L107: =IF(E107>0,J107/E107,0) -> 0.08137143 | M107: =IF(13<=Supuestos!$B$18,H107-Supuestos!$B$22*$C$26*(1+Supuestos!$B$9)^(13-1),0) -> 3110678.7 | N107: =IF(13<=Supuestos!$B$19,I107-Supuestos!$B$23*$C$29*(1+Supuestos!$B$9)^(13-1),0) -> 8036442.4 | O107: =O106+M107 -> 17777596 | P107: =P106+N107 -> 44355960
...
