Workbook

Sheet Resumen
A1: GEPP — PROPUESTA SOLAR + BESS, 4 SITIOS | Resumen comparativo (MXN sin IVA) | jul-2026
A3: Sitio | B3: Opción / Esquema | C3: PV (kWp) | D3: BESS (kW) | E3: BESS (kWh) | F3: Gen (kWh/año) | G3: Gasto real hoy ($/año) | H3: Beneficio autoab. ($/año, →2032) | I3: Ahorro bruto ($) | J3: Pago PPA ($) | K3: Pago partic. ($) | L3: AHORRO NETO GEPP ($) | M3: % bruto | N3: % neto | O3: PPA (MXN/kWh) | P3: TIR PV | Q3: TIR BESS @50%
A4: Ixtlahuacán | B4: Op1: Autoconsumo | C4: ='Ixtlahuacán'!C26 -> 4550 | D4: ='Ixtlahuacán'!C28 -> 3700 | E4: ='Ixtlahuacán'!C29 -> 7400 | F4: ='Ixtlahuacán'!C41 -> 8114834 | G4: ='Ixtlahuacán'!N19 -> 52141327 | H4: ='Ixtlahuacán'!C38 -> 1649527 | I4: ='Ixtlahuacán'!C45 -> 25368712 | J4: ='Ixtlahuacán'!C46 -> 8343801.8 | K4: ='Ixtlahuacán'!C47 -> 5678437.2 | L4: ='Ixtlahuacán'!C48 -> 11346473 | M4: ='Ixtlahuacán'!C49 -> 0.48653752 | N4: ='Ixtlahuacán'!C50 -> 0.21760998 | O4: ='Ixtlahuacán'!C31 -> 1.0492 | P4: ='Ixtlahuacán'!C51 -> 0.14315285 | Q4: ='Ixtlahuacán'!C52 -> 0.1136277
B5: Op2: GD Medición Neta | C5: ='Ixtlahuacán'!D26 -> 839.45 | D5: ='Ixtlahuacán'!D28 -> 3700 | E5: ='Ixtlahuacán'!D29 -> 7400 | F5: ='Ixtlahuacán'!D41 -> 1497142.3 | G5: ='Ixtlahuacán'!N19 -> 52141327 | H5: ='Ixtlahuacán'!C38 -> 1649527 | I5: ='Ixtlahuacán'!D45 -> 13993338 | J5: ='Ixtlahuacán'!D46 -> 1539363.8 | K5: ='Ixtlahuacán'!D47 -> 5678437.2 | L5: ='Ixtlahuacán'!D48 -> 6775536.7 | M5: ='Ixtlahuacán'!D49 -> 0.26837325 | N5: ='Ixtlahuacán'!D50 -> 0.12994561 | O5: ='Ixtlahuacán'!D31 -> 1.0282 | P5: ='Ixtlahuacán'!D51 -> 0.14314976 | Q5: ='Ixtlahuacán'!D52 -> 0.1136277
A6: Acapulco | B6: Op1: Autoconsumo | C6: =Acapulco!C26 -> 1618 | D6: =Acapulco!C28 -> 1648 | E6: =Acapulco!C29 -> 3296 | F6: =Acapulco!C41 -> 3024766.9 | G6: =Acapulco!N19 -> 27061919 | H6: =Acapulco!C38 -> 0 | I6: =Acapulco!C45 -> 9819504 | J6: =Acapulco!C46 -> 2967232.1 | K6: =Acapulco!C47 -> 2090144.8 | L6: =Acapulco!C48 -> 4762127.1 | M6: =Acapulco!C49 -> 0.3628532 | N6: =Acapulco!C50 -> 0.17597152 | O6: =Acapulco!C31 -> 1.001 | P6: =Acapulco!C51 -> 0.1431631 | Q6: =Acapulco!C52 -> 0.071985139
B7: Op2: GD Medición Neta | C7: =Acapulco!D26 -> 839.45 | D7: =Acapulco!D28 -> 1648 | E7: =Acapulco!D29 -> 3296 | F7: =Acapulco!D41 -> 1569308.1 | G7: =Acapulco!N19 -> 27061919 | H7: =Acapulco!C38 -> 0 | I7: =Acapulco!D45 -> 7285068.6 | J7: =Acapulco!D46 -> 1539495.2 | K7: =Acapulco!D47 -> 2090144.8 | L7: =Acapulco!D48 -> 3655428.6 | M7: =Acapulco!D49 -> 0.2692 | N7: =Acapulco!D50 -> 0.13507647 | O7: =Acapulco!D31 -> 0.981 | P7: =Acapulco!D51 -> 0.14316836 | Q7: =Acapulco!D52 -> 0.071985139
A8: Cancún | B8: Op1: Autoconsumo | C8: ='Cancún'!C26 -> 1100 | D8: ='Cancún'!C28 -> 981 | E8: ='Cancún'!C29 -> 1962 | F8: ='Cancún'!C41 -> 1649771.2 | G8: ='Cancún'!N19 -> 15152838 | H8: ='Cancún'!C38 -> 0 | I8: ='Cancún'!C45 -> 6277408.3 | J8: ='Cancún'!C46 -> 2017227.2 | K8: ='Cancún'!C47 -> 1372048.8 | L8: ='Cancún'!C48 -> 2888132.3 | M8: ='Cancún'!C49 -> 0.41427278 | N8: ='Cancún'!C50 -> 0.19060009 | O8: ='Cancún'!C31 -> 1.2476 | P8: ='Cancún'!C51 -> 0.14315765 | Q8: ='Cancún'!C52 -> 0.093055732
B9: Op2: GD Medición Neta | C9: ='Cancún'!D26 -> 839.45 | D9: ='Cancún'!D28 -> 981 | E9: ='Cancún'!D29 -> 1962 | F9: ='Cancún'!D41 -> 1259000.4 | G9: ='Cancún'!N19 -> 15152838 | H9: ='Cancún'!C38 -> 0 | I9: ='Cancún'!D45 -> 5511211 | J9: ='Cancún'!D46 -> 1539383.4 | K9: ='Cancún'!D47 -> 1372048.8 | L9: ='Cancún'!D48 -> 2599778.7 | M9: ='Cancún'!D49 -> 0.36370817 | N9: ='Cancún'!D50 -> 0.17157042 | O9: ='Cancún'!D31 -> 1.2227 | P9: ='Cancún'!D51 -> 0.14315255 | Q9: ='Cancún'!D52 -> 0.093055732
A10: Proplasa | B10: Op1: 2×GD + Autoconsumo | C10: =Proplasa!C26 -> 3848.9 | D10: =Proplasa!C28 -> 11787 | E10: =Proplasa!C29 -> 23574 | F10: =Proplasa!C41 -> 6389820.6 | G10: =Proplasa!N19 -> 202250117 | H10: =Proplasa!C38 -> 57664106 | I10: =Proplasa!C45 -> 50181166 | J10: =Proplasa!C46 -> 7058195.9 | K10: =Proplasa!C47 -> 19088041 | L10: =Proplasa!C48 -> 24034930 | M10: =Proplasa!C49 -> 0.2481144 | N10: =Proplasa!C50 -> 0.11883766 | O10: =Proplasa!C31 -> 1.1046 | P10: =Proplasa!C51 -> 0.14315511 | Q10: =Proplasa!C52 -> 0.12584659
B11: Op2: 3× GD Medición Neta | C11: =Proplasa!D26 -> 2518.35 | D11: =Proplasa!D28 -> 11787 | E11: =Proplasa!D29 -> 23574 | F11: =Proplasa!D41 -> 4180884.1 | G11: =Proplasa!N19 -> 202250117 | H11: =Proplasa!C38 -> 57664106 | I11: =Proplasa!D45 -> 46033331 | J11: =Proplasa!D46 -> 4618204.6 | K11: =Proplasa!D47 -> 19088041 | L11: =Proplasa!D48 -> 22327086 | M11: =Proplasa!D49 -> 0.22760595 | N11: =Proplasa!D50 -> 0.11039344 | O11: =Proplasa!D31 -> 1.1046 | P11: =Proplasa!D51 -> 0.14315511 | Q11: =Proplasa!D52 -> 0.12584659
A13: PORTAFOLIO | B13: Suma Opción 1 | C13: =C4+C6+C8+C10 -> 11116.9 | D13: =D4+D6+D8+D10 -> 18116 | E13: =E4+E6+E8+E10 -> 36232 | F13: =F4+F6+F8+F10 -> 19179193 | G13: =G4+G6+G8+G10 -> 296606201 | H13: =H4+H6+H8+H10 -> 59313633 | I13: =I4+I6+I8+I10 -> 91646790 | J13: =J4+J6+J8+J10 -> 20386457 | ... L13: =L4+L6+L8+L10 -> 43031662
B14: Suma Opción 2 | C14: =C5+C7+C9+C11 -> 5036.7 | D14: =D5+D7+D9+D11 -> 18116 | E14: =E5+E7+E9+E11 -> 36232 | F14: =F5+F7+F9+F11 -> 8506334.9 | G14: =G5+G7+G9+G11 -> 296606201 | H14: =H5+H7+H9+H11 -> 59313633 | I14: =I5+I7+I9+I11 -> 72822948 | J14: =J5+J7+J9+J11 -> 9236447 | ... L14: =L5+L7+L9+L11 -> 35357830
A16: Nota: "Gasto real hoy" ya refleja el descuento de autoabasto; el "Beneficio autoab." (naranja) se pierde en 2032 → el gasto real del cliente salta en 2033 (ver proyección 20 años de cada sitio). Nuestro ahorro $ es el hedge.

Sheet Supuestos
A1: SUPUESTOS DEL MODELO — editar celdas amarillas (todo sin IVA)
A4: Tipo de cambio (MXN/USD) | B4: 17.55 | C4: MXN/USD
A5: Precio de venta PV (USD/Wp) | B5: 0.65 | C5: USD/Wp
A6: Costo duro PV — informativo (USD/Wp) | B6: 0.5 | C6: USD/Wp
A7: Precio BESS instalado (USD/Wh) | B7: 0.28 | C7: USD/Wh
A8: Costo FOB BESS — informativo (USD/Wh) | B8: 0.18 | C8: USD/Wh
A9: Escalación tarifas CFE (anual) | B9: 0.04 | C9: %
A10: Escalación precio PPA (anual) | B10: 0.04 | C10: %
A11: Degradación PV (anual) | B11: 0.005 | C11: %
A12: Degradación BESS (anual) | B12: 0.0125 | C12: %
A13: Profundidad de descarga BESS (DoD) | B13: 0.96
A14: Eficiencia round-trip BESS (RTE) | B14: 0.96
A15: Factor de carga p/ umbral de demanda | B15: 0.57
A16: Meses sin ahorro BESS al año (merma de riesgo) | B16: 2 | C16: meses
A17: Participación del inversionista en ahorro BESS | B17: 0.5 | C17: %
A18: Plazo PPA / venta de energía PV (años) | B18: 15 | C18: años
A19: Plazo BESS / participación en ahorro (años) | B19: 15 | C19: años
A20: Horizonte de análisis (años) | B20: 20 | C20: años
A21: Tasa de descuento / WACC | B21: 0.12 | C21: %
A22: O&M PV (MXN/kWp·año) | B22: 310 | C22: MXN/kWp
A23: O&M BESS (MXN/kWh·año) | B23: 180 | C23: MXN/kWh
A24: Densidad de instalación (m²/kWp) | B24: 4 | C24: m²/kWp
A25: Año base del modelo (Año 1) | B25: 2026 | C25: año
A26: Año de término autoabasto TALA / ENEL | B26: 2032 | C26: año
A29: SITIOS — recurso solar y superficie
A30: Sitio | B30: Municipio | C30: Tarifa | D30: Yield (kWh/kWp·año) | E30: Superficie disp. (m²)
A31: Sitio | B31: Municipio | C31: Tarifa | D31: Yield (kWh/kWp·año) | E31: Superficie disp. (m²)
A32: Ixtlahuacán | B32: Ixtlahuacán de los Membrillos, Jal. | C32: DIST (Jalisco) | D32: 1783 | E32: 25308
A33: Acapulco | B33: Acapulco de Juárez, Gro. | C33: GDMTH (Centro Sur) | D33: 1869 | E33: 7019
A34: Cancún | B34: Benito Juárez, Q.R. | C34: GDMTH (Peninsular) | D34: 1500 | E34: 6828
A35: Proplasa | B35: Cuautitlán Izcalli, Méx. | C35: GDMTH (V. de México Norte) | D35: 1660 | E35: 15396
A38: SUPUESTOS Y NOTAS CLAVE
A39: • Baseline: últimos 12 meses reales may-25 → abr-26 (recibos CFE, sin IVA).
A40: • Autoabasto TALA (Ixtlahuacán, zafra) y ENEL (Proplasa) vencen 2032. Su beneficio actual se
A41: cuantifica por sitio (fila "Beneficio autoabasto") y aparece en la proyección 20 años como la
A42: brecha entre "Gasto CFE pleno" y "Gasto real"; esa brecha se cierra en 2033 → el gasto real del
A43: cliente DA UN SALTO. El ahorro $ de nuestro sistema (PPA fijo) no cambia, por lo que cubre un %
A44: menor de un recibo mayor, pero es justo el hedge que amortigua ese salto. Editar beneficio y año.
A45: • Plazo PPA y plazo BESS ahora son independientes (celdas B18/B19). Ej.: 12 años PPA + 20 de
A46: participación en ahorro BESS. Tras el plazo PPA el ahorro PV queda 100% para GEPP (pago=0).
A47: • TIR nominal MXN, pre-IVA, sin apalancamiento, sobre precio de venta. PPA resuelto p/ TIR PV ~14%.
A48: • Marco legal: Ley del Sector Eléctrico (DOF 18-mar-2025). GD Exento <0.7 MW sin permiso (Art. 30).
A49: • Módulo Tongwei TWMNF-66HD715 (715 Wp, η 23.0%). Densidad 4.0 m²/kWp.
A50: • Ahorros de demanda calibrados con simulación horaria al tamaño de diseño; escalan linealmente.

Sheet Ixtlahuacán
A1: GEPP Ixtlahuacán — Propuesta Solar + BESS | DIST (Jalisco) | Ixtlahuacán de los Membrillos, Jal. (montos MXN sin IVA)
A3: 1. DATOS BASE — últimos 12 meses reales (recibos CFE, sin IVA)
A4: Mes | B4: may-25 | C4: jun-25 | D4: jul-25 | E4: ago-25 | F4: sep-25 | G4: oct-25 | H4: nov-25 | I4: dic-25 | J4: ene-26 | K4: feb-26 | L4: mar-26 | M4: abr-26 | N4: TOTAL
A5: Consumo Base (kWh) | B5: 664426 | C5: 630738 | D5: 534017 | E5: 701321 | F5: 593175 | G5: 641906 | H5: 719936 | I5: 704647 | J5: 591649 | K5: 449327 | L5: 725263 | M5: 574838 | N5: =SUM(B5:M5) -> 7531243
A6: Consumo Intermedia (kWh) | B6: 1271980 | C6: 1133752 | D6: 1146833 | E6: 1065260 | F6: 941250 | G6: 1065460 | H6: 965437 | I6: 1049782 | J6: 969708 | K6: 811294 | L6: 1035362 | M6: 1202190 | N6: =SUM(B6:M6) -> 12658308
A7: Consumo Punta (kWh) | B7: 118279 | C7: 116822 | D7: 122085 | E7: 176568 | F7: 167798 | G7: 218540 | H7: 254095 | I7: 282952 | J7: 268637 | K7: 148414 | L7: 178884 | M7: 135622 | N7: =SUM(B7:M7) -> 2188696
A8: Consumo Total (kWh) | B8: =SUM(B5:B7) -> 2054685 | C8: =SUM(C5:C7) -> 1881312 | D8: =SUM(D5:D7) -> 1802935 | E8: =SUM(E5:E7) -> 1943149 | F8: =SUM(F5:F7) -> 1702223 | G8: =SUM(G5:G7) -> 1925906 | H8: =SUM(H5:H7) -> 1939468 | I8: =SUM(I5:I7) -> 2037381 | ... M8: =SUM(M5:M7) -> 1912650 | N8: =SUM(B8:M8) -> 22378247
A9: Dem. máx. en punta (kW) | B9: 2688 | C9: 2781 | D9: 2654 | E9: 4204 | F9: 3814 | G9: 4361 | H9: 3102 | I9: 3105 | J9: 3011 | K9: 1852 | L9: 2045 | M9: 2926 | N9: =MAX(B9:M9) -> 4361
A10: Dem. máx. mensual (kW) | B10: 3011 | C10: 2799 | D10: 2655 | E10: 4204 | F10: 3814 | G10: 4361 | H10: 3714 | I10: 3760 | J10: 3128 | K10: 2589 | L10: 3687 | M10: 3138 | N10: =MAX(B10:M10) -> 4361
A11: Días con punta | B11: 22 | C11: 21 | D11: 23 | E11: 21 | F11: 22 | G11: 23 | H11: 25 | I11: 27 | J11: 27 | K11: 24 | L11: 26 | M11: 23
A12: Horas punta/día | B12: 2 | C12: 2 | D12: 2 | E12: 2 | F12: 2 | G12: 2.43 | H12: 3.6 | I12: 3.7 | J12: 3.63 | K12: 3.67 | L12: 3.69 | M12: 2.26
A13: Días del mes | B13: 31 | C13: 30 | D13: 31 | E13: 31 | F13: 30 | G13: 31 | H13: 30 | I13: 31 | J13: 31 | K13: 28 | L13: 31 | M13: 30
A14: Tarifa Base ($/kWh) | B14: 1.1444 | C14: 1.1669 | D14: 1.1815 | E14: 1.1829 | F14: 1.178 | G14: 1.178 | H14: 1.1485 | I14: 1.101 | J14: 1.0776 | K14: 1.0781 | L14: 1.0786 | M14: 1.0786
A15: Tarifa Intermedia ($/kWh) | B15: 1.8911 | C15: 1.9314 | D15: 1.9575 | E15: 1.96 | F15: 1.9479 | G15: 1.9479 | H15: 1.8954 | I15: 1.8105 | J15: 1.7711 | K15: 1.772 | L15: 1.773 | M15: 1.7729
A16: Tarifa Punta ($/kWh) | B16: 2.2374 | C16: 2.2859 | D16: 2.3173 | E16: 2.3203 | F16: 2.3049 | G16: 2.3049 | H16: 2.2417 | I16: 2.1395 | J16: 2.0927 | K16: 2.0938 | L16: 2.0949 | M16: 2.0948
A17: Tarifa Capacidad ($/kW·mes) | B17: 432.62 | C17: 442.9 | D17: 449.54 | E17: 450.17 | F17: 446.05 | G17: 446.06 | H17: 432.66 | I17: 411.03 | J17: 401.78 | K17: 402 | L17: 402.26 | M17: 402.24
A18: Tarifa Distribución ($/kW·mes) | B18: 0 | C18: 0 | D18: 0 | E18: 0 | F18: 0 | G18: 0 | H18: 0 | I18: 0 | J18: 0 | K18: 0 | L18: 0 | M18: 0 | O18: FC umbral (DIST)
A19: Gasto actual facturado ($ MXN) | B19: 4462726 | C19: 4700643 | D19: 4627503 | E19: 4932162 | F19: 4336535 | G19: 4904162 | H19: 4836407 | I19: 4353098 | J19: 3828426 | K19: 3026757 | L19: 3987520 | M19: 4145388 | N19: =SUM(B19:M19) -> 52141327 | O19: GDMTH=0.57 · DIST=0.74
A20: Umbral de demanda (kW) — FC DIST 0.74 | B20: =B8/(24*B13*$O$20) -> 3731.9911 | C20: =C8/(24*C13*$O$20) -> 3530.991 | D20: =D8/(24*D13*$O$20) -> 3274.7294 | E20: =E8/(24*E13*$O$20) -> 3529.4046 | F20: =F8/(24*F13*$O$20) -> 3194.863 | G20: =G8/(24*G13*$O$20) -> 3498.0856 | H20: =H8/(24*H13*$O$20) -> 3640.1426 | I20: =I8/(24*I13*$O$20) -> 3700.5612 | ... M20: =M8/(24*M13*$O$20) -> 3589.8086 | O20: 0.74
A21: Yield PV (kWh/kWp) | B21: 162.688 | C21: 148.08 | D21: 138.632 | E21: 131.688 | F21: 126.72 | G21: 146.816 | H21: 151.92 | I21: 138.384 | J21: 147.064 | K21: 142.464 | L21: 180.544 | M21: 168.48 | N21: =SUM(B21:M21) -> 1783.48
A23: 2. SISTEMA PROPUESTO — Opción 1 y Opción 2 (amarillo = editable)
A24: Concepto | C24: OPCIÓN 1 — Autoconsumo | D24: OPCIÓN 2 — GD Medición Neta
A25: Esquema legal | C25: Autoconsumo interconectado (permiso CNE simplificado) | D25: Generación Distribuida <0.7 MW (sin permiso)
A26: Potencia PV (kWp DC) | C26: 4550 | D26: 839.45
A27: Superficie requerida (m²) | C27: =C26*Supuestos!$B$24 -> 18200 | D27: =D26*Supuestos!$B$24 -> 3357.8
A28: BESS potencia (kW) | C28: 3700 | D28: 3700
A29: BESS capacidad (kWh) | C29: 7400 | D29: 7400
A30: Energía útil BESS (kWh) | C30: =C29*Supuestos!$B$13*SQRT(Supuestos!$B$14) -> 6960.4701 | D30: =D29*Supuestos!$B$13*SQRT(Supuestos!$B$14) -> 6960.4701
A31: Precio PPA (MXN/kWh, año 1) | C31: 1.2848231 | D31: 1.5031642
A32: Participación inversionista BESS (%) | C32: =Supuestos!$B$17 -> 0.5 | D32: =Supuestos!$B$17 -> 0.5
A33: CAPEX PV (USD) | C33: =C26*1000*Supuestos!$B$5 -> 2957500 | D33: =D26*1000*Supuestos!$B$5 -> 545642.5
A34: CAPEX PV (MXN) | C34: =C33*Supuestos!$B$4 -> 51904125 | D34: =D33*Supuestos!$B$4 -> 9576025.9
A35: CAPEX BESS (USD) | C35: =C29*1000*Supuestos!$B$7 -> 2072000 | D35: =D29*1000*Supuestos!$B$7 -> 2072000
A36: CAPEX BESS (MXN) | C36: =C35*Supuestos!$B$4 -> 36363600 | D36: =D35*Supuestos!$B$4 -> 36363600
A37: — Autoabasto TALA / ENEL (vence 2032) —
A38: Beneficio autoabasto actual ($/año) | C38: 1649527 | D38: =C38 -> 1649527
A39: Gasto sin autoabasto — CFE pleno ($/año) | C39: =$N$19+C38 -> 53790854 | D39: =$N$19+D38 -> 53790854
A40: Gasto real hoy (con autoabasto) ($/año) | C40: =C39-C38 -> 52141327 | D40: =D39-D38 -> 52141327
A41: Generación PV año 1 (kWh) | C41: =C72 -> 8114834 | D41: =C89 -> 1497142.3
A42: Energía facturada al PPA (kWh) | C42: =K72 -> 7952537 | D42: =K89 -> 1497144.3
A43: Ahorro bruto PV año 1 ($) | C43: =M72 -> 14011838 | D43: =M89 -> 2636463.3
A44: Ahorro bruto BESS año 1 c/merma ($) | C44: =R72*(12-Supuestos!$B$16)/12 -> 11356874 | D44: =R89*(12-Supuestos!$B$16)/12 -> 11356874
A45: Ahorro bruto total ($) | C45: =C43+C44 -> 25368712 | D45: =D43+D44 -> 13993338
A46: Pago PPA año 1 ($) | C46: =C42*C31 -> 8343801.8 | D46: =D42*D31 -> 1539363.8
A47: Pago participación BESS ($) | C47: =C44*C32 -> 5678437.2 | D47: =D44*D32 -> 5678437.2
A48: AHORRO NETO GEPP año 1 ($) | C48: =C45-C46-C47 -> 11346473 | D48: =D45-D46-D47 -> 6775536.7
A49: % ahorro bruto (vs gasto real hoy) | C49: =C45/$N$19 -> 0.48653752 | D49: =D45/$N$19 -> 0.26837325
A50: % ahorro neto (vs gasto real hoy) | C50: =C48/$N$19 -> 0.21760998 | D50: =D48/$N$19 -> 0.12994561
A51: TIR inversionista PV | C51: =IRR(M94:M114) -> 0.14315285 | D51: =IRR(M119:M139) -> 0.14314976
A52: TIR inversionista BESS | C52: =IRR(N94:N114) -> 0.1136277 | D52: =IRR(N119:N139) -> 0.1136277
A53: Participación req. p/ TIR BESS 16% | C53: 0.5961 | D53: 0.5961
A54: Payback simple inversionista PV (años) | C54: =COUNTIF(O94:O114,"<0") -> 7 | D54: =COUNTIF(O119:O139,"<0") -> 7
A55: VAN GEPP del ahorro neto 20a (@WACC) | C55: {=NPV(Supuestos!$B$21,J95:J114)} -> 1.2863038e+08 | D55: {=NPV(Supuestos!$B$21,J120:J139)} -> 73644042
A58: 3. MODELO MENSUAL AÑO 1 — OPCIÓN 1 — Autoconsumo (vertical)
B59: Mes | C59: Gen PV (kWh) | D59: %Base | E59: %Int | F59: %Punta | G59: PV→Base | H59: PV→Int | I59: PV→Punta | J59: Ahorro energía PV $ | K59: Energía PPA (kWh) | L59: Ahorro distrib/umbral $ (motor) | M59: Ahorro PV total $ | N59: BESS despl. punta kWh | O59: Costo carga base $ | P59: Ahorro arbitraje $ | Q59: Ahorro capacidad $ (motor) | R59: Ahorro BESS bruto $ | S59: Reducción dem. punta (kW) | T59: Dem. punta después (kW)
B60: may-25 | C60: =$C$26*B$21 -> 740230.4 | D60: 0.12903287 | E60: 0.86825987 | F60: 0 | G60: =C60*D60 -> 95514.052 | H60: =C60*E60 -> 642712.35 | I60: =C60*F60 -> 0 | J60: =G60*B$14+H60*B$15+I60*B$16 -> 1324739.6 | K60: =G60+H60+I60 -> 738226.4 | L60: 0 | M60: =J60+L60*$C$26/4550 -> 1324739.6 | N60: =MIN($C$30*B$11,$C$28*B$12*B$11,B$7) -> 118279 | O60: =N60/Supuestos!$B$14*B$14 -> 140998.42 | P60: =N60*B$16-O60 -> 123639.01 | Q60: =1162951*MIN(1,$C$30/6960) -> 1162951 | R60: =P60+Q60 -> 1286590 | S60: =Q60/B$17 -> 2688.1582 | T60: =B$9-S60 -> -0.15819888
B61: jun-25 | C61: =$C$26*C$21 -> 673764 | D61: 0.16642177 | E61: 0.83255413 | F61: 0 | G61: =C61*D61 -> 112129 | H61: =C61*E61 -> 560945 | I61: =C61*F61 -> 0 | J61: =G61*C$14+H61*C$15+I61*C$16 -> 1214252.5 | K61: =G61+H61+I61 -> 673074 | L61: 0 | M61: =J61+L61*$C$26/4550 -> 1214252.5 | N61: =MIN($C$30*C$11,$C$28*C$12*C$11,C$7) -> 116822 | O61: =N61/Supuestos!$B$14*C$14 -> 141999.57 | P61: =N61*C$16-O61 -> 125043.84 | Q61: =1231916*MIN(1,$C$30/6960) -> 1231916 | R61: =P61+Q61 -> 1356959.8 | S61: =Q61/C$17 -> 2781.4766 | T61: =C$9-S61 -> -0.47663129
B62: jul-25 | C62: =$C$26*D$21 -> 630775.6 | D62: 0.12766656 | E62: 0.87096687 | F62: 0 | G62: =C62*D62 -> 80528.949 | H62: =C62*E62 -> 549384.65 | I62: =C62*F62 -> 0 | J62: =G62*D$14+H62*D$15+I62*D$16 -> 1170565.4 | K62: =G62+H62+I62 -> 629913.6 | L62: 0 | M62: =J62+L62*$C$26/4550 -> 1170565.4 | N62: =MIN($C$30*D$11,$C$28*D$12*D$11,D$7) -> 122085 | O62: =N62/Supuestos!$B$14*D$14 -> 150253.57 | P62: =N62*D$16-O62 -> 132654 | Q62: =1193089*MIN(1,$C$30/6960) -> 1193089 | R62: =P62+Q62 -> 1325743 | S62: =Q62/D$17 -> 2654.0219 | T62: =D$9-S62 -> -0.021889042
B63: ago-25 | C63: =$C$26*E$21 -> 599180.4 | D63: 0.16129043 | E63: 0.83870957 | F63: 0 | G63: =C63*D63 -> 96642.065 | H63: =C63*E63 -> 502538.34 | I63: =C63*F63 -> 0 | J63: =G63*E$14+H63*E$15+I63*E$16 -> 1099293 | K63: =G63+H63+I63 -> 599180.4 | L63: 0 | M63: =J63+L63*$C$26/4550 -> 1099293 | N63: =MIN($C$30*E$11,$C$28*E$12*E$11,E$7) -> 146169.87 | O63: =N63/Supuestos!$B$14*E$14 -> 180108.69 | P63: =N63*E$16-O63 -> 159049.26 | Q63: =1566698*MIN(1,$C$30/6960) -> 1566698 | R63: =P63+Q63 -> 1725747.3 | S63: =Q63/E$17 -> 3480.2364 | T63: =E$9-S63 -> 723.76364
B64: sep-25 | C64: =$C$26*F$21 -> 576576 | D64: 0.13333368 | E64: 0.85261093 | F64: 0 | G64: =C64*D64 -> 76877 | H64: =C64*E64 -> 491595 | I64: =C64*F64 -> 0 | J64: =G64*F$14+H64*F$15+I64*F$16 -> 1048139 | K64: =G64+H64+I64 -> 568472 | L64: 0 | M64: =J64+L64*$C$26/4550 -> 1048139 | N64: =MIN($C$30*F$11,$C$28*F$12*F$11,F$7) -> 153130.34 | O64: =N64/Supuestos!$B$14*F$14 -> 187903.69 | P64: =N64*F$16-O64 -> 165046.43 | Q64: =1552359*MIN(1,$C$30/6960) -> 1552359 | R64: =P64+Q64 -> 1717405.4 | S64: =Q64/F$17 -> 3480.2354 | T64: =F$9-S64 -> 333.7646
B65: oct-25 | C65: =$C$26*G$21 -> 668012.8 | D65: 0.12852295 | E65: 0.85281873 | F65: 0.0025433637 | G65: =C65*D65 -> 85854.974 | H65: =C65*E65 -> 569693.83 | I65: =C65*F65 -> 1698.9995 | J65: =G65*G$14+H65*G$15+I65*G$16 -> 1214759.8 | K65: =G65+H65+I65 -> 657247.8 | L65: 0 | M65: =J65+L65*$C$26/4550 -> 1214759.8 | N65: =MIN($C$30*G$11,$C$28*G$12*G$11,G$7) -> 160090.81 | O65: =N65/Supuestos!$B$14*G$14 -> 196444.77 | P65: =N65*G$16-O65 -> 172548.54 | Q65: =776197*MIN(1,$C$30/6960) -> 776197 | R65: =P65+Q65 -> 948745.54 | S65: =Q65/G$17 -> 1740.1179 | T65: =G$9-S65 -> 2620.8821
B66: nov-25 | C66: =$C$26*H$21 -> 691236 | D66: 0.16925334 | E66: 0.80487561 | F66: 0.010513052 | G66: =C66*D66 -> 116994 | H66: =C66*E66 -> 556359 | I66: =C66*F66 -> 7267 | J66: =G66*H$14+H66*H$15+I66*H$16 -> 1205180.9 | K66: =G66+H66+I66 -> 680620 | L66: 0 | M66: =J66+L66*$C$26/4550 -> 1205180.9 | N66: =MIN($C$30*H$11,$C$28*H$12*H$11,H$7) -> 174011.75 | O66: =N66/Supuestos!$B$14*H$14 -> 208179.68 | P66: =N66*H$16-O66 -> 181902.46 | Q66: =752879*MIN(1,$C$30/6960) -> 752879 | R66: =P66+Q66 -> 934781.46 | S66: =Q66/H$17 -> 1740.117 | T66: =H$9-S66 -> 1361.883
B67: dic-25 | C67: =$C$26*I$21 -> 629647.2 | D67: 0.13103533 | E67: 0.85726447 | F67: 0.011700207 | G67: =C67*D67 -> 82506.026 | H67: =C67*E67 -> 539774.17 | I67: =C67*F67 -> 7367.0023 | J67: =G67*I$14+H67*I$15+I67*I$16 -> 1083862 | K67: =G67+H67+I67 -> 629647.2 | L67: 0 | M67: =J67+L67*$C$26/4550 -> 1083862 | N67: =MIN($C$30*I$11,$C$28*I$12*I$11,I$7) -> 187932.69 | O67: =N67/Supuestos!$B$14*I$14 -> 215535.31 | P67: =N67*I$16-O67 -> 186546.69 | Q67: =715241*MIN(1,$C$30/6960) -> 715241 | R67: =P67+Q67 -> 901787.69 | S67: =Q67/I$17 -> 1740.1187 | T67: =I$9-S67 -> 1364.8813
B68: ene-26 | C68: =$C$26*J$21 -> 669141.2 | D68: 0.13167628 | E68: 0.84356212 | F68: 0.011191961 | G68: =C68*D68 -> 88110.026 | H68: =C68*E68 -> 564462.17 | I68: =C68*F68 -> 7489.0022 | J68: =G68*J$14+H68*J$15+I68*J$16 -> 1110338.5 | K68: =G68+H68+I68 -> 660061.2 | L68: 0 | M68: =J68+L68*$C$26/4550 -> 1110338.5 | N68: =MIN($C$30*J$11,$C$28*J$12*J$11,J$7) -> 187932.69 | O68: =N68/Supuestos!$B$14*J$14 -> 210954.45 | P68: =N68*J$16-O68 -> 182332.3 | Q68: =699145*MIN(1,$C$30/6960) -> 699145 | R68: =P68+Q68 -> 881477.3 | S68: =Q68/J$17 -> 1740.119 | T68: =J$9-S68 -> 1270.881
B69: feb-26 | C69: =$C$26*K$21 -> 648211.2 | D69: 0.1285677 | E69: 0.77972913 | F69: 0.01126485 | G69: =C69*D69 -> 83339.026 | H69: =C69*E69 -> 505429.16 | I69: =C69*F69 -> 7302.0023 | J69: =G69*K$14+H69*K$15+I69*K$16 -> 1000757.2 | K69: =G69+H69+I69 -> 596070.18 | L69: 0 | M69: =J69+L69*$C$26/4550 -> 1000757.2 | N69: =MIN($C$30*K$11,$C$28*K$12*K$11,K$7) -> 148414 | O69: =N69/Supuestos!$B$14*K$14 -> 166672.01 | P69: =N69*K$16-O69 -> 144077.22 | Q69: =699527*MIN(1,$C$30/6960) -> 699527 | R69: =P69+Q69 -> 843604.22 | S69: =Q69/K$17 -> 1740.1169 | T69: =K$9-S69 -> 111.88308
B70: mar-26 | C70: =$C$26*L$21 -> 821475.2 | D70: 0.16051614 | E70: 0.77249703 | F70: 0.011192063 | G70: =C70*D70 -> 131860.03 | H70: =C70*E70 -> 634587.15 | I70: =C70*F70 -> 9194.0022 | J70: =G70*L$14+H70*L$15+I70*L$16 -> 1286607.8 | K70: =G70+H70+I70 -> 775641.19 | L70: 0 | M70: =J70+L70*$C$26/4550 -> 1286607.8 | N70: =MIN($C$30*L$11,$C$28*L$12*L$11,L$7) -> 178884 | O70: =N70/Supuestos!$B$14*L$14 -> 200983.63 | P70: =N70*L$16-O70 -> 173760.46 | Q70: =699979*MIN(1,$C$30/6960) -> 699979 | R70: =P70+Q70 -> 873739.46 | S70: =Q70/L$17 -> 1740.1158 | T70: =L$9-S70 -> 304.88415
B71: abr-26 | C71: =$C$26*M$21 -> 766584 | D71: 0.12543961 | E71: 0.84402231 | F71: 0.0015771266 | G71: =C71*D71 -> 96160 | H71: =C71*E71 -> 647014 | I71: =C71*F71 -> 1209 | J71: =G71*M$14+H71*M$15+I71*M$16 -> 1253341.9 | K71: =G71+H71+I71 -> 744383 | L71: 0 | M71: =J71+L71*$C$26/4550 -> 1253341.9 | N71: =MIN($C$30*M$11,$C$28*M$12*M$11,M$7) -> 135622 | O71: =N71/Supuestos!$B$14*M$14 -> 152376.97 | P71: =N71*M$16-O71 -> 131724 | Q71: =699944*MIN(1,$C$30/6960) -> 699944 | R71: =P71+Q71 -> 831668 | S71: =Q71/M$17 -> 1740.1154 | T71: =M$9-S71 -> 1185.8846
B72: TOTAL | C72: =SUM(C60:C71) -> 8114834 | G72: =SUM(G60:G71) -> 1146515.1 | H72: =SUM(H60:H71) -> 6764494.8 | I72: =SUM(I60:I71) -> 41527.009 | J72: =SUM(J60:J71) -> 14011838 | K72: =SUM(K60:K71) -> 7952537 | M72: =SUM(M60:M71) -> 14011838 | N72: =SUM(N60:N71) -> 1829374.2 | O72: =SUM(O60:O71) -> 2152410.8 | P72: =SUM(P60:P71) -> 1878324.2 | Q72: =SUM(Q60:Q71) -> 11749925 | R72: =SUM(R60:R71) -> 13628249 | S72: =AVERAGE(S60:S71) -> 2272.0791 | T72: =AVERAGE(T60:T71) -> 773.1709
A73: Q (Ahorro capacidad → flujo BESS) y L (Ahorro distrib/umbral → flujo PV) provienen de la simulación horaria al tamaño de diseño (memoria MC-GEPP-4SITIOS-2026-07 §4); escalan con MIN(1, E_útil/E_diseño). El rasurado que los sustenta se ilustra abajo (Despacho día típico, rasurado plano). Columnas S–T: demanda de punta facturable resultante mes a mes (Reducción = Q ÷ tarifa capacidad; Después = Dmáx punta − Reducción).
A75: 4. MODELO MENSUAL AÑO 1 — OPCIÓN 2 — GD Medición Neta (vertical)
B76: Mes | C76: Gen PV (kWh) | D76: %Base | E76: %Int | F76: %Punta | G76: PV→Base | H76: PV→Int | I76: PV→Punta | J76: Ahorro energía PV $ | K76: Energía PPA (kWh) | L76: Ahorro distrib/umbral $ (motor) | M76: Ahorro PV total $ | N76: BESS despl. punta kWh | O76: Costo carga base $ | P76: Ahorro arbitraje $ | Q76: Ahorro capacidad $ (motor) | R76: Ahorro BESS bruto $ | S76: Reducción dem. punta (kW) | T76: Dem. punta después (kW)
B77: may-25 | C77: =$D$26*B$21 -> 136568.44 | D77: 0.12903462 | E77: 0.8709727 | F77: 0 | G77: =C77*D77 -> 17622.057 | H77: =C77*E77 -> 118947.38 | I77: =C77*F77 -> 0 | J77: =G77*B$14+H77*B$15+I77*B$16 -> 245108.08 | K77: =G77+H77+I77 -> 136569.44 | L77: 0 | M77: =J77+L77*$D$26/839.45 -> 245108.08 | N77: =MIN($D$30*B$11,$D$28*B$12*B$11,B$7) -> 118279 | O77: =N77/Supuestos!$B$14*B$14 -> 140998.42 | P77: =N77*B$16-O77 -> 123639.01 | Q77: =1162951*MIN(1,$D$30/6960) -> 1162951 | R77: =P77+Q77 -> 1286590 | S77: =Q77/B$17 -> 2688.1582 | T77: =B$9-S77 -> -0.15819888
B78: jun-25 | C78: =$D$26*C$21 -> 124305.76 | D78: 0.16666935 | E78: 0.83333065 | F78: 0 | G78: =C78*D78 -> 20717.959 | H78: =C78*E78 -> 103587.8 | I78: =C78*F78 -> 0 | J78: =G78*C$14+H78*C$15+I78*C$16 -> 224245.26 | K78: =G78+H78+I78 -> 124305.76 | L78: 0 | M78: =J78+L78*$D$26/839.45 -> 224245.26 | N78: =MIN($D$30*C$11,$D$28*C$12*C$11,C$7) -> 116822 | O78: =N78/Supuestos!$B$14*C$14 -> 141999.57 | P78: =N78*C$16-O78 -> 125043.84 | Q78: =1231916*MIN(1,$D$30/6960) -> 1231916 | R78: =P78+Q78 -> 1356959.8 | S78: =Q78/C$17 -> 2781.4766 | T78: =C$9-S78 -> -0.47663129
B79: jul-25 | C79: =$D$26*D$21 -> 116374.63 | D79: 0.12903115 | E79: 0.87096885 | F79: 0 | G79: =C79*D79 -> 15015.953 | H79: =C79*E79 -> 101358.68 | I79: =C79*F79 -> 0 | J79: =G79*D$14+H79*D$15+I79*D$16 -> 216150.96 | K79: =G79+H79+I79 -> 116374.63 | L79: 0 | M79: =J79+L79*$D$26/839.45 -> 216150.96 | N79: =MIN($D$30*D$11,$D$28*D$12*D$11,D$7) -> 122085 | O79: =N79/Supuestos!$B$14*D$14 -> 150253.57 | P79: =N79*D$16-O79 -> 132654 | Q79: =1193089*MIN(1,$D$30/6960) -> 1193089 | R79: =P79+Q79 -> 1325743 | S79: =Q79/D$17 -> 2654.0219 | T79: =D$9-S79 -> -0.021889042
B80: ago-25 | C80: =$D$26*E$21 -> 110545.49 | D80: 0.16129178 | E80: 0.83871726 | F80: 0 | G80: =C80*D80 -> 17830.079 | H80: =C80*E80 -> 92716.412 | I80: =C80*F80 -> 0 | J80: =G80*E$14+H80*E$15+I80*E$16 -> 202815.37 | K80: =G80+H80+I80 -> 110546.49 | L80: 0 | M80: =J80+L80*$D$26/839.45 -> 202815.37 | N80: =MIN($D$30*E$11,$D$28*E$12*E$11,E$7) -> 146169.87 | O80: =N80/Supuestos!$B$14*E$14 -> 180108.69 | P80: =N80*E$16-O80 -> 159049.26 | Q80: =1566698*MIN(1,$D$30/6960) -> 1566698 | R80: =P80+Q80 -> 1725747.3 | S80: =Q80/E$17 -> 3480.2364 | T80: =E$9-S80 -> 723.76364
B81: sep-25 | C81: =$D$26*F$21 -> 106375.1 | D81: 0.1333302 | E81: 0.8666698 | F81: 0 | G81: =C81*D81 -> 14183.014 | H81: =C81*E81 -> 92192.09 | I81: =C81*F81 -> 0 | J81: =G81*F$14+H81*F$15+I81*F$16 -> 196288.56 | K81: =G81+H81+I81 -> 106375.1 | L81: 0 | M81: =J81+L81*$D$26/839.45 -> 196288.56 | N81: =MIN($D$30*F$11,$D$28*F$12*F$11,F$7) -> 153130.34 | O81: =N81/Supuestos!$B$14*F$14 -> 187903.69 | P81: =N81*F$16-O81 -> 165046.43 | Q81: =1552359*MIN(1,$D$30/6960) -> 1552359 | R81: =P81+Q81 -> 1717405.4 | S81: =Q81/F$17 -> 3480.2354 | T81: =F$9-S81 -> 333.7646
B82: oct-25 | C82: =$D$26*G$21 -> 123244.69 | D82: 0.12852448 | E82: 0.86892775 | F82: 0.0025396568 | G82: =C82*D82 -> 15839.96 | H82: =C82*E82 -> 107090.73 | I82: =C82*F82 -> 312.99922 | J82: =G82*G$14+H82*G$15+I82*G$16 -> 227982.94 | K82: =G82+H82+I82 -> 123243.69 | L82: 0 | M82: =J82+L82*$D$26/839.45 -> 227982.94 | N82: =MIN($D$30*G$11,$D$28*G$12*G$11,G$7) -> 160090.81 | O82: =N82/Supuestos!$B$14*G$14 -> 196444.77 | P82: =N82*G$16-O82 -> 172548.54 | Q82: =776197*MIN(1,$D$30/6960) -> 776197 | R82: =P82+Q82 -> 948745.54 | S82: =Q82/G$17 -> 1740.1179 | T82: =G$9-S82 -> 2620.8821
B83: nov-25 | C83: =$D$26*H$21 -> 127529.24 | D83: 0.16925562 | E83: 0.82023697 | F83: 0.010515255 | G83: =C83*D83 -> 21585.041 | H83: =C83*E83 -> 104604.2 | I83: =C83*F83 -> 1341.0026 | J83: =G83*H$14+H83*H$15+I83*H$16 -> 226063.35 | K83: =G83+H83+I83 -> 127530.24 | L83: 0 | M83: =J83+L83*$D$26/839.45 -> 226063.35 | N83: =MIN($D$30*H$11,$D$28*H$12*H$11,H$7) -> 174011.75 | O83: =N83/Supuestos!$B$14*H$14 -> 208179.68 | P83: =N83*H$16-O83 -> 181902.46 | Q83: =752879*MIN(1,$D$30/6960) -> 752879 | R83: =P83+Q83 -> 934781.46 | S83: =Q83/H$17 -> 1740.117 | T83: =H$9-S83 -> 1361.883
B84: dic-25 | C84: =$D$26*I$21 -> 116166.45 | D84: 0.13103662 | E84: 0.8572646 | F84: 0.011698776 | G84: =C84*D84 -> 15222.059 | H84: =C84*E84 -> 99585.385 | I84: =C84*F84 -> 1359.0052 | J84: =G84*I$14+H84*I$15+I84*I$16 -> 199966.42 | K84: =G84+H84+I84 -> 116166.45 | L84: 0 | M84: =J84+L84*$D$26/839.45 -> 199966.42 | N84: =MIN($D$30*I$11,$D$28*I$12*I$11,I$7) -> 187932.69 | O84: =N84/Supuestos!$B$14*I$14 -> 215535.31 | P84: =N84*I$16-O84 -> 186546.69 | Q84: =715241*MIN(1,$D$30/6960) -> 715241 | R84: =P84+Q84 -> 901787.69 | S84: =Q84/I$17 -> 1740.1187 | T84: =I$9-S84 -> 1364.8813
B85: ene-26 | C85: =$D$26*J$21 -> 123452.87 | D85: 0.13204215 | E85: 0.8567633 | F85: 0.011194544 | G85: =C85*D85 -> 16300.983 | H85: =C85*E85 -> 105769.89 | I85: =C85*F85 -> 1381.9986 | J85: =G85*J$14+H85*J$15+I85*J$16 -> 207787.11 | K85: =G85+H85+I85 -> 123452.87 | L85: 0 | M85: =J85+L85*$D$26/839.45 -> 207787.11 | N85: =MIN($D$30*J$11,$D$28*J$12*J$11,J$7) -> 187932.69 | O85: =N85/Supuestos!$B$14*J$14 -> 210954.45 | P85: =N85*J$16-O85 -> 182332.3 | Q85: =699145*MIN(1,$D$30/6960) -> 699145 | R85: =P85+Q85 -> 881477.3 | S85: =Q85/J$17 -> 1740.119 | T85: =J$9-S85 -> 1270.881
B86: feb-26 | C86: =$D$26*K$21 -> 119591.4 | D86: 0.14507781 | E86: 0.84366717 | F86: 0.011263389 | G86: =C86*D86 -> 17350.059 | H86: =C86*E86 -> 100895.34 | I86: =C86*F86 -> 1347.0046 | J86: =G86*K$14+H86*K$15+I86*K$16 -> 200312 | K86: =G86+H86+I86 -> 119592.4 | L86: 0 | M86: =J86+L86*$D$26/839.45 -> 200312 | N86: =MIN($D$30*K$11,$D$28*K$12*K$11,K$7) -> 148414 | O86: =N86/Supuestos!$B$14*K$14 -> 166672.01 | P86: =N86*K$16-O86 -> 144077.22 | Q86: =699527*MIN(1,$D$30/6960) -> 699527 | R86: =P86+Q86 -> 843604.22 | S86: =Q86/K$17 -> 1740.1169 | T86: =K$9-S86 -> 111.88308
B87: mar-26 | C87: =$D$26*L$21 -> 151557.66 | D87: 0.16278257 | E87: 0.8260204 | F87: 0.011190435 | G87: =C87*D87 -> 24670.945 | H87: =C87*E87 -> 125189.72 | I87: =C87*F87 -> 1695.9962 | J87: =G87*L$14+H87*L$15+I87*L$16 -> 252124.4 | K87: =G87+H87+I87 -> 151556.66 | L87: 0 | M87: =J87+L87*$D$26/839.45 -> 252124.4 | N87: =MIN($D$30*L$11,$D$28*L$12*L$11,L$7) -> 178884 | O87: =N87/Supuestos!$B$14*L$14 -> 200983.63 | P87: =N87*L$16-O87 -> 173760.46 | Q87: =699979*MIN(1,$D$30/6960) -> 699979 | R87: =P87+Q87 -> 873739.46 | S87: =Q87/L$17 -> 1740.1158 | T87: =L$9-S87 -> 304.88415
B88: abr-26 | C88: =$D$26*M$21 -> 141430.54 | D88: 0.13437648 | E88: 0.86404678 | F88: 0.0015767406 | G88: =C88*D88 -> 19004.938 | H88: =C88*E88 -> 122202.6 | I88: =C88*F88 -> 222.99927 | J88: =G88*M$14+H88*M$15+I88*M$16 -> 237618.85 | K88: =G88+H88+I88 -> 141430.54 | L88: 0 | M88: =J88+L88*$D$26/839.45 -> 237618.85 | N88: =MIN($D$30*M$11,$D$28*M$12*M$11,M$7) -> 135622 | O88: =N88/Supuestos!$B$14*M$14 -> 152376.97 | P88: =N88*M$16-O88 -> 131724 | Q88: =699944*MIN(1,$D$30/6960) -> 699944 | R88: =P88+Q88 -> 831668 | S88: =Q88/M$17 -> 1740.1154 | T88: =M$9-S88 -> 1185.8846
B89: TOTAL | C89: =SUM(C77:C88) -> 1497142.3 | G89: =SUM(G77:G88) -> 215343.05 | H89: =SUM(H77:H88) -> 1274140.2 | I89: =SUM(I77:I88) -> 7661.0057 | J89: =SUM(J77:J88) -> 2636463.3 | K89: =SUM(K77:K88) -> 1497144.3 | M89: =SUM(M77:M88) -> 2636463.3 | N89: =SUM(N77:N88) -> 1829374.2 | O89: =SUM(O77:O88) -> 2152410.8 | P89: =SUM(P77:P88) -> 1878324.2 | Q89: =SUM(Q77:Q88) -> 11749925 | R89: =SUM(R77:R88) -> 13628249 | S89: =AVERAGE(S77:S88) -> 2272.0791 | T89: =AVERAGE(T77:T88) -> 773.1709
A92: 5. PROYECCIÓN 20 AÑOS — OPCIÓN 1 — Autoconsumo (vertical, con cliff autoabasto 2032)
B93: Año | C93: Gasto CFE pleno $ | D93: Beneficio autoabasto $ | E93: Gasto real sin sistema $ | F93: Ahorro PV $ | G93: Ahorro BESS $ | H93: Pago PPA $ | I93: Pago particip. BESS $ | J93: Ahorro neto GEPP $ | K93: Acumulado GEPP $ | L93: % ahorro | M93: Flujo inv. PV $ | N93: Flujo inv. BESS $ | O93: Flujo inv. PV acum $ | P93: Flujo inv. BESS acum $
B94: Año 0 | C94: 0 | D94: 0 | E94: 0 | F94: 0 | G94: 0 | H94: 0 | I94: 0 | J94: 0 | K94: 0 | L94: 0 | M94: =-$C$34 -> -51904125 | N94: =-$C$36 -> -36363600 | O94: =M94 -> -51904125 | P94: =N94 -> -36363600
B95: =Supuestos!$B$25+1-1 -> 2026 | C95: =$C$39*(1+Supuestos!$B$9)^(1-1) -> 53790854 | D95: =IF(B95<=Supuestos!$B$26,$C$38*(1+Supuestos!$B$9)^(1-1),0) -> 1649527 | E95: =C95-D95 -> 52141327 | F95: =$C$43*(1+Supuestos!$B$9)^(1-1)*(1-Supuestos!$B$11)^(1-1) -> 14011838 | G95: =$C$44*(1+Supuestos!$B$9)^(1-1)*(1-Supuestos!$B$12)^(1-1) -> 11356874 | H95: =IF(1<=Supuestos!$B$18,$C$42*$C$31*(1+Supuestos!$B$10)^(1-1)*(1-Supuestos!$B$11)^(1-1),0) -> 8343801.8 | I95: =IF(1<=Supuestos!$B$19,G95*$C$32,0) -> 5678437.2 | J95: =F95+G95-H95-I95 -> 11346473 | K95: =K94+J95 -> 11346473 | L95: =IF(E95>0,J95/E95,0) -> 0.21760998 | M95: =IF(1<=Supuestos!$B$18,H95-Supuestos!$B$22*$C$26*(1+Supuestos!$B$9)^(1-1),0) -> 6933301.8 | N95: =IF(1<=Supuestos!$B$19,I95-Supuestos!$B$23*$C$29*(1+Supuestos!$B$9)^(1-1),0) -> 4346437.2 | O95: =O94+M95 -> -44970823 | P95: =P94+N95 -> -32017163
B96: =Supuestos!$B$25+2-1 -> 2027 | C96: =$C$39*(1+Supuestos!$B$9)^(2-1) -> 56480397 | D96: =IF(B96<=Supuestos!$B$26,$C$38*(1+Supuestos!$B$9)^(2-1),0) -> 1732003.3 | E96: =C96-D96 -> 54748393 | F96: =$C$43*(1+Supuestos!$B$9)^(2-1)*(1-Supuestos!$B$11)^(2-1) -> 14638867 | G96: =$C$44*(1+Supuestos!$B$9)^(2-1)*(1-Supuestos!$B$12)^(2-1) -> 11775659 | H96: =IF(2<=Supuestos!$B$18,$C$42*$C$31*(1+Supuestos!$B$10)^(2-1)*(1-Supuestos!$B$11)^(2-1),0) -> 8717186.9 | I96: =IF(2<=Supuestos!$B$19,G96*$C$32,0) -> 5887829.5 | J96: =F96+G96-H96-I96 -> 11809510 | K96: =K95+J96 -> 23155983 | L96: =IF(E96>0,J96/E96,0) -> 0.21570514 | M96: =IF(2<=Supuestos!$B$18,H96-Supuestos!$B$22*$C$26*(1+Supuestos!$B$9)^(2-1),0) -> 7236161.9 | N96: =IF(2<=Supuestos!$B$19,I96-Supuestos!$B$23*$C$29*(1+Supuestos!$B$9)^(2-1),0) -> 4489229.5 | O96: =O95+M96 -> -37734661 | P96: =P95+N96 -> -27527933
B97: =Supuestos!$B$25+3-1 -> 2028 | C97: =$C$39*(1+Supuestos!$B$9)^(3-1) -> 59304416 | D97: =IF(B97<=Supuestos!$B$26,$C$38*(1+Supuestos!$B$9)^(3-1),0) -> 1818603.5 | E97: =C97-D97 -> 57485813 | F97: =$C$43*(1+Supuestos!$B$9)^(3-1)*(1-Supuestos!$B$11)^(3-1) -> 15293957 | G97: =$C$44*(1+Supuestos!$B$9)^(3-1)*(1-Supuestos!$B$12)^(3-1) -> 12209887 | H97: =IF(3<=Supuestos!$B$18,$C$42*$C$31*(1+Supuestos!$B$10)^(3-1)*(1-Supuestos!$B$11)^(3-1),0) -> 9107281 | I97: =IF(3<=Supuestos!$B$19,G97*$C$32,0) -> 6104943.3 | J97: =F97+G97-H97-I97 -> 12291619 | K97: =K96+J97 -> 35447602 | L97: =IF(E97>0,J97/E97,0) -> 0.21382004 | M97: =IF(3<=Supuestos!$B$18,H97-Supuestos!$B$22*$C$26*(1+Supuestos!$B$9)^(3-1),0) -> 7552204.8 | N97: =IF(3<=Supuestos!$B$19,I97-Supuestos!$B$23*$C$29*(1+Supuestos!$B$9)^(3-1),0) -> 4636413.3 | O97: =O96+M97 -> -30182456 | P97: =P96+N97 -> -22891520
B98: =Supuestos!$B$25+4-1 -> 2029 | C98: =$C$39*(1+Supuestos!$B$9)^(4-1) -> 62269637 | D98: =IF(B98<=Supuestos!$B$26,$C$38*(1+Supuestos!$B$9)^(4-1),0) -> 1909533.6 | E98: =C98-D98 -> 60360104 | F98: =$C$43*(1+Supuestos!$B$9)^(4-1)*(1-Supuestos!$B$11)^(4-1) -> 15978361 | G98: =$C$44*(1+Supuestos!$B$9)^(4-1)*(1-Supuestos!$B$12)^(4-1) -> 12660126 | H98: =IF(4<=Supuestos!$B$18,$C$42*$C$31*(1+Supuestos!$B$10)^(4-1)*(1-Supuestos!$B$11)^(4-1),0) -> 9514831.9 | I98: =IF(4<=Supuestos!$B$19,G98*$C$32,0) -> 6330063 | J98: =F98+G98-H98-I98 -> 12793592 | K98: =K97+J98 -> 48241194 | L98: =IF(E98>0,J98/E98,0) -> 0.21195445 | M98: =IF(4<=Supuestos!$B$18,H98-Supuestos!$B$22*$C$26*(1+Supuestos!$B$9)^(4-1),0) -> 7882001.8 | N98: =IF(4<=Supuestos!$B$19,I98-Supuestos!$B$23*$C$29*(1+Supuestos!$B$9)^(4-1),0) -> 4788106.5 | O98: =O97+M98 -> -22300455 | P98: =P97+N98 -> -18103413
B99: =Supuestos!$B$25+5-1 -> 2030 | C99: =$C$39*(1+Supuestos!$B$9)^(5-1) -> 65383119 | D99: =IF(B99<=Supuestos!$B$26,$C$38*(1+Supuestos!$B$9)^(5-1),0) -> 2005010.3 | E99: =C99-D99 -> 63378109 | F99: =$C$43*(1+Supuestos!$B$9)^(5-1)*(1-Supuestos!$B$11)^(5-1) -> 16693393 | G99: =$C$44*(1+Supuestos!$B$9)^(5-1)*(1-Supuestos!$B$12)^(5-1) -> 13126968 | H99: =IF(5<=Supuestos!$B$18,$C$42*$C$31*(1+Supuestos!$B$10)^(5-1)*(1-Supuestos!$B$11)^(5-1),0) -> 9940620.6 | I99: =IF(5<=Supuestos!$B$19,G99*$C$32,0) -> 6563484.1 | J99: =F99+G99-H99-I99 -> 13316256 | K99: =K98+J99 -> 61557451 | L99: =IF(E99>0,J99/E99,0) -> 0.21010814 | M99: =IF(5<=Supuestos!$B$18,H99-Supuestos!$B$22*$C$26*(1+Supuestos!$B$9)^(5-1),0) -> 8226149 | N99: =IF(5<=Supuestos!$B$19,I99-Supuestos!$B$23*$C$29*(1+Supuestos!$B$9)^(5-1),0) -> 4944429.8 | O99: =O98+M99 -> -14074306 | P99: =P98+N99 -> -13158984
B100: =Supuestos!$B$25+6-1 -> 2031 | C100: =$C$39*(1+Supuestos!$B$9)^(6-1) -> 68652275 | D100: =IF(B100<=Supuestos!$B$26,$C$38*(1+Supuestos!$B$9)^(6-1),0) -> 2105260.8 | E100: =C100-D100 -> 66547014 | F100: =$C$43*(1+Supuestos!$B$9)^(6-1)*(1-Supuestos!$B$11)^(6-1) -> 17440422 | G100: =$C$44*(1+Supuestos!$B$9)^(6-1)*(1-Supuestos!$B$12)^(6-1) -> 13611025 | H100: =IF(6<=Supuestos!$B$18,$C$42*$C$31*(1+Supuestos!$B$10)^(6-1)*(1-Supuestos!$B$11)^(6-1),0) -> 10385463 | I100: =IF(6<=Supuestos!$B$19,G100*$C$32,0) -> 6805512.6 | J100: =F100+G100-H100-I100 -> 13860471 | K100: =K99+J100 -> 75417922 | L100: =IF(E100>0,J100/E100,0) -> 0.20828089 | M100: =IF(6<=Supuestos!$B$18,H100-Supuestos!$B$22*$C$26*(1+Supuestos!$B$9)^(6-1),0) -> 8585268.2 | N100: =IF(6<=Supuestos!$B$19,I100-Supuestos!$B$23*$C$29*(1+Supuestos!$B$9)^(6-1),0) -> 5105505.5 | O100: =O99+M100 -> -5489037.5 | P100: =P99+N100 -> -8053478.1
B101: =Supuestos!$B$25+7-1 -> 2032 | C101: =$C$39*(1+Supuestos!$B$9)^(7-1) -> 72084889 | D101: =IF(B101<=Supuestos!$B$26,$C$38*(1+Supuestos!$B$9)^(7-1),0) -> 2210523.9 | E101: =C101-D101 -> 69874365 | F101: =$C$43*(1+Supuestos!$B$9)^(7-1)*(1-Supuestos!$B$11)^(7-1) -> 18220881 | G101: =$C$44*(1+Supuestos!$B$9)^(7-1)*(1-Supuestos!$B$12)^(7-1) -> 14112932 | H101: =IF(7<=Supuestos!$B$18,$C$42*$C$31*(1+Supuestos!$B$10)^(7-1)*(1-Supuestos!$B$11)^(7-1),0) -> 10850213 | I101: =IF(7<=Supuestos!$B$19,G101*$C$32,0) -> 7056465.9 | J101: =F101+G101-H101-I101 -> 14427134 | K101: =K100+J101 -> 89845056 | L101: =IF(E101>0,J101/E101,0) -> 0.20647249 | M101: =IF(7<=Supuestos!$B$18,H101-Supuestos!$B$22*$C$26*(1+Supuestos!$B$9)^(7-1),0) -> 8960007.9 | N101: =IF(7<=Supuestos!$B$19,I101-Supuestos!$B$23*$C$29*(1+Supuestos!$B$9)^(7-1),0) -> 5271458.5 | O101: =O100+M101 -> 3470970.5 | P101: =P100+N101 -> -2782019.7
B102: =Supuestos!$B$25+8-1 -> 2033 | C102: =$C$39*(1+Supuestos!$B$9)^(8-1) -> 75689133 | D102: =IF(B102<=Supuestos!$B$26,$C$38*(1+Supuestos!$B$9)^(8-1),0) -> 0 | E102: =C102-D102 -> 75689133 | F102: =$C$43*(1+Supuestos!$B$9)^(8-1)*(1-Supuestos!$B$11)^(8-1) -> 19036266 | G102: =$C$44*(1+Supuestos!$B$9)^(8-1)*(1-Supuestos!$B$12)^(8-1) -> 14633346 | H102: =IF(8<=Supuestos!$B$18,$C$42*$C$31*(1+Supuestos!$B$10)^(8-1)*(1-Supuestos!$B$11)^(8-1),0) -> 11335760 | I102: =IF(8<=Supuestos!$B$19,G102*$C$32,0) -> 7316673 | J102: =F102+G102-H102-I102 -> 15017179 | K102: =K101+J102 -> 1.0486224e+08 | L102: =IF(E102>0,J102/E102,0) -> 0.19840601 | M102: =IF(8<=Supuestos!$B$18,H102-Supuestos!$B$22*$C$26*(1+Supuestos!$B$9)^(8-1),0) -> 9351044.7 | N102: =IF(8<=Supuestos!$B$19,I102-Supuestos!$B$23*$C$29*(1+Supuestos!$B$9)^(8-1),0) -> 5442415.3 | O102: =O101+M102 -> 12822015 | P102: =P101+N102 -> 2660395.6
B103: =Supuestos!$B$25+9-1 -> 2034 | C103: =$C$39*(1+Supuestos!$B$9)^(9-1) -> 79473590 | D103: =IF(B103<=Supuestos!$B$26,$C$38*(1+Supuestos!$B$9)^(9-1),0) -> 0 | E103: =C103-D103 -> 79473590 | F103: =$C$43*(1+Supuestos!$B$9)^(9-1)*(1-Supuestos!$B$11)^(9-1) -> 19888138 | G103: =$C$44*(1+Supuestos!$B$9)^(9-1)*(1-Supuestos!$B$12)^(9-1) -> 15172951 | H103: =IF(9<=Supuestos!$B$18,$C$42*$C$31*(1+Supuestos!$B$10)^(9-1)*(1-Supuestos!$B$11)^(9-1),0) -> 11843035 | I103: =IF(9<=Supuestos!$B$19,G103*$C$32,0) -> 7586475.4 | J103: =F103+G103-H103-I103 -> 15631579 | K103: =K102+J103 -> 1.2049381e+08 | L103: =IF(E103>0,J103/E103,0) -> 0.19668897 | M103: =IF(9<=Supuestos!$B$18,H103-Supuestos!$B$22*$C$26*(1+Supuestos!$B$9)^(9-1),0) -> 9759084.2 | N103: =IF(9<=Supuestos!$B$19,I103-Supuestos!$B$23*$C$29*(1+Supuestos!$B$9)^(9-1),0) -> 5618504.7 | O103: =O102+M103 -> 22581099 | P103: =P102+N103 -> 8278900.3
B104: =Supuestos!$B$25+10-1 -> 2035 | C104: =$C$39*(1+Supuestos!$B$9)^(10-1) -> 83447270 | D104: =IF(B104<=Supuestos!$B$26,$C$38*(1+Supuestos!$B$9)^(10-1),0) -> 0 | E104: =C104-D104 -> 83447270 | F104: =$C$43*(1+Supuestos!$B$9)^(10-1)*(1-Supuestos!$B$11)^(10-1) -> 20778133 | G104: =$C$44*(1+Supuestos!$B$9)^(10-1)*(1-Supuestos!$B$12)^(10-1) -> 15732453 | H104: =IF(10<=Supuestos!$B$18,$C$42*$C$31*(1+Supuestos!$B$10)^(10-1)*(1-Supuestos!$B$11)^(10-1),0) -> 12373011 | I104: =IF(10<=Supuestos!$B$19,G104*$C$32,0) -> 7866226.6 | J104: =F104+G104-H104-I104 -> 16271348 | K104: =K103+J104 -> 1.3676516e+08 | L104: =IF(E104>0,J104/E104,0) -> 0.19498958 | M104: =IF(10<=Supuestos!$B$18,H104-Supuestos!$B$22*$C$26*(1+Supuestos!$B$9)^(10-1),0) -> 10184862 | N104: =IF(10<=Supuestos!$B$19,I104-Supuestos!$B$23*$C$29*(1+Supuestos!$B$9)^(10-1),0) -> 5799857.5 | O104: =O103+M104 -> 32765962 | P104: =P103+N104 -> 14078758
B105: =Supuestos!$B$25+11-1 -> 2036 | C105: =$C$39*(1+Supuestos!$B$9)^(11-1) -> 87619633 | D105: =IF(B105<=Supuestos!$B$26,$C$38*(1+Supuestos!$B$9)^(11-1),0) -> 0 | E105: =C105-D105 -> 87619633 | F105: =$C$43*(1+Supuestos!$B$9)^(11-1)*(1-Supuestos!$B$11)^(11-1) -> 21707954 | G105: =$C$44*(1+Supuestos!$B$9)^(11-1)*(1-Supuestos!$B$12)^(11-1) -> 16312588 | H105: =IF(11<=Supuestos!$B$18,$C$42*$C$31*(1+Supuestos!$B$10)^(11-1)*(1-Supuestos!$B$11)^(11-1),0) -> 12926703 | I105: =IF(11<=Supuestos!$B$19,G105*$C$32,0) -> 8156293.8 | J105: =F105+G105-H105-I105 -> 16937545 | K105: =K104+J105 -> 1.5370271e+08 | L105: =IF(E105>0,J105/E105,0) -> 0.19330764 | M105: =IF(11<=Supuestos!$B$18,H105-Supuestos!$B$22*$C$26*(1+Supuestos!$B$9)^(11-1),0) -> 10629147 | N105: =IF(11<=Supuestos!$B$19,I105-Supuestos!$B$23*$C$29*(1+Supuestos!$B$9)^(11-1),0) -> 5986606.1 | O105: =O104+M105 -> 43395109 | P105: =P104+N105 -> 20065364
B106: =Supuestos!$B$25+12-1 -> 2037 | C106: =$C$39*(1+Supuestos!$B$9)^(12-1) -> 92000615 | D106: =IF(B106<=Supuestos!$B$26,$C$38*(1+Supuestos!$B$9)^(12-1),0) -> 0 | E106: =C106-D106 -> 92000615 | F106: =$C$43*(1+Supuestos!$B$9)^(12-1)*(1-Supuestos!$B$11)^(12-1) -> 22679385 | G106: =$C$44*(1+Supuestos!$B$9)^(12-1)*(1-Supuestos!$B$12)^(12-1) -> 16914114 | H106: =IF(12<=Supuestos!$B$18,$C$42*$C$31*(1+Supuestos!$B$10)^(12-1)*(1-Supuestos!$B$11)^(12-1),0) -> 13505173 | I106: =IF(12<=Supuestos!$B$19,G106*$C$32,0) -> 8457057.1 | J106: =F106+G106-H106-I106 -> 17631269 | K106: =K105+J106 -> 1.7133398e+08 | L106: =IF(E106>0,J106/E106,0) -> 0.19164295 | M106: =IF(12<=Supuestos!$B$18,H106-Supuestos!$B$22*$C$26*(1+Supuestos!$B$9)^(12-1),0) -> 11092739 | N106: =IF(12<=Supuestos!$B$19,I106-Supuestos!$B$23*$C$29*(1+Supuestos!$B$9)^(12-1),0) -> 6178885.1 | O106: =O105+M106 -> 54487849 | P106: =P105+N106 -> 26244249
B107: =Supuestos!$B$25+13-1 -> 2038 | C107: =$C$39*(1+Supuestos!$B$9)^(13-1) -> 96600645 | D107: =IF(B107<=Supuestos!$B$26,$C$38*(1+Supuestos!$B$9)^(13-1),0) -> 0 | E107: =C107-D107 -> 96600645 | F107: =$C$43*(1+Supuestos!$B$9)^(13-1)*(1-Supuestos!$B$11)^(13-1) -> 23694288 | G107: =$C$44*(1+Supuestos!$B$9)^(13-1)*(1-Supuestos!$B$12)^(13-1) -> 17537822 | H107: =IF(13<=Supuestos!$B$18,$C$42*$C$31*(1+Supuestos!$B$10)^(13-1)*(1-Supuestos!$B$11)^(13-1),0) -> 14109530 | I107: =IF(13<=Supuestos!$B$19,G107*$C$32,0) -> 8768911.1 | J107: =F107+G107-H107-I107 -> 18353669 | K107: =K106+J107 -> 1.8968764e+08 | L107: =IF(E107>0,J107/E107,0) -> 0.1899953 | M107: =IF(13<=Supuestos!$B$18,H107-Supuestos!$B$22*$C$26*(1+Supuestos!$B$9)^(13-1),0) -> 11576474 | N107: =IF(13<=Supuestos!$B$19,I107-Supuestos!$B$23*$C$29*(1+Supuestos!$B$9)^(13-1),0) -> 6376830.4 | O107: =O106+M107 -> 66064323 | P107: =P106+N107 -> 32621079
...

Sheet Acapulco
A1: GEPP Acapulco — Propuesta Solar + BESS | GDMTH (Centro Sur) | Acapulco de Juárez, Gro. (montos MXN sin IVA)
A3: 1. DATOS BASE — últimos 12 meses reales (recibos CFE, sin IVA)
A4: Mes | B4: may-25 | C4: jun-25 | D4: jul-25 | E4: ago-25 | F4: sep-25 | G4: oct-25 | H4: nov-25 | I4: dic-25 | J4: ene-26 | K4: feb-26 | L4: mar-26 | M4: abr-26 | N4: TOTAL
A5: Consumo Base (kWh) | B5: 312618 | C5: 233673 | D5: 213143 | E5: 210539 | F5: 197847 | G5: 172712 | H5: 248446 | I5: 268553 | J5: 172176 | K5: 167957 | L5: 206958 | M5: 210087 | N5: =SUM(B5:M5) -> 2614709
A6: Consumo Intermedia (kWh) | B6: 506177 | C6: 395913 | D6: 485674 | E6: 466847 | F6: 411635 | G6: 415203 | H6: 348173 | I6: 419527 | J6: 362748 | K6: 300801 | L6: 391377 | M6: 464168 | N6: =SUM(B6:M6) -> 4968243
A7: Consumo Punta (kWh) | B7: 49413 | C7: 42282 | D7: 56718 | E7: 44577 | F7: 49268 | G7: 56344 | H7: 86947 | I7: 116821 | J7: 101854 | K7: 87531 | L7: 105161 | M7: 60762 | N7: =SUM(B7:M7) -> 857678
A8: Consumo Total (kWh) | B8: =SUM(B5:B7) -> 868208 | C8: =SUM(C5:C7) -> 671868 | D8: =SUM(D5:D7) -> 755535 | E8: =SUM(E5:E7) -> 721963 | F8: =SUM(F5:F7) -> 658750 | G8: =SUM(G5:G7) -> 644259 | H8: =SUM(H5:H7) -> 683566 | I8: =SUM(I5:I7) -> 804901 | ... M8: =SUM(M5:M7) -> 735017 | N8: =SUM(B8:M8) -> 8440630
A9: Dem. máx. en punta (kW) | B9: 1123 | C9: 1007 | D9: 1233 | E9: 1061 | F9: 1120 | G9: 1124 | H9: 1061 | I9: 1282 | J9: 1141 | K9: 1092 | L9: 1202 | M9: 1311 | N9: =MAX(B9:M9) -> 1311
A10: Dem. máx. mensual (kW) | B10: 1417 | C10: 1033 | D10: 1233 | E10: 1108 | F10: 1120 | G10: 1124 | H10: 1282 | I10: 1433 | J10: 1141 | K10: 1092 | L10: 1202 | M10: 1311 | N10: =MAX(B10:M10) -> 1433
A11: Días con punta | B11: 22 | C11: 21 | D11: 23 | E11: 21 | F11: 22 | G11: 23 | H11: 25 | I11: 27 | J11: 27 | K11: 24 | L11: 26 | M11: 23
A12: Horas punta/día | B12: 2 | C12: 2 | D12: 2 | E12: 2 | F12: 2 | G12: 2.43 | H12: 3.6 | I12: 3.7 | J12: 3.63 | K12: 3.67 | L12: 3.69 | M12: 2.26
A13: Días del mes | B13: 31 | C13: 30 | D13: 31 | E13: 31 | F13: 30 | G13: 31 | H13: 30 | I13: 31 | J13: 31 | K13: 28 | L13: 31 | M13: 30
A14: Tarifa Base ($/kWh) | B14: 1.0246 | C14: 1.0444 | D14: 1.0571 | E14: 1.0583 | F14: 1.0545 | G14: 1.0545 | H14: 1.0288 | I14: 0.9872 | J14: 0.9664 | K14: 0.9668 | L14: 0.9673 | M14: 0.9673
A15: Tarifa Intermedia ($/kWh) | B15: 1.8215 | C15: 1.8602 | D15: 1.8852 | E15: 1.8875 | F15: 1.8761 | G15: 1.8761 | H15: 1.8257 | I15: 1.7443 | J15: 1.7064 | K15: 1.7073 | L15: 1.7082 | M15: 1.7082
A16: Tarifa Punta ($/kWh) | B16: 2.0638 | C16: 2.1082 | D16: 2.1369 | E16: 2.1396 | F16: 2.1259 | G16: 2.1259 | H16: 2.068 | I16: 1.9745 | J16: 1.9314 | K16: 1.9325 | L16: 1.9335 | M16: 1.9334
A17: Tarifa Capacidad ($/kW·mes) | B17: 392.89 | C17: 402.23 | D17: 408.26 | E17: 408.83 | F17: 405.09 | G17: 405.09 | H17: 392.93 | I17: 373.28 | J17: 364.88 | K17: 365.09 | L17: 365.31 | M17: 365.3
A18: Tarifa Distribución ($/kW·mes) | B18: 230.35 | C18: 230.35 | D18: 230.35 | E18: 230.35 | F18: 230.35 | G18: 230.35 | H18: 230.35 | I18: 230.35 | J18: 221.09 | K18: 221.09 | L18: 221.09 | M18: 221.09
A19: Gasto actual facturado ($ MXN) | B19: 2520372 | C19: 2223521 | D19: 2510130 | E19: 2435442 | F19: 2253138 | G19: 2183503 | H19: 2247709 | I19: 2457378 | J19: 1987516 | K19: 1813798 | L19: 2181066 | M19: 2248346 | N19: =SUM(B19:M19) -> 27061919
A20: Umbral de demanda (kW) | B20: =B8/(24*B13*Supuestos!$B$15) -> 2047.2741 | C20: =C8/(24*C13*Supuestos!$B$15) -> 1637.1053 | D20: =D8/(24*D13*Supuestos!$B$15) -> 1781.586 | E20: =E8/(24*E13*Supuestos!$B$15) -> 1702.4217 | F20: =F8/(24*F13*Supuestos!$B$15) -> 1605.1413 | G20: =G8/(24*G13*Supuestos!$B$15) -> 1519.1921 | H20: =H8/(24*H13*Supuestos!$B$15) -> 1665.6092 | I20: =I8/(24*I13*Supuestos!$B$15) -> 1897.9933 | ... M20: =M8/(24*M13*Supuestos!$B$15) -> 1790.9771
A21: Yield PV (kWh/kWp) | B21: 166.408 | C21: 146.88 | D21: 156.984 | E21: 143.592 | F21: 129.84 | G21: 152.768 | H21: 154.32 | I21: 153.264 | J21: 159.712 | K21: 150.528 | L21: 184.512 | M21: 170.64 | N21: =SUM(B21:M21) -> 1869.448
A23: 2. SISTEMA PROPUESTO — Opción 1 y Opción 2 (amarillo = editable)
A24: Concepto | C24: OPCIÓN 1 — Autoconsumo | D24: OPCIÓN 2 — GD Medición Neta
A25: Esquema legal | C25: Autoconsumo interconectado (permiso CNE simplificado) | D25: Generación Distribuida <0.7 MW (sin permiso)
A26: Potencia PV (kWp DC) | C26: 1618 | D26: 839.45
A27: Superficie requerida (m²) | C27: =C26*Supuestos!$B$24 -> 6472 | D27: =D26*Supuestos!$B$24 -> 3357.8
A28: BESS potencia (kW) | C28: 1648 | D28: 1648
A29: BESS capacidad (kWh) | C29: 3296 | D29: 3296
A30: Energía útil BESS (kWh) | C30: =C29*Supuestos!$B$13*SQRT(Supuestos!$B$14) -> 3100.231 | D30: =D29*Supuestos!$B$13*SQRT(Supuestos!$B$14) -> 3100.231
A31: Precio PPA (MXN/kWh, año 1) | C31: 1.2257987 | D31: 1.4341607
A32: Participación inversionista BESS (%) | C32: =Supuestos!$B$17 -> 0.5 | D32: =Supuestos!$B$17 -> 0.5
A33: CAPEX PV (USD) | C33: =C26*1000*Supuestos!$B$5 -> 1051700 | D33: =D26*1000*Supuestos!$B$5 -> 545642.5
A34: CAPEX PV (MXN) | C34: =C33*Supuestos!$B$4 -> 18457335 | D34: =D33*Supuestos!$B$4 -> 9576025.9
A35: CAPEX BESS (USD) | C35: =C29*1000*Supuestos!$B$7 -> 922880 | D35: =D29*1000*Supuestos!$B$7 -> 922880
A36: CAPEX BESS (MXN) | C36: =C35*Supuestos!$B$4 -> 16196544 | D36: =D35*Supuestos!$B$4 -> 16196544
A37: — Autoabasto TALA / ENEL (vence 2032) —
A38: Beneficio autoabasto actual ($/año) | C38: 0 | D38: =C38 -> 0
A39: Gasto sin autoabasto — CFE pleno ($/año) | C39: =$N$19+C38 -> 27061919 | D39: =$N$19+D38 -> 27061919
A40: Gasto real hoy (con autoabasto) ($/año) | C40: =C39-C38 -> 27061919 | D40: =D39-D38 -> 27061919
A41: Generación PV año 1 (kWh) | C41: =C72 -> 3024766.9 | D41: =C89 -> 1569308.1
A42: Energía facturada al PPA (kWh) | C42: =K72 -> 2964267.8 | D42: =K89 -> 1569312.1
A43: Ahorro bruto PV año 1 ($) | C43: =M72 -> 5639214.4 | D43: =M89 -> 3104779
A44: Ahorro bruto BESS año 1 c/merma ($) | C44: =R72*(12-Supuestos!$B$16)/12 -> 4180289.6 | D44: =R89*(12-Supuestos!$B$16)/12 -> 4180289.6
A45: Ahorro bruto total ($) | C45: =C43+C44 -> 9819504 | D45: =D43+D44 -> 7285068.6
A46: Pago PPA año 1 ($) | C46: =C42*C31 -> 2967232.1 | D46: =D42*D31 -> 1539495.2
A47: Pago participación BESS ($) | C47: =C44*C32 -> 2090144.8 | D47: =D44*D32 -> 2090144.8
A48: AHORRO NETO GEPP año 1 ($) | C48: =C45-C46-C47 -> 4762127.1 | D48: =D45-D46-D47 -> 3655428.6
A49: % ahorro bruto (vs gasto real hoy) | C49: =C45/$N$19 -> 0.3628532 | D49: =D45/$N$19 -> 0.2692
A50: % ahorro neto (vs gasto real hoy) | C50: =C48/$N$19 -> 0.17597152 | D50: =D48/$N$19 -> 0.13507647
A51: TIR inversionista PV | C51: =IRR(M94:M114) -> 0.1431631 | D51: =IRR(M119:M139) -> 0.14316836
A52: TIR inversionista BESS | C52: =IRR(N94:N114) -> 0.071985139 | D52: =IRR(N119:N139) -> 0.071985139
A53: Participación req. p/ TIR BESS 16% | C53: 0.7236 | D53: 0.7236
A54: Payback simple inversionista PV (años) | C54: =COUNTIF(O94:O114,"<0") -> 7 | D54: =COUNTIF(O119:O139,"<0") -> 7
A55: VAN GEPP del ahorro neto 20a (@WACC) | C55: {=NPV(Supuestos!$B$21,J95:J114)} -> 53050225 | D55: {=NPV(Supuestos!$B$21,J120:J139)} -> 40039295
A58: 3. MODELO MENSUAL AÑO 1 — OPCIÓN 1 — Autoconsumo (vertical)
B59: Mes | C59: Gen PV (kWh) | D59: %Base | E59: %Int | F59: %Punta | G59: PV→Base | H59: PV→Int | I59: PV→Punta | J59: Ahorro energía PV $ | K59: Energía PPA (kWh) | L59: Ahorro distrib/umbral $ (motor) | M59: Ahorro PV total $ | N59: BESS despl. punta kWh | O59: Costo carga base $ | P59: Ahorro arbitraje $ | Q59: Ahorro capacidad $ (motor) | R59: Ahorro BESS bruto $ | S59: Reducción dem. punta (kW) | T59: Dem. punta después (kW)
B60: may-25 | C60: =$C$26*B$21 -> 269248.14 | D60: 0.12903346 | E60: 0.87096654 | F60: 0 | G60: =C60*D60 -> 34742.019 | H60: =C60*E60 -> 234506.13 | I60: =C60*F60 -> 0 | J60: =G60*B$14+H60*B$15+I60*B$16 -> 462749.58 | K60: =G60+H60+I60 -> 269248.14 | L60: 31009 | M60: =J60+L60*$C$26/1618 -> 493758.58 | N60: =MIN($C$30*B$11,$C$28*B$12*B$11,B$7) -> 49413 | O60: =N60/Supuestos!$B$14*B$14 -> 52738.083 | P60: =N60*B$16-O60 -> 49240.466 | Q60: =441224*MIN(1,$C$30/3100) -> 441224 | R60: =P60+Q60 -> 490464.47 | S60: =Q60/B$17 -> 1123.0217 | T60: =B$9-S60 -> -0.021710911
B61: jun-25 | C61: =$C$26*C$21 -> 237651.84 | D61: 0.16666807 | E61: 0.83135425 | F61: 0 | G61: =C61*D61 -> 39608.973 | H61: =C61*E61 -> 197572.87 | I61: =C61*F61 -> 0 | J61: =G61*C$14+H61*C$15+I61*C$16 -> 408892.66 | K61: =G61+H61+I61 -> 237181.84 | L61: 22603 | M61: =J61+L61*$C$26/1618 -> 431495.66 | N61: =MIN($C$30*C$11,$C$28*C$12*C$11,C$7) -> 42282 | O61: =N61/Supuestos!$B$14*C$14 -> 45999.293 | P61: =N61*C$16-O61 -> 43139.62 | Q61: =404931*MIN(1,$C$30/3100) -> 404931 | R61: =P61+Q61 -> 448070.62 | S61: =Q61/C$17 -> 1006.7151 | T61: =C$9-S61 -> 0.28493648
B62: jul-25 | C62: =$C$26*D$21 -> 254000.11 | D62: 0.12725984 | E62: 0.8709685 | F62: 0 | G62: =C62*D62 -> 32324.014 | H62: =C62*E62 -> 221226.1 | I62: =C62*F62 -> 0 | J62: =G62*D$14+H62*D$15+I62*D$16 -> 451225.15 | K62: =G62+H62+I62 -> 253550.11 | L62: 54790 | M62: =J62+L62*$C$26/1618 -> 506015.15 | N62: =MIN($C$30*D$11,$C$28*D$12*D$11,D$7) -> 56718 | O62: =N62/Supuestos!$B$14*D$14 -> 62454.789 | P62: =N62*D$16-O62 -> 58745.905 | Q62: =503385*MIN(1,$C$30/3100) -> 503385 | R62: =P62+Q62 -> 562130.9 | S62: =Q62/D$17 -> 1233.001 | T62: =D$9-S62 -> -0.0010287562
B63: ago-25 | C63: =$C$26*E$21 -> 232331.86 | D63: 0.16005544 | E63: 0.83870926 | F63: 0 | G63: =C63*D63 -> 37185.977 | H63: =C63*E63 -> 194858.88 | I63: =C63*F63 -> 0 | J63: =G63*E$14+H63*E$15+I63*E$16 -> 407150.05 | K63: =G63+H63+I63 -> 232044.86 | L63: 27226 | M63: =J63+L63*$C$26/1618 -> 434376.05 | N63: =MIN($C$30*E$11,$C$28*E$12*E$11,E$7) -> 44577 | O63: =N63/Supuestos!$B$14*E$14 -> 49141.499 | P63: =N63*E$16-O63 -> 46235.45 | Q63: =433915*MIN(1,$C$30/3100) -> 433915 | R63: =P63+Q63 -> 480150.45 | S63: =Q63/E$17 -> 1061.358 | T63: =E$9-S63 -> -0.35802167
B64: sep-25 | C64: =$C$26*F$21 -> 210081.12 | D64: 0.13333429 | E64: 0.86666571 | F64: 0 | G64: =C64*D64 -> 28011.016 | H64: =C64*E64 -> 182070.1 | I64: =C64*F64 -> 0 | J64: =G64*F$14+H64*F$15+I64*F$16 -> 371119.34 | K64: =G64+H64+I64 -> 210081.12 | L64: 55789 | M64: =J64+L64*$C$26/1618 -> 426908.34 | N64: =MIN($C$30*F$11,$C$28*F$12*F$11,F$7) -> 49268 | O64: =N64/Supuestos!$B$14*F$14 -> 54117.819 | P64: =N64*F$16-O64 -> 50621.022 | Q64: =453590*MIN(1,$C$30/3100) -> 453590 | R64: =P64+Q64 -> 504211.02 | S64: =Q64/F$17 -> 1119.7265 | T64: =F$9-S64 -> 0.27351946
B65: oct-25 | C65: =$C$26*G$21 -> 247178.62 | D65: 0.11640957 | E65: 0.86614963 | F65: 0.0025447146 | G65: =C65*D65 -> 28773.956 | H65: =C65*E65 -> 214093.67 | I65: =C65*F65 -> 628.99904 | J65: =G65*G$14+H65*G$15+I65*G$16 -> 433340.47 | K65: =G65+H65+I65 -> 243496.63 | L65: 59144 | M65: =J65+L65*$C$26/1618 -> 492484.47 | N65: =MIN($C$30*G$11,$C$28*G$12*G$11,G$7) -> 56344 | O65: =N65/Supuestos!$B$14*G$14 -> 61890.363 | P65: =N65*G$16-O65 -> 57891.347 | Q65: =313968*MIN(1,$C$30/3100) -> 313968 | R65: =P65+Q65 -> 371859.35 | S65: =Q65/G$17 -> 775.05739 | T65: =G$9-S65 -> 348.94261
B66: nov-25 | C66: =$C$26*H$21 -> 249689.76 | D66: 0.16925387 | E66: 0.80440146 | F66: 0.010513036 | G66: =C66*D66 -> 42260.959 | H66: =C66*E66 -> 200850.81 | I66: =C66*F66 -> 2624.9975 | J66: =G66*H$14+H66*H$15+I66*H$16 -> 415599.89 | K66: =G66+H66+I66 -> 245736.76 | L66: 59994 | M66: =J66+L66*$C$26/1618 -> 475593.89 | N66: =MIN($C$30*H$11,$C$28*H$12*H$11,H$7) -> 77505.775 | O66: =N66/Supuestos!$B$14*H$14 -> 83060.355 | P66: =N66*H$16-O66 -> 77221.587 | Q66: =304543*MIN(1,$C$30/3100) -> 304543 | R66: =P66+Q66 -> 381764.59 | S66: =Q66/H$17 -> 775.05663 | T66: =H$9-S66 -> 285.94337
B67: dic-25 | C67: =$C$26*I$21 -> 247981.15 | D67: 0.13103423 | E67: 0.85726326 | F67: 0.011702509 | G67: =C67*D67 -> 32494.02 | H67: =C67*E67 -> 212585.13 | I67: =C67*F67 -> 2902.0018 | J67: =G67*I$14+H67*I$15+I67*I$16 -> 408620.34 | K67: =G67+H67+I67 -> 247981.15 | L67: 57661 | M67: =J67+L67*$C$26/1618 -> 466281.34 | N67: =MIN($C$30*I$11,$C$28*I$12*I$11,I$7) -> 83706.237 | O67: =N67/Supuestos!$B$14*I$14 -> 86077.913 | P67: =N67*I$16-O67 -> 79200.051 | Q67: =289313*MIN(1,$C$30/3100) -> 289313 | R67: =P67+Q67 -> 368513.05 | S67: =Q67/I$17 -> 775.05626 | T67: =I$9-S67 -> 506.94374
B68: ene-26 | C68: =$C$26*J$21 -> 258414.02 | D68: 0.11539235 | E68: 0.83390219 | F68: 0.011191344 | G68: =C68*D68 -> 29819.002 | H68: =C68*E68 -> 215492.01 | I68: =C68*F68 -> 2892.0002 | J68: =G68*J$14+H68*J$15+I68*J$16 -> 402118.26 | K68: =G68+H68+I68 -> 248203.02 | L68: 66179 | M68: =J68+L68*$C$26/1618 -> 468297.26 | N68: =MIN($C$30*J$11,$C$28*J$12*J$11,J$7) -> 83706.237 | O68: =N68/Supuestos!$B$14*J$14 -> 84264.278 | P68: =N68*J$16-O68 -> 77405.947 | Q68: =282804*MIN(1,$C$30/3100) -> 282804 | R68: =P68+Q68 -> 360209.95 | S68: =Q68/J$17 -> 775.06029 | T68: =J$9-S68 -> 365.93971
B69: feb-26 | C69: =$C$26*K$21 -> 243554.3 | D69: 0.12814817 | E69: 0.7739023 | F69: 0.011266495 | G69: =C69*D69 -> 31211.039 | H69: =C69*E69 -> 188487.24 | I69: =C69*F69 -> 2744.0034 | J69: =G69*K$14+H69*K$15+I69*K$16 -> 357281.88 | K69: =G69+H69+I69 -> 222442.28 | L69: 68744 | M69: =J69+L69*$C$26/1618 -> 426025.88 | N69: =MIN($C$30*K$11,$C$28*K$12*K$11,K$7) -> 74405.544 | O69: =N69/Supuestos!$B$14*K$14 -> 74932.583 | P69: =N69*K$16-O69 -> 68856.13 | Q69: =282966*MIN(1,$C$30/3100) -> 282966 | R69: =P69+Q69 -> 351822.13 | S69: =Q69/K$17 -> 775.0582 | T69: =K$9-S69 -> 316.9418
B70: mar-26 | C70: =$C$26*L$21 -> 298540.42 | D70: 0.14202117 | E70: 0.78766329 | F70: 0.01119113 | G70: =C70*D70 -> 42399.059 | H70: =C70*E70 -> 235149.33 | I70: =C70*F70 -> 3341.0047 | J70: =G70*L$14+H70*L$15+I70*L$16 -> 449154.52 | K70: =G70+H70+I70 -> 280889.39 | L70: 60076 | M70: =J70+L70*$C$26/1618 -> 509230.52 | N70: =MIN($C$30*L$11,$C$28*L$12*L$11,L$7) -> 80606.006 | O70: =N70/Supuestos!$B$14*L$14 -> 81218.947 | P70: =N70*L$16-O70 -> 74632.765 | Q70: =283136*MIN(1,$C$30/3100) -> 283136 | R70: =P70+Q70 -> 357768.76 | S70: =Q70/L$17 -> 775.0568 | T70: =L$9-S70 -> 426.9432
B71: abr-26 | C71: =$C$26*M$21 -> 276095.52 | D71: 0.12646688 | E71: 0.86223995 | F71: 0.0015755389 | G71: =C71*D71 -> 34916.939 | H71: =C71*E71 -> 238060.59 | I71: =C71*F71 -> 434.99924 | J71: =G71*M$14+H71*M$15+I71*M$16 -> 441271.28 | K71: =G71+H71+I71 -> 273412.52 | L71: 67476 | M71: =J71+L71*$C$26/1618 -> 508747.28 | N71: =MIN($C$30*M$11,$C$28*M$12*M$11,M$7) -> 60762 | O71: =N71/Supuestos!$B$14*M$14 -> 61224.044 | P71: =N71*M$16-O71 -> 56253.206 | Q71: =283129*MIN(1,$C$30/3100) -> 283129 | R71: =P71+Q71 -> 339382.21 | S71: =Q71/M$17 -> 775.05886 | T71: =M$9-S71 -> 535.94114
B72: TOTAL | C72: =SUM(C60:C71) -> 3024766.9 | G72: =SUM(G60:G71) -> 413746.97 | H72: =SUM(H60:H71) -> 2534952.8 | I72: =SUM(I60:I71) -> 15568.006 | J72: =SUM(J60:J71) -> 5008523.4 | K72: =SUM(K60:K71) -> 2964267.8 | M72: =SUM(M60:M71) -> 5639214.4 | N72: =SUM(N60:N71) -> 759293.8 | O72: =SUM(O60:O71) -> 797119.97 | P72: =SUM(P60:P71) -> 739443.5 | Q72: =SUM(Q60:Q71) -> 4276904 | R72: =SUM(R60:R71) -> 5016347.5 | S72: =AVERAGE(S60:S71) -> 914.10223 | T72: =AVERAGE(T60:T71) -> 232.31444
A73: Q (Ahorro capacidad → flujo BESS) y L (Ahorro distrib/umbral → flujo PV) provienen de la simulación horaria al tamaño de diseño (memoria MC-GEPP-4SITIOS-2026-07 §4); escalan con MIN(1, E_útil/E_diseño). El rasurado que los sustenta se ilustra abajo (Despacho día típico, rasurado plano). Columnas S–T: demanda de punta facturable resultante mes a mes (Reducción = Q ÷ tarifa capacidad; Después = Dmáx punta − Reducción).
A75: 4. MODELO MENSUAL AÑO 1 — OPCIÓN 2 — GD Medición Neta (vertical)
B76: Mes | C76: Gen PV (kWh) | D76: %Base | E76: %Int | F76: %Punta | G76: PV→Base | H76: PV→Int | I76: PV→Punta | J76: Ahorro energía PV $ | K76: Energía PPA (kWh) | L76: Ahorro distrib/umbral $ (motor) | M76: Ahorro PV total $ | N76: BESS despl. punta kWh | O76: Costo carga base $ | P76: Ahorro arbitraje $ | Q76: Ahorro capacidad $ (motor) | R76: Ahorro BESS bruto $ | S76: Reducción dem. punta (kW) | T76: Dem. punta después (kW)
B77: may-25 | C77: =$D$26*B$21 -> 139691.2 | D77: 0.1290348 | E77: 0.87097236 | F77: 0 | G77: =C77*D77 -> 18025.025 | H77: =C77*E77 -> 121667.17 | I77: =C77*F77 -> 0 | J77: =G77*B$14+H77*B$15+I77*B$16 -> 240085.19 | K77: =G77+H77+I77 -> 139692.2 | L77: 16370 | M77: =J77+L77*$D$26/839.45 -> 256455.19 | N77: =MIN($D$30*B$11,$D$28*B$12*B$11,B$7) -> 49413 | O77: =N77/Supuestos!$B$14*B$14 -> 52738.083 | P77: =N77*B$16-O77 -> 49240.466 | Q77: =441224*MIN(1,$D$30/3100) -> 441224 | R77: =P77+Q77 -> 490464.47 | S77: =Q77/B$17 -> 1123.0217 | T77: =B$9-S77 -> -0.021710911
B78: jun-25 | C78: =$D$26*C$21 -> 123298.42 | D78: 0.16666937 | E78: 0.83333874 | F78: 0 | G78: =C78*D78 -> 20550.069 | H78: =C78*E78 -> 102749.35 | I78: =C78*F78 -> 0 | J78: =G78*C$14+H78*C$15+I78*C$16 -> 212596.83 | K78: =G78+H78+I78 -> 123299.42 | L78: 14931 | M78: =J78+L78*$D$26/839.45 -> 227527.83 | N78: =MIN($D$30*C$11,$D$28*C$12*C$11,C$7) -> 42282 | O78: =N78/Supuestos!$B$14*C$14 -> 45999.293 | P78: =N78*C$16-O78 -> 43139.62 | Q78: =404931*MIN(1,$D$30/3100) -> 404931 | R78: =P78+Q78 -> 448070.62 | S78: =Q78/C$17 -> 1006.7151 | T78: =C$9-S78 -> 0.28493648
B79: jul-25 | C79: =$D$26*D$21 -> 131780.22 | D79: 0.12903324 | E79: 0.87096676 | F79: 0 | G79: =C79*D79 -> 17004.028 | H79: =C79*E79 -> 114776.19 | I79: =C79*F79 -> 0 | J79: =G79*D$14+H79*D$15+I79*D$16 -> 234351.03 | K79: =G79+H79+I79 -> 131780.22 | L79: 40467 | M79: =J79+L79*$D$26/839.45 -> 274818.03 | N79: =MIN($D$30*D$11,$D$28*D$12*D$11,D$7) -> 56718 | O79: =N79/Supuestos!$B$14*D$14 -> 62454.789 | P79: =N79*D$16-O79 -> 58745.905 | Q79: =503385*MIN(1,$D$30/3100) -> 503385 | R79: =P79+Q79 -> 562130.9 | S79: =Q79/D$17 -> 1233.001 | T79: =D$9-S79 -> -0.0010287562
B80: ago-25 | C80: =$D$26*E$21 -> 120538.3 | D80: 0.16129353 | E80: 0.83871476 | F80: 0 | G80: =C80*D80 -> 19442.049 | H80: =C80*E80 -> 101097.26 | I80: =C80*F80 -> 0 | J80: =G80*E$14+H80*E$15+I80*E$16 -> 211396.59 | K80: =G80+H80+I80 -> 120539.3 | L80: 14126 | M80: =J80+L80*$D$26/839.45 -> 225522.59 | N80: =MIN($D$30*E$11,$D$28*E$12*E$11,E$7) -> 44577 | O80: =N80/Supuestos!$B$14*E$14 -> 49141.499 | P80: =N80*E$16-O80 -> 46235.45 | Q80: =433915*MIN(1,$D$30/3100) -> 433915 | R80: =P80+Q80 -> 480150.45 | S80: =Q80/E$17 -> 1061.358 | T80: =E$9-S80 -> -0.35802167
B81: sep-25 | C81: =$D$26*F$21 -> 108994.19 | D81: 0.13333761 | E81: 0.86667156 | F81: 0 | G81: =C81*D81 -> 14533.025 | H81: =C81*E81 -> 94462.163 | I81: =C81*F81 -> 0 | J81: =G81*F$14+H81*F$15+I81*F$16 -> 192545.54 | K81: =G81+H81+I81 -> 108995.19 | L81: 43548 | M81: =J81+L81*$D$26/839.45 -> 236093.54 | N81: =MIN($D$30*F$11,$D$28*F$12*F$11,F$7) -> 49268 | O81: =N81/Supuestos!$B$14*F$14 -> 54117.819 | P81: =N81*F$16-O81 -> 50621.022 | Q81: =453590*MIN(1,$D$30/3100) -> 453590 | R81: =P81+Q81 -> 504211.02 | S81: =Q81/F$17 -> 1119.7265 | T81: =F$9-S81 -> 0.27351946
B82: oct-25 | C82: =$D$26*G$21 -> 128241.1 | D82: 0.12852364 | E82: 0.86893427 | F82: 0.0025420887 | G82: =C82*D82 -> 16482.013 | H82: =C82*E82 -> 111433.08 | I82: =C82*F82 -> 326.00025 | J82: =G82*G$14+H82*G$15+I82*G$16 -> 227132.94 | K82: =G82+H82+I82 -> 128241.1 | L82: 48106 | M82: =J82+L82*$D$26/839.45 -> 275238.94 | N82: =MIN($D$30*G$11,$D$28*G$12*G$11,G$7) -> 56344 | O82: =N82/Supuestos!$B$14*G$14 -> 61890.363 | P82: =N82*G$16-O82 -> 57891.347 | Q82: =313968*MIN(1,$D$30/3100) -> 313968 | R82: =P82+Q82 -> 371859.35 | S82: =Q82/G$17 -> 775.05739 | T82: =G$9-S82 -> 348.94261
B83: nov-25 | C83: =$D$26*H$21 -> 129543.92 | D83: 0.16925523 | E83: 0.82023096 | F83: 0.010513802 | G83: =C83*D83 -> 21925.987 | H83: =C83*E83 -> 106255.94 | I83: =C83*F83 -> 1361.9992 | J83: =G83*H$14+H83*H$15+I83*H$16 -> 219365.54 | K83: =G83+H83+I83 -> 129543.92 | L83: 31126 | M83: =J83+L83*$D$26/839.45 -> 250491.54 | N83: =MIN($D$30*H$11,$D$28*H$12*H$11,H$7) -> 77505.775 | O83: =N83/Supuestos!$B$14*H$14 -> 83060.355 | P83: =N83*H$16-O83 -> 77221.587 | Q83: =304543*MIN(1,$D$30/3100) -> 304543 | R83: =P83+Q83 -> 381764.59 | S83: =Q83/H$17 -> 775.05663 | T83: =H$9-S83 -> 285.94337
B84: dic-25 | C84: =$D$26*I$21 -> 128657.46 | D84: 0.13103834 | E84: 0.85726389 | F84: 0.01169777 | G84: =C84*D84 -> 16859.061 | H84: =C84*E84 -> 110293.4 | I84: =C84*F84 -> 1505.0054 | J84: =G84*I$14+H84*I$15+I84*I$16 -> 211999.67 | K84: =G84+H84+I84 -> 128657.46 | L84: 29915 | M84: =J84+L84*$D$26/839.45 -> 241914.67 | N84: =MIN($D$30*I$11,$D$28*I$12*I$11,I$7) -> 83706.237 | O84: =N84/Supuestos!$B$14*I$14 -> 86077.913 | P84: =N84*I$16-O84 -> 79200.051 | Q84: =289313*MIN(1,$D$30/3100) -> 289313 | R84: =P84+Q84 -> 368513.05 | S84: =Q84/I$17 -> 775.05626 | T84: =I$9-S84 -> 506.94374
B85: ene-26 | C85: =$D$26*J$21 -> 134070.24 | D85: 0.13204296 | E85: 0.85676139 | F85: 0.011195644 | G85: =C85*D85 -> 17703.031 | H85: =C85*E85 -> 114866.2 | I85: =C85*F85 -> 1501.0027 | J85: =G85*J$14+H85*J$15+I85*J$16 -> 216014.94 | K85: =G85+H85+I85 -> 134070.24 | L85: 56973 | M85: =J85+L85*$D$26/839.45 -> 272987.94 | N85: =MIN($D$30*J$11,$D$28*J$12*J$11,J$7) -> 83706.237 | O85: =N85/Supuestos!$B$14*J$14 -> 84264.278 | P85: =N85*J$16-O85 -> 77405.947 | Q85: =282804*MIN(1,$D$30/3100) -> 282804 | R85: =P85+Q85 -> 360209.95 | S85: =Q85/J$17 -> 775.06029 | T85: =J$9-S85 -> 365.93971
B86: feb-26 | C86: =$D$26*K$21 -> 126360.73 | D86: 0.14507641 | E86: 0.84366221 | F86: 0.011261386 | G86: =C86*D86 -> 18331.961 | H86: =C86*E86 -> 106605.77 | I86: =C86*F86 -> 1422.997 | J86: =G86*K$14+H86*K$15+I86*K$16 -> 202481.32 | K86: =G86+H86+I86 -> 126360.73 | L86: 58701 | M86: =J86+L86*$D$26/839.45 -> 261182.32 | N86: =MIN($D$30*K$11,$D$28*K$12*K$11,K$7) -> 74405.544 | O86: =N86/Supuestos!$B$14*K$14 -> 74932.583 | P86: =N86*K$16-O86 -> 68856.13 | Q86: =282966*MIN(1,$D$30/3100) -> 282966 | R86: =P86+Q86 -> 351822.13 | S86: =Q86/K$17 -> 775.0582 | T86: =K$9-S86 -> 316.9418
B87: mar-26 | C87: =$D$26*L$21 -> 154888.6 | D87: 0.16278109 | E87: 0.8260238 | F87: 0.011195114 | G87: =C87*D87 -> 25212.935 | H87: =C87*E87 -> 127941.67 | I87: =C87*F87 -> 1733.9955 | J87: =G87*L$14+H87*L$15+I87*L$16 -> 246291.11 | K87: =G87+H87+I87 -> 154888.6 | L87: 50659 | M87: =J87+L87*$D$26/839.45 -> 296950.11 | N87: =MIN($D$30*L$11,$D$28*L$12*L$11,L$7) -> 80606.006 | O87: =N87/Supuestos!$B$14*L$14 -> 81218.947 | P87: =N87*L$16-O87 -> 74632.765 | Q87: =283136*MIN(1,$D$30/3100) -> 283136 | R87: =P87+Q87 -> 357768.76 | S87: =Q87/L$17 -> 775.0568 | T87: =L$9-S87 -> 426.9432
B88: abr-26 | C88: =$D$26*M$21 -> 143243.75 | D88: 0.1343791 | E88: 0.86404317 | F88: 0.0015777275 | G88: =C88*D88 -> 19248.966 | H88: =C88*E88 -> 123768.78 | I88: =C88*F88 -> 225.9996 | J88: =G88*M$14+H88*M$15+I88*M$16 -> 230478.31 | K88: =G88+H88+I88 -> 143243.75 | L88: 55118 | M88: =J88+L88*$D$26/839.45 -> 285596.31 | N88: =MIN($D$30*M$11,$D$28*M$12*M$11,M$7) -> 60762 | O88: =N88/Supuestos!$B$14*M$14 -> 61224.044 | P88: =N88*M$16-O88 -> 56253.206 | Q88: =283129*MIN(1,$D$30/3100) -> 283129 | R88: =P88+Q88 -> 339382.21 | S88: =Q88/M$17 -> 775.05886 | T88: =M$9-S88 -> 535.94114
B89: TOTAL | C89: =SUM(C77:C88) -> 1569308.1 | G89: =SUM(G77:G88) -> 225318.15 | H89: =SUM(H77:H88) -> 1335917 | I89: =SUM(I77:I88) -> 8076.9996 | J89: =SUM(J77:J88) -> 2644739 | K89: =SUM(K77:K88) -> 1569312.1 | M89: =SUM(M77:M88) -> 3104779 | N89: =SUM(N77:N88) -> 759293.8 | O89: =SUM(O77:O88) -> 797119.97 | P89: =SUM(P77:P88) -> 739443.5 | Q89: =SUM(Q77:Q88) -> 4276904 | R89: =SUM(R77:R88) -> 5016347.5 | S89: =AVERAGE(S77:S88) -> 914.10223 | T89: =AVERAGE(T77:T88) -> 232.31444
A92: 5. PROYECCIÓN 20 AÑOS — OPCIÓN 1 — Autoconsumo (vertical, con cliff autoabasto 2032)
B93: Año | C93: Gasto CFE pleno $ | D93: Beneficio autoabasto $ | E93: Gasto real sin sistema $ | F93: Ahorro PV $ | G93: Ahorro BESS $ | H93: Pago PPA $ | I93: Pago particip. BESS $ | J93: Ahorro neto GEPP $ | K93: Acumulado GEPP $ | L93: % ahorro | M93: Flujo inv. PV $ | N93: Flujo inv. BESS $ | O93: Flujo inv. PV acum $ | P93: Flujo inv. BESS acum $
B94: Año 0 | C94: 0 | D94: 0 | E94: 0 | F94: 0 | G94: 0 | H94: 0 | I94: 0 | J94: 0 | K94: 0 | L94: 0 | M94: =-$C$34 -> -18457335 | N94: =-$C$36 -> -16196544 | O94: =M94 -> -18457335 | P94: =N94 -> -16196544
B95: =Supuestos!$B$25+1-1 -> 2026 | C95: =$C$39*(1+Supuestos!$B$9)^(1-1) -> 27061919 | D95: =IF(B95<=Supuestos!$B$26,$C$38*(1+Supuestos!$B$9)^(1-1),0) -> 0 | E95: =C95-D95 -> 27061919 | F95: =$C$43*(1+Supuestos!$B$9)^(1-1)*(1-Supuestos!$B$11)^(1-1) -> 5639214.4 | G95: =$C$44*(1+Supuestos!$B$9)^(1-1)*(1-Supuestos!$B$12)^(1-1) -> 4180289.6 | H95: =IF(1<=Supuestos!$B$18,$C$42*$C$31*(1+Supuestos!$B$10)^(1-1)*(1-Supuestos!$B$11)^(1-1),0) -> 2967232.1 | I95: =IF(1<=Supuestos!$B$19,G95*$C$32,0) -> 2090144.8 | J95: =F95+G95-H95-I95 -> 4762127.1 | K95: =K94+J95 -> 4762127.1 | L95: =IF(E95>0,J95/E95,0) -> 0.17597152 | M95: =IF(1<=Supuestos!$B$18,H95-Supuestos!$B$22*$C$26*(1+Supuestos!$B$9)^(1-1),0) -> 2465652.1 | N95: =IF(1<=Supuestos!$B$19,I95-Supuestos!$B$23*$C$29*(1+Supuestos!$B$9)^(1-1),0) -> 1496864.8 | O95: =O94+M95 -> -15991683 | P95: =P94+N95 -> -14699679
B96: =Supuestos!$B$25+2-1 -> 2027 | C96: =$C$39*(1+Supuestos!$B$9)^(2-1) -> 28415015 | D96: =IF(B96<=Supuestos!$B$26,$C$38*(1+Supuestos!$B$9)^(2-1),0) -> 0 | E96: =C96-D96 -> 28415015 | F96: =$C$43*(1+Supuestos!$B$9)^(2-1)*(1-Supuestos!$B$11)^(2-1) -> 5891569.3 | G96: =$C$44*(1+Supuestos!$B$9)^(2-1)*(1-Supuestos!$B$12)^(2-1) -> 4334437.8 | H96: =IF(2<=Supuestos!$B$18,$C$42*$C$31*(1+Supuestos!$B$10)^(2-1)*(1-Supuestos!$B$11)^(2-1),0) -> 3100015.7 | I96: =IF(2<=Supuestos!$B$19,G96*$C$32,0) -> 2167218.9 | J96: =F96+G96-H96-I96 -> 4958772.4 | K96: =K95+J96 -> 9720899.5 | L96: =IF(E96>0,J96/E96,0) -> 0.1745124 | M96: =IF(2<=Supuestos!$B$18,H96-Supuestos!$B$22*$C$26*(1+Supuestos!$B$9)^(2-1),0) -> 2573356.7 | N96: =IF(2<=Supuestos!$B$19,I96-Supuestos!$B$23*$C$29*(1+Supuestos!$B$9)^(2-1),0) -> 1544274.9 | O96: =O95+M96 -> -13418326 | P96: =P95+N96 -> -13155404
B97: =Supuestos!$B$25+3-1 -> 2028 | C97: =$C$39*(1+Supuestos!$B$9)^(3-1) -> 29835766 | D97: =IF(B97<=Supuestos!$B$26,$C$38*(1+Supuestos!$B$9)^(3-1),0) -> 0 | E97: =C97-D97 -> 29835766 | F97: =$C$43*(1+Supuestos!$B$9)^(3-1)*(1-Supuestos!$B$11)^(3-1) -> 6155217 | G97: =$C$44*(1+Supuestos!$B$9)^(3-1)*(1-Supuestos!$B$12)^(3-1) -> 4494270.2 | H97: =IF(3<=Supuestos!$B$18,$C$42*$C$31*(1+Supuestos!$B$10)^(3-1)*(1-Supuestos!$B$11)^(3-1),0) -> 3238741.4 | I97: =IF(3<=Supuestos!$B$19,G97*$C$32,0) -> 2247135.1 | J97: =F97+G97-H97-I97 -> 5163610.6 | K97: =K96+J97 -> 14884510 | L97: =IF(E97>0,J97/E97,0) -> 0.17306781 | M97: =IF(3<=Supuestos!$B$18,H97-Supuestos!$B$22*$C$26*(1+Supuestos!$B$9)^(3-1),0) -> 2685749.5 | N97: =IF(3<=Supuestos!$B$19,I97-Supuestos!$B$23*$C$29*(1+Supuestos!$B$9)^(3-1),0) -> 1593043.9 | O97: =O96+M97 -> -10732577 | P97: =P96+N97 -> -11562360
B98: =Supuestos!$B$25+4-1 -> 2029 | C98: =$C$39*(1+Supuestos!$B$9)^(4-1) -> 31327554 | D98: =IF(B98<=Supuestos!$B$26,$C$38*(1+Supuestos!$B$9)^(4-1),0) -> 0 | E98: =C98-D98 -> 31327554 | F98: =$C$43*(1+Supuestos!$B$9)^(4-1)*(1-Supuestos!$B$11)^(4-1) -> 6430663 | G98: =$C$44*(1+Supuestos!$B$9)^(4-1)*(1-Supuestos!$B$12)^(4-1) -> 4659996.4 | H98: =IF(4<=Supuestos!$B$18,$C$42*$C$31*(1+Supuestos!$B$10)^(4-1)*(1-Supuestos!$B$11)^(4-1),0) -> 3383675.1 | I98: =IF(4<=Supuestos!$B$19,G98*$C$32,0) -> 2329998.2 | J98: =F98+G98-H98-I98 -> 5376986 | K98: =K97+J98 -> 20261496 | L98: =IF(E98>0,J98/E98,0) -> 0.1716376 | M98: =IF(4<=Supuestos!$B$18,H98-Supuestos!$B$22*$C$26*(1+Supuestos!$B$9)^(4-1),0) -> 2803033.6 | N98: =IF(4<=Supuestos!$B$19,I98-Supuestos!$B$23*$C$29*(1+Supuestos!$B$9)^(4-1),0) -> 1643202.4 | O98: =O97+M98 -> -7929543.1 | P98: =P97+N98 -> -9919158
B99: =Supuestos!$B$25+5-1 -> 2030 | C99: =$C$39*(1+Supuestos!$B$9)^(5-1) -> 32893932 | D99: =IF(B99<=Supuestos!$B$26,$C$38*(1+Supuestos!$B$9)^(5-1),0) -> 0 | E99: =C99-D99 -> 32893932 | F99: =$C$43*(1+Supuestos!$B$9)^(5-1)*(1-Supuestos!$B$11)^(5-1) -> 6718435.1 | G99: =$C$44*(1+Supuestos!$B$9)^(5-1)*(1-Supuestos!$B$12)^(5-1) -> 4831833.7 | H99: =IF(5<=Supuestos!$B$18,$C$42*$C$31*(1+Supuestos!$B$10)^(5-1)*(1-Supuestos!$B$11)^(5-1),0) -> 3535094.6 | I99: =IF(5<=Supuestos!$B$19,G99*$C$32,0) -> 2415916.9 | J99: =F99+G99-H99-I99 -> 5599257.4 | K99: =K98+J99 -> 25860754 | L99: =IF(E99>0,J99/E99,0) -> 0.17022159 | M99: =IF(5<=Supuestos!$B$18,H99-Supuestos!$B$22*$C$26*(1+Supuestos!$B$9)^(5-1),0) -> 2925421 | N99: =IF(5<=Supuestos!$B$19,I99-Supuestos!$B$23*$C$29*(1+Supuestos!$B$9)^(5-1),0) -> 1694781.3 | O99: =O98+M99 -> -5004122.2 | P99: =P98+N99 -> -8224376.7
B100: =Supuestos!$B$25+6-1 -> 2031 | C100: =$C$39*(1+Supuestos!$B$9)^(6-1) -> 34538628 | D100: =IF(B100<=Supuestos!$B$26,$C$38*(1+Supuestos!$B$9)^(6-1),0) -> 0 | E100: =C100-D100 -> 34538628 | F100: =$C$43*(1+Supuestos!$B$9)^(6-1)*(1-Supuestos!$B$11)^(6-1) -> 7019085.1 | G100: =$C$44*(1+Supuestos!$B$9)^(6-1)*(1-Supuestos!$B$12)^(6-1) -> 5010007.6 | H100: =IF(6<=Supuestos!$B$18,$C$42*$C$31*(1+Supuestos!$B$10)^(6-1)*(1-Supuestos!$B$11)^(6-1),0) -> 3693290.1 | I100: =IF(6<=Supuestos!$B$19,G100*$C$32,0) -> 2505003.8 | J100: =F100+G100-H100-I100 -> 5830798.8 | K100: =K99+J100 -> 31691552 | L100: =IF(E100>0,J100/E100,0) -> 0.16881964 | M100: =IF(6<=Supuestos!$B$18,H100-Supuestos!$B$22*$C$26*(1+Supuestos!$B$9)^(6-1),0) -> 3053132.8 | N100: =IF(6<=Supuestos!$B$19,I100-Supuestos!$B$23*$C$29*(1+Supuestos!$B$9)^(6-1),0) -> 1747811.5 | O100: =O99+M100 -> -1950989.4 | P100: =P99+N100 -> -6476565.2
B101: =Supuestos!$B$25+7-1 -> 2032 | C101: =$C$39*(1+Supuestos!$B$9)^(7-1) -> 36265560 | D101: =IF(B101<=Supuestos!$B$26,$C$38*(1+Supuestos!$B$9)^(7-1),0) -> 0 | E101: =C101-D101 -> 36265560 | F101: =$C$43*(1+Supuestos!$B$9)^(7-1)*(1-Supuestos!$B$11)^(7-1) -> 7333189.2 | G101: =$C$44*(1+Supuestos!$B$9)^(7-1)*(1-Supuestos!$B$12)^(7-1) -> 5194751.6 | H101: =IF(7<=Supuestos!$B$18,$C$42*$C$31*(1+Supuestos!$B$10)^(7-1)*(1-Supuestos!$B$11)^(7-1),0) -> 3858564.8 | I101: =IF(7<=Supuestos!$B$19,G101*$C$32,0) -> 2597375.8 | J101: =F101+G101-H101-I101 -> 6072000.2 | K101: =K100+J101 -> 37763553 | L101: =IF(E101>0,J101/E101,0) -> 0.16743159 | M101: =IF(7<=Supuestos!$B$18,H101-Supuestos!$B$22*$C$26*(1+Supuestos!$B$9)^(7-1),0) -> 3186399.6 | N101: =IF(7<=Supuestos!$B$19,I101-Supuestos!$B$23*$C$29*(1+Supuestos!$B$9)^(7-1),0) -> 1802323.9 | O101: =O100+M101 -> 1235410.2 | P101: =P100+N101 -> -4674241.4
B102: =Supuestos!$B$25+8-1 -> 2033 | C102: =$C$39*(1+Supuestos!$B$9)^(8-1) -> 38078838 | D102: =IF(B102<=Supuestos!$B$26,$C$38*(1+Supuestos!$B$9)^(8-1),0) -> 0 | E102: =C102-D102 -> 38078838 | F102: =$C$43*(1+Supuestos!$B$9)^(8-1)*(1-Supuestos!$B$11)^(8-1) -> 7661349.4 | G102: =$C$44*(1+Supuestos!$B$9)^(8-1)*(1-Supuestos!$B$12)^(8-1) -> 5386308.1 | H102: =IF(8<=Supuestos!$B$18,$C$42*$C$31*(1+Supuestos!$B$10)^(8-1)*(1-Supuestos!$B$11)^(8-1),0) -> 4031235.6 | I102: =IF(8<=Supuestos!$B$19,G102*$C$32,0) -> 2693154 | J102: =F102+G102-H102-I102 -> 6323267.9 | K102: =K101+J102 -> 44086820 | L102: =IF(E102>0,J102/E102,0) -> 0.16605727 | M102: =IF(8<=Supuestos!$B$18,H102-Supuestos!$B$22*$C$26*(1+Supuestos!$B$9)^(8-1),0) -> 3325462.1 | N102: =IF(8<=Supuestos!$B$19,I102-Supuestos!$B$23*$C$29*(1+Supuestos!$B$9)^(8-1),0) -> 1858349.5 | O102: =O101+M102 -> 4560872.3 | P102: =P101+N102 -> -2815891.9
B103: =Supuestos!$B$25+9-1 -> 2034 | C103: =$C$39*(1+Supuestos!$B$9)^(9-1) -> 39982780 | D103: =IF(B103<=Supuestos!$B$26,$C$38*(1+Supuestos!$B$9)^(9-1),0) -> 0 | E103: =C103-D103 -> 39982780 | F103: =$C$43*(1+Supuestos!$B$9)^(9-1)*(1-Supuestos!$B$11)^(9-1) -> 8004194.8 | G103: =$C$44*(1+Supuestos!$B$9)^(9-1)*(1-Supuestos!$B$12)^(9-1) -> 5584928.2 | H103: =IF(9<=Supuestos!$B$18,$C$42*$C$31*(1+Supuestos!$B$10)^(9-1)*(1-Supuestos!$B$11)^(9-1),0) -> 4211633.4 | I103: =IF(9<=Supuestos!$B$19,G103*$C$32,0) -> 2792464.1 | J103: =F103+G103-H103-I103 -> 6585025.5 | K103: =K102+J103 -> 50671846 | L103: =IF(E103>0,J103/E103,0) -> 0.16469654 | M103: =IF(9<=Supuestos!$B$18,H103-Supuestos!$B$22*$C$26*(1+Supuestos!$B$9)^(9-1),0) -> 3470571.3 | N103: =IF(9<=Supuestos!$B$19,I103-Supuestos!$B$23*$C$29*(1+Supuestos!$B$9)^(9-1),0) -> 1915919.3 | O103: =O102+M103 -> 8031443.6 | P103: =P102+N103 -> -899972.52
B104: =Supuestos!$B$25+10-1 -> 2035 | C104: =$C$39*(1+Supuestos!$B$9)^(10-1) -> 41981919 | D104: =IF(B104<=Supuestos!$B$26,$C$38*(1+Supuestos!$B$9)^(10-1),0) -> 0 | E104: =C104-D104 -> 41981919 | F104: =$C$43*(1+Supuestos!$B$9)^(10-1)*(1-Supuestos!$B$11)^(10-1) -> 8362382.5 | G104: =$C$44*(1+Supuestos!$B$9)^(10-1)*(1-Supuestos!$B$12)^(10-1) -> 5790872.4 | H104: =IF(10<=Supuestos!$B$18,$C$42*$C$31*(1+Supuestos!$B$10)^(10-1)*(1-Supuestos!$B$11)^(10-1),0) -> 4400103.9 | I104: =IF(10<=Supuestos!$B$19,G104*$C$32,0) -> 2895436.2 | J104: =F104+G104-H104-I104 -> 6857714.7 | K104: =K103+J104 -> 57529561 | L104: =IF(E104>0,J104/E104,0) -> 0.16334925 | M104: =IF(10<=Supuestos!$B$18,H104-Supuestos!$B$22*$C$26*(1+Supuestos!$B$9)^(10-1),0) -> 3621988.7 | N104: =IF(10<=Supuestos!$B$19,I104-Supuestos!$B$23*$C$29*(1+Supuestos!$B$9)^(10-1),0) -> 1975064.2 | O104: =O103+M104 -> 11653432 | P104: =P103+N104 -> 1075091.7
B105: =Supuestos!$B$25+11-1 -> 2036 | C105: =$C$39*(1+Supuestos!$B$9)^(11-1) -> 44081014 | D105: =IF(B105<=Supuestos!$B$26,$C$38*(1+Supuestos!$B$9)^(11-1),0) -> 0 | E105: =C105-D105 -> 44081014 | F105: =$C$43*(1+Supuestos!$B$9)^(11-1)*(1-Supuestos!$B$11)^(11-1) -> 8736599.1 | G105: =$C$44*(1+Supuestos!$B$9)^(11-1)*(1-Supuestos!$B$12)^(11-1) -> 6004410.9 | H105: =IF(11<=Supuestos!$B$18,$C$42*$C$31*(1+Supuestos!$B$10)^(11-1)*(1-Supuestos!$B$11)^(11-1),0) -> 4597008.6 | I105: =IF(11<=Supuestos!$B$19,G105*$C$32,0) -> 3002205.4 | J105: =F105+G105-H105-I105 -> 7141795.9 | K105: =K104+J105 -> 64671357 | L105: =IF(E105>0,J105/E105,0) -> 0.16201523 | M105: =IF(11<=Supuestos!$B$18,H105-Supuestos!$B$22*$C$26*(1+Supuestos!$B$9)^(11-1),0) -> 3779987.6 | N105: =IF(11<=Supuestos!$B$19,I105-Supuestos!$B$23*$C$29*(1+Supuestos!$B$9)^(11-1),0) -> 2035814.8 | O105: =O104+M105 -> 15433420 | P105: =P104+N105 -> 3110906.5
B106: =Supuestos!$B$25+12-1 -> 2037 | C106: =$C$39*(1+Supuestos!$B$9)^(12-1) -> 46285065 | D106: =IF(B106<=Supuestos!$B$26,$C$38*(1+Supuestos!$B$9)^(12-1),0) -> 0 | E106: =C106-D106 -> 46285065 | F106: =$C$43*(1+Supuestos!$B$9)^(12-1)*(1-Supuestos!$B$11)^(12-1) -> 9127561.9 | G106: =$C$44*(1+Supuestos!$B$9)^(12-1)*(1-Supuestos!$B$12)^(12-1) -> 6225823.5 | H106: =IF(12<=Supuestos!$B$18,$C$42*$C$31*(1+Supuestos!$B$10)^(12-1)*(1-Supuestos!$B$11)^(12-1),0) -> 4802724.7 | I106: =IF(12<=Supuestos!$B$19,G106*$C$32,0) -> 3112911.8 | J106: =F106+G106-H106-I106 -> 7437748.9 | K106: =K105+J106 -> 72109106 | L106: =IF(E106>0,J106/E106,0) -> 0.16069436 | M106: =IF(12<=Supuestos!$B$18,H106-Supuestos!$B$22*$C$26*(1+Supuestos!$B$9)^(12-1),0) -> 3944852.7 | N106: =IF(12<=Supuestos!$B$19,I106-Supuestos!$B$23*$C$29*(1+Supuestos!$B$9)^(12-1),0) -> 2098201.6 | O106: =O105+M106 -> 19378273 | P106: =P105+N106 -> 5209108.1
B107: =Supuestos!$B$25+13-1 -> 2038 | C107: =$C$39*(1+Supuestos!$B$9)^(13-1) -> 48599318 | D107: =IF(B107<=Supuestos!$B$26,$C$38*(1+Supuestos!$B$9)^(13-1),0) -> 0 | E107: =C107-D107 -> 48599318 | F107: =$C$43*(1+Supuestos!$B$9)^(13-1)*(1-Supuestos!$B$11)^(13-1) -> 9536020.3 | G107: =$C$44*(1+Supuestos!$B$9)^(13-1)*(1-Supuestos!$B$12)^(13-1) -> 6455400.7 | H107: =IF(13<=Supuestos!$B$18,$C$42*$C$31*(1+Supuestos!$B$10)^(13-1)*(1-Supuestos!$B$11)^(13-1),0) -> 5017646.7 | I107: =IF(13<=Supuestos!$B$19,G107*$C$32,0) -> 3227700.4 | J107: =F107+G107-H107-I107 -> 7746074 | K107: =K106+J107 -> 79855180 | L107: =IF(E107>0,J107/E107,0) -> 0.15938647 | M107: =IF(13<=Supuestos!$B$18,H107-Supuestos!$B$22*$C$26*(1+Supuestos!$B$9)^(13-1),0) -> 4116881 | N107: =IF(13<=Supuestos!$B$19,I107-Supuestos!$B$23*$C$29*(1+Supuestos!$B$9)^(13-1),0) -> 2162254.7 | O107: =O106+M107 -> 23495154 | P107: =P106+N107 -> 7371362.9
...

Sheet Cancún
A1: GEPP Cancún — Propuesta Solar + BESS | GDMTH (Peninsular) | Benito Juárez, Q.R. (montos MXN sin IVA)
A3: 1. DATOS BASE — últimos 12 meses reales (recibos CFE, sin IVA)
A4: Mes | B4: may-25 | C4: jun-25 | D4: jul-25 | E4: ago-25 | F4: sep-25 | G4: oct-25 | H4: nov-25 | I4: dic-25 | J4: ene-26 | K4: feb-26 | L4: mar-26 | M4: abr-26 | N4: TOTAL
A5: Consumo Base (kWh) | B5: 131219 | C5: 135885 | D5: 101439 | E5: 116365 | F5: 100169 | G5: 98572 | H5: 94126 | I5: 102510 | J5: 100399 | K5: 112612 | L5: 121096 | M5: 87120 | N5: =SUM(B5:M5) -> 1301512
A6: Consumo Intermedia (kWh) | B6: 271299 | C6: 268040 | D6: 274792 | E6: 275738 | F6: 231786 | G6: 224586 | H6: 183552 | I6: 225061 | J6: 190456 | K6: 186342 | L6: 201871 | M6: 213852 | N6: =SUM(B6:M6) -> 2747375
A7: Consumo Punta (kWh) | B7: 30661 | C7: 30139 | D7: 34785 | E7: 28280 | F7: 26471 | G7: 35922 | H7: 53993 | I7: 64699 | J7: 54255 | K7: 51438 | L7: 55161 | M7: 28376 | N7: =SUM(B7:M7) -> 494180
A8: Consumo Total (kWh) | B8: =SUM(B5:B7) -> 433179 | C8: =SUM(C5:C7) -> 434064 | D8: =SUM(D5:D7) -> 411016 | E8: =SUM(E5:E7) -> 420383 | F8: =SUM(F5:F7) -> 358426 | G8: =SUM(G5:G7) -> 359080 | H8: =SUM(H5:H7) -> 331671 | I8: =SUM(I5:I7) -> 392270 | ... M8: =SUM(M5:M7) -> 329348 | N8: =SUM(B8:M8) -> 4543067
A9: Dem. máx. en punta (kW) | B9: 697 | C9: 718 | D9: 756 | E9: 673 | F9: 602 | G9: 717 | H9: 659 | I9: 710 | J9: 608 | K9: 642 | L9: 631 | M9: 612 | N9: =MAX(B9:M9) -> 756
A10: Dem. máx. mensual (kW) | B10: 697 | C10: 718 | D10: 756 | E10: 673 | F10: 602 | G10: 717 | H10: 659 | I10: 710 | J10: 608 | K10: 649 | L10: 631 | M10: 612 | N10: =MAX(B10:M10) -> 756
A11: Días con punta | B11: 22 | C11: 21 | D11: 23 | E11: 21 | F11: 22 | G11: 23 | H11: 25 | I11: 27 | J11: 27 | K11: 24 | L11: 26 | M11: 23
A12: Horas punta/día | B12: 2 | C12: 2 | D12: 2 | E12: 2 | F12: 2 | G12: 2.43 | H12: 3.6 | I12: 3.7 | J12: 3.63 | K12: 3.67 | L12: 3.69 | M12: 2.26
A13: Días del mes | B13: 31 | C13: 30 | D13: 31 | E13: 31 | F13: 30 | G13: 31 | H13: 30 | I13: 31 | J13: 31 | K13: 28 | L13: 31 | M13: 30
A14: Tarifa Base ($/kWh) | B14: 1.3138 | C14: 1.3404 | D14: 1.3576 | E14: 1.3593 | F14: 1.3527 | G14: 1.3527 | H14: 1.318 | I14: 1.262 | J14: 1.235 | K14: 1.2356 | L14: 1.2362 | M14: 1.2362
A15: Tarifa Intermedia ($/kWh) | B15: 2.2227 | C15: 2.2709 | D15: 2.3021 | E15: 2.305 | F15: 2.2898 | G15: 2.2898 | H15: 2.227 | I15: 2.1256 | J15: 2.0791 | K15: 2.0802 | L15: 2.0813 | M15: 2.0812
A16: Tarifa Punta ($/kWh) | B16: 2.4821 | C16: 2.5365 | D16: 2.5716 | E16: 2.5749 | F16: 2.5572 | G16: 2.5572 | H16: 2.4864 | I16: 2.372 | J16: 2.32 | K16: 2.3212 | L16: 2.3225 | M16: 2.3224
A17: Tarifa Capacidad ($/kW·mes) | B17: 422.31 | C17: 432.34 | D17: 438.82 | E17: 439.43 | F17: 435.41 | G17: 435.41 | H17: 422.34 | I17: 401.23 | J17: 392.2 | K17: 392.43 | L17: 392.66 | M17: 392.65
A18: Tarifa Distribución ($/kW·mes) | B18: 94.61 | C18: 94.61 | D18: 94.61 | E18: 94.61 | F18: 94.61 | G18: 94.61 | H18: 94.61 | I18: 94.61 | J18: 91.87 | K18: 91.87 | L18: 91.87 | M18: 91.87
A19: Gasto actual facturado ($ MXN) | B19: 1428537 | C19: 1476755 | D19: 1432719 | E19: 1449835 | F19: 1246694 | G19: 1242022 | H19: 1133482 | I19: 1270329 | J19: 1087142 | K19: 1138796 | L19: 1181496 | M19: 1065031 | N19: =SUM(B19:M19) -> 15152838
A20: Umbral de demanda (kW) | B20: =B8/(24*B13*Supuestos!$B$15) -> 1021.4559 | C20: =C8/(24*C13*Supuestos!$B$15) -> 1057.6608 | D20: =D8/(24*D13*Supuestos!$B$15) -> 969.19449 | E20: =E8/(24*E13*Supuestos!$B$15) -> 991.28231 | F20: =F8/(24*F13*Supuestos!$B$15) -> 873.3577 | G20: =G8/(24*G13*Supuestos!$B$15) -> 846.72703 | H20: =H8/(24*H13*Supuestos!$B$15) -> 808.1652 | I20: =I8/(24*I13*Supuestos!$B$15) -> 924.99057 | ... M20: =M8/(24*M13*Supuestos!$B$15) -> 802.50487
A21: Yield PV (kWh/kWp) | B21: 139.624 | C21: 127.44 | D21: 131.192 | E21: 123.256 | F21: 118.32 | G21: 121.768 | H21: 114.96 | I21: 112.592 | J21: 116.312 | K21: 113.792 | L21: 140.616 | M21: 139.92 | N21: =SUM(B21:M21) -> 1499.792
A23: 2. SISTEMA PROPUESTO — Opción 1 y Opción 2 (amarillo = editable)
A24: Concepto | C24: OPCIÓN 1 — Autoconsumo | D24: OPCIÓN 2 — GD Medición Neta
A25: Esquema legal | C25: Autoconsumo interconectado (permiso CNE simplificado) | D25: Generación Distribuida <0.7 MW (sin permiso)
A26: Potencia PV (kWp DC) | C26: 1100 | D26: 839.45
A27: Superficie requerida (m²) | C27: =C26*Supuestos!$B$24 -> 4400 | D27: =D26*Supuestos!$B$24 -> 3357.8
A28: BESS potencia (kW) | C28: 981 | D28: 981
A29: BESS capacidad (kWh) | C29: 1962 | D29: 1962
A30: Energía útil BESS (kWh) | C30: =C29*Supuestos!$B$13*SQRT(Supuestos!$B$14) -> 1845.4652 | D30: =D29*Supuestos!$B$13*SQRT(Supuestos!$B$14) -> 1845.4652
A31: Precio PPA (MXN/kWh, año 1) | C31: 1.5277786 | D31: 1.787511
A32: Participación inversionista BESS (%) | C32: =Supuestos!$B$17 -> 0.5 | D32: =Supuestos!$B$17 -> 0.5
A33: CAPEX PV (USD) | C33: =C26*1000*Supuestos!$B$5 -> 715000 | D33: =D26*1000*Supuestos!$B$5 -> 545642.5
A34: CAPEX PV (MXN) | C34: =C33*Supuestos!$B$4 -> 12548250 | D34: =D33*Supuestos!$B$4 -> 9576025.9
A35: CAPEX BESS (USD) | C35: =C29*1000*Supuestos!$B$7 -> 549360 | D35: =D29*1000*Supuestos!$B$7 -> 549360
A36: CAPEX BESS (MXN) | C36: =C35*Supuestos!$B$4 -> 9641268 | D36: =D35*Supuestos!$B$4 -> 9641268
A37: — Autoabasto TALA / ENEL (vence 2032) —
A38: Beneficio autoabasto actual ($/año) | C38: 0 | D38: =C38 -> 0
A39: Gasto sin autoabasto — CFE pleno ($/año) | C39: =$N$19+C38 -> 15152838 | D39: =$N$19+D38 -> 15152838
A40: Gasto real hoy (con autoabasto) ($/año) | C40: =C39-C38 -> 15152838 | D40: =D39-D38 -> 15152838
A41: Generación PV año 1 (kWh) | C41: =C72 -> 1649771.2 | D41: =C89 -> 1259000.4
A42: Energía facturada al PPA (kWh) | C42: =K72 -> 1616886.2 | D42: =K89 -> 1259003.4
A43: Ahorro bruto PV año 1 ($) | C43: =M72 -> 3533310.7 | D43: =M89 -> 2767113.3
A44: Ahorro bruto BESS año 1 c/merma ($) | C44: =R72*(12-Supuestos!$B$16)/12 -> 2744097.6 | D44: =R89*(12-Supuestos!$B$16)/12 -> 2744097.6
A45: Ahorro bruto total ($) | C45: =C43+C44 -> 6277408.3 | D45: =D43+D44 -> 5511211
A46: Pago PPA año 1 ($) | C46: =C42*C31 -> 2017227.2 | D46: =D42*D31 -> 1539383.4
A47: Pago participación BESS ($) | C47: =C44*C32 -> 1372048.8 | D47: =D44*D32 -> 1372048.8
A48: AHORRO NETO GEPP año 1 ($) | C48: =C45-C46-C47 -> 2888132.3 | D48: =D45-D46-D47 -> 2599778.7
A49: % ahorro bruto (vs gasto real hoy) | C49: =C45/$N$19 -> 0.41427278 | D49: =D45/$N$19 -> 0.36370817
A50: % ahorro neto (vs gasto real hoy) | C50: =C48/$N$19 -> 0.19060009 | D50: =D48/$N$19 -> 0.17157042
A51: TIR inversionista PV | C51: =IRR(M94:M114) -> 0.14315765 | D51: =IRR(M119:M139) -> 0.14315255
A52: TIR inversionista BESS | C52: =IRR(N94:N114) -> 0.093055732 | D52: =IRR(N119:N139) -> 0.093055732
A53: Participación req. p/ TIR BESS 16% | C53: 0.6564 | D53: 0.6564
A54: Payback simple inversionista PV (años) | C54: =COUNTIF(O94:O114,"<0") -> 7 | D54: =COUNTIF(O119:O139,"<0") -> 7
A55: VAN GEPP del ahorro neto 20a (@WACC) | C55: {=NPV(Supuestos!$B$21,J95:J114)} -> 32544738 | D55: {=NPV(Supuestos!$B$21,J120:J139)} -> 29009151
A58: 3. MODELO MENSUAL AÑO 1 — OPCIÓN 1 — Autoconsumo (vertical)
B59: Mes | C59: Gen PV (kWh) | D59: %Base | E59: %Int | F59: %Punta | G59: PV→Base | H59: PV→Int | I59: PV→Punta | J59: Ahorro energía PV $ | K59: Energía PPA (kWh) | L59: Ahorro distrib/umbral $ (motor) | M59: Ahorro PV total $ | N59: BESS despl. punta kWh | O59: Costo carga base $ | P59: Ahorro arbitraje $ | Q59: Ahorro capacidad $ (motor) | R59: Ahorro BESS bruto $ | S59: Reducción dem. punta (kW) | T59: Dem. punta después (kW)
B60: may-25 | C60: =$C$26*B$21 -> 153586.4 | D60: 0.12785671 | E60: 0.87097131 | F60: 0 | G60: =C60*D60 -> 19637.051 | H60: =C60*E60 -> 133769.35 | I60: =C60*F60 -> 0 | J60: =G60*B$14+H60*B$15+I60*B$16 -> 323128.29 | K60: =G60+H60+I60 -> 153406.4 | L60: 13484 | M60: =J60+L60*$C$26/1100 -> 336612.29 | N60: =MIN($C$30*B$11,$C$28*B$12*B$11,B$7) -> 30661 | O60: =N60/Supuestos!$B$14*B$14 -> 41960.856 | P60: =N60*B$16-O60 -> 34142.812 | Q60: =294283*MIN(1,$C$30/1845) -> 294283 | R60: =P60+Q60 -> 328425.81 | S60: =Q60/B$17 -> 696.84118 | T60: =B$9-S60 -> 0.15881698
B61: jun-25 | C61: =$C$26*C$21 -> 140184 | D61: 0.16666667 | E61: 0.83333333 | F61: 0 | G61: =C61*D61 -> 23364 | H61: =C61*E61 -> 116820 | I61: =C61*F61 -> 0 | J61: =G61*C$14+H61*C$15+I61*C$16 -> 296603.64 | K61: =G61+H61+I61 -> 140184 | L61: 12249 | M61: =J61+L61*$C$26/1100 -> 308852.64 | N61: =MIN($C$30*C$11,$C$28*C$12*C$11,C$7) -> 30139 | O61: =N61/Supuestos!$B$14*C$14 -> 42081.579 | P61: =N61*C$16-O61 -> 34365.995 | Q61: =310245*MIN(1,$C$30/1845) -> 310245 | R61: =P61+Q61 -> 344610.99 | S61: =Q61/C$17 -> 717.59495 | T61: =C$9-S61 -> 0.40505158
B62: jul-25 | C62: =$C$26*D$21 -> 144311.2 | D62: 0.11701118 | E62: 0.87096618 | F62: 0 | G62: =C62*D62 -> 16886.023 | H62: =C62*E62 -> 125690.17 | I62: =C62*F62 -> 0 | J62: =G62*D$14+H62*D$15+I62*D$16 -> 312275.82 | K62: =G62+H62+I62 -> 142576.2 | L62: 18302 | M62: =J62+L62*$C$26/1100 -> 330577.82 | N62: =MIN($C$30*D$11,$C$28*D$12*D$11,D$7) -> 34785 | O62: =N62/Supuestos!$B$14*D$14 -> 49191.787 | P62: =N62*D$16-O62 -> 40261.319 | Q62: =331834*MIN(1,$C$30/1845) -> 331834 | R62: =P62+Q62 -> 372095.32 | S62: =Q62/D$17 -> 756.19616 | T62: =D$9-S62 -> -0.19616244
B63: ago-25 | C63: =$C$26*E$21 -> 135581.6 | D63: 0.15713738 | E63: 0.83871015 | F63: 0 | G63: =C63*D63 -> 21304.937 | H63: =C63*E63 -> 113713.66 | I63: =C63*F63 -> 0 | J63: =G63*E$14+H63*E$15+I63*E$16 -> 291069.8 | K63: =G63+H63+I63 -> 135018.6 | L63: 8309 | M63: =J63+L63*$C$26/1100 -> 299378.8 | N63: =MIN($C$30*E$11,$C$28*E$12*E$11,E$7) -> 28280 | O63: =N63/Supuestos!$B$14*E$14 -> 40042.713 | P63: =N63*E$16-O63 -> 32775.459 | Q63: =295883*MIN(1,$C$30/1845) -> 295883 | R63: =P63+Q63 -> 328658.46 | S63: =Q63/E$17 -> 673.33364 | T63: =E$9-S63 -> -0.33363676
B64: sep-25 | C64: =$C$26*F$21 -> 130152 | D64: 0.12642141 | E64: 0.86666359 | F64: 0 | G64: =C64*D64 -> 16454 | H64: =C64*E64 -> 112798 | I64: =C64*F64 -> 0 | J64: =G64*F$14+H64*F$15+I64*F$16 -> 280542.19 | K64: =G64+H64+I64 -> 129252 | L64: 10359 | M64: =J64+L64*$C$26/1100 -> 290901.19 | N64: =MIN($C$30*F$11,$C$28*F$12*F$11,F$7) -> 26471 | O64: =N64/Supuestos!$B$14*F$14 -> 37299.293 | P64: =N64*F$16-O64 -> 30392.348 | Q64: =261949*MIN(1,$C$30/1845) -> 261949 | R64: =P64+Q64 -> 292341.35 | S64: =Q64/F$17 -> 601.61457 | T64: =F$9-S64 -> 0.38542982
B65: oct-25 | C65: =$C$26*G$21 -> 133944.8 | D65: 0.11981037 | E65: 0.86575833 | F65: 0.002545821 | G65: =C65*D65 -> 16047.976 | H65: =C65*E65 -> 115963.83 | I65: =C65*F65 -> 340.99949 | J65: =G65*G$14+H65*G$15+I65*G$16 -> 288114.07 | K65: =G65+H65+I65 -> 132352.8 | L65: 23419 | M65: =J65+L65*$C$26/1100 -> 311533.07 | N65: =MIN($C$30*G$11,$C$28*G$12*G$11,G$7) -> 35922 | O65: =N65/Supuestos!$B$14*G$14 -> 50616.343 | P65: =N65*G$16-O65 -> 41243.395 | Q65: =200884*MIN(1,$C$30/1845) -> 200884 | R65: =P65+Q65 -> 242127.4 | S65: =Q65/G$17 -> 461.36745 | T65: =G$9-S65 -> 255.63255
B66: nov-25 | C66: =$C$26*H$21 -> 126456 | D66: 0.15268552 | E66: 0.81490004 | F66: 0.010517492 | G66: =C66*D66 -> 19308 | H66: =C66*E66 -> 103049 | I66: =C66*F66 -> 1330 | J66: =G66*H$14+H66*H$15+I66*H$16 -> 258244.98 | K66: =G66+H66+I66 -> 123687 | L66: 19529 | M66: =J66+L66*$C$26/1100 -> 277773.98 | N66: =MIN($C$30*H$11,$C$28*H$12*H$11,H$7) -> 46136.629 | O66: =N66/Supuestos!$B$14*H$14 -> 63341.747 | P66: =N66*H$16-O66 -> 51372.368 | Q66: =194853*MIN(1,$C$30/1845) -> 194853 | R66: =P66+Q66 -> 246225.37 | S66: =Q66/H$17 -> 461.36525 | T66: =H$9-S66 -> 197.63475
B67: dic-25 | C67: =$C$26*I$21 -> 123851.2 | D67: 0.12849311 | E67: 0.85726397 | F67: 0.011699542 | G67: =C67*D67 -> 15914.026 | H67: =C67*E67 -> 106173.17 | I67: =C67*F67 -> 1449.0023 | J67: =G67*I$14+H67*I$15+I67*I$16 -> 249202.23 | K67: =G67+H67+I67 -> 123536.2 | L67: 17244 | M67: =J67+L67*$C$26/1100 -> 266446.23 | N67: =MIN($C$30*I$11,$C$28*I$12*I$11,I$7) -> 49827.56 | O67: =N67/Supuestos!$B$14*I$14 -> 65502.479 | P67: =N67*I$16-O67 -> 52688.492 | Q67: =185114*MIN(1,$C$30/1845) -> 185114 | R67: =P67+Q67 -> 237802.49 | S67: =Q67/I$17 -> 461.3663 | T67: =I$9-S67 -> 248.6337
B68: ene-26 | C68: =$C$26*J$21 -> 127943.2 | D68: 0.12617337 | E68: 0.85069132 | F68: 0.011192484 | G68: =C68*D68 -> 16143.025 | H68: =C68*E68 -> 108840.17 | I68: =C68*F68 -> 1432.0022 | J68: =G68*J$14+H68*J$15+I68*J$16 -> 249548.48 | K68: =G68+H68+I68 -> 126415.2 | L68: 15239 | M68: =J68+L68*$C$26/1100 -> 264787.48 | N68: =MIN($C$30*J$11,$C$28*J$12*J$11,J$7) -> 49827.56 | O68: =N68/Supuestos!$B$14*J$14 -> 64101.079 | P68: =N68*J$16-O68 -> 51498.859 | Q68: =180947*MIN(1,$C$30/1845) -> 180947 | R68: =P68+Q68 -> 232445.86 | S68: =Q68/J$17 -> 461.3641 | T68: =J$9-S68 -> 146.6359
B69: feb-26 | C69: =$C$26*K$21 -> 125171.2 | D69: 0.14473001 | E69: 0.83983511 | F69: 0.01126459 | G69: =C69*D69 -> 18116.029 | H69: =C69*E69 -> 105123.17 | I69: =C69*F69 -> 1410.0023 | J69: =G69*K$14+H69*K$15+I69*K$16 -> 244334.28 | K69: =G69+H69+I69 -> 124649.2 | L69: 12852 | M69: =J69+L69*$C$26/1100 -> 257186.28 | N69: =MIN($C$30*K$11,$C$28*K$12*K$11,K$7) -> 44291.164 | O69: =N69/Supuestos!$B$14*K$14 -> 57006.419 | P69: =N69*K$16-O69 -> 45802.231 | Q69: =181054*MIN(1,$C$30/1845) -> 181054 | R69: =P69+Q69 -> 226856.23 | S69: =Q69/K$17 -> 461.36636 | T69: =K$9-S69 -> 180.63364
B70: mar-26 | C70: =$C$26*L$21 -> 154677.6 | D70: 0.15236815 | E70: 0.78601999 | F70: 0.01119099 | G70: =C70*D70 -> 23567.939 | H70: =C70*E70 -> 121579.69 | I70: =C70*F70 -> 1730.9955 | J70: =G70*L$14+H70*L$15+I70*L$16 -> 286198.72 | K70: =G70+H70+I70 -> 146878.62 | L70: 13841 | M70: =J70+L70*$C$26/1100 -> 300039.72 | N70: =MIN($C$30*L$11,$C$28*L$12*L$11,L$7) -> 47982.094 | O70: =N70/Supuestos!$B$14*L$14 -> 61786.943 | P70: =N70*L$16-O70 -> 49651.471 | Q70: =181160*MIN(1,$C$30/1845) -> 181160 | R70: =P70+Q70 -> 230811.47 | S70: =Q70/L$17 -> 461.36607 | T70: =L$9-S70 -> 169.63393
B71: abr-26 | C71: =$C$26*M$21 -> 153912 | D71: 0.10498207 | E71: 0.79609777 | F71: 0.0015788243 | G71: =C71*D71 -> 16158 | H71: =C71*E71 -> 122529 | I71: =C71*F71 -> 243 | J71: =G71*M$14+H71*M$15+I71*M$16 -> 275546.22 | K71: =G71+H71+I71 -> 138930 | L71: 13675 | M71: =J71+L71*$C$26/1100 -> 289221.22 | N71: =MIN($C$30*M$11,$C$28*M$12*M$11,M$7) -> 28376 | O71: =N71/Supuestos!$B$14*M$14 -> 36540.012 | P71: =N71*M$16-O71 -> 29360.411 | Q71: =181156*MIN(1,$C$30/1845) -> 181156 | R71: =P71+Q71 -> 210516.41 | S71: =Q71/M$17 -> 461.36763 | T71: =M$9-S71 -> 150.63237
B72: TOTAL | C72: =SUM(C60:C71) -> 1649771.2 | G72: =SUM(G60:G71) -> 222901.01 | H72: =SUM(H60:H71) -> 1386049.2 | I72: =SUM(I60:I71) -> 7936.0018 | J72: =SUM(J60:J71) -> 3354808.7 | K72: =SUM(K60:K71) -> 1616886.2 | M72: =SUM(M60:M71) -> 3533310.7 | N72: =SUM(N60:N71) -> 452699.01 | O72: =SUM(O60:O71) -> 609471.25 | P72: =SUM(P60:P71) -> 493555.16 | Q72: =SUM(Q60:Q71) -> 2799362 | R72: =SUM(R60:R71) -> 3292917.2 | S72: =AVERAGE(S60:S71) -> 556.26197 | T72: =AVERAGE(T60:T71) -> 112.48803
A73: Q (Ahorro capacidad → flujo BESS) y L (Ahorro distrib/umbral → flujo PV) provienen de la simulación horaria al tamaño de diseño (memoria MC-GEPP-4SITIOS-2026-07 §4); escalan con MIN(1, E_útil/E_diseño). El rasurado que los sustenta se ilustra abajo (Despacho día típico, rasurado plano). Columnas S–T: demanda de punta facturable resultante mes a mes (Reducción = Q ÷ tarifa capacidad; Después = Dmáx punta − Reducción).
A75: 4. MODELO MENSUAL AÑO 1 — OPCIÓN 2 — GD Medición Neta (vertical)
B76: Mes | C76: Gen PV (kWh) | D76: %Base | E76: %Int | F76: %Punta | G76: PV→Base | H76: PV→Int | I76: PV→Punta | J76: Ahorro energía PV $ | K76: Energía PPA (kWh) | L76: Ahorro distrib/umbral $ (motor) | M76: Ahorro PV total $ | N76: BESS despl. punta kWh | O76: Costo carga base $ | P76: Ahorro arbitraje $ | Q76: Ahorro capacidad $ (motor) | R76: Ahorro BESS bruto $ | S76: Reducción dem. punta (kW) | T76: Dem. punta después (kW)
B77: may-25 | C77: =$D$26*B$21 -> 117207.37 | D77: 0.12903666 | E77: 0.87097187 | F77: 0 | G77: =C77*D77 -> 15124.047 | H77: =C77*E77 -> 102084.32 | I77: =C77*F77 -> 0 | J77: =G77*B$14+H77*B$15+I77*B$16 -> 246772.79 | K77: =G77+H77+I77 -> 117208.37 | L77: 12284 | M77: =J77+L77*$D$26/839.45 -> 259056.79 | N77: =MIN($D$30*B$11,$D$28*B$12*B$11,B$7) -> 30661 | O77: =N77/Supuestos!$B$14*B$14 -> 41960.856 | P77: =N77*B$16-O77 -> 34142.812 | Q77: =294283*MIN(1,$D$30/1845) -> 294283 | R77: =P77+Q77 -> 328425.81 | S77: =Q77/B$17 -> 696.84118 | T77: =B$9-S77 -> 0.15881698
B78: jun-25 | C78: =$D$26*C$21 -> 106979.51 | D78: 0.16666667 | E78: 0.83333333 | F78: 0 | G78: =C78*D78 -> 17829.918 | H78: =C78*E78 -> 89149.59 | I78: =C78*F78 -> 0 | J78: =G78*C$14+H78*C$15+I78*C$16 -> 226349.03 | K78: =G78+H78+I78 -> 106979.51 | L78: 10597 | M78: =J78+L78*$D$26/839.45 -> 236946.03 | N78: =MIN($D$30*C$11,$D$28*C$12*C$11,C$7) -> 30139 | O78: =N78/Supuestos!$B$14*C$14 -> 42081.579 | P78: =N78*C$16-O78 -> 34365.995 | Q78: =310245*MIN(1,$D$30/1845) -> 310245 | R78: =P78+Q78 -> 344610.99 | S78: =Q78/C$17 -> 717.59495 | T78: =C$9-S78 -> 0.40505158
B79: jul-25 | C79: =$D$26*D$21 -> 110129.12 | D79: 0.1290305 | E79: 0.8709695 | F79: 0 | G79: =C79*D79 -> 14210.016 | H79: =C79*E79 -> 95919.108 | I79: =C79*F79 -> 0 | J79: =G79*D$14+H79*D$15+I79*D$16 -> 240106.9 | K79: =G79+H79+I79 -> 110129.12 | L79: 16657 | M79: =J79+L79*$D$26/839.45 -> 256763.9 | N79: =MIN($D$30*D$11,$D$28*D$12*D$11,D$7) -> 34785 | O79: =N79/Supuestos!$B$14*D$14 -> 49191.787 | P79: =N79*D$16-O79 -> 40261.319 | Q79: =331834*MIN(1,$D$30/1845) -> 331834 | R79: =P79+Q79 -> 372095.32 | S79: =Q79/D$17 -> 756.19616 | T79: =D$9-S79 -> -0.19616244
B80: ago-25 | C80: =$D$26*E$21 -> 103467.25 | D80: 0.16128814 | E80: 0.83871186 | F80: 0 | G80: =C80*D80 -> 16688.04 | H80: =C80*E80 -> 86779.209 | I80: =C80*F80 -> 0 | J80: =G80*E$14+H80*E$15+I80*E$16 -> 222710.13 | K80: =G80+H80+I80 -> 103467.25 | L80: 6763 | M80: =J80+L80*$D$26/839.45 -> 229473.13 | N80: =MIN($D$30*E$11,$D$28*E$12*E$11,E$7) -> 28280 | O80: =N80/Supuestos!$B$14*E$14 -> 40042.713 | P80: =N80*E$16-O80 -> 32775.459 | Q80: =295883*MIN(1,$D$30/1845) -> 295883 | R80: =P80+Q80 -> 328658.46 | S80: =Q80/E$17 -> 673.33364 | T80: =E$9-S80 -> -0.33363676
B81: sep-25 | C81: =$D$26*F$21 -> 99323.724 | D81: 0.13333132 | E81: 0.86666868 | F81: 0 | G81: =C81*D81 -> 13242.963 | H81: =C81*E81 -> 86080.761 | I81: =C81*F81 -> 0 | J81: =G81*F$14+H81*F$15+I81*F$16 -> 215021.48 | K81: =G81+H81+I81 -> 99323.724 | L81: 9226 | M81: =J81+L81*$D$26/839.45 -> 224247.48 | N81: =MIN($D$30*F$11,$D$28*F$12*F$11,F$7) -> 26471 | O81: =N81/Supuestos!$B$14*F$14 -> 37299.293 | P81: =N81*F$16-O81 -> 30392.348 | Q81: =261949*MIN(1,$D$30/1845) -> 261949 | R81: =P81+Q81 -> 292341.35 | S81: =Q81/F$17 -> 601.61457 | T81: =F$9-S81 -> 0.38542982
B82: oct-25 | C82: =$D$26*G$21 -> 102218.15 | D82: 0.12851944 | E82: 0.86893698 | F82: 0.0025435833 | G82: =C82*D82 -> 13137.019 | H82: =C82*E82 -> 88821.128 | I82: =C82*F82 -> 260.00038 | J82: =G82*G$14+H82*G$15+I82*G$16 -> 221817.94 | K82: =G82+H82+I82 -> 102218.15 | L82: 22548 | M82: =J82+L82*$D$26/839.45 -> 244365.94 | N82: =MIN($D$30*G$11,$D$28*G$12*G$11,G$7) -> 35922 | O82: =N82/Supuestos!$B$14*G$14 -> 50616.343 | P82: =N82*G$16-O82 -> 41243.395 | Q82: =200884*MIN(1,$D$30/1845) -> 200884 | R82: =P82+Q82 -> 242127.4 | S82: =Q82/G$17 -> 461.36745 | T82: =G$9-S82 -> 255.63255
B83: nov-25 | C83: =$D$26*H$21 -> 96503.172 | D83: 0.16925899 | E83: 0.82023357 | F83: 0.010517808 | G83: =C83*D83 -> 16334.029 | H83: =C83*E83 -> 79155.141 | I83: =C83*F83 -> 1015.0018 | J83: =G83*H$14+H83*H$15+I83*H$16 -> 200330.45 | K83: =G83+H83+I83 -> 96504.172 | L83: 18743 | M83: =J83+L83*$D$26/839.45 -> 219073.45 | N83: =MIN($D$30*H$11,$D$28*H$12*H$11,H$7) -> 46136.629 | O83: =N83/Supuestos!$B$14*H$14 -> 63341.747 | P83: =N83*H$16-O83 -> 51372.368 | Q83: =194853*MIN(1,$D$30/1845) -> 194853 | R83: =P83+Q83 -> 246225.37 | S83: =Q83/H$17 -> 461.36525 | T83: =H$9-S83 -> 197.63475
B84: dic-25 | C84: =$D$26*I$21 -> 94515.354 | D84: 0.1310374 | E84: 0.85727133 | F84: 0.011701846 | G84: =C84*D84 -> 12385.046 | H84: =C84*E84 -> 81025.304 | I84: =C84*F84 -> 1106.0041 | J84: =G84*I$14+H84*I$15+I84*I$16 -> 190480.76 | K84: =G84+H84+I84 -> 94516.354 | L84: 15832 | M84: =J84+L84*$D$26/839.45 -> 206312.76 | N84: =MIN($D$30*I$11,$D$28*I$12*I$11,I$7) -> 49827.56 | O84: =N84/Supuestos!$B$14*I$14 -> 65502.479 | P84: =N84*I$16-O84 -> 52688.492 | Q84: =185114*MIN(1,$D$30/1845) -> 185114 | R84: =P84+Q84 -> 237802.49 | S84: =Q84/I$17 -> 461.3663 | T84: =I$9-S84 -> 248.6337
B85: ene-26 | C85: =$D$26*J$21 -> 97638.108 | D85: 0.132049 | E85: 0.85676683 | F85: 0.011194412 | G85: =C85*D85 -> 12893.014 | H85: =C85*E85 -> 83653.093 | I85: =C85*F85 -> 1093.0012 | J85: =G85*J$14+H85*J$15+I85*J$16 -> 192381.78 | K85: =G85+H85+I85 -> 97639.108 | L85: 14504 | M85: =J85+L85*$D$26/839.45 -> 206885.78 | N85: =MIN($D$30*J$11,$D$28*J$12*J$11,J$7) -> 49827.56 | O85: =N85/Supuestos!$B$14*J$14 -> 64101.079 | P85: =N85*J$16-O85 -> 51498.859 | Q85: =180947*MIN(1,$D$30/1845) -> 180947 | R85: =P85+Q85 -> 232445.86 | S85: =Q85/J$17 -> 461.3641 | T85: =J$9-S85 -> 146.6359
B86: feb-26 | C86: =$D$26*K$21 -> 95522.694 | D86: 0.14507501 | E86: 0.84366069 | F86: 0.011264303 | G86: =C86*D86 -> 13857.956 | H86: =C86*E86 -> 80588.742 | I86: =C86*F86 -> 1075.9966 | J86: =G86*K$14+H86*K$15+I86*K$16 -> 187261.19 | K86: =G86+H86+I86 -> 95522.694 | L86: 9808 | M86: =J86+L86*$D$26/839.45 -> 197069.19 | N86: =MIN($D$30*K$11,$D$28*K$12*K$11,K$7) -> 44291.164 | O86: =N86/Supuestos!$B$14*K$14 -> 57006.419 | P86: =N86*K$16-O86 -> 45802.231 | Q86: =181054*MIN(1,$D$30/1845) -> 181054 | R86: =P86+Q86 -> 226856.23 | S86: =Q86/K$17 -> 461.36636 | T86: =K$9-S86 -> 180.63364
B87: mar-26 | C87: =$D$26*L$21 -> 118040.1 | D87: 0.1627838 | E87: 0.82602508 | F87: 0.011191122 | G87: =C87*D87 -> 19215.016 | H87: =C87*E87 -> 97504.084 | I87: =C87*F87 -> 1321.0011 | J87: =G87*L$14+H87*L$15+I87*L$16 -> 229756.88 | K87: =G87+H87+I87 -> 118040.1 | L87: 12332 | M87: =J87+L87*$D$26/839.45 -> 242088.88 | N87: =MIN($D$30*L$11,$D$28*L$12*L$11,L$7) -> 47982.094 | O87: =N87/Supuestos!$B$14*L$14 -> 61786.943 | P87: =N87*L$16-O87 -> 49651.471 | Q87: =181160*MIN(1,$D$30/1845) -> 181160 | R87: =P87+Q87 -> 230811.47 | S87: =Q87/L$17 -> 461.36607 | T87: =L$9-S87 -> 169.63393
B88: abr-26 | C88: =$D$26*M$21 -> 117455.84 | D88: 0.13437372 | E88: 0.86404271 | F88: 0.0015750579 | G88: =C88*D88 -> 15782.979 | H88: =C88*E88 -> 101486.87 | I88: =C88*F88 -> 184.99975 | J88: =G88*M$14+H88*M$15+I88*M$16 -> 231155.03 | K88: =G88+H88+I88 -> 117454.84 | L88: 13675 | M88: =J88+L88*$D$26/839.45 -> 244830.03 | N88: =MIN($D$30*M$11,$D$28*M$12*M$11,M$7) -> 28376 | O88: =N88/Supuestos!$B$14*M$14 -> 36540.012 | P88: =N88*M$16-O88 -> 29360.411 | Q88: =181156*MIN(1,$D$30/1845) -> 181156 | R88: =P88+Q88 -> 210516.41 | S88: =Q88/M$17 -> 461.36763 | T88: =M$9-S88 -> 150.63237
B89: TOTAL | C89: =SUM(C77:C88) -> 1259000.4 | G89: =SUM(G77:G88) -> 180700.04 | H89: =SUM(H77:H88) -> 1072247.3 | I89: =SUM(I77:I88) -> 6056.005 | J89: =SUM(J77:J88) -> 2604144.3 | K89: =SUM(K77:K88) -> 1259003.4 | M89: =SUM(M77:M88) -> 2767113.3 | N89: =SUM(N77:N88) -> 452699.01 | O89: =SUM(O77:O88) -> 609471.25 | P89: =SUM(P77:P88) -> 493555.16 | Q89: =SUM(Q77:Q88) -> 2799362 | R89: =SUM(R77:R88) -> 3292917.2 | S89: =AVERAGE(S77:S88) -> 556.26197 | T89: =AVERAGE(T77:T88) -> 112.48803
A92: 5. PROYECCIÓN 20 AÑOS — OPCIÓN 1 — Autoconsumo (vertical, con cliff autoabasto 2032)
B93: Año | C93: Gasto CFE pleno $ | D93: Beneficio autoabasto $ | E93: Gasto real sin sistema $ | F93: Ahorro PV $ | G93: Ahorro BESS $ | H93: Pago PPA $ | I93: Pago particip. BESS $ | J93: Ahorro neto GEPP $ | K93: Acumulado GEPP $ | L93: % ahorro | M93: Flujo inv. PV $ | N93: Flujo inv. BESS $ | O93: Flujo inv. PV acum $ | P93: Flujo inv. BESS acum $
B94: Año 0 | C94: 0 | D94: 0 | E94: 0 | F94: 0 | G94: 0 | H94: 0 | I94: 0 | J94: 0 | K94: 0 | L94: 0 | M94: =-$C$34 -> -12548250 | N94: =-$C$36 -> -9641268 | O94: =M94 -> -12548250 | P94: =N94 -> -9641268
B95: =Supuestos!$B$25+1-1 -> 2026 | C95: =$C$39*(1+Supuestos!$B$9)^(1-1) -> 15152838 | D95: =IF(B95<=Supuestos!$B$26,$C$38*(1+Supuestos!$B$9)^(1-1),0) -> 0 | E95: =C95-D95 -> 15152838 | F95: =$C$43*(1+Supuestos!$B$9)^(1-1)*(1-Supuestos!$B$11)^(1-1) -> 3533310.7 | G95: =$C$44*(1+Supuestos!$B$9)^(1-1)*(1-Supuestos!$B$12)^(1-1) -> 2744097.6 | H95: =IF(1<=Supuestos!$B$18,$C$42*$C$31*(1+Supuestos!$B$10)^(1-1)*(1-Supuestos!$B$11)^(1-1),0) -> 2017227.2 | I95: =IF(1<=Supuestos!$B$19,G95*$C$32,0) -> 1372048.8 | J95: =F95+G95-H95-I95 -> 2888132.3 | K95: =K94+J95 -> 2888132.3 | L95: =IF(E95>0,J95/E95,0) -> 0.19060009 | M95: =IF(1<=Supuestos!$B$18,H95-Supuestos!$B$22*$C$26*(1+Supuestos!$B$9)^(1-1),0) -> 1676227.2 | N95: =IF(1<=Supuestos!$B$19,I95-Supuestos!$B$23*$C$29*(1+Supuestos!$B$9)^(1-1),0) -> 1018888.8 | O95: =O94+M95 -> -10872023 | P95: =P94+N95 -> -8622379.2
B96: =Supuestos!$B$25+2-1 -> 2027 | C96: =$C$39*(1+Supuestos!$B$9)^(2-1) -> 15910480 | D96: =IF(B96<=Supuestos!$B$26,$C$38*(1+Supuestos!$B$9)^(2-1),0) -> 0 | E96: =C96-D96 -> 15910480 | F96: =$C$43*(1+Supuestos!$B$9)^(2-1)*(1-Supuestos!$B$11)^(2-1) -> 3691426.4 | G96: =$C$44*(1+Supuestos!$B$9)^(2-1)*(1-Supuestos!$B$12)^(2-1) -> 2845286.2 | H96: =IF(2<=Supuestos!$B$18,$C$42*$C$31*(1+Supuestos!$B$10)^(2-1)*(1-Supuestos!$B$11)^(2-1),0) -> 2107498.2 | I96: =IF(2<=Supuestos!$B$19,G96*$C$32,0) -> 1422643.1 | J96: =F96+G96-H96-I96 -> 3006571.3 | K96: =K95+J96 -> 5894703.6 | L96: =IF(E96>0,J96/E96,0) -> 0.18896798 | M96: =IF(2<=Supuestos!$B$18,H96-Supuestos!$B$22*$C$26*(1+Supuestos!$B$9)^(2-1),0) -> 1749448.2 | N96: =IF(2<=Supuestos!$B$19,I96-Supuestos!$B$23*$C$29*(1+Supuestos!$B$9)^(2-1),0) -> 1051825.1 | O96: =O95+M96 -> -9122574.6 | P96: =P95+N96 -> -7570554.1
B97: =Supuestos!$B$25+3-1 -> 2028 | C97: =$C$39*(1+Supuestos!$B$9)^(3-1) -> 16706004 | D97: =IF(B97<=Supuestos!$B$26,$C$38*(1+Supuestos!$B$9)^(3-1),0) -> 0 | E97: =C97-D97 -> 16706004 | F97: =$C$43*(1+Supuestos!$B$9)^(3-1)*(1-Supuestos!$B$11)^(3-1) -> 3856617.7 | G97: =$C$44*(1+Supuestos!$B$9)^(3-1)*(1-Supuestos!$B$12)^(3-1) -> 2950206.2 | H97: =IF(3<=Supuestos!$B$18,$C$42*$C$31*(1+Supuestos!$B$10)^(3-1)*(1-Supuestos!$B$11)^(3-1),0) -> 2201808.7 | I97: =IF(3<=Supuestos!$B$19,G97*$C$32,0) -> 1475103.1 | J97: =F97+G97-H97-I97 -> 3129912.1 | K97: =K96+J97 -> 9024615.7 | L97: =IF(E97>0,J97/E97,0) -> 0.18735253 | M97: =IF(3<=Supuestos!$B$18,H97-Supuestos!$B$22*$C$26*(1+Supuestos!$B$9)^(3-1),0) -> 1825856.2 | N97: =IF(3<=Supuestos!$B$19,I97-Supuestos!$B$23*$C$29*(1+Supuestos!$B$9)^(3-1),0) -> 1085744.2 | O97: =O96+M97 -> -7296718.4 | P97: =P96+N97 -> -6484809.9
B98: =Supuestos!$B$25+4-1 -> 2029 | C98: =$C$39*(1+Supuestos!$B$9)^(4-1) -> 17541304 | D98: =IF(B98<=Supuestos!$B$26,$C$38*(1+Supuestos!$B$9)^(4-1),0) -> 0 | E98: =C98-D98 -> 17541304 | F98: =$C$43*(1+Supuestos!$B$9)^(4-1)*(1-Supuestos!$B$11)^(4-1) -> 4029201.3 | G98: =$C$44*(1+Supuestos!$B$9)^(4-1)*(1-Supuestos!$B$12)^(4-1) -> 3058995 | H98: =IF(4<=Supuestos!$B$18,$C$42*$C$31*(1+Supuestos!$B$10)^(4-1)*(1-Supuestos!$B$11)^(4-1),0) -> 2300339.6 | I98: =IF(4<=Supuestos!$B$19,G98*$C$32,0) -> 1529497.5 | J98: =F98+G98-H98-I98 -> 3258359.2 | K98: =K97+J98 -> 12282975 | L98: =IF(E98>0,J98/E98,0) -> 0.18575353 | M98: =IF(4<=Supuestos!$B$18,H98-Supuestos!$B$22*$C$26*(1+Supuestos!$B$9)^(4-1),0) -> 1905589.5 | N98: =IF(4<=Supuestos!$B$19,I98-Supuestos!$B$23*$C$29*(1+Supuestos!$B$9)^(4-1),0) -> 1120670.7 | O98: =O97+M98 -> -5391128.9 | P98: =P97+N98 -> -5364139.2
B99: =Supuestos!$B$25+5-1 -> 2030 | C99: =$C$39*(1+Supuestos!$B$9)^(5-1) -> 18418369 | D99: =IF(B99<=Supuestos!$B$26,$C$38*(1+Supuestos!$B$9)^(5-1),0) -> 0 | E99: =C99-D99 -> 18418369 | F99: =$C$43*(1+Supuestos!$B$9)^(5-1)*(1-Supuestos!$B$11)^(5-1) -> 4209508.1 | G99: =$C$44*(1+Supuestos!$B$9)^(5-1)*(1-Supuestos!$B$12)^(5-1) -> 3171795.5 | H99: =IF(5<=Supuestos!$B$18,$C$42*$C$31*(1+Supuestos!$B$10)^(5-1)*(1-Supuestos!$B$11)^(5-1),0) -> 2403279.8 | I99: =IF(5<=Supuestos!$B$19,G99*$C$32,0) -> 1585897.7 | J99: =F99+G99-H99-I99 -> 3392126 | K99: =K98+J99 -> 15675101 | L99: =IF(E99>0,J99/E99,0) -> 0.18417081 | M99: =IF(5<=Supuestos!$B$18,H99-Supuestos!$B$22*$C$26*(1+Supuestos!$B$9)^(5-1),0) -> 1988792.2 | N99: =IF(5<=Supuestos!$B$19,I99-Supuestos!$B$23*$C$29*(1+Supuestos!$B$9)^(5-1),0) -> 1156629.5 | O99: =O98+M99 -> -3402336.6 | P99: =P98+N99 -> -4207509.7
B100: =Supuestos!$B$25+6-1 -> 2031 | C100: =$C$39*(1+Supuestos!$B$9)^(6-1) -> 19339288 | D100: =IF(B100<=Supuestos!$B$26,$C$38*(1+Supuestos!$B$9)^(6-1),0) -> 0 | E100: =C100-D100 -> 19339288 | F100: =$C$43*(1+Supuestos!$B$9)^(6-1)*(1-Supuestos!$B$11)^(6-1) -> 4397883.6 | G100: =$C$44*(1+Supuestos!$B$9)^(6-1)*(1-Supuestos!$B$12)^(6-1) -> 3288755.4 | H100: =IF(6<=Supuestos!$B$18,$C$42*$C$31*(1+Supuestos!$B$10)^(6-1)*(1-Supuestos!$B$11)^(6-1),0) -> 2510826.6 | I100: =IF(6<=Supuestos!$B$19,G100*$C$32,0) -> 1644377.7 | J100: =F100+G100-H100-I100 -> 3531434.7 | K100: =K99+J100 -> 19206535 | L100: =IF(E100>0,J100/E100,0) -> 0.18260417 | M100: =IF(6<=Supuestos!$B$18,H100-Supuestos!$B$22*$C$26*(1+Supuestos!$B$9)^(6-1),0) -> 2075614.6 | N100: =IF(6<=Supuestos!$B$19,I100-Supuestos!$B$23*$C$29*(1+Supuestos!$B$9)^(6-1),0) -> 1193646.1 | O100: =O99+M100 -> -1326722 | P100: =P99+N100 -> -3013863.6
B101: =Supuestos!$B$25+7-1 -> 2032 | C101: =$C$39*(1+Supuestos!$B$9)^(7-1) -> 20306252 | D101: =IF(B101<=Supuestos!$B$26,$C$38*(1+Supuestos!$B$9)^(7-1),0) -> 0 | E101: =C101-D101 -> 20306252 | F101: =$C$43*(1+Supuestos!$B$9)^(7-1)*(1-Supuestos!$B$11)^(7-1) -> 4594688.9 | G101: =$C$44*(1+Supuestos!$B$9)^(7-1)*(1-Supuestos!$B$12)^(7-1) -> 3410028.3 | H101: =IF(7<=Supuestos!$B$18,$C$42*$C$31*(1+Supuestos!$B$10)^(7-1)*(1-Supuestos!$B$11)^(7-1),0) -> 2623186.1 | I101: =IF(7<=Supuestos!$B$19,G101*$C$32,0) -> 1705014.1 | J101: =F101+G101-H101-I101 -> 3676516.9 | K101: =K100+J101 -> 22883052 | L101: =IF(E101>0,J101/E101,0) -> 0.18105344 | M101: =IF(7<=Supuestos!$B$18,H101-Supuestos!$B$22*$C$26*(1+Supuestos!$B$9)^(7-1),0) -> 2166213.5 | N101: =IF(7<=Supuestos!$B$19,I101-Supuestos!$B$23*$C$29*(1+Supuestos!$B$9)^(7-1),0) -> 1231746 | O101: =O100+M101 -> 839491.46 | P101: =P100+N101 -> -1782117.6
B102: =Supuestos!$B$25+8-1 -> 2033 | C102: =$C$39*(1+Supuestos!$B$9)^(8-1) -> 21321565 | D102: =IF(B102<=Supuestos!$B$26,$C$38*(1+Supuestos!$B$9)^(8-1),0) -> 0 | E102: =C102-D102 -> 21321565 | F102: =$C$43*(1+Supuestos!$B$9)^(8-1)*(1-Supuestos!$B$11)^(8-1) -> 4800301.2 | G102: =$C$44*(1+Supuestos!$B$9)^(8-1)*(1-Supuestos!$B$12)^(8-1) -> 3535773.1 | H102: =IF(8<=Supuestos!$B$18,$C$42*$C$31*(1+Supuestos!$B$10)^(8-1)*(1-Supuestos!$B$11)^(8-1),0) -> 2740573.7 | I102: =IF(8<=Supuestos!$B$19,G102*$C$32,0) -> 1767886.5 | J102: =F102+G102-H102-I102 -> 3827614 | K102: =K101+J102 -> 26710666 | L102: =IF(E102>0,J102/E102,0) -> 0.17951844 | M102: =IF(8<=Supuestos!$B$18,H102-Supuestos!$B$22*$C$26*(1+Supuestos!$B$9)^(8-1),0) -> 2260752.4 | N102: =IF(8<=Supuestos!$B$19,I102-Supuestos!$B$23*$C$29*(1+Supuestos!$B$9)^(8-1),0) -> 1270954.9 | O102: =O101+M102 -> 3100243.9 | P102: =P101+N102 -> -511162.67
B103: =Supuestos!$B$25+9-1 -> 2034 | C103: =$C$39*(1+Supuestos!$B$9)^(9-1) -> 22387643 | D103: =IF(B103<=Supuestos!$B$26,$C$38*(1+Supuestos!$B$9)^(9-1),0) -> 0 | E103: =C103-D103 -> 22387643 | F103: =$C$43*(1+Supuestos!$B$9)^(9-1)*(1-Supuestos!$B$11)^(9-1) -> 5015114.7 | G103: =$C$44*(1+Supuestos!$B$9)^(9-1)*(1-Supuestos!$B$12)^(9-1) -> 3666154.7 | H103: =IF(9<=Supuestos!$B$18,$C$42*$C$31*(1+Supuestos!$B$10)^(9-1)*(1-Supuestos!$B$11)^(9-1),0) -> 2863214.4 | I103: =IF(9<=Supuestos!$B$19,G103*$C$32,0) -> 1833077.3 | J103: =F103+G103-H103-I103 -> 3984977.7 | K103: =K102+J103 -> 30695644 | L103: =IF(E103>0,J103/E103,0) -> 0.17799898 | M103: =IF(9<=Supuestos!$B$18,H103-Supuestos!$B$22*$C$26*(1+Supuestos!$B$9)^(9-1),0) -> 2359402.1 | N103: =IF(9<=Supuestos!$B$19,I103-Supuestos!$B$23*$C$29*(1+Supuestos!$B$9)^(9-1),0) -> 1311299.2 | O103: =O102+M103 -> 5459646 | P103: =P102+N103 -> 800136.51
B104: =Supuestos!$B$25+10-1 -> 2035 | C104: =$C$39*(1+Supuestos!$B$9)^(10-1) -> 23507025 | D104: =IF(B104<=Supuestos!$B$26,$C$38*(1+Supuestos!$B$9)^(10-1),0) -> 0 | E104: =C104-D104 -> 23507025 | F104: =$C$43*(1+Supuestos!$B$9)^(10-1)*(1-Supuestos!$B$11)^(10-1) -> 5239541.1 | G104: =$C$44*(1+Supuestos!$B$9)^(10-1)*(1-Supuestos!$B$12)^(10-1) -> 3801344.1 | H104: =IF(10<=Supuestos!$B$18,$C$42*$C$31*(1+Supuestos!$B$10)^(10-1)*(1-Supuestos!$B$11)^(10-1),0) -> 2991343.2 | I104: =IF(10<=Supuestos!$B$19,G104*$C$32,0) -> 1900672.1 | J104: =F104+G104-H104-I104 -> 4148869.9 | K104: =K103+J104 -> 34844514 | L104: =IF(E104>0,J104/E104,0) -> 0.17649489 | M104: =IF(10<=Supuestos!$B$18,H104-Supuestos!$B$22*$C$26*(1+Supuestos!$B$9)^(10-1),0) -> 2462340.3 | N104: =IF(10<=Supuestos!$B$19,I104-Supuestos!$B$23*$C$29*(1+Supuestos!$B$9)^(10-1),0) -> 1352805 | O104: =O103+M104 -> 7921986.2 | P104: =P103+N104 -> 2152941.5
B105: =Supuestos!$B$25+11-1 -> 2036 | C105: =$C$39*(1+Supuestos!$B$9)^(11-1) -> 24682376 | D105: =IF(B105<=Supuestos!$B$26,$C$38*(1+Supuestos!$B$9)^(11-1),0) -> 0 | E105: =C105-D105 -> 24682376 | F105: =$C$43*(1+Supuestos!$B$9)^(11-1)*(1-Supuestos!$B$11)^(11-1) -> 5474010.5 | G105: =$C$44*(1+Supuestos!$B$9)^(11-1)*(1-Supuestos!$B$12)^(11-1) -> 3941518.7 | H105: =IF(11<=Supuestos!$B$18,$C$42*$C$31*(1+Supuestos!$B$10)^(11-1)*(1-Supuestos!$B$11)^(11-1),0) -> 3125205.8 | I105: =IF(11<=Supuestos!$B$19,G105*$C$32,0) -> 1970759.4 | J105: =F105+G105-H105-I105 -> 4319564.1 | K105: =K104+J105 -> 39164078 | L105: =IF(E105>0,J105/E105,0) -> 0.175006 | M105: =IF(11<=Supuestos!$B$18,H105-Supuestos!$B$22*$C$26*(1+Supuestos!$B$9)^(11-1),0) -> 2569752.7 | N105: =IF(11<=Supuestos!$B$19,I105-Supuestos!$B$23*$C$29*(1+Supuestos!$B$9)^(11-1),0) -> 1395498.9 | O105: =O104+M105 -> 10491739 | P105: =P104+N105 -> 3548440.4
B106: =Supuestos!$B$25+12-1 -> 2037 | C106: =$C$39*(1+Supuestos!$B$9)^(12-1) -> 25916495 | D106: =IF(B106<=Supuestos!$B$26,$C$38*(1+Supuestos!$B$9)^(12-1),0) -> 0 | E106: =C106-D106 -> 25916495 | F106: =$C$43*(1+Supuestos!$B$9)^(12-1)*(1-Supuestos!$B$11)^(12-1) -> 5718972.5 | G106: =$C$44*(1+Supuestos!$B$9)^(12-1)*(1-Supuestos!$B$12)^(12-1) -> 4086862.2 | H106: =IF(12<=Supuestos!$B$18,$C$42*$C$31*(1+Supuestos!$B$10)^(12-1)*(1-Supuestos!$B$11)^(12-1),0) -> 3265058.8 | I106: =IF(12<=Supuestos!$B$19,G106*$C$32,0) -> 2043431.1 | J106: =F106+G106-H106-I106 -> 4497344.8 | K106: =K105+J106 -> 43661423 | L106: =IF(E106>0,J106/E106,0) -> 0.17353214 | M106: =IF(12<=Supuestos!$B$18,H106-Supuestos!$B$22*$C$26*(1+Supuestos!$B$9)^(12-1),0) -> 2681833.1 | N106: =IF(12<=Supuestos!$B$19,I106-Supuestos!$B$23*$C$29*(1+Supuestos!$B$9)^(12-1),0) -> 1439407.7 | O106: =O105+M106 -> 13173572 | P106: =P105+N106 -> 4987848.1
B107: =Supuestos!$B$25+13-1 -> 2038 | C107: =$C$39*(1+Supuestos!$B$9)^(13-1) -> 27212320 | D107: =IF(B107<=Supuestos!$B$26,$C$38*(1+Supuestos!$B$9)^(13-1),0) -> 0 | E107: =C107-D107 -> 27212320 | F107: =$C$43*(1+Supuestos!$B$9)^(13-1)*(1-Supuestos!$B$11)^(13-1) -> 5974896.5 | G107: =$C$44*(1+Supuestos!$B$9)^(13-1)*(1-Supuestos!$B$12)^(13-1) -> 4237565.3 | H107: =IF(13<=Supuestos!$B$18,$C$42*$C$31*(1+Supuestos!$B$10)^(13-1)*(1-Supuestos!$B$11)^(13-1),0) -> 3411170.2 | I107: =IF(13<=Supuestos!$B$19,G107*$C$32,0) -> 2118782.6 | J107: =F107+G107-H107-I107 -> 4682509 | K107: =K106+J107 -> 48343932 | L107: =IF(E107>0,J107/E107,0) -> 0.17207313 | M107: =IF(13<=Supuestos!$B$18,H107-Supuestos!$B$22*$C$26*(1+Supuestos!$B$9)^(13-1),0) -> 2798783.1 | N107: =IF(13<=Supuestos!$B$19,I107-Supuestos!$B$23*$C$29*(1+Supuestos!$B$9)^(13-1),0) -> 1484558 | O107: =O106+M107 -> 15972355 | P107: =P106+N107 -> 6472406.1
...

Sheet Proplasa
A1: GEPP Proplasa — Propuesta Solar + BESS | GDMTH (V. de México Norte) | Cuautitlán Izcalli, Méx. (montos MXN sin IVA)
A3: 1. DATOS BASE — últimos 12 meses reales (recibos CFE, sin IVA)
A4: Mes | B4: may-25 | C4: jun-25 | D4: jul-25 | E4: ago-25 | F4: sep-25 | G4: oct-25 | H4: nov-25 | I4: dic-25 | J4: ene-26 | K4: feb-26 | L4: mar-26 | M4: abr-26 | N4: TOTAL
A5: Consumo Base (kWh) | B5: 3062070 | C5: 2851900 | D5: 2393563 | E5: 2871886 | F5: 2475285 | G5: 2270491 | H5: 2403501 | I5: 2273858 | J5: 2435462 | K5: 2403239 | L5: 2852898 | M5: 2449911 | N5: =SUM(B5:M5) -> 30744064
A6: Consumo Intermedia (kWh) | B6: 5295526 | C6: 4915625 | D6: 4440610 | E6: 4951683 | F6: 4289473 | G6: 4217095 | H6: 3548867 | I6: 3514507 | J6: 4007070 | K6: 3515595 | L6: 4098354 | M6: 4443548 | N6: =SUM(B6:M6) -> 51237953
A7: Consumo Punta (kWh) | B7: 504661 | C7: 491592 | D7: 454077 | E7: 472890 | F7: 419682 | G7: 522441 | H7: 864535 | I7: 837753 | J7: 967455 | K7: 851537 | L7: 979353 | M7: 525209 | N7: =SUM(B7:M7) -> 7891185
A8: Consumo Total (kWh) | B8: =SUM(B5:B7) -> 8862257 | C8: =SUM(C5:C7) -> 8259117 | D8: =SUM(D5:D7) -> 7288250 | E8: =SUM(E5:E7) -> 8296459 | F8: =SUM(F5:F7) -> 7184440 | G8: =SUM(G5:G7) -> 7010027 | H8: =SUM(H5:H7) -> 6816903 | I8: =SUM(I5:I7) -> 6626118 | ... M8: =SUM(M5:M7) -> 7418668 | N8: =SUM(B8:M8) -> 89873202
A9: Dem. máx. en punta (kW) | B9: 11470 | C9: 11705 | D9: 9871 | E9: 11259 | F9: 9538 | G9: 10425 | H9: 10553 | I9: 9194 | J9: 10842 | K9: 10624 | L9: 11198 | M9: 11332 | N9: =MAX(B9:M9) -> 11705
A10: Dem. máx. mensual (kW) | B10: 13876 | C10: 12603 | D10: 10891 | E10: 12346 | F10: 11549 | G10: 10451 | H10: 12398 | I10: 12134 | J10: 12875 | K10: 13847 | L10: 14503 | M10: 13374 | N10: =MAX(B10:M10) -> 14503
A11: Días con punta | B11: 22 | C11: 21 | D11: 23 | E11: 21 | F11: 22 | G11: 23 | H11: 25 | I11: 27 | J11: 27 | K11: 24 | L11: 26 | M11: 23
A12: Horas punta/día | B12: 2 | C12: 2 | D12: 2 | E12: 2 | F12: 2 | G12: 2.43 | H12: 3.6 | I12: 3.7 | J12: 3.63 | K12: 3.67 | L12: 3.69 | M12: 2.26
A13: Días del mes | B13: 31 | C13: 30 | D13: 31 | E13: 31 | F13: 30 | G13: 31 | H13: 30 | I13: 31 | J13: 31 | K13: 28 | L13: 31 | M13: 30
A14: Tarifa Base ($/kWh) | B14: 1.1749 | C14: 1.1983 | D14: 1.2133 | E14: 1.2147 | F14: 1.2095 | G14: 1.2095 | H14: 1.1791 | I14: 1.1301 | J14: 1.106 | K14: 1.1065 | L14: 1.1071 | M14: 1.107
A15: Tarifa Intermedia ($/kWh) | B15: 1.9422 | C15: 1.9837 | D15: 2.0106 | E15: 2.0131 | F15: 2.0005 | G15: 2.0006 | H15: 1.9464 | I15: 1.859 | J15: 1.8185 | K15: 1.8194 | L15: 1.8204 | M15: 1.8204
A16: Tarifa Punta ($/kWh) | B16: 2.273 | C16: 2.3224 | D16: 2.3544 | E16: 2.3574 | F16: 2.3417 | G16: 2.3417 | H16: 2.2773 | I16: 2.1734 | J16: 2.1258 | K16: 2.1269 | L16: 2.1281 | M16: 2.128
A17: Tarifa Capacidad ($/kW·mes) | B17: 432.62 | C17: 442.9 | D17: 449.54 | E17: 450.17 | F17: 446.05 | G17: 446.05 | H17: 432.66 | I17: 411.03 | J17: 401.78 | K17: 402.01 | L17: 402.26 | M17: 402.24
A18: Tarifa Distribución ($/kW·mes) | B18: 91.12 | C18: 91.12 | D18: 91.12 | E18: 91.12 | F18: 91.12 | G18: 91.12 | H18: 91.12 | I18: 91.12 | J18: 86.15 | K18: 86.15 | L18: 86.15 | M18: 86.15
A19: Gasto actual facturado ($ MXN) | B19: 18374851 | C19: 19150128 | D19: 16543765 | E19: 18816263 | F19: 16458917 | G19: 16143663 | H19: 15535451 | I19: 14564709 | J19: 15688788 | K19: 14520758 | L19: 18689765 | M19: 17763059 | N19: =SUM(B19:M19) -> 202250117
A20: Umbral de demanda (kW) | B20: =B8/(24*B13*Supuestos!$B$15) -> 20897.607 | C20: =C8/(24*C13*Supuestos!$B$15) -> 20124.554 | D20: =D8/(24*D13*Supuestos!$B$15) -> 17186.026 | E20: =E8/(24*E13*Supuestos!$B$15) -> 19563.429 | F20: =F8/(24*F13*Supuestos!$B$15) -> 17505.945 | G20: =G8/(24*G13*Supuestos!$B$15) -> 16529.964 | H20: =H8/(24*H13*Supuestos!$B$15) -> 16610.387 | I20: =I8/(24*I13*Supuestos!$B$15) -> 15624.689 | ... M20: =M8/(24*M13*Supuestos!$B$15) -> 18076.676
A21: Yield PV (kWh/kWp) | B21: 143.096 | C21: 133.92 | D21: 135.16 | E21: 126.48 | F21: 119.52 | G21: 131.688 | H21: 136.56 | I21: 130.944 | J21: 142.848 | K21: 139.104 | L21: 170.128 | M21: 150.72 | N21: =SUM(B21:M21) -> 1660.168
A23: 2. SISTEMA PROPUESTO — Opción 1 y Opción 2 (amarillo = editable)
A24: Concepto | C24: OPCIÓN 1 — Autoconsumo | D24: OPCIÓN 2 — GD Medición Neta
A25: Esquema legal | C25: Autoconsumo interconectado (permiso CNE simplificado) | D25: Generación Distribuida <0.7 MW (sin permiso)
A26: Potencia PV (kWp DC) | C26: 3848.9 | D26: 2518.35
A27: Superficie requerida (m²) | C27: =C26*Supuestos!$B$24 -> 15395.6 | D27: =D26*Supuestos!$B$24 -> 10073.4
A28: BESS potencia (kW) | C28: 11787 | D28: 11787
A29: BESS capacidad (kWh) | C29: 23574 | D29: 23574
A30: Energía útil BESS (kWh) | C30: =C29*Supuestos!$B$13*SQRT(Supuestos!$B$14) -> 22173.8 | D30: =D29*Supuestos!$B$13*SQRT(Supuestos!$B$14) -> 22173.8
A31: Precio PPA (MXN/kWh, año 1) | C31: 1.3526645 | D31: 1.6148562
A32: Participación inversionista BESS (%) | C32: =Supuestos!$B$17 -> 0.5 | D32: =Supuestos!$B$17 -> 0.5
A33: CAPEX PV (USD) | C33: =C26*1000*Supuestos!$B$5 -> 2501785 | D33: =D26*1000*Supuestos!$B$5 -> 1636927.5
A34: CAPEX PV (MXN) | C34: =C33*Supuestos!$B$4 -> 43906327 | D34: =D33*Supuestos!$B$4 -> 28728078
A35: CAPEX BESS (USD) | C35: =C29*1000*Supuestos!$B$7 -> 6600720 | D35: =D29*1000*Supuestos!$B$7 -> 6600720
A36: CAPEX BESS (MXN) | C36: =C35*Supuestos!$B$4 -> 115842636 | D36: =D35*Supuestos!$B$4 -> 115842636
A37: — Autoabasto TALA / ENEL (vence 2032) —
A38: Beneficio autoabasto actual ($/año) | C38: 57664106 | D38: =C38 -> 57664106
A39: Gasto sin autoabasto — CFE pleno ($/año) | C39: =$N$19+C38 -> 2.5991422e+08 | D39: =$N$19+D38 -> 2.5991422e+08
A40: Gasto real hoy (con autoabasto) ($/año) | C40: =C39-C38 -> 202250117 | D40: =D39-D38 -> 202250117
A41: Generación PV año 1 (kWh) | C41: =C72 -> 6389820.6 | D41: =C89 -> 4180884.1
A42: Energía facturada al PPA (kWh) | C42: =K72 -> 6389820.6 | D42: =K89 -> 4180884.1
A43: Ahorro bruto PV año 1 ($) | C43: =M72 -> 12005085 | D43: =M89 -> 7857249.5
A44: Ahorro bruto BESS año 1 c/merma ($) | C44: =R72*(12-Supuestos!$B$16)/12 -> 38176081 | D44: =R89*(12-Supuestos!$B$16)/12 -> 38176081
A45: Ahorro bruto total ($) | C45: =C43+C44 -> 50181166 | D45: =D43+D44 -> 46033331
A46: Pago PPA año 1 ($) | C46: =C42*C31 -> 7058195.9 | D46: =D42*D31 -> 4618204.6
A47: Pago participación BESS ($) | C47: =C44*C32 -> 19088041 | D47: =D44*D32 -> 19088041
A48: AHORRO NETO GEPP año 1 ($) | C48: =C45-C46-C47 -> 24034930 | D48: =D45-D46-D47 -> 22327086
A49: % ahorro bruto (vs gasto real hoy) | C49: =C45/$N$19 -> 0.2481144 | D49: =D45/$N$19 -> 0.22760595
A50: % ahorro neto (vs gasto real hoy) | C50: =C48/$N$19 -> 0.11883766 | D50: =D48/$N$19 -> 0.11039344
A51: TIR inversionista PV | C51: =IRR(M94:M114) -> 0.14315511 | D51: =IRR(M119:M139) -> 0.14315511
A52: TIR inversionista BESS | C52: =IRR(N94:N114) -> 0.12584659 | D52: =IRR(N119:N139) -> 0.12584659
A53: Participación req. p/ TIR BESS 16% | C53: 0.5655 | D53: 0.5655
A54: Payback simple inversionista PV (años) | C54: =COUNTIF(O94:O114,"<0") -> 7 | D54: =COUNTIF(O119:O139,"<0") -> 7
A55: VAN GEPP del ahorro neto 20a (@WACC) | C55: {=NPV(Supuestos!$B$21,J95:J114)} -> 2.6271225e+08 | D55: {=NPV(Supuestos!$B$21,J120:J139)} -> 2.423084e+08
A58: 3. MODELO MENSUAL AÑO 1 — OPCIÓN 1 — Autoconsumo (vertical)
B59: Mes | C59: Gen PV (kWh) | D59: %Base | E59: %Int | F59: %Punta | G59: PV→Base | H59: PV→Int | I59: PV→Punta | J59: Ahorro energía PV $ | K59: Energía PPA (kWh) | L59: Ahorro distrib/umbral $ (motor) | M59: Ahorro PV total $ | N59: BESS despl. punta kWh | O59: Costo carga base $ | P59: Ahorro arbitraje $ | Q59: Ahorro capacidad $ (motor) | R59: Ahorro BESS bruto $ | S59: Reducción dem. punta (kW) | T59: Dem. punta después (kW)
B60: may-25 | C60: =$C$26*B$21 -> 550762.19 | D60: 0.12903214 | E60: 0.87096786 | F60: 0 | G60: =C60*D60 -> 71066.025 | H60: =C60*E60 -> 479696.17 | I60: =C60*F60 -> 0 | J60: =G60*B$14+H60*B$15+I60*B$16 -> 1015161.4 | K60: =G60+H60+I60 -> 550762.19 | L60: 25531 | M60: =J60+L60*$C$26/3848.9 -> 1040692.4 | N60: =MIN($C$30*B$11,$C$28*B$12*B$11,B$7) -> 487823.6 | O60: =N60/Supuestos!$B$14*B$14 -> 597024.95 | P60: =N60*B$16-O60 -> 511798.1 | Q60: =4796415*MIN(1,$C$30/22174) -> 4796371.8 | R60: =P60+Q60 -> 5308169.9 | S60: =Q60/B$17 -> 11086.801 | T60: =B$9-S60 -> 383.19919
B61: jun-25 | C61: =$C$26*C$21 -> 515444.69 | D61: 0.1666657 | E61: 0.83333236 | F61: 0 | G61: =C61*D61 -> 85906.948 | H61: =C61*E61 -> 429536.74 | I61: =C61*F61 -> 0 | J61: =G61*C$14+H61*C$15+I61*C$16 -> 955014.33 | K61: =G61+H61+I61 -> 515443.69 | L61: 24690 | M61: =J61+L61*$C$26/3848.9 -> 979704.33 | N61: =MIN($C$30*C$11,$C$28*C$12*C$11,C$7) -> 465649.8 | O61: =N61/Supuestos!$B$14*C$14 -> 581237.67 | P61: =N61*C$16-O61 -> 500187.44 | Q61: =4910388*MIN(1,$C$30/22174) -> 4910343.7 | R61: =P61+Q61 -> 5410531.2 | S61: =Q61/C$17 -> 11086.8 | T61: =C$9-S61 -> 618.19995
B62: jul-25 | C62: =$C$26*D$21 -> 520217.32 | D62: 0.12903269 | E62: 0.87096923 | F62: 0 | G62: =C62*D62 -> 67125.042 | H62: =C62*E62 -> 453093.28 | I62: =C62*F62 -> 0 | J62: =G62*D$14+H62*D$15+I62*D$16 -> 992432.17 | K62: =G62+H62+I62 -> 520218.32 | L62: 24115 | M62: =J62+L62*$C$26/3848.9 -> 1016547.2 | N62: =MIN($C$30*D$11,$C$28*D$12*D$11,D$7) -> 454077 | O62: =N62/Supuestos!$B$14*D$14 -> 573887.11 | P62: =N62*D$16-O62 -> 495191.78 | Q62: =4437517*MIN(1,$C$30/22174) -> 4437477 | R62: =P62+Q62 -> 4932668.8 | S62: =Q62/D$17 -> 9871.1505 | T62: =D$9-S62 -> -0.15051696
B63: ago-25 | C63: =$C$26*E$21 -> 486808.87 | D63: 0.16129118 | E63: 0.83870882 | F63: 0 | G63: =C63*D63 -> 78517.979 | H63: =C63*E63 -> 408290.89 | I63: =C63*F63 -> 0 | J63: =G63*E$14+H63*E$15+I63*E$16 -> 917306.19 | K63: =G63+H63+I63 -> 486808.87 | L63: 22566 | M63: =J63+L63*$C$26/3848.9 -> 939872.19 | N63: =MIN($C$30*E$11,$C$28*E$12*E$11,E$7) -> 465649.8 | O63: =N63/Supuestos!$B$14*E$14 -> 589192.52 | P63: =N63*E$16-O63 -> 508530.33 | Q63: =4987648*MIN(1,$C$30/22174) -> 4987603 | R63: =P63+Q63 -> 5496133.4 | S63: =Q63/E$17 -> 11079.377 | T63: =E$9-S63 -> 179.62322
B64: sep-25 | C64: =$C$26*F$21 -> 460020.53 | D64: 0.13333304 | E64: 0.86666478 | F64: 0 | G64: =C64*D64 -> 61335.937 | H64: =C64*E64 -> 398683.59 | I64: =C64*F64 -> 0 | J64: =G64*F$14+H64*F$15+I64*F$16 -> 871752.34 | K64: =G64+H64+I64 -> 460019.53 | L64: 22035 | M64: =J64+L64*$C$26/3848.9 -> 893787.34 | N64: =MIN($C$30*F$11,$C$28*F$12*F$11,F$7) -> 419682 | O64: =N64/Supuestos!$B$14*F$14 -> 528755.6 | P64: =N64*F$16-O64 -> 454013.74 | Q64: =4254526*MIN(1,$C$30/22174) -> 4254487.7 | R64: =P64+Q64 -> 4708501.4 | S64: =Q64/F$17 -> 9538.1407 | T64: =F$9-S64 -> -0.14068544
B65: oct-25 | C65: =$C$26*G$21 -> 506853.94 | D65: 0.12852419 | E65: 0.86893267 | F65: 0.0025431387 | G65: =C65*D65 -> 65142.993 | H65: =C65*E65 -> 440421.95 | I65: =C65*F65 -> 1288.9999 | J65: =G65*G$14+H65*G$15+I65*G$16 -> 962917.06 | K65: =G65+H65+I65 -> 506853.94 | L65: 30074 | M65: =J65+L65*$C$26/3848.9 -> 992991.06 | N65: =MIN($C$30*G$11,$C$28*G$12*G$11,G$7) -> 509997.4 | O65: =N65/Supuestos!$B$14*G$14 -> 642543.6 | P65: =N65*G$16-O65 -> 551717.32 | Q65: =2472655*MIN(1,$C$30/22174) -> 2472632.7 | R65: =P65+Q65 -> 3024350 | S65: =Q65/G$17 -> 5543.3981 | T65: =G$9-S65 -> 4881.6019
B66: nov-25 | C66: =$C$26*H$21 -> 525605.78 | D66: 0.16925416 | E66: 0.82023227 | F66: 0.010513579 | G66: =C66*D66 -> 88960.963 | H66: =C66*E66 -> 431118.82 | I66: =C66*F66 -> 5525.9977 | J66: =G66*H$14+H66*H$15+I66*H$16 -> 956607.9 | K66: =G66+H66+I66 -> 525605.78 | L66: 49957 | M66: =J66+L66*$C$26/3848.9 -> 1006564.9 | N66: =MIN($C$30*H$11,$C$28*H$12*H$11,H$7) -> 554345 | O66: =N66/Supuestos!$B$14*H$14 -> 680862.7 | P66: =N66*H$16-O66 -> 581547.17 | Q66: =2398429*MIN(1,$C$30/22174) -> 2398407.4 | R66: =P66+Q66 -> 2979954.6 | S66: =Q66/H$17 -> 5543.3999 | T66: =H$9-S66 -> 5009.6001
B67: dic-25 | C67: =$C$26*I$21 -> 503990.36 | D67: 0.13103435 | E67: 0.85726503 | F67: 0.011700629 | G67: =C67*D67 -> 66040.047 | H67: =C67*E67 -> 432053.31 | I67: =C67*F67 -> 5897.0042 | J67: =G67*I$14+H67*I$15+I67*I$16 -> 890635.51 | K67: =G67+H67+I67 -> 503990.36 | L67: 46357 | M67: =J67+L67*$C$26/3848.9 -> 936992.51 | N67: =MIN($C$30*I$11,$C$28*I$12*I$11,I$7) -> 598692.6 | O67: =N67/Supuestos!$B$14*I$14 -> 704773.45 | P67: =N67*I$16-O67 -> 596425.06 | Q67: =2278524*MIN(1,$C$30/22174) -> 2278503.5 | R67: =P67+Q67 -> 2874928.5 | S67: =Q67/I$17 -> 5543.3994 | T67: =I$9-S67 -> 3650.6006
B68: ene-26 | C68: =$C$26*J$21 -> 549807.67 | D68: 0.13204428 | E68: 0.85676272 | F68: 0.011191179 | G68: =C68*D68 -> 72598.956 | H68: =C68*E68 -> 471054.71 | I68: =C68*F68 -> 6152.9963 | J68: =G68*J$14+H68*J$15+I68*J$16 -> 949987.48 | K68: =G68+H68+I68 -> 549806.67 | L68: 47812 | M68: =J68+L68*$C$26/3848.9 -> 997799.48 | N68: =MIN($C$30*J$11,$C$28*J$12*J$11,J$7) -> 598692.6 | O68: =N68/Supuestos!$B$14*J$14 -> 689743.77 | P68: =N68*J$16-O68 -> 582956.97 | Q68: =2227247*MIN(1,$C$30/22174) -> 2227226.9 | R68: =P68+Q68 -> 2810183.9 | S68: =Q68/J$17 -> 5543.3992 | T68: =J$9-S68 -> 5298.6008
B69: feb-26 | C69: =$C$26*K$21 -> 535397.39 | D69: 0.14507552 | E69: 0.84366181 | F69: 0.011264538 | G69: =C69*D69 -> 77673.056 | H69: =C69*E69 -> 451694.33 | I69: =C69*F69 -> 6031.0043 | J69: =G69*K$14+H69*K$15+I69*K$16 -> 920585.23 | K69: =G69+H69+I69 -> 535398.39 | L69: 51548 | M69: =J69+L69*$C$26/3848.9 -> 972133.23 | N69: =MIN($C$30*K$11,$C$28*K$12*K$11,K$7) -> 532171.2 | O69: =N69/Supuestos!$B$14*K$14 -> 613382.75 | P69: =N69*K$16-O69 -> 518492.19 | Q69: =2228523*MIN(1,$C$30/22174) -> 2228502.9 | R69: =P69+Q69 -> 2746995.1 | S69: =Q69/K$17 -> 5543.4017 | T69: =K$9-S69 -> 5080.5983
B70: mar-26 | C70: =$C$26*L$21 -> 654805.66 | D70: 0.16278409 | E70: 0.82602328 | F70: 0.011192628 | G70: =C70*D70 -> 106591.94 | H70: =C70*E70 -> 540884.72 | I70: =C70*F70 -> 7328.9962 | J70: =G70*L$14+H70*L$15+I70*L$16 -> 1118231.3 | K70: =G70+H70+I70 -> 654805.66 | L70: 56943 | M70: =J70+L70*$C$26/3848.9 -> 1175174.3 | N70: =MIN($C$30*L$11,$C$28*L$12*L$11,L$7) -> 576518.8 | O70: =N70/Supuestos!$B$14*L$14 -> 664858.3 | P70: =N70*L$16-O70 -> 562031.37 | Q70: =2229908*MIN(1,$C$30/22174) -> 2229887.9 | R70: =P70+Q70 -> 2791919.3 | S70: =Q70/L$17 -> 5543.3995 | T70: =L$9-S70 -> 5654.6005
B71: abr-26 | C71: =$C$26*M$21 -> 580106.21 | D71: 0.13437717 | E71: 0.86404726 | F71: 0.0015772979 | G71: =C71*D71 -> 77953.028 | H71: =C71*E71 -> 501239.18 | I71: =C71*F71 -> 915.00033 | J71: =G71*M$14+H71*M$15+I71*M$16 -> 1000696.9 | K71: =G71+H71+I71 -> 580107.21 | L71: 52129 | M71: =J71+L71*$C$26/3848.9 -> 1052825.9 | N71: =MIN($C$30*M$11,$C$28*M$12*M$11,M$7) -> 509997.4 | O71: =N71/Supuestos!$B$14*M$14 -> 588090.76 | P71: =N71*M$16-O71 -> 497183.72 | Q71: =2229798*MIN(1,$C$30/22174) -> 2229777.9 | R71: =P71+Q71 -> 2726961.6 | S71: =Q71/M$17 -> 5543.4017 | T71: =M$9-S71 -> 5788.5983
B72: TOTAL | C72: =SUM(C60:C71) -> 6389820.6 | G72: =SUM(G60:G71) -> 918912.92 | H72: =SUM(H60:H71) -> 5437767.7 | I72: =SUM(I60:I71) -> 33139.999 | J72: =SUM(J60:J71) -> 11551328 | K72: =SUM(K60:K71) -> 6389820.6 | M72: =SUM(M60:M71) -> 12005085 | N72: =SUM(N60:N71) -> 6173297.2 | O72: =SUM(O60:O71) -> 7454353.2 | P72: =SUM(P60:P71) -> 6360075.2 | Q72: =SUM(Q60:Q71) -> 39451222 | R72: =SUM(R60:R71) -> 45811298 | S72: =AVERAGE(S60:S71) -> 7622.1724 | T72: =AVERAGE(T60:T71) -> 3045.411
A73: Q (Ahorro capacidad → flujo BESS) y L (Ahorro distrib/umbral → flujo PV) provienen de la simulación horaria al tamaño de diseño (memoria MC-GEPP-4SITIOS-2026-07 §4); escalan con MIN(1, E_útil/E_diseño). El rasurado que los sustenta se ilustra abajo (Despacho día típico, rasurado plano). Columnas S–T: demanda de punta facturable resultante mes a mes (Reducción = Q ÷ tarifa capacidad; Después = Dmáx punta − Reducción).
A75: 4. MODELO MENSUAL AÑO 1 — OPCIÓN 2 — GD Medición Neta (vertical)
B76: Mes | C76: Gen PV (kWh) | D76: %Base | E76: %Int | F76: %Punta | G76: PV→Base | H76: PV→Int | I76: PV→Punta | J76: Ahorro energía PV $ | K76: Energía PPA (kWh) | L76: Ahorro distrib/umbral $ (motor) | M76: Ahorro PV total $ | N76: BESS despl. punta kWh | O76: Costo carga base $ | P76: Ahorro arbitraje $ | Q76: Ahorro capacidad $ (motor) | R76: Ahorro BESS bruto $ | S76: Reducción dem. punta (kW) | T76: Dem. punta después (kW)
B77: may-25 | C77: =$D$26*B$21 -> 360365.81 | D77: 0.12903271 | E77: 0.87096729 | F77: 0 | G77: =C77*D77 -> 46498.976 | H77: =C77*E77 -> 313866.84 | I77: =C77*F77 -> 0 | J77: =G77*B$14+H77*B$15+I77*B$16 -> 664223.82 | K77: =G77+H77+I77 -> 360365.81 | L77: 16705 | M77: =J77+L77*$D$26/2518.35 -> 680928.82 | N77: =MIN($D$30*B$11,$D$28*B$12*B$11,B$7) -> 487823.6 | O77: =N77/Supuestos!$B$14*B$14 -> 597024.95 | P77: =N77*B$16-O77 -> 511798.1 | Q77: =4796415*MIN(1,$D$30/22174) -> 4796371.8 | R77: =P77+Q77 -> 5308169.9 | S77: =Q77/B$17 -> 11086.801 | T77: =B$9-S77 -> 383.19919
B78: jun-25 | C78: =$D$26*C$21 -> 337257.43 | D78: 0.16666815 | E78: 0.83333482 | F78: 0 | G78: =C78*D78 -> 56210.072 | H78: =C78*E78 -> 281048.36 | I78: =C78*F78 -> 0 | J78: =G78*C$14+H78*C$15+I78*C$16 -> 624872.16 | K78: =G78+H78+I78 -> 337258.43 | L78: 16155 | M78: =J78+L78*$D$26/2518.35 -> 641027.16 | N78: =MIN($D$30*C$11,$D$28*C$12*C$11,C$7) -> 465649.8 | O78: =N78/Supuestos!$B$14*C$14 -> 581237.67 | P78: =N78*C$16-O78 -> 500187.44 | Q78: =4910388*MIN(1,$D$30/22174) -> 4910343.7 | R78: =P78+Q78 -> 5410531.2 | S78: =Q78/C$17 -> 11086.8 | T78: =C$9-S78 -> 618.19995
B79: jul-25 | C79: =$D$26*D$21 -> 340380.19 | D79: 0.12903226 | E79: 0.87096774 | F79: 0 | G79: =C79*D79 -> 43920.024 | H79: =C79*E79 -> 296460.16 | I79: =C79*F79 -> 0 | J79: =G79*D$14+H79*D$15+I79*D$16 -> 649350.97 | K79: =G79+H79+I79 -> 340380.19 | L79: 15779 | M79: =J79+L79*$D$26/2518.35 -> 665129.97 | N79: =MIN($D$30*D$11,$D$28*D$12*D$11,D$7) -> 454077 | O79: =N79/Supuestos!$B$14*D$14 -> 573887.11 | P79: =N79*D$16-O79 -> 495191.78 | Q79: =4437517*MIN(1,$D$30/22174) -> 4437477 | R79: =P79+Q79 -> 4932668.8 | S79: =Q79/D$17 -> 9871.1505 | T79: =D$9-S79 -> -0.15051696
B80: ago-25 | C80: =$D$26*E$21 -> 318520.91 | D80: 0.16128921 | E80: 0.83871079 | F80: 0 | G80: =C80*D80 -> 51373.985 | H80: =C80*E80 -> 267146.92 | I80: =C80*F80 -> 0 | J80: =G80*E$14+H80*E$15+I80*E$16 -> 600197.45 | K80: =G80+H80+I80 -> 318520.91 | L80: 14765 | M80: =J80+L80*$D$26/2518.35 -> 614962.45 | N80: =MIN($D$30*E$11,$D$28*E$12*E$11,E$7) -> 465649.8 | O80: =N80/Supuestos!$B$14*E$14 -> 589192.52 | P80: =N80*E$16-O80 -> 508530.33 | Q80: =4987648*MIN(1,$D$30/22174) -> 4987603 | R80: =P80+Q80 -> 5496133.4 | S80: =Q80/E$17 -> 11079.377 | T80: =E$9-S80 -> 179.62322
B81: sep-25 | C81: =$D$26*F$21 -> 300993.19 | D81: 0.133332 | E81: 0.866668 | F81: 0 | G81: =C81*D81 -> 40132.026 | H81: =C81*E81 -> 260861.17 | I81: =C81*F81 -> 0 | J81: =G81*F$14+H81*F$15+I81*F$16 -> 570392.45 | K81: =G81+H81+I81 -> 300993.19 | L81: 14418 | M81: =J81+L81*$D$26/2518.35 -> 584810.45 | N81: =MIN($D$30*F$11,$D$28*F$12*F$11,F$7) -> 419682 | O81: =N81/Supuestos!$B$14*F$14 -> 528755.6 | P81: =N81*F$16-O81 -> 454013.74 | Q81: =4254526*MIN(1,$D$30/22174) -> 4254487.7 | R81: =P81+Q81 -> 4708501.4 | S81: =Q81/F$17 -> 9538.1407 | T81: =F$9-S81 -> -0.14068544
B82: oct-25 | C82: =$D$26*G$21 -> 331636.47 | D82: 0.12852344 | E82: 0.86893462 | F82: 0.0025449589 | G82: =C82*D82 -> 42623.061 | H82: =C82*E82 -> 288170.41 | I82: =C82*F82 -> 844.00121 | J82: =G82*G$14+H82*G$15+I82*G$16 -> 630042.72 | K82: =G82+H82+I82 -> 331637.47 | L82: 21952 | M82: =J82+L82*$D$26/2518.35 -> 651994.72 | N82: =MIN($D$30*G$11,$D$28*G$12*G$11,G$7) -> 509997.4 | O82: =N82/Supuestos!$B$14*G$14 -> 642543.6 | P82: =N82*G$16-O82 -> 551717.32 | Q82: =2472655*MIN(1,$D$30/22174) -> 2472632.7 | R82: =P82+Q82 -> 3024350 | S82: =Q82/G$17 -> 5543.3981 | T82: =G$9-S82 -> 4881.6019
B83: nov-25 | C83: =$D$26*H$21 -> 343905.88 | D83: 0.16925264 | E83: 0.82023285 | F83: 0.010514501 | G83: =C83*D83 -> 58206.979 | H83: =C83*E83 -> 282082.9 | I83: =C83*F83 -> 3615.9987 | J83: =G83*H$14+H83*H$15+I83*H$16 -> 625912.72 | K83: =G83+H83+I83 -> 343905.88 | L83: 32687 | M83: =J83+L83*$D$26/2518.35 -> 658599.72 | N83: =MIN($D$30*H$11,$D$28*H$12*H$11,H$7) -> 554345 | O83: =N83/Supuestos!$B$14*H$14 -> 680862.7 | P83: =N83*H$16-O83 -> 581547.17 | Q83: =2398429*MIN(1,$D$30/22174) -> 2398407.4 | R83: =P83+Q83 -> 2979954.6 | S83: =Q83/H$17 -> 5543.3999 | T83: =H$9-S83 -> 5009.6001
B84: dic-25 | C84: =$D$26*I$21 -> 329762.82 | D84: 0.1310335 | E84: 0.85726416 | F84: 0.011699311 | G84: =C84*D84 -> 43209.977 | H84: =C84*E84 -> 282693.85 | I84: =C84*F84 -> 3857.9979 | J84: =G84*I$14+H84*I$15+I84*I$16 -> 582744.43 | K84: =G84+H84+I84 -> 329761.82 | L84: 30331 | M84: =J84+L84*$D$26/2518.35 -> 613075.43 | N84: =MIN($D$30*I$11,$D$28*I$12*I$11,I$7) -> 598692.6 | O84: =N84/Supuestos!$B$14*I$14 -> 704773.45 | P84: =N84*I$16-O84 -> 596425.06 | Q84: =2278524*MIN(1,$D$30/22174) -> 2278503.5 | R84: =P84+Q84 -> 2874928.5 | S84: =Q84/I$17 -> 5543.3994 | T84: =I$9-S84 -> 3650.6006
B85: ene-26 | C85: =$D$26*J$21 -> 359741.26 | D85: 0.132045 | E85: 0.85676362 | F85: 0.011191385 | G85: =C85*D85 -> 47502.034 | H85: =C85*E85 -> 308213.22 | I85: =C85*F85 -> 4026.0029 | J85: =G85*J$14+H85*J$15+I85*J$16 -> 621581.47 | K85: =G85+H85+I85 -> 359741.26 | L85: 31284 | M85: =J85+L85*$D$26/2518.35 -> 652865.47 | N85: =MIN($D$30*J$11,$D$28*J$12*J$11,J$7) -> 598692.6 | O85: =N85/Supuestos!$B$14*J$14 -> 689743.77 | P85: =N85*J$16-O85 -> 582956.97 | Q85: =2227247*MIN(1,$D$30/22174) -> 2227226.9 | R85: =P85+Q85 -> 2810183.9 | S85: =Q85/J$17 -> 5543.3992 | T85: =J$9-S85 -> 5298.6008
B86: feb-26 | C86: =$D$26*K$21 -> 350312.56 | D86: 0.14507312 | E86: 0.84365981 | F86: 0.011264212 | G86: =C86*D86 -> 50820.936 | H86: =C86*E86 -> 295544.63 | I86: =C86*F86 -> 3945.995 | J86: =G86*K$14+H86*K$15+I86*K$16 -> 602340 | K86: =G86+H86+I86 -> 350311.56 | L86: 33728 | M86: =J86+L86*$D$26/2518.35 -> 636068 | N86: =MIN($D$30*K$11,$D$28*K$12*K$11,K$7) -> 532171.2 | O86: =N86/Supuestos!$B$14*K$14 -> 613382.75 | P86: =N86*K$16-O86 -> 518492.19 | Q86: =2228523*MIN(1,$D$30/22174) -> 2228502.9 | R86: =P86+Q86 -> 2746995.1 | S86: =Q86/K$17 -> 5543.4017 | T86: =K$9-S86 -> 5080.5983
B87: mar-26 | C87: =$D$26*L$21 -> 428441.85 | D87: 0.16278516 | E87: 0.82602313 | F87: 0.011191713 | G87: =C87*D87 -> 69743.975 | H87: =C87*E87 -> 353902.88 | I87: =C87*F87 -> 4794.9983 | J87: =G87*L$14+H87*L$15+I87*L$16 -> 731662.58 | K87: =G87+H87+I87 -> 428441.85 | L87: 37258 | M87: =J87+L87*$D$26/2518.35 -> 768920.58 | N87: =MIN($D$30*L$11,$D$28*L$12*L$11,L$7) -> 576518.8 | O87: =N87/Supuestos!$B$14*L$14 -> 664858.3 | P87: =N87*L$16-O87 -> 562031.37 | Q87: =2229908*MIN(1,$D$30/22174) -> 2229887.9 | R87: =P87+Q87 -> 2791919.3 | S87: =Q87/L$17 -> 5543.3995 | T87: =L$9-S87 -> 5654.6005
B88: abr-26 | C88: =$D$26*M$21 -> 379565.71 | D88: 0.13437716 | E88: 0.86404472 | F88: 0.0015781182 | G88: =C88*D88 -> 51004.961 | H88: =C88*E88 -> 327961.75 | I88: =C88*F88 -> 598.99955 | J88: =G88*M$14+H88*M$15+I88*M$16 -> 654758.73 | K88: =G88+H88+I88 -> 379565.71 | L88: 34108 | M88: =J88+L88*$D$26/2518.35 -> 688866.73 | N88: =MIN($D$30*M$11,$D$28*M$12*M$11,M$7) -> 509997.4 | O88: =N88/Supuestos!$B$14*M$14 -> 588090.76 | P88: =N88*M$16-O88 -> 497183.72 | Q88: =2229798*MIN(1,$D$30/22174) -> 2229777.9 | R88: =P88+Q88 -> 2726961.6 | S88: =Q88/M$17 -> 5543.4017 | T88: =M$9-S88 -> 5788.5983
B89: TOTAL | C89: =SUM(C77:C88) -> 4180884.1 | G89: =SUM(G77:G88) -> 601247.01 | H89: =SUM(H77:H88) -> 3557953.1 | I89: =SUM(I77:I88) -> 21683.994 | J89: =SUM(J77:J88) -> 7558079.5 | K89: =SUM(K77:K88) -> 4180884.1 | M89: =SUM(M77:M88) -> 7857249.5 | N89: =SUM(N77:N88) -> 6173297.2 | O89: =SUM(O77:O88) -> 7454353.2 | P89: =SUM(P77:P88) -> 6360075.2 | Q89: =SUM(Q77:Q88) -> 39451222 | R89: =SUM(R77:R88) -> 45811298 | S89: =AVERAGE(S77:S88) -> 7622.1724 | T89: =AVERAGE(T77:T88) -> 3045.411
A92: 5. PROYECCIÓN 20 AÑOS — OPCIÓN 1 — Autoconsumo (vertical, con cliff autoabasto 2032)
B93: Año | C93: Gasto CFE pleno $ | D93: Beneficio autoabasto $ | E93: Gasto real sin sistema $ | F93: Ahorro PV $ | G93: Ahorro BESS $ | H93: Pago PPA $ | I93: Pago particip. BESS $ | J93: Ahorro neto GEPP $ | K93: Acumulado GEPP $ | L93: % ahorro | M93: Flujo inv. PV $ | N93: Flujo inv. BESS $ | O93: Flujo inv. PV acum $ | P93: Flujo inv. BESS acum $
B94: Año 0 | C94: 0 | D94: 0 | E94: 0 | F94: 0 | G94: 0 | H94: 0 | I94: 0 | J94: 0 | K94: 0 | L94: 0 | M94: =-$C$34 -> -43906327 | N94: =-$C$36 -> -115842636 | O94: =M94 -> -43906327 | P94: =N94 -> -115842636
B95: =Supuestos!$B$25+1-1 -> 2026 | C95: =$C$39*(1+Supuestos!$B$9)^(1-1) -> 2.5991422e+08 | D95: =IF(B95<=Supuestos!$B$26,$C$38*(1+Supuestos!$B$9)^(1-1),0) -> 57664106 | E95: =C95-D95 -> 202250117 | F95: =$C$43*(1+Supuestos!$B$9)^(1-1)*(1-Supuestos!$B$11)^(1-1) -> 12005085 | G95: =$C$44*(1+Supuestos!$B$9)^(1-1)*(1-Supuestos!$B$12)^(1-1) -> 38176081 | H95: =IF(1<=Supuestos!$B$18,$C$42*$C$31*(1+Supuestos!$B$10)^(1-1)*(1-Supuestos!$B$11)^(1-1),0) -> 7058195.9 | I95: =IF(1<=Supuestos!$B$19,G95*$C$32,0) -> 19088041 | J95: =F95+G95-H95-I95 -> 24034930 | K95: =K94+J95 -> 24034930 | L95: =IF(E95>0,J95/E95,0) -> 0.11883766 | M95: =IF(1<=Supuestos!$B$18,H95-Supuestos!$B$22*$C$26*(1+Supuestos!$B$9)^(1-1),0) -> 5865036.9 | N95: =IF(1<=Supuestos!$B$19,I95-Supuestos!$B$23*$C$29*(1+Supuestos!$B$9)^(1-1),0) -> 14844721 | O95: =O94+M95 -> -38041290 | P95: =P94+N95 -> -1.0099792e+08
B96: =Supuestos!$B$25+2-1 -> 2027 | C96: =$C$39*(1+Supuestos!$B$9)^(2-1) -> 2.7290993e+08 | D96: =IF(B96<=Supuestos!$B$26,$C$38*(1+Supuestos!$B$9)^(2-1),0) -> 60547311 | E96: =C96-D96 -> 2.1236262e+08 | F96: =$C$43*(1+Supuestos!$B$9)^(2-1)*(1-Supuestos!$B$11)^(2-1) -> 12542312 | G96: =$C$44*(1+Supuestos!$B$9)^(2-1)*(1-Supuestos!$B$12)^(2-1) -> 39583824 | H96: =IF(2<=Supuestos!$B$18,$C$42*$C$31*(1+Supuestos!$B$10)^(2-1)*(1-Supuestos!$B$11)^(2-1),0) -> 7374050.1 | I96: =IF(2<=Supuestos!$B$19,G96*$C$32,0) -> 19791912 | J96: =F96+G96-H96-I96 -> 24960174 | K96: =K95+J96 -> 48995104 | L96: =IF(E96>0,J96/E96,0) -> 0.11753563 | M96: =IF(2<=Supuestos!$B$18,H96-Supuestos!$B$22*$C$26*(1+Supuestos!$B$9)^(2-1),0) -> 6121233.2 | N96: =IF(2<=Supuestos!$B$19,I96-Supuestos!$B$23*$C$29*(1+Supuestos!$B$9)^(2-1),0) -> 15336426 | O96: =O95+M96 -> -31920057 | P96: =P95+N96 -> -85661489
B97: =Supuestos!$B$25+3-1 -> 2028 | C97: =$C$39*(1+Supuestos!$B$9)^(3-1) -> 2.8655543e+08 | D97: =IF(B97<=Supuestos!$B$26,$C$38*(1+Supuestos!$B$9)^(3-1),0) -> 63574676 | E97: =C97-D97 -> 222980754 | F97: =$C$43*(1+Supuestos!$B$9)^(3-1)*(1-Supuestos!$B$11)^(3-1) -> 13103581 | G97: =$C$44*(1+Supuestos!$B$9)^(3-1)*(1-Supuestos!$B$12)^(3-1) -> 41043478 | H97: =IF(3<=Supuestos!$B$18,$C$42*$C$31*(1+Supuestos!$B$10)^(3-1)*(1-Supuestos!$B$11)^(3-1),0) -> 7704038.9 | I97: =IF(3<=Supuestos!$B$19,G97*$C$32,0) -> 20521739 | J97: =F97+G97-H97-I97 -> 25921281 | K97: =K96+J97 -> 74916385 | L97: =IF(E97>0,J97/E97,0) -> 0.11624896 | M97: =IF(3<=Supuestos!$B$18,H97-Supuestos!$B$22*$C$26*(1+Supuestos!$B$9)^(3-1),0) -> 6388581.1 | N97: =IF(3<=Supuestos!$B$19,I97-Supuestos!$B$23*$C$29*(1+Supuestos!$B$9)^(3-1),0) -> 15843479 | O97: =O96+M97 -> -25531476 | P97: =P96+N97 -> -69818011
B98: =Supuestos!$B$25+4-1 -> 2029 | C98: =$C$39*(1+Supuestos!$B$9)^(4-1) -> 300883202 | D98: =IF(B98<=Supuestos!$B$26,$C$38*(1+Supuestos!$B$9)^(4-1),0) -> 66753410 | E98: =C98-D98 -> 2.3412979e+08 | F98: =$C$43*(1+Supuestos!$B$9)^(4-1)*(1-Supuestos!$B$11)^(4-1) -> 13689966 | G98: =$C$44*(1+Supuestos!$B$9)^(4-1)*(1-Supuestos!$B$12)^(4-1) -> 42556956 | H98: =IF(4<=Supuestos!$B$18,$C$42*$C$31*(1+Supuestos!$B$10)^(4-1)*(1-Supuestos!$B$11)^(4-1),0) -> 8048794.6 | I98: =IF(4<=Supuestos!$B$19,G98*$C$32,0) -> 21278478 | J98: =F98+G98-H98-I98 -> 26919650 | K98: =K97+J98 -> 1.0183603e+08 | L98: =IF(E98>0,J98/E98,0) -> 0.11497746 | M98: =IF(4<=Supuestos!$B$18,H98-Supuestos!$B$22*$C$26*(1+Supuestos!$B$9)^(4-1),0) -> 6667563.9 | N98: =IF(4<=Supuestos!$B$19,I98-Supuestos!$B$23*$C$29*(1+Supuestos!$B$9)^(4-1),0) -> 16366305 | O98: =O97+M98 -> -18863912 | P98: =P97+N98 -> -53451706
B99: =Supuestos!$B$25+5-1 -> 2030 | C99: =$C$39*(1+Supuestos!$B$9)^(5-1) -> 3.1592736e+08 | D99: =IF(B99<=Supuestos!$B$26,$C$38*(1+Supuestos!$B$9)^(5-1),0) -> 70091081 | E99: =C99-D99 -> 2.4583628e+08 | F99: =$C$43*(1+Supuestos!$B$9)^(5-1)*(1-Supuestos!$B$11)^(5-1) -> 14302592 | G99: =$C$44*(1+Supuestos!$B$9)^(5-1)*(1-Supuestos!$B$12)^(5-1) -> 44126244 | H99: =IF(5<=Supuestos!$B$18,$C$42*$C$31*(1+Supuestos!$B$10)^(5-1)*(1-Supuestos!$B$11)^(5-1),0) -> 8408978.2 | I99: =IF(5<=Supuestos!$B$19,G99*$C$32,0) -> 22063122 | J99: =F99+G99-H99-I99 -> 27956736 | K99: =K98+J99 -> 1.2979277e+08 | L99: =IF(E99>0,J99/E99,0) -> 0.11372095 | M99: =IF(5<=Supuestos!$B$18,H99-Supuestos!$B$22*$C$26*(1+Supuestos!$B$9)^(5-1),0) -> 6958685.9 | N99: =IF(5<=Supuestos!$B$19,I99-Supuestos!$B$23*$C$29*(1+Supuestos!$B$9)^(5-1),0) -> 16905340 | O99: =O98+M99 -> -11905226 | P99: =P98+N99 -> -36546366
B100: =Supuestos!$B$25+6-1 -> 2031 | C100: =$C$39*(1+Supuestos!$B$9)^(6-1) -> 3.3172373e+08 | D100: =IF(B100<=Supuestos!$B$26,$C$38*(1+Supuestos!$B$9)^(6-1),0) -> 73595635 | E100: =C100-D100 -> 2.581281e+08 | F100: =$C$43*(1+Supuestos!$B$9)^(6-1)*(1-Supuestos!$B$11)^(6-1) -> 14942633 | G100: =$C$44*(1+Supuestos!$B$9)^(6-1)*(1-Supuestos!$B$12)^(6-1) -> 45753399 | H100: =IF(6<=Supuestos!$B$18,$C$42*$C$31*(1+Supuestos!$B$10)^(6-1)*(1-Supuestos!$B$11)^(6-1),0) -> 8785279.9 | I100: =IF(6<=Supuestos!$B$19,G100*$C$32,0) -> 22876700 | J100: =F100+G100-H100-I100 -> 29034053 | K100: =K99+J100 -> 158826823 | L100: =IF(E100>0,J100/E100,0) -> 0.11247924 | M100: =IF(6<=Supuestos!$B$18,H100-Supuestos!$B$22*$C$26*(1+Supuestos!$B$9)^(6-1),0) -> 7262473.1 | N100: =IF(6<=Supuestos!$B$19,I100-Supuestos!$B$23*$C$29*(1+Supuestos!$B$9)^(6-1),0) -> 17461028 | O100: =O99+M100 -> -4642752.7 | P100: =P99+N100 -> -19085337
B101: =Supuestos!$B$25+7-1 -> 2032 | C101: =$C$39*(1+Supuestos!$B$9)^(7-1) -> 3.4830992e+08 | D101: =IF(B101<=Supuestos!$B$26,$C$38*(1+Supuestos!$B$9)^(7-1),0) -> 77275417 | E101: =C101-D101 -> 2.710345e+08 | F101: =$C$43*(1+Supuestos!$B$9)^(7-1)*(1-Supuestos!$B$11)^(7-1) -> 15611316 | G101: =$C$44*(1+Supuestos!$B$9)^(7-1)*(1-Supuestos!$B$12)^(7-1) -> 47440556 | H101: =IF(7<=Supuestos!$B$18,$C$42*$C$31*(1+Supuestos!$B$10)^(7-1)*(1-Supuestos!$B$11)^(7-1),0) -> 9178421.2 | I101: =IF(7<=Supuestos!$B$19,G101*$C$32,0) -> 23720278 | J101: =F101+G101-H101-I101 -> 30153173 | K101: =K100+J101 -> 1.8898e+08 | L101: =IF(E101>0,J101/E101,0) -> 0.11125216 | M101: =IF(7<=Supuestos!$B$18,H101-Supuestos!$B$22*$C$26*(1+Supuestos!$B$9)^(7-1),0) -> 7579474 | N101: =IF(7<=Supuestos!$B$19,I101-Supuestos!$B$23*$C$29*(1+Supuestos!$B$9)^(7-1),0) -> 18033823 | O101: =O100+M101 -> 2936721.3 | P101: =P100+N101 -> -1051514.2
B102: =Supuestos!$B$25+8-1 -> 2033 | C102: =$C$39*(1+Supuestos!$B$9)^(8-1) -> 3.6572541e+08 | D102: =IF(B102<=Supuestos!$B$26,$C$38*(1+Supuestos!$B$9)^(8-1),0) -> 0 | E102: =C102-D102 -> 3.6572541e+08 | F102: =$C$43*(1+Supuestos!$B$9)^(8-1)*(1-Supuestos!$B$11)^(8-1) -> 16309922 | G102: =$C$44*(1+Supuestos!$B$9)^(8-1)*(1-Supuestos!$B$12)^(8-1) -> 49189926 | H102: =IF(8<=Supuestos!$B$18,$C$42*$C$31*(1+Supuestos!$B$10)^(8-1)*(1-Supuestos!$B$11)^(8-1),0) -> 9589155.6 | I102: =IF(8<=Supuestos!$B$19,G102*$C$32,0) -> 24594963 | J102: =F102+G102-H102-I102 -> 31315730 | K102: =K101+J102 -> 2.2029573e+08 | L102: =IF(E102>0,J102/E102,0) -> 0.085626344 | M102: =IF(8<=Supuestos!$B$18,H102-Supuestos!$B$22*$C$26*(1+Supuestos!$B$9)^(8-1),0) -> 7910261 | N102: =IF(8<=Supuestos!$B$19,I102-Supuestos!$B$23*$C$29*(1+Supuestos!$B$9)^(8-1),0) -> 18624186 | O102: =O101+M102 -> 10846982 | P102: =P101+N102 -> 17572671
B103: =Supuestos!$B$25+9-1 -> 2034 | C103: =$C$39*(1+Supuestos!$B$9)^(9-1) -> 3.8401168e+08 | D103: =IF(B103<=Supuestos!$B$26,$C$38*(1+Supuestos!$B$9)^(9-1),0) -> 0 | E103: =C103-D103 -> 3.8401168e+08 | F103: =$C$43*(1+Supuestos!$B$9)^(9-1)*(1-Supuestos!$B$11)^(9-1) -> 17039791 | G103: =$C$44*(1+Supuestos!$B$9)^(9-1)*(1-Supuestos!$B$12)^(9-1) -> 51003805 | H103: =IF(9<=Supuestos!$B$18,$C$42*$C$31*(1+Supuestos!$B$10)^(9-1)*(1-Supuestos!$B$11)^(9-1),0) -> 10018270 | I103: =IF(9<=Supuestos!$B$19,G103*$C$32,0) -> 25501902 | J103: =F103+G103-H103-I103 -> 32523423 | K103: =K102+J103 -> 2.5281915e+08 | L103: =IF(E103>0,J103/E103,0) -> 0.084693838 | M103: =IF(9<=Supuestos!$B$18,H103-Supuestos!$B$22*$C$26*(1+Supuestos!$B$9)^(9-1),0) -> 8255431 | N103: =IF(9<=Supuestos!$B$19,I103-Supuestos!$B$23*$C$29*(1+Supuestos!$B$9)^(9-1),0) -> 19232586 | O103: =O102+M103 -> 19102413 | P103: =P102+N103 -> 36805258
B104: =Supuestos!$B$25+10-1 -> 2035 | C104: =$C$39*(1+Supuestos!$B$9)^(10-1) -> 4.0321227e+08 | D104: =IF(B104<=Supuestos!$B$26,$C$38*(1+Supuestos!$B$9)^(10-1),0) -> 0 | E104: =C104-D104 -> 4.0321227e+08 | F104: =$C$43*(1+Supuestos!$B$9)^(10-1)*(1-Supuestos!$B$11)^(10-1) -> 17802322 | G104: =$C$44*(1+Supuestos!$B$9)^(10-1)*(1-Supuestos!$B$12)^(10-1) -> 52884570 | H104: =IF(10<=Supuestos!$B$18,$C$42*$C$31*(1+Supuestos!$B$10)^(10-1)*(1-Supuestos!$B$11)^(10-1),0) -> 10466588 | I104: =IF(10<=Supuestos!$B$19,G104*$C$32,0) -> 26442285 | J104: =F104+G104-H104-I104 -> 33778019 | K104: =K103+J104 -> 2.8659717e+08 | L104: =IF(E104>0,J104/E104,0) -> 0.0837723 | M104: =IF(10<=Supuestos!$B$18,H104-Supuestos!$B$22*$C$26*(1+Supuestos!$B$9)^(10-1),0) -> 8615606.6 | N104: =IF(10<=Supuestos!$B$19,I104-Supuestos!$B$23*$C$29*(1+Supuestos!$B$9)^(10-1),0) -> 19859503 | O104: =O103+M104 -> 27718020 | P104: =P103+N104 -> 56664761
B105: =Supuestos!$B$25+11-1 -> 2036 | C105: =$C$39*(1+Supuestos!$B$9)^(11-1) -> 4.2337288e+08 | D105: =IF(B105<=Supuestos!$B$26,$C$38*(1+Supuestos!$B$9)^(11-1),0) -> 0 | E105: =C105-D105 -> 4.2337288e+08 | F105: =$C$43*(1+Supuestos!$B$9)^(11-1)*(1-Supuestos!$B$11)^(11-1) -> 18598976 | G105: =$C$44*(1+Supuestos!$B$9)^(11-1)*(1-Supuestos!$B$12)^(11-1) -> 54834688 | H105: =IF(11<=Supuestos!$B$18,$C$42*$C$31*(1+Supuestos!$B$10)^(11-1)*(1-Supuestos!$B$11)^(11-1),0) -> 10934968 | I105: =IF(11<=Supuestos!$B$19,G105*$C$32,0) -> 27417344 | J105: =F105+G105-H105-I105 -> 35081352 | K105: =K104+J105 -> 3.2167852e+08 | L105: =IF(E105>0,J105/E105,0) -> 0.082861596 | M105: =IF(11<=Supuestos!$B$18,H105-Supuestos!$B$22*$C$26*(1+Supuestos!$B$9)^(11-1),0) -> 8991437.4 | N105: =IF(11<=Supuestos!$B$19,I105-Supuestos!$B$23*$C$29*(1+Supuestos!$B$9)^(11-1),0) -> 20505423 | O105: =O104+M105 -> 36709457 | P105: =P104+N105 -> 77170184
B106: =Supuestos!$B$25+12-1 -> 2037 | C106: =$C$39*(1+Supuestos!$B$9)^(12-1) -> 4.4454152e+08 | D106: =IF(B106<=Supuestos!$B$26,$C$38*(1+Supuestos!$B$9)^(12-1),0) -> 0 | E106: =C106-D106 -> 4.4454152e+08 | F106: =$C$43*(1+Supuestos!$B$9)^(12-1)*(1-Supuestos!$B$11)^(12-1) -> 19431280 | G106: =$C$44*(1+Supuestos!$B$9)^(12-1)*(1-Supuestos!$B$12)^(12-1) -> 56856718 | H106: =IF(12<=Supuestos!$B$18,$C$42*$C$31*(1+Supuestos!$B$10)^(12-1)*(1-Supuestos!$B$11)^(12-1),0) -> 11424307 | I106: =IF(12<=Supuestos!$B$19,G106*$C$32,0) -> 28428359 | J106: =F106+G106-H106-I106 -> 36435331 | K106: =K105+J106 -> 3.5811385e+08 | L106: =IF(E106>0,J106/E106,0) -> 0.081961593 | M106: =IF(12<=Supuestos!$B$18,H106-Supuestos!$B$22*$C$26*(1+Supuestos!$B$9)^(12-1),0) -> 9383600.7 | N106: =IF(12<=Supuestos!$B$19,I106-Supuestos!$B$23*$C$29*(1+Supuestos!$B$9)^(12-1),0) -> 21170842 | O106: =O105+M106 -> 46093058 | P106: =P105+N106 -> 98341025
B107: =Supuestos!$B$25+13-1 -> 2038 | C107: =$C$39*(1+Supuestos!$B$9)^(13-1) -> 466768601 | D107: =IF(B107<=Supuestos!$B$26,$C$38*(1+Supuestos!$B$9)^(13-1),0) -> 0 | E107: =C107-D107 -> 466768601 | F107: =$C$43*(1+Supuestos!$B$9)^(13-1)*(1-Supuestos!$B$11)^(13-1) -> 20300830 | G107: =$C$44*(1+Supuestos!$B$9)^(13-1)*(1-Supuestos!$B$12)^(13-1) -> 58953309 | H107: =IF(13<=Supuestos!$B$18,$C$42*$C$31*(1+Supuestos!$B$10)^(13-1)*(1-Supuestos!$B$11)^(13-1),0) -> 11935545 | I107: =IF(13<=Supuestos!$B$19,G107*$C$32,0) -> 29476655 | J107: =F107+G107-H107-I107 -> 37841939 | K107: =K106+J107 -> 3.9595579e+08 | L107: =IF(E107>0,J107/E107,0) -> 0.081072161 | M107: =IF(13<=Supuestos!$B$18,H107-Supuestos!$B$22*$C$26*(1+Supuestos!$B$9)^(13-1),0) -> 9792803.1 | N107: =IF(13<=Supuestos!$B$19,I107-Supuestos!$B$23*$C$29*(1+Supuestos!$B$9)^(13-1),0) -> 21856261 | O107: =O106+M107 -> 55885861 | P107: =P106+N107 -> 1.2019729e+08
...
